Workbook

Sheet 00_使用说明
A1: T01-03 | 使用说明
A2: 编制基线 · 2026-09-26 | 第4份复查优先；用户明确答复与全局定案优先 | 设计资料，未接入游戏
A3: 返回说明 | B3: 39 条记录 | 表头可筛选 | 依据中的B1／B2／B3／R4／Q01与原行号可回查12表
A5: 记录ID | B5: 类别 | C5: 主题／分表 | D5: 说明 | E5: 记录性质 | F5: 依据
A6: U01 | B6: 定位 | C6: 本文件职责 | D6: 规定不同品级使用既有机制的深度、边界与审查要求；不充当完整强度评分公式。 | E6: 本次编制基线 | F6: B3§二十八 L812–835
A7: U02 | B7: 来源优先级 | C7: 三批＋第4份复查 | D7: 第4份复查及用户最新定案优先。2026-09-29共鸣同步为结丹10／元婴20／化神30；原文旧门槛已覆盖，历史原话保留。 | E7: 用户指定 | F7: 本轮用户请求；R4
A8: U03 | B8: 权威入口 | C8: 02_能力权限主表 | D8: 只在能力主表维护品级权限。03～05是按能力ID自动引用的矩阵视图；不独立手改。 | E8: 编制结构 | F8: R4§七 L252–286
A9: U04 | B9: 参照 | C9: 与前两词典分工 | D9: 01负责机制语言，02负责状态／控制语义，03负责品级深度；具体规则按核心定案与前两份词典。 | E9: 本次编制基线 | F9: B3§二十八 L812–835
A10: U05 | B10: 概念 | C10: 品级≠境界／稀有度／强化／剧情地位 | D10: 四者分列；有剧情、数值大或效果多，都不足以自动提高机制品级。 | E10: 本次编制基线 | F10: B1§一 L16–95
A11: U06 | B11: 符号 | C11: ◎ 核心常规 | D11: 本品级可常规使用的核心设计空间；不表示每件物品都必须使用。 | E11: 符号定义 | F11: B3§一 L18–40
A12: U07 | B12: 符号 | C12: ○ 正常辅助 | D12: 允许作为正常辅助机制；与◎都属于常规许可。 | E12: 符号定义 | F12: B3§一 L18–40
A13: U08 | B13: 符号 | C13: △ 少量候选 | D13: 不作为常规最低品级的依据；必须描述范围、次数、节奏与理由，不能只写“很轻”。不代表具体资产已批准。 | E13: 符号定义 | F13: B3§一 L18–40；R4§七 L252–286
A14: U09 | B14: 符号 | C14: ◇ 明确例外 | D14: 该品级仅在具体物品例外被确认后可用；当前没有因本表而自动批准的物品例外。 | E14: 符号定义 | F14: B3§一 L18–40；R4§十二 L422–446
A15: U10 | B15: 符号 | C15: — 非常规空间 | D15: 普通物品不进入；不是程序不支持，也不因一件例外变成新常规。 | E15: 符号定义 | F15: B3§一 L18–40；B3§十八 L548–569
A16: U11 | B16: 符号 | C16: ? 待专项／停用／基础 | D16: ?为原稿有分歧或未给起点；停用不可生成；基础为所有品级继承的后台规则，不是特色词条。 | E16: 编制标记 | F16: 核心01§1.8；R4§九 L312–355
... A44: U25 | B44: 状态口径 | C44: 编制基线与正式资产 | D44: 前三批与复查构成词典编制基线；不冒称每个符号都经过用户逐项确认。专案、候选、未定项须随资产再审。 | E44: 使用边界 | F44: 本轮编制

Sheet 01_品级总纲
A1: T01-03 | 品级总纲
A2: 编制基线 · 2026-09-26 | 第4份复查优先；用户明确答复与全局定案优先 | 设计资料，未接入游戏
A3: 返回说明 | B3: 7 条记录 | 表头可筛选 | 依据中的B1／B2／B3／R4／Q01与原行号可回查12表
A5: 品级 | B5: 复杂度参考 | C5: 核心定位 | D5: 玩家认知／玩法 | E5: 常规使用门槛 | F5: 设计预算与取舍 | G5: 禁止误读／边界 | H5: 依据
A6: 下品 | B6: L0 | C6: 无属性基础器具 | D6: 认识器具类别及基础参数取舍 | E6: 凡人可用 | F6: 同阶段比较速度、命中、费用、占格等 | G6: 不做特色状态／控制／邻接／来源玩法 | H6: B1§十一 L443–466～十六；R4§九 L312–355
A7: 凡品 | B7: L0～L1 | C7: 固定单元素与一种简单状态可组合 | D7: 认识属性与状态 | E7: 凡人可用 | F7: 允许简单数值差异，不以Effect行数定级 | G7: 凡品开放固定单元素＋一种简单状态；不据此开放双状态、复杂监听、来源改写、自由功能槽。 | H7: 原编制基线；t01-08凡品第2／3批与用户直接更正、FP02；2026-09-28
A8: 良品 | B8: L1～L2 | C8: 一个清楚、可搭配的特色机制 | D8: 简单监听／计数／读状态／邻接 | E8: 炼气起 | F8: 通常一个机制中心，不能靠低数值掩盖高规则权限 | G8: 公共状态转换、他器当前CD和敌器控制不因“轻”字常规下放 | H8: B1§二十六 L780–800～三十六；R4§七 L252–286
A9: 上品 | B9: L2～L3 | C9: 一个成熟的局部构筑核心 | D9: 管理状态兑现、领域、恢复防护或控制 | E9: 筑基起 | F9: 一个主中心及少量支撑；投入随概念同步审查 | G9: 不默认为局部共享池常规品级；给另一武器赋固定元素在此开放 | H9: B2§二 L32–45～八；R4§七 L252–286；Q01 L3–5
A10: 灵品 | B10: L3～L4 | C10: 两个成熟机制实质耦合 | D10: 单向联动／取舍／阶段衔接／反馈 | E10: 结丹起 | F10: 通常1～2个观察变量；检查双方有独立玩法 | G10: 不要求闭环；不把“3次攻击→火球”一个中心误判为双核心 | H10: R4§五 L181–224；B2§九 L272–287～十七
A11: 玄品 | B11: L4～L5 | C11: 在明确范围内改变规则 | D11: 发动、来源、阵式或连携规则核心 | E11: 元婴起 | F11: 通常一个规则核心加1～2个支撑 | G11: 权限不自动豁免全局限制；有限次数不降低规则权力层级 | H11: B2§十八 L519–536～二十六；R4§七 L252–286
A12: 仙品 | B12: 按当前成长阶段，无L6 | C12: 专属身份＋长期成长＋代表性能力 | D12: 独特战术选择，能力与边界成对设计 | E12: 按各成长阶段条件；不统一等化神 | F12: 按同阶段、同阵位及投入比较；不必始终强过玄品 | G12: 六项对照与档案见10表；“开场择相甲”仅工作名和标杆方向 | H12: R4§一 L9–37～四、八；B2§二十七 L741–760～三十四

Sheet 02_能力权限主表
A1: T01-03 | 能力权限主表
A2: 编制基线 · 2026-09-26 | 第4份复查优先；用户明确答复与全局定案优先 | 设计资料，未接入游戏
A3: 返回说明 | B3: 103 条记录 | 表头可筛选 | 依据中的B1／B2／B3／R4／Q01与原行号可回查12表
A5: 能力ID | B5: 能力名称 | C5: 常规最低品级 | D5: 下品 | E5: 凡品 | F5: 良品 | G5: 上品 | H5: 灵品 | I5: 玄品 | J5: 仙品 | K5: 基础／特色 | L5: 权限边界 | M5: 前置／未决 | N5: 规则状态 | O5: 已确认例外 | P5: 依据
A6: C001 | B6: 基础攻击／防护／恢复 | C6: =IF(D6="停用","停用",IF(D6="基础","全品级基础",IF(OR(D6="◎",D6="○"),D$5,IF(OR(E6="◎",E6="○"),E$5,IF(OR(F6="◎",F6="○"),F$5,IF(OR(G6="◎",G6="○"),G$5,IF(OR(H6="◎",H6="○"),H$5,IF(OR(I6="◎",I6="○"),I$5,"未设常规起点")))))))) -> 下品 | D6: ◎ | E6: ◎ | F6: ◎ | G6: ◎ | H6: ◎ | I6: ◎ | J6: 专案 | K6: 基础动作 | L6: 作为器具类别主体动作；下品无七属性、无状态联动。伤害包只有一种Attack_Type，Element与来源另记，不以品级豁免唯一类型规则。 | M6: 按具体资产填写参数 | N6: 编制基线；全局规则优先 | O6: 无已确认物品例外 | P6: B1§十二 L467–509；B3§三 L65–128
A7: C002 | B7: 基础参数与类别固有标签 | C7: =IF(D7="停用","停用",IF(D7="基础","全品级基础",IF(OR(D7="◎",D7="○"),D$5,IF(OR(E7="◎",E7="○"),E$5,IF(OR(F7="◎",F7="○"),F$5,IF(OR(G7="◎",G7="○"),G$5,IF(OR(H7="◎",H7="○"),H$5,IF(OR(I7="◎",I7="○"),I$5,"未设常规起点")))))))) -> 下品 | D7: ◎ | E7: ◎ | F7: ◎ | G7: ◎ | H7: ◎ | I7: ◎ | J7: 专案 | K7: 基础规格 | L7: 攻击、CD、命中、费用、护甲、占格、物理甲型等；参数差异不自动增加机制中心。 | M7: 按具体资产填写参数 | N7: 编制基线；全局规则优先 | O7: 无已确认物品例外 | P7: B1§八 L371–398；B1§十二 L467–509
A8: C003 | B8: 基础轮转与手动／自动模式 | C8: =IF(D8="停用","停用",IF(D8="基础","全品级基础",IF(OR(D8="◎",D8="○"),D$5,IF(OR(E8="◎",E8="○"),E$5,IF(OR(F8="◎",F8="○"),F$5,IF(OR(G8="◎",G8="○"),G$5,IF(OR(H8="◎",H8="○"),H$5,IF(OR(I8="◎",I8="○"),I$5,"未设常规起点")))))))) -> 下品 | D8: ◎ | E8: ◎ | F8: ◎ | G8: ◎ | H8: ◎ | I8: ◎ | J8: 专案 | K8: 基础动作 | L8: 正常发动仍检查目标、资源、控制等；不可用低品级理由省略后台判断。 | M8: 按具体资产填写参数 | N8: 编制基线；全局规则优先 | O8: 无已确认物品例外 | P8: B3§三 L65–128；核心01§1.4
A9: C004 | B9: 标准事件、叠加与资格检查 | C9: =IF(D9="停用","停用",IF(D9="基础","全品级基础",IF(OR(D9="◎",D9="○"),D$5,IF(OR(E9="◎",E9="○"),E$5,IF(OR(F9="◎",F9="○"),F$5,IF(OR(G9="◎",G9="○"),G$5,IF(OR(H9="◎",H9="○"),H$5,IF(OR(I9="◎",I9="○"),I$5,"未设常规起点")))))))) -> 全品级基础 | D9: 基础 | E9: 基础 | F9: 基础 | G9: 基础 | H9: 基础 | I9: 基础 | J9: 基础 | K9: 后台必备 | L9: 所有器具都产生合法事件并遵守基础叠加、去重、暴击与命中规则；不等于带特色监听词条。 | M9: 按具体资产填写参数 | N9: 编制基线；全局规则优先 | O9: 无已确认物品例外 | P9: R4§九 L312–355；B3§三 L65–128
A10: C005 | B10: 真实来源记录与显示 | C10: =IF(D10="停用","停用",IF(D10="基础","全品级基础",IF(OR(D10="◎",D10="○"),D$5,IF(OR(E10="◎",E10="○"),E$5,IF(OR(F10="◎",F10="○"),F$5,IF(OR(G10="◎",G10="○"),G$5,IF(OR(H10="◎",H10="○"),H$5,IF(OR(I10="◎",I10="○"),I$5,"未设常规起点")))))))) -> 全品级基础 | D10: 基础 | E10: 基础 | F10: 基础 | G10: 基础 | H10: 基础 | I10: 基础 | J10: 基础 | K10: 后台必备 | L10: 记录真实施加者、器具、效果与因果；不因任何品级省略或伪装。 | M10: 按具体资产填写参数 | N10: 编制基线；全局规则优先 | O10: 无已确认物品例外 | P10: B3§十二 L359–390
A11: C006 | B11: 器具固定自带单一元素属性 | C11: =IF(D11="停用","停用",IF(D11="基础","全品级基础",IF(OR(D11="◎",D11="○"),D$5,IF(OR(E11="◎",E11="○"),E$5,IF(OR(F11="◎",F11="○"),F$5,IF(OR(G11="◎",G11="○"),G$5,IF(OR(H11="◎",H11="○"),H$5,IF(OR(I11="◎",I11="○"),I$5,"未设常规起点")))))))) -> 凡品 | D11: — | E11: ◎ | F11: ◎ | G11: ◎ | H11: ◎ | I11: ◎ | J11: 专案 | K11: 特色权限 | L11: 凡品开始允许，仍可设计无属性高品级；固定属性不等于独立附伤包。 | M11: 按具体资产填写参数 | N11: 编制基线；全局规则优先 | O11: 无已确认物品例外 | P11: B1§十九 L636–661；R4§九 L312–355
A12: C007 | B12: 固定双属性／复合标签（攻击／检索） | C12: =IF(D12="停用","停用",IF(D12="基础","全品级基础",IF(OR(D12="◎",D12="○"),D$5,IF(OR(E12="◎",E12="○"),E$5,IF(OR(F12="◎",F12="○"),F$5,IF(OR(G12="◎",G12="○"),G$5,IF(OR(H12="◎",H12="○"),H$5,IF(OR(I12="◎",I12="○"),I$5,"未设常规起点")))))))) -> 良品 | D12: — | E12: △ | F12: ○ | G12: ◎ | H12: ◎ | I12: ◎ | J12: 专案 | K12: 特色权限 | L12: 仅按适用攻击元素或检索标签使用，保留合规多元素攻击；不授权同一防具同时拥有多个当前防御元素，不授权同一伤害包具有多个Attack Type。不自动改写来源；须明确各伤害包、元素分量及基础规则。 | M12: 按具体资产填写参数 | N12: 编制基线；全局规则优先 | O12: 无已确认物品例外 | P12: B3§十二 L359–390
A13: C008 | B13: 临时给另一武器赋予固定元素 | C13: =IF(D13="停用","停用",IF(D13="基础","全品级基础",IF(OR(D13="◎",D13="○"),D$5,IF(OR(E13="◎",E13="○"),E$5,IF(OR(F13="◎",F13="○"),F$5,IF(OR(G13="◎",G13="○"),G$5,IF(OR(H13="◎",H13="○"),H$5,IF(OR(I13="◎",I13="○"),I$5,"未设常规起点")))))))) -> 上品 | D13: — | E13: — | F13: — | G13: ◎ | H13: ◎ | I13: ◎ | J13: 专案 | K13: 特色权限 | L13: 用户确认上品常规起点；是否替换原属性或追加属性须由资产明确，不自动获得来源或连携资格。 | M13: 附加／替换、目标、持续、费用待具体资产 | N13: 用户已定起点；参数待资产 | O13: 无已确认物品例外 | P13: Q01 L3–5；R4§九 L312–355
A14: C009 | B14: 受限自主选择固定身份／配置 | C14: =IF(D14="停用","停用",IF(D14="基础","全品级基础",IF(OR(D14="◎",D14="○"),D$5,IF(OR(E14="◎",E14="○"),E$5,IF(OR(F14="◎",F14="○"),F$5,IF(OR(G14="◎",G14="○"),G$5,IF(OR(H14="◎",H14="○"),H$5,IF(OR(I14="◎",I14="○"),I$5,"未设常规起点")))))))) -> 未设常规起点 | D14: ? | E14: ? | F14: ? | G14: ? | H14: ? | I14: ? | J14: 专案 | K14: 特色权限 | L14: 仙品择相是参考方向；其他品级的自主改换能力未给统一起点，不能从固定属性行推导。 | M14: 非仙品适用起点待具体方案；仙品按六项标准 | N14: 编制基线；含待专项单元格 | O14: 无已确认物品例外 | P14: R4§二 L38–119；R4§六 L225–251；R4§九 L312–355
A15: C010 | B15: 元素攻击与额外状态等独立收益组合 | C15: =IF(D15="停用","停用",IF(D15="基础","全品级基础",IF(OR(D15="◎",D15="○"),D$5,IF(OR(E15="◎",E15="○"),E$5,IF(OR(F15="◎",F15="○"),F$5,IF(OR(G15="◎",G15="○"),G$5,IF(OR(H15="◎",H15="○"),H$5,IF(OR(I15="◎",I15="○"),I$5,"未设常规起点")))))))) -> 凡品 | D15: — | E15: ○ | F15: ○ | G15: ◎ | H15: ◎ | I15: ◎ | J15: 专案 | K15: 特色权限 | L15: 凡品常规允许固定单元素＋一种简单状态的组合，仍按各状态已定触发门槛与容量；不顺带开放双状态、复杂监听、来源改写或自由功能槽。其他多份独立收益组合仍须审查。 | M15: 按具体资产填写参数 | N15: 本次08覆盖旧“凡品少量候选、良品常规”口径，许可限本行明确范围。 | O15: 无已确认物品例外 | P15: R4§七历史口径；t01-08凡品第2／3批与用户直接更正、FP02；2026-09-28
A16: C011 | B16: 简单条件发动 | C16: =IF(D16="停用","停用",IF(D16="基础","全品级基础",IF(OR(D16="◎",D16="○"),D$5,IF(OR(E16="◎",E16="○"),E$5,IF(OR(F16="◎",F16="○"),F$5,IF(OR(G16="◎",G16="○"),G$5,IF(OR(H16="◎",H16="○"),H$5,IF(OR(I16="◎",I16="○"),I$5,"未设常规起点")))))))) -> 良品 | D16: — | E16: △ | F16: ◎ | G16: ◎ | H16: ◎ | I16: ◎ | J16: 专案 | K16: 特色权限 | L16: 一条直观条件；凡品限极简单特定候选，不扩展成计数／状态兑现链。 | M16: 按具体资产填写参数 | N16: 编制基线；全局规则优先 | O16: 无已确认物品例外 | P16: B3§三 L65–128
A17: C012 | B17: 待发／预备式 | C17: =IF(D17="停用","停用",IF(D17="基础","全品级基础",IF(OR(D17="◎",D17="○"),D$5,IF(OR(E17="◎",E17="○"),E$5,IF(OR(F17="◎",F17="○"),F$5,IF(OR(G17="◎",G17="○"),G$5,IF(OR(H17="◎",H17="○"),H$5,IF(OR(I17="◎",I17="○"),I$5,"未设常规起点")))))))) -> 良品 | D17: — | E17: △ | F17: ○ | G17: ◎ | H17: ◎ | I17: ◎ | J17: 专案 | K17: 特色权限 | L17: 等待资格与支付时点按01；已定冻结／禁用／沉默对旧待发资格的处理继续生效。 | M17: 按具体资产填写参数 | N17: 编制基线；全局规则优先 | O17: 无已确认物品例外 | P17: B3§三 L65–128；核心01§1.4、§1.8
... A108: C103 | B108: 简单静态附加数值 | C108: =IF(D108="停用","停用",IF(D108="基础","全品级基础",IF(OR(D108="◎",D108="○"),D$5,IF(OR(E108="◎",E108="○"),E$5,IF(OR(F108="◎",F108="○"),F$5,IF(OR(G108="◎",G108="○"),G$5,IF(OR(H108="◎",H108="○"),H$5,IF(OR(I108="◎",I108="○"),I$5,"未设常规起点")))))))) -> 凡品 | D108: — | E108: ◎ | F108: ◎ | G108: ◎ | H108: ◎ | I108: ◎ | J108: 专案 | K108: 特色权限 | L108: 凡品可直接提高某项数值；状态条件、事件计数与按层动态收益另查。数值大小仍须预算。 | M108: 按具体资产填写参数 | N108: 编制基线；全局规则优先 | O108: 无已确认物品例外 | P108: B1§二十三 L724–739

Sheet 03_M机制权限
A1: T01-03 | M机制权限
A2: 按能力ID引用02主表；排序不改变对应关系。◎核心 ○常规辅助 △有限候选 ◇明确例外 —非常规 ?待专项；仙品看10表。
A3: 返回说明 | B3: 164 条记录 | 表头可筛选 | 依据中的B1／B2／B3／R4／Q01与原行号可回查12表
A5: 模块 | B5: 能力ID | C5: 能力名称 | D5: 常规最低品级 | E5: 下品 | F5: 凡品 | G5: 良品 | H5: 上品 | I5: 灵品 | J5: 玄品 | K5: 仙品 | L5: 权限边界 | M5: 前置／未决 | N5: 规则状态 | O5: 依据
A6: M01 发动范式 | B6: C003 | C6: =INDEX('02_能力权限主表'!$B$6:$B$108,MATCH($B6,'02_能力权限主表'!$A$6:$A$108,0)) -> 基础轮转与手动／自动模式 | D6: =INDEX('02_能力权限主表'!$C$6:$C$108,MATCH($B6,'02_能力权限主表'!$A$6:$A$108,0)) -> 下品 | E6: =INDEX('02_能力权限主表'!$D$6:$D$108,MATCH($B6,'02_能力权限主表'!$A$6:$A$108,0)) -> ◎ | F6: =INDEX('02_能力权限主表'!$E$6:$E$108,MATCH($B6,'02_能力权限主表'!$A$6:$A$108,0)) -> ◎ | G6: =INDEX('02_能力权限主表'!$F$6:$F$108,MATCH($B6,'02_能力权限主表'!$A$6:$A$108,0)) -> ◎ | H6: =INDEX('02_能力权限主表'!$G$6:$G$108,MATCH($B6,'02_能力权限主表'!$A$6:$A$108,0)) -> ◎ | I6: =INDEX('02_能力权限主表'!$H$6:$H$108,MATCH($B6,'02_能力权限主表'!$A$6:$A$108,0)) -> ◎ | J6: =INDEX('02_能力权限主表'!$I$6:$I$108,MATCH($B6,'02_能力权限主表'!$A$6:$A$108,0)) -> ◎ | K6: =INDEX('02_能力权限主表'!$J$6:$J$108,MATCH($B6,'02_能力权限主表'!$A$6:$A$108,0)) -> 专案 | L6: =INDEX('02_能力权限主表'!$L$6:$L$108,MATCH($B6,'02_能力权限主表'!$A$6:$A$108,0)) -> 正常发动仍检查目标、资源、控制等；不可用低品级理由省略后台判断。 | M6: =INDEX('02_能力权限主表'!$M$6:$M$108,MATCH($B6,'02_能力权限主表'!$A$6:$A$108,0)) -> 按具体资产填写参数 | N6: =INDEX('02_能力权限主表'!$N$6:$N$108,MATCH($B6,'02_能力权限主表'!$A$6:$A$108,0)) -> 编制基线；全局规则优先 | O6: =INDEX('02_能力权限主表'!$P$6:$P$108,MATCH($B6,'02_能力权限主表'!$A$6:$A$108,0)) -> B3§三 L65–128；核心01§1.4
A7: M01 发动范式 | B7: C011 | C7: =INDEX('02_能力权限主表'!$B$6:$B$108,MATCH($B7,'02_能力权限主表'!$A$6:$A$108,0)) -> 简单条件发动 | D7: =INDEX('02_能力权限主表'!$C$6:$C$108,MATCH($B7,'02_能力权限主表'!$A$6:$A$108,0)) -> 良品 | E7: =INDEX('02_能力权限主表'!$D$6:$D$108,MATCH($B7,'02_能力权限主表'!$A$6:$A$108,0)) -> — | F7: =INDEX('02_能力权限主表'!$E$6:$E$108,MATCH($B7,'02_能力权限主表'!$A$6:$A$108,0)) -> △ | G7: =INDEX('02_能力权限主表'!$F$6:$F$108,MATCH($B7,'02_能力权限主表'!$A$6:$A$108,0)) -> ◎ | H7: =INDEX('02_能力权限主表'!$G$6:$G$108,MATCH($B7,'02_能力权限主表'!$A$6:$A$108,0)) -> ◎ | I7: =INDEX('02_能力权限主表'!$H$6:$H$108,MATCH($B7,'02_能力权限主表'!$A$6:$A$108,0)) -> ◎ | J7: =INDEX('02_能力权限主表'!$I$6:$I$108,MATCH($B7,'02_能力权限主表'!$A$6:$A$108,0)) -> ◎ | K7: =INDEX('02_能力权限主表'!$J$6:$J$108,MATCH($B7,'02_能力权限主表'!$A$6:$A$108,0)) -> 专案 | L7: =INDEX('02_能力权限主表'!$L$6:$L$108,MATCH($B7,'02_能力权限主表'!$A$6:$A$108,0)) -> 一条直观条件；凡品限极简单特定候选，不扩展成计数／状态兑现链。 | M7: =INDEX('02_能力权限主表'!$M$6:$M$108,MATCH($B7,'02_能力权限主表'!$A$6:$A$108,0)) -> 按具体资产填写参数 | N7: =INDEX('02_能力权限主表'!$N$6:$N$108,MATCH($B7,'02_能力权限主表'!$A$6:$A$108,0)) -> 编制基线；全局规则优先 | O7: =INDEX('02_能力权限主表'!$P$6:$P$108,MATCH($B7,'02_能力权限主表'!$A$6:$A$108,0)) -> B3§三 L65–128
A8: M01 发动范式 | B8: C012 | C8: =INDEX('02_能力权限主表'!$B$6:$B$108,MATCH($B8,'02_能力权限主表'!$A$6:$A$108,0)) -> 待发／预备式 | D8: =INDEX('02_能力权限主表'!$C$6:$C$108,MATCH($B8,'02_能力权限主表'!$A$6:$A$108,0)) -> 良品 | E8: =INDEX('02_能力权限主表'!$D$6:$D$108,MATCH($B8,'02_能力权限主表'!$A$6:$A$108,0)) -> — | F8: =INDEX('02_能力权限主表'!$E$6:$E$108,MATCH($B8,'02_能力权限主表'!$A$6:$A$108,0)) -> △ | G8: =INDEX('02_能力权限主表'!$F$6:$F$108,MATCH($B8,'02_能力权限主表'!$A$6:$A$108,0)) -> ○ | H8: =INDEX('02_能力权限主表'!$G$6:$G$108,MATCH($B8,'02_能力权限主表'!$A$6:$A$108,0)) -> ◎ | I8: =INDEX('02_能力权限主表'!$H$6:$H$108,MATCH($B8,'02_能力权限主表'!$A$6:$A$108,0)) -> ◎ | J8: =INDEX('02_能力权限主表'!$I$6:$I$108,MATCH($B8,'02_能力权限主表'!$A$6:$A$108,0)) -> ◎ | K8: =INDEX('02_能力权限主表'!$J$6:$J$108,MATCH($B8,'02_能力权限主表'!$A$6:$A$108,0)) -> 专案 | L8: =INDEX('02_能力权限主表'!$L$6:$L$108,MATCH($B8,'02_能力权限主表'!$A$6:$A$108,0)) -> 等待资格与支付时点按01；已定冻结／禁用／沉默对旧待发资格的处理继续生效。 | M8: =INDEX('02_能力权限主表'!$M$6:$M$108,MATCH($B8,'02_能力权限主表'!$A$6:$A$108,0)) -> 按具体资产填写参数 | N8: =INDEX('02_能力权限主表'!$N$6:$N$108,MATCH($B8,'02_能力权限主表'!$A$6:$A$108,0)) -> 编制基线；全局规则优先 | O8: =INDEX('02_能力权限主表'!$P$6:$P$108,MATCH($B8,'02_能力权限主表'!$A$6:$A$108,0)) -> B3§三 L65–128；核心01§1.4、§1.8
A9: M01 发动范式 | B9: C013 | C9: =INDEX('02_能力权限主表'!$B$6:$B$108,MATCH($B9,'02_能力权限主表'!$A$6:$A$108,0)) -> 简单延迟生效 | D9: =INDEX('02_能力权限主表'!$C$6:$C$108,MATCH($B9,'02_能力权限主表'!$A$6:$A$108,0)) -> 良品 | E9: =INDEX('02_能力权限主表'!$D$6:$D$108,MATCH($B9,'02_能力权限主表'!$A$6:$A$108,0)) -> — | F9: =INDEX('02_能力权限主表'!$E$6:$E$108,MATCH($B9,'02_能力权限主表'!$A$6:$A$108,0)) -> △ | G9: =INDEX('02_能力权限主表'!$F$6:$F$108,MATCH($B9,'02_能力权限主表'!$A$6:$A$108,0)) -> ○ | H9: =INDEX('02_能力权限主表'!$G$6:$G$108,MATCH($B9,'02_能力权限主表'!$A$6:$A$108,0)) -> ◎ | I9: =INDEX('02_能力权限主表'!$H$6:$H$108,MATCH($B9,'02_能力权限主表'!$A$6:$A$108,0)) -> ◎ | J9: =INDEX('02_能力权限主表'!$I$6:$I$108,MATCH($B9,'02_能力权限主表'!$A$6:$A$108,0)) -> ◎ | K9: =INDEX('02_能力权限主表'!$J$6:$J$108,MATCH($B9,'02_能力权限主表'!$A$6:$A$108,0)) -> 专案 | L9: =INDEX('02_能力权限主表'!$L$6:$L$108,MATCH($B9,'02_能力权限主表'!$A$6:$A$108,0)) -> 如已发动效果延迟1秒落地；计时本身不等于高品级。不得恢复蓄势机制。 | M9: =INDEX('02_能力权限主表'!$M$6:$M$108,MATCH($B9,'02_能力权限主表'!$A$6:$A$108,0)) -> 按具体资产填写参数 | N9: =INDEX('02_能力权限主表'!$N$6:$N$108,MATCH($B9,'02_能力权限主表'!$A$6:$A$108,0)) -> 编制基线；全局规则优先 | O9: =INDEX('02_能力权限主表'!$P$6:$P$108,MATCH($B9,'02_能力权限主表'!$A$6:$A$108,0)) -> B3§四 L129–152；核心01§1.8
A10: M01 发动范式 | B10: C014 | C10: =INDEX('02_能力权限主表'!$B$6:$B$108,MATCH($B10,'02_能力权限主表'!$A$6:$A$108,0)) -> 蓄势／蓄势中断（停用） | D10: =INDEX('02_能力权限主表'!$C$6:$C$108,MATCH($B10,'02_能力权限主表'!$A$6:$A$108,0)) -> 停用 | E10: =INDEX('02_能力权限主表'!$D$6:$D$108,MATCH($B10,'02_能力权限主表'!$A$6:$A$108,0)) -> 停用 | F10: =INDEX('02_能力权限主表'!$E$6:$E$108,MATCH($B10,'02_能力权限主表'!$A$6:$A$108,0)) -> 停用 | G10: =INDEX('02_能力权限主表'!$F$6:$F$108,MATCH($B10,'02_能力权限主表'!$A$6:$A$108,0)) -> 停用 | H10: =INDEX('02_能力权限主表'!$G$6:$G$108,MATCH($B10,'02_能力权限主表'!$A$6:$A$108,0)) -> 停用 | I10: =INDEX('02_能力权限主表'!$H$6:$H$108,MATCH($B10,'02_能力权限主表'!$A$6:$A$108,0)) -> 停用 | J10: =INDEX('02_能力权限主表'!$I$6:$I$108,MATCH($B10,'02_能力权限主表'!$A$6:$A$108,0)) -> 停用 | K10: =INDEX('02_能力权限主表'!$J$6:$J$108,MATCH($B10,'02_能力权限主表'!$A$6:$A$108,0)) -> 停用 | L10: =INDEX('02_能力权限主表'!$L$6:$L$108,MATCH($B10,'02_能力权限主表'!$A$6:$A$108,0)) -> 用户已全局去除。三批旧词只在原文追溯，不可作为任何品级候选。 | M10: =INDEX('02_能力权限主表'!$M$6:$M$108,MATCH($B10,'02_能力权限主表'!$A$6:$A$108,0)) -> 不开放；恢复须另有明确新决定 | N10: =INDEX('02_能力权限主表'!$N$6:$N$108,MATCH($B10,'02_能力权限主表'!$A$6:$A$108,0)) -> 既有定案：停用 | O10: =INDEX('02_能力权限主表'!$P$6:$P$108,MATCH($B10,'02_能力权限主表'!$A$6:$A$108,0)) -> 核心01§1.8；t01-01 T01-D03
A11: M01 发动范式 | B11: C015 | C11: =INDEX('02_能力权限主表'!$B$6:$B$108,MATCH($B11,'02_能力权限主表'!$A$6:$A$108,0)) -> 改写其他器具发动方式 | D11: =INDEX('02_能力权限主表'!$C$6:$C$108,MATCH($B11,'02_能力权限主表'!$A$6:$A$108,0)) -> 玄品 | E11: =INDEX('02_能力权限主表'!$D$6:$D$108,MATCH($B11,'02_能力权限主表'!$A$6:$A$108,0)) -> — | F11: =INDEX('02_能力权限主表'!$E$6:$E$108,MATCH($B11,'02_能力权限主表'!$A$6:$A$108,0)) -> — | G11: =INDEX('02_能力权限主表'!$F$6:$F$108,MATCH($B11,'02_能力权限主表'!$A$6:$A$108,0)) -> — | H11: =INDEX('02_能力权限主表'!$G$6:$G$108,MATCH($B11,'02_能力权限主表'!$A$6:$A$108,0)) -> — | I11: =INDEX('02_能力权限主表'!$H$6:$H$108,MATCH($B11,'02_能力权限主表'!$A$6:$A$108,0)) -> ◇ | J11: =INDEX('02_能力权限主表'!$I$6:$I$108,MATCH($B11,'02_能力权限主表'!$A$6:$A$108,0)) -> ◎ | K11: =INDEX('02_能力权限主表'!$J$6:$J$108,MATCH($B11,'02_能力权限主表'!$A$6:$A$108,0)) -> 专案 | L11: =INDEX('02_能力权限主表'!$L$6:$L$108,MATCH($B11,'02_能力权限主表'!$A$6:$A$108,0)) -> 玄品常规；灵品只能逐件明确例外。保留支付、控制、待发、原CD等边界。 | M11: =INDEX('02_能力权限主表'!$M$6:$M$108,MATCH($B11,'02_能力权限主表'!$A$6:$A$108,0)) -> 按具体资产填写参数 | N11: =INDEX('02_能力权限主表'!$N$6:$N$108,MATCH($B11,'02_能力权限主表'!$A$6:$A$108,0)) -> 编制基线；全局规则优先 | O11: =INDEX('02_能力权限主表'!$P$6:$P$108,MATCH($B11,'02_能力权限主表'!$A$6:$A$108,0)) -> R4§七 L252–286；B2§十九 L537–558
A12: M02 事件与监听 | B12: C004 | C12: =INDEX('02_能力权限主表'!$B$6:$B$108,MATCH($B12,'02_能力权限主表'!$A$6:$A$108,0)) -> 标准事件、叠加与资格检查 | D12: =INDEX('02_能力权限主表'!$C$6:$C$108,MATCH($B12,'02_能力权限主表'!$A$6:$A$108,0)) -> 全品级基础 | E12: =INDEX('02_能力权限主表'!$D$6:$D$108,MATCH($B12,'02_能力权限主表'!$A$6:$A$108,0)) -> 基础 | F12: =INDEX('02_能力权限主表'!$E$6:$E$108,MATCH($B12,'02_能力权限主表'!$A$6:$A$108,0)) -> 基础 | G12: =INDEX('02_能力权限主表'!$F$6:$F$108,MATCH($B12,'02_能力权限主表'!$A$6:$A$108,0)) -> 基础 | H12: =INDEX('02_能力权限主表'!$G$6:$G$108,MATCH($B12,'02_能力权限主表'!$A$6:$A$108,0)) -> 基础 | I12: =INDEX('02_能力权限主表'!$H$6:$H$108,MATCH($B12,'02_能力权限主表'!$A$6:$A$108,0)) -> 基础 | J12: =INDEX('02_能力权限主表'!$I$6:$I$108,MATCH($B12,'02_能力权限主表'!$A$6:$A$108,0)) -> 基础 | K12: =INDEX('02_能力权限主表'!$J$6:$J$108,MATCH($B12,'02_能力权限主表'!$A$6:$A$108,0)) -> 基础 | L12: =INDEX('02_能力权限主表'!$L$6:$L$108,MATCH($B12,'02_能力权限主表'!$A$6:$A$108,0)) -> 所有器具都产生合法事件并遵守基础叠加、去重、暴击与命中规则；不等于带特色监听词条。 | M12: =INDEX('02_能力权限主表'!$M$6:$M$108,MATCH($B12,'02_能力权限主表'!$A$6:$A$108,0)) -> 按具体资产填写参数 | N12: =INDEX('02_能力权限主表'!$N$6:$N$108,MATCH($B12,'02_能力权限主表'!$A$6:$A$108,0)) -> 编制基线；全局规则优先 | O12: =INDEX('02_能力权限主表'!$P$6:$P$108,MATCH($B12,'02_能力权限主表'!$A$6:$A$108,0)) -> R4§九 L312–355；B3§三 L65–128
A13: M02 事件与监听 | B13: C014 | C13: =INDEX('02_能力权限主表'!$B$6:$B$108,MATCH($B13,'02_能力权限主表'!$A$6:$A$108,0)) -> 蓄势／蓄势中断（停用） | D13: =INDEX('02_能力权限主表'!$C$6:$C$108,MATCH($B13,'02_能力权限主表'!$A$6:$A$108,0)) -> 停用 | E13: =INDEX('02_能力权限主表'!$D$6:$D$108,MATCH($B13,'02_能力权限主表'!$A$6:$A$108,0)) -> 停用 | F13: =INDEX('02_能力权限主表'!$E$6:$E$108,MATCH($B13,'02_能力权限主表'!$A$6:$A$108,0)) -> 停用 | G13: =INDEX('02_能力权限主表'!$F$6:$F$108,MATCH($B13,'02_能力权限主表'!$A$6:$A$108,0)) -> 停用 | H13: =INDEX('02_能力权限主表'!$G$6:$G$108,MATCH($B13,'02_能力权限主表'!$A$6:$A$108,0)) -> 停用 | I13: =INDEX('02_能力权限主表'!$H$6:$H$108,MATCH($B13,'02_能力权限主表'!$A$6:$A$108,0)) -> 停用 | J13: =INDEX('02_能力权限主表'!$I$6:$I$108,MATCH($B13,'02_能力权限主表'!$A$6:$A$108,0)) -> 停用 | K13: =INDEX('02_能力权限主表'!$J$6:$J$108,MATCH($B13,'02_能力权限主表'!$A$6:$A$108,0)) -> 停用 | L13: =INDEX('02_能力权限主表'!$L$6:$L$108,MATCH($B13,'02_能力权限主表'!$A$6:$A$108,0)) -> 用户已全局去除。三批旧词只在原文追溯，不可作为任何品级候选。 | M13: =INDEX('02_能力权限主表'!$M$6:$M$108,MATCH($B13,'02_能力权限主表'!$A$6:$A$108,0)) -> 不开放；恢复须另有明确新决定 | N13: =INDEX('02_能力权限主表'!$N$6:$N$108,MATCH($B13,'02_能力权限主表'!$A$6:$A$108,0)) -> 既有定案：停用 | O13: =INDEX('02_能力权限主表'!$P$6:$P$108,MATCH($B13,'02_能力权限主表'!$A$6:$A$108,0)) -> 核心01§1.8；t01-01 T01-D03
A14: M02 事件与监听 | B14: C016 | C14: =INDEX('02_能力权限主表'!$B$6:$B$108,MATCH($B14,'02_能力权限主表'!$A$6:$A$108,0)) -> 使用自身命中／受击的直接特效 | D14: =INDEX('02_能力权限主表'!$C$6:$C$108,MATCH($B14,'02_能力权限主表'!$A$6:$A$108,0)) -> 凡品 | E14: =INDEX('02_能力权限主表'!$D$6:$D$108,MATCH($B14,'02_能力权限主表'!$A$6:$A$108,0)) -> — | F14: =INDEX('02_能力权限主表'!$E$6:$E$108,MATCH($B14,'02_能力权限主表'!$A$6:$A$108,0)) -> ○ | G14: =INDEX('02_能力权限主表'!$F$6:$F$108,MATCH($B14,'02_能力权限主表'!$A$6:$A$108,0)) -> ◎ | H14: =INDEX('02_能力权限主表'!$G$6:$G$108,MATCH($B14,'02_能力权限主表'!$A$6:$A$108,0)) -> ◎ | I14: =INDEX('02_能力权限主表'!$H$6:$H$108,MATCH($B14,'02_能力权限主表'!$A$6:$A$108,0)) -> ◎ | J14: =INDEX('02_能力权限主表'!$I$6:$I$108,MATCH($B14,'02_能力权限主表'!$A$6:$A$108,0)) -> ◎ | K14: =INDEX('02_能力权限主表'!$J$6:$J$108,MATCH($B14,'02_能力权限主表'!$A$6:$A$108,0)) -> 专案 | L14: =INDEX('02_能力权限主表'!$L$6:$L$108,MATCH($B14,'02_能力权限主表'!$A$6:$A$108,0)) -> 凡品为直接单一效果；复杂监听与反向反馈按更高机制项。 | M14: =INDEX('02_能力权限主表'!$M$6:$M$108,MATCH($B14,'02_能力权限主表'!$A$6:$A$108,0)) -> 按具体资产填写参数 | N14: =INDEX('02_能力权限主表'!$N$6:$N$108,MATCH($B14,'02_能力权限主表'!$A$6:$A$108,0)) -> 编制基线；全局规则优先 | O14: =INDEX('02_能力权限主表'!$P$6:$P$108,MATCH($B14,'02_能力权限主表'!$A$6:$A$108,0)) -> B3§三 L65–128
A15: M02 事件与监听 | B15: C017 | C15: =INDEX('02_能力权限主表'!$B$6:$B$108,MATCH($B15,'02_能力权限主表'!$A$6:$A$108,0)) -> 监听其他器具或全盘事件 | D15: =INDEX('02_能力权限主表'!$C$6:$C$108,MATCH($B15,'02_能力权限主表'!$A$6:$A$108,0)) -> 良品 | E15: =INDEX('02_能力权限主表'!$D$6:$D$108,MATCH($B15,'02_能力权限主表'!$A$6:$A$108,0)) -> — | F15: =INDEX('02_能力权限主表'!$E$6:$E$108,MATCH($B15,'02_能力权限主表'!$A$6:$A$108,0)) -> — | G15: =INDEX('02_能力权限主表'!$F$6:$F$108,MATCH($B15,'02_能力权限主表'!$A$6:$A$108,0)) -> ◎ | H15: =INDEX('02_能力权限主表'!$G$6:$G$108,MATCH($B15,'02_能力权限主表'!$A$6:$A$108,0)) -> ◎ | I15: =INDEX('02_能力权限主表'!$H$6:$H$108,MATCH($B15,'02_能力权限主表'!$A$6:$A$108,0)) -> ◎ | J15: =INDEX('02_能力权限主表'!$I$6:$I$108,MATCH($B15,'02_能力权限主表'!$A$6:$A$108,0)) -> ◎ | K15: =INDEX('02_能力权限主表'!$J$6:$J$108,MATCH($B15,'02_能力权限主表'!$A$6:$A$108,0)) -> 专案 | L15: =INDEX('02_能力权限主表'!$L$6:$L$108,MATCH($B15,'02_能力权限主表'!$A$6:$A$108,0)) -> 良品一条直观触发链；真实事件只记一次，来源过滤仍合法。 | M15: =INDEX('02_能力权限主表'!$M$6:$M$108,MATCH($B15,'02_能力权限主表'!$A$6:$A$108,0)) -> 按具体资产填写参数 | N15: =INDEX('02_能力权限主表'!$N$6:$N$108,MATCH($B15,'02_能力权限主表'!$A$6:$A$108,0)) -> 编制基线；全局规则优先 | O15: =INDEX('02_能力权限主表'!$P$6:$P$108,MATCH($B15,'02_能力权限主表'!$A$6:$A$108,0)) -> B1§二十八 L821–840；B3§三 L65–128
A16: M02 事件与监听 | B16: C096 | C16: =INDEX('02_能力权限主表'!$B$6:$B$108,MATCH($B16,'02_能力权限主表'!$A$6:$A$108,0)) -> 监听连携成功事件 | D16: =INDEX('02_能力权限主表'!$C$6:$C$108,MATCH($B16,'02_能力权限主表'!$A$6:$A$108,0)) -> 上品 | E16: =INDEX('02_能力权限主表'!$D$6:$D$108,MATCH($B16,'02_能力权限主表'!$A$6:$A$108,0)) -> — | F16: =INDEX('02_能力权限主表'!$E$6:$E$108,MATCH($B16,'02_能力权限主表'!$A$6:$A$108,0)) -> — | G16: =INDEX('02_能力权限主表'!$F$6:$F$108,MATCH($B16,'02_能力权限主表'!$A$6:$A$108,0)) -> △ | H16: =INDEX('02_能力权限主表'!$G$6:$G$108,MATCH($B16,'02_能力权限主表'!$A$6:$A$108,0)) -> ◎ | I16: =INDEX('02_能力权限主表'!$H$6:$H$108,MATCH($B16,'02_能力权限主表'!$A$6:$A$108,0)) -> ◎ | J16: =INDEX('02_能力权限主表'!$I$6:$I$108,MATCH($B16,'02_能力权限主表'!$A$6:$A$108,0)) -> ◎ | K16: =INDEX('02_能力权限主表'!$J$6:$J$108,MATCH($B16,'02_能力权限主表'!$A$6:$A$108,0)) -> 专案 | L16: =INDEX('02_能力权限主表'!$L$6:$L$108,MATCH($B16,'02_能力权限主表'!$A$6:$A$108,0)) -> 只监听实际合法成功事件，不因物品高品级制造成功。 | M16: =INDEX('02_能力权限主表'!$M$6:$M$108,MATCH($B16,'02_能力权限主表'!$A$6:$A$108,0)) -> 按具体资产填写参数 | N16: =INDEX('02_能力权限主表'!$N$6:$N$108,MATCH($B16,'02_能力权限主表'!$A$6:$A$108,0)) -> 编制基线；全局规则优先 | O16: =INDEX('02_能力权限主表'!$P$6:$P$108,MATCH($B16,'02_能力权限主表'!$A$6:$A$108,0)) -> B3§十三 L391–425
A17: M02 事件与监听 | B17: C102 | C17: =INDEX('02_能力权限主表'!$B$6:$B$108,MATCH($B17,'02_能力权限主表'!$A$6:$A$108,0)) -> 简单追击／反击特色 | D17: =INDEX('02_能力权限主表'!$C$6:$C$108,MATCH($B17,'02_能力权限主表'!$A$6:$A$108,0)) -> 良品 | E17: =INDEX('02_能力权限主表'!$D$6:$D$108,MATCH($B17,'02_能力权限主表'!$A$6:$A$108,0)) -> — | F17: =INDEX('02_能力权限主表'!$E$6:$E$108,MATCH($B17,'02_能力权限主表'!$A$6:$A$108,0)) -> — | G17: =INDEX('02_能力权限主表'!$F$6:$F$108,MATCH($B17,'02_能力权限主表'!$A$6:$A$108,0)) -> ○ | H17: =INDEX('02_能力权限主表'!$G$6:$G$108,MATCH($B17,'02_能力权限主表'!$A$6:$A$108,0)) -> ◎ | I17: =INDEX('02_能力权限主表'!$H$6:$H$108,MATCH($B17,'02_能力权限主表'!$A$6:$A$108,0)) -> ◎ | J17: =INDEX('02_能力权限主表'!$I$6:$I$108,MATCH($B17,'02_能力权限主表'!$A$6:$A$108,0)) -> ◎ | K17: =INDEX('02_能力权限主表'!$J$6:$J$108,MATCH($B17,'02_能力权限主表'!$A$6:$A$108,0)) -> 专案 | L17: =INDEX('02_能力权限主表'!$L$6:$L$108,MATCH($B17,'02_能力权限主表'!$A$6:$A$108,0)) -> 基础合法暴击、命中不等于特色追击；良品特色仍服从追击／反击顺序与来源资格，不复制全部伤害包。 | M17: =INDEX('02_能力权限主表'!$M$6:$M$108,MATCH($B17,'02_能力权限主表'!$A$6:$A$108,0)) -> 按具体资产填写参数 | N17: =INDEX('02_能力权限主表'!$N$6:$N$108,MATCH($B17,'02_能力权限主表'!$A$6:$A$108,0)) -> 编制基线；全局规则优先 | O17: =INDEX('02_能力权限主表'!$P$6:$P$108,MATCH($B17,'02_能力权限主表'!$A$6:$A$108,0)) -> B1§三十一 L895–912；核心01§1.4、§3.3
... A169: M10 来源与资格 | B169: C101 | C169: =INDEX('02_能力权限主表'!$B$6:$B$108,MATCH($B169,'02_能力权限主表'!$A$6:$A$108,0)) -> 改变连携节点来源资格 | D169: =INDEX('02_能力权限主表'!$C$6:$C$108,MATCH($B169,'02_能力权限主表'!$A$6:$A$108,0)) -> 玄品 | E169: =INDEX('02_能力权限主表'!$D$6:$D$108,MATCH($B169,'02_能力权限主表'!$A$6:$A$108,0)) -> — | F169: =INDEX('02_能力权限主表'!$E$6:$E$108,MATCH($B169,'02_能力权限主表'!$A$6:$A$108,0)) -> — | G169: =INDEX('02_能力权限主表'!$F$6:$F$108,MATCH($B169,'02_能力权限主表'!$A$6:$A$108,0)) -> — | H169: =INDEX('02_能力权限主表'!$G$6:$G$108,MATCH($B169,'02_能力权限主表'!$A$6:$A$108,0)) -> — | I169: =INDEX('02_能力权限主表'!$H$6:$H$108,MATCH($B169,'02_能力权限主表'!$A$6:$A$108,0)) -> ◇ | J169: =INDEX('02_能力权限主表'!$I$6:$I$108,MATCH($B169,'02_能力权限主表'!$A$6:$A$108,0)) -> ◎ | K169: =INDEX('02_能力权限主表'!$J$6:$J$108,MATCH($B169,'02_能力权限主表'!$A$6:$A$108,0)) -> 专案 | L169: =INDEX('02_能力权限主表'!$L$6:$L$108,MATCH($B169,'02_能力权限主表'!$A$6:$A$108,0)) -> 与数值／窗口辅助分开；若提前系统解锁，另登记全局规则例外。 | M169: =INDEX('02_能力权限主表'!$M$6:$M$108,MATCH($B169,'02_能力权限主表'!$A$6:$A$108,0)) -> 按具体资产填写参数 | N169: =INDEX('02_能力权限主表'!$N$6:$N$108,MATCH($B169,'02_能力权限主表'!$A$6:$A$108,0)) -> 编制基线；全局规则优先 | O169: =INDEX('02_能力权限主表'!$P$6:$P$108,MATCH($B169,'02_能力权限主表'!$A$6:$A$108,0)) -> R4§七 L252–286；B3§十三 L391–425

Sheet 04_状态操作权限
A1: T01-03 | 状态操作权限
A2: 按能力ID引用02主表；排序不改变对应关系。◎核心 ○常规辅助 △有限候选 ◇明确例外 —非常规 ?待专项；仙品看10表。
A3: 返回说明 | B3: 63 条记录 | 表头可筛选 | 依据中的B1／B2／B3／R4／Q01与原行号可回查12表
A5: 状态／操作 | B5: 能力ID | C5: 能力名称 | D5: 常规最低品级 | E5: 下品 | F5: 凡品 | G5: 良品 | H5: 上品 | I5: 灵品 | J5: 玄品 | K5: 仙品 | L5: 权限边界 | M5: 前置／未决 | N5: 规则状态 | O5: 依据
A6: S1 核心状态 | B6: C010 | C6: =INDEX('02_能力权限主表'!$B$6:$B$108,MATCH($B6,'02_能力权限主表'!$A$6:$A$108,0)) -> 元素攻击与额外状态等独立收益组合 | D6: =INDEX('02_能力权限主表'!$C$6:$C$108,MATCH($B6,'02_能力权限主表'!$A$6:$A$108,0)) -> 凡品 | E6: =INDEX('02_能力权限主表'!$D$6:$D$108,MATCH($B6,'02_能力权限主表'!$A$6:$A$108,0)) -> — | F6: =INDEX('02_能力权限主表'!$E$6:$E$108,MATCH($B6,'02_能力权限主表'!$A$6:$A$108,0)) -> ○ | G6: =INDEX('02_能力权限主表'!$F$6:$F$108,MATCH($B6,'02_能力权限主表'!$A$6:$A$108,0)) -> ○ | H6: =INDEX('02_能力权限主表'!$G$6:$G$108,MATCH($B6,'02_能力权限主表'!$A$6:$A$108,0)) -> ◎ | I6: =INDEX('02_能力权限主表'!$H$6:$H$108,MATCH($B6,'02_能力权限主表'!$A$6:$A$108,0)) -> ◎ | J6: =INDEX('02_能力权限主表'!$I$6:$I$108,MATCH($B6,'02_能力权限主表'!$A$6:$A$108,0)) -> ◎ | K6: =INDEX('02_能力权限主表'!$J$6:$J$108,MATCH($B6,'02_能力权限主表'!$A$6:$A$108,0)) -> 专案 | L6: =INDEX('02_能力权限主表'!$L$6:$L$108,MATCH($B6,'02_能力权限主表'!$A$6:$A$108,0)) -> 凡品常规允许固定单元素＋一种简单状态的组合，仍按各状态已定触发门槛与容量；不顺带开放双状态、复杂监听、来源改写或自由功能槽。其他多份独立收益组合仍须审查。 | M6: =INDEX('02_能力权限主表'!$M$6:$M$108,MATCH($B6,'02_能力权限主表'!$A$6:$A$108,0)) -> 按具体资产填写参数 | N6: =INDEX('02_能力权限主表'!$N$6:$N$108,MATCH($B6,'02_能力权限主表'!$A$6:$A$108,0)) -> 本次08覆盖旧“凡品少量候选、良品常规”口径，许可限本行明确范围。 | O6: =INDEX('02_能力权限主表'!$P$6:$P$108,MATCH($B6,'02_能力权限主表'!$A$6:$A$108,0)) -> R4§七历史口径；t01-08凡品第2／3批与用户直接更正、FP02；2026-09-28
A7: S1 核心状态 | B7: C028 | C7: =INDEX('02_能力权限主表'!$B$6:$B$108,MATCH($B7,'02_能力权限主表'!$A$6:$A$108,0)) -> 两个成熟机制实质耦合 | D7: =INDEX('02_能力权限主表'!$C$6:$C$108,MATCH($B7,'02_能力权限主表'!$A$6:$A$108,0)) -> 灵品 | E7: =INDEX('02_能力权限主表'!$D$6:$D$108,MATCH($B7,'02_能力权限主表'!$A$6:$A$108,0)) -> — | F7: =INDEX('02_能力权限主表'!$E$6:$E$108,MATCH($B7,'02_能力权限主表'!$A$6:$A$108,0)) -> — | G7: =INDEX('02_能力权限主表'!$F$6:$F$108,MATCH($B7,'02_能力权限主表'!$A$6:$A$108,0)) -> — | H7: =INDEX('02_能力权限主表'!$G$6:$G$108,MATCH($B7,'02_能力权限主表'!$A$6:$A$108,0)) -> △ | I7: =INDEX('02_能力权限主表'!$H$6:$H$108,MATCH($B7,'02_能力权限主表'!$A$6:$A$108,0)) -> ◎ | J7: =INDEX('02_能力权限主表'!$I$6:$I$108,MATCH($B7,'02_能力权限主表'!$A$6:$A$108,0)) -> ◎ | K7: =INDEX('02_能力权限主表'!$J$6:$J$108,MATCH($B7,'02_能力权限主表'!$A$6:$A$108,0)) -> 专案 | L7: =INDEX('02_能力权限主表'!$L$6:$L$108,MATCH($B7,'02_能力权限主表'!$A$6:$A$108,0)) -> 单向联动、共享取舍、阶段衔接、反馈均可；必须各自具有可管理玩法，不要求A→B→A。上品△仅候选，仍需按两个成熟核心审查。 | M7: =INDEX('02_能力权限主表'!$M$6:$M$108,MATCH($B7,'02_能力权限主表'!$A$6:$A$108,0)) -> 按具体资产填写参数 | N7: =INDEX('02_能力权限主表'!$N$6:$N$108,MATCH($B7,'02_能力权限主表'!$A$6:$A$108,0)) -> 编制基线；全局规则优先 | O7: =INDEX('02_能力权限主表'!$P$6:$P$108,MATCH($B7,'02_能力权限主表'!$A$6:$A$108,0)) -> R4§五 L181–224；B2§十六 L470–491
A8: S1 核心状态 | B8: C038 | C8: =INDEX('02_能力权限主表'!$B$6:$B$108,MATCH($B8,'02_能力权限主表'!$A$6:$A$108,0)) -> S1核心状态施加／增层 | D8: =INDEX('02_能力权限主表'!$C$6:$C$108,MATCH($B8,'02_能力权限主表'!$A$6:$A$108,0)) -> 凡品 | E8: =INDEX('02_能力权限主表'!$D$6:$D$108,MATCH($B8,'02_能力权限主表'!$A$6:$A$108,0)) -> — | F8: =INDEX('02_能力权限主表'!$E$6:$E$108,MATCH($B8,'02_能力权限主表'!$A$6:$A$108,0)) -> ◎ | G8: =INDEX('02_能力权限主表'!$F$6:$F$108,MATCH($B8,'02_能力权限主表'!$A$6:$A$108,0)) -> ◎ | H8: =INDEX('02_能力权限主表'!$G$6:$G$108,MATCH($B8,'02_能力权限主表'!$A$6:$A$108,0)) -> ◎ | I8: =INDEX('02_能力权限主表'!$H$6:$H$108,MATCH($B8,'02_能力权限主表'!$A$6:$A$108,0)) -> ◎ | J8: =INDEX('02_能力权限主表'!$I$6:$I$108,MATCH($B8,'02_能力权限主表'!$A$6:$A$108,0)) -> ◎ | K8: =INDEX('02_能力权限主表'!$J$6:$J$108,MATCH($B8,'02_能力权限主表'!$A$6:$A$108,0)) -> 专案 | L8: =INDEX('02_能力权限主表'!$L$6:$L$108,MATCH($B8,'02_能力权限主表'!$A$6:$A$108,0)) -> Buff按自身；Debuff按施加者，主角辅助归主角、独立怪物读自身。不能照抄B3§六的目标容量旧口径。 | M8: =INDEX('02_能力权限主表'!$M$6:$M$108,MATCH($B8,'02_能力权限主表'!$A$6:$A$108,0)) -> 具体状态、层数、容量来源按资产 | N8: =INDEX('02_能力权限主表'!$N$6:$N$108,MATCH($B8,'02_能力权限主表'!$A$6:$A$108,0)) -> 编制基线；全局规则优先 | O8: =INDEX('02_能力权限主表'!$P$6:$P$108,MATCH($B8,'02_能力权限主表'!$A$6:$A$108,0)) -> B3§五 L153–194；核心01§1.8
A9: S1 核心状态 | B9: C039 | C9: =INDEX('02_能力权限主表'!$B$6:$B$108,MATCH($B9,'02_能力权限主表'!$A$6:$A$108,0)) -> S1有无／简单层数读取 | D9: =INDEX('02_能力权限主表'!$C$6:$C$108,MATCH($B9,'02_能力权限主表'!$A$6:$A$108,0)) -> 良品 | E9: =INDEX('02_能力权限主表'!$D$6:$D$108,MATCH($B9,'02_能力权限主表'!$A$6:$A$108,0)) -> — | F9: =INDEX('02_能力权限主表'!$E$6:$E$108,MATCH($B9,'02_能力权限主表'!$A$6:$A$108,0)) -> — | G9: =INDEX('02_能力权限主表'!$F$6:$F$108,MATCH($B9,'02_能力权限主表'!$A$6:$A$108,0)) -> ◎ | H9: =INDEX('02_能力权限主表'!$G$6:$G$108,MATCH($B9,'02_能力权限主表'!$A$6:$A$108,0)) -> ◎ | I9: =INDEX('02_能力权限主表'!$H$6:$H$108,MATCH($B9,'02_能力权限主表'!$A$6:$A$108,0)) -> ◎ | J9: =INDEX('02_能力权限主表'!$I$6:$I$108,MATCH($B9,'02_能力权限主表'!$A$6:$A$108,0)) -> ◎ | K9: =INDEX('02_能力权限主表'!$J$6:$J$108,MATCH($B9,'02_能力权限主表'!$A$6:$A$108,0)) -> 专案 | L9: =INDEX('02_能力权限主表'!$L$6:$L$108,MATCH($B9,'02_能力权限主表'!$A$6:$A$108,0)) -> 良品有无、简单阈值或少量读层；不等于成熟消费转换。 | M9: =INDEX('02_能力权限主表'!$M$6:$M$108,MATCH($B9,'02_能力权限主表'!$A$6:$A$108,0)) -> 按具体资产填写参数 | N9: =INDEX('02_能力权限主表'!$N$6:$N$108,MATCH($B9,'02_能力权限主表'!$A$6:$A$108,0)) -> 编制基线；全局规则优先 | O9: =INDEX('02_能力权限主表'!$P$6:$P$108,MATCH($B9,'02_能力权限主表'!$A$6:$A$108,0)) -> B1§三十 L865–894；B3§五 L153–194
A10: S1 核心状态 | B10: C040 | C10: =INDEX('02_能力权限主表'!$B$6:$B$108,MATCH($B10,'02_能力权限主表'!$A$6:$A$108,0)) -> S1层数阈值利用 | D10: =INDEX('02_能力权限主表'!$C$6:$C$108,MATCH($B10,'02_能力权限主表'!$A$6:$A$108,0)) -> 良品 | E10: =INDEX('02_能力权限主表'!$D$6:$D$108,MATCH($B10,'02_能力权限主表'!$A$6:$A$108,0)) -> — | F10: =INDEX('02_能力权限主表'!$E$6:$E$108,MATCH($B10,'02_能力权限主表'!$A$6:$A$108,0)) -> — | G10: =INDEX('02_能力权限主表'!$F$6:$F$108,MATCH($B10,'02_能力权限主表'!$A$6:$A$108,0)) -> ○ | H10: =INDEX('02_能力权限主表'!$G$6:$G$108,MATCH($B10,'02_能力权限主表'!$A$6:$A$108,0)) -> ◎ | I10: =INDEX('02_能力权限主表'!$H$6:$H$108,MATCH($B10,'02_能力权限主表'!$A$6:$A$108,0)) -> ◎ | J10: =INDEX('02_能力权限主表'!$I$6:$I$108,MATCH($B10,'02_能力权限主表'!$A$6:$A$108,0)) -> ◎ | K10: =INDEX('02_能力权限主表'!$J$6:$J$108,MATCH($B10,'02_能力权限主表'!$A$6:$A$108,0)) -> 专案 | L10: =INDEX('02_能力权限主表'!$L$6:$L$108,MATCH($B10,'02_能力权限主表'!$A$6:$A$108,0)) -> 读层与耗层分开，按明确快照和新层参与资格。 | M10: =INDEX('02_能力权限主表'!$M$6:$M$108,MATCH($B10,'02_能力权限主表'!$A$6:$A$108,0)) -> 按具体资产填写参数 | N10: =INDEX('02_能力权限主表'!$N$6:$N$108,MATCH($B10,'02_能力权限主表'!$A$6:$A$108,0)) -> 编制基线；全局规则优先 | O10: =INDEX('02_能力权限主表'!$P$6:$P$108,MATCH($B10,'02_能力权限主表'!$A$6:$A$108,0)) -> B3§五 L153–194
A11: S1 核心状态 | B11: C041 | C11: =INDEX('02_能力权限主表'!$B$6:$B$108,MATCH($B11,'02_能力权限主表'!$A$6:$A$108,0)) -> S1公共状态主动消耗兑现 | D11: =INDEX('02_能力权限主表'!$C$6:$C$108,MATCH($B11,'02_能力权限主表'!$A$6:$A$108,0)) -> 上品 | E11: =INDEX('02_能力权限主表'!$D$6:$D$108,MATCH($B11,'02_能力权限主表'!$A$6:$A$108,0)) -> — | F11: =INDEX('02_能力权限主表'!$E$6:$E$108,MATCH($B11,'02_能力权限主表'!$A$6:$A$108,0)) -> — | G11: =INDEX('02_能力权限主表'!$F$6:$F$108,MATCH($B11,'02_能力权限主表'!$A$6:$A$108,0)) -> △ | H11: =INDEX('02_能力权限主表'!$G$6:$G$108,MATCH($B11,'02_能力权限主表'!$A$6:$A$108,0)) -> ◎ | I11: =INDEX('02_能力权限主表'!$H$6:$H$108,MATCH($B11,'02_能力权限主表'!$A$6:$A$108,0)) -> ◎ | J11: =INDEX('02_能力权限主表'!$I$6:$I$108,MATCH($B11,'02_能力权限主表'!$A$6:$A$108,0)) -> ◎ | K11: =INDEX('02_能力权限主表'!$J$6:$J$108,MATCH($B11,'02_能力权限主表'!$A$6:$A$108,0)) -> 专案 | L11: =INDEX('02_能力权限主表'!$L$6:$L$108,MATCH($B11,'02_能力权限主表'!$A$6:$A$108,0)) -> 常规上品；良品只保留具体少量候选，不等于公共状态互转。 | M11: =INDEX('02_能力权限主表'!$M$6:$M$108,MATCH($B11,'02_能力权限主表'!$A$6:$A$108,0)) -> 按具体资产填写参数 | N11: =INDEX('02_能力权限主表'!$N$6:$N$108,MATCH($B11,'02_能力权限主表'!$A$6:$A$108,0)) -> 编制基线；全局规则优先 | O11: =INDEX('02_能力权限主表'!$P$6:$P$108,MATCH($B11,'02_能力权限主表'!$A$6:$A$108,0)) -> B3§五 L153–194；R4§七 L252–286
A12: S1 核心状态 | B12: C042 | C12: =INDEX('02_能力权限主表'!$B$6:$B$108,MATCH($B12,'02_能力权限主表'!$A$6:$A$108,0)) -> 公共状态转换／成熟兑现 | D12: =INDEX('02_能力权限主表'!$C$6:$C$108,MATCH($B12,'02_能力权限主表'!$A$6:$A$108,0)) -> 上品 | E12: =INDEX('02_能力权限主表'!$D$6:$D$108,MATCH($B12,'02_能力权限主表'!$A$6:$A$108,0)) -> — | F12: =INDEX('02_能力权限主表'!$E$6:$E$108,MATCH($B12,'02_能力权限主表'!$A$6:$A$108,0)) -> — | G12: =INDEX('02_能力权限主表'!$F$6:$F$108,MATCH($B12,'02_能力权限主表'!$A$6:$A$108,0)) -> ◇ | H12: =INDEX('02_能力权限主表'!$G$6:$G$108,MATCH($B12,'02_能力权限主表'!$A$6:$A$108,0)) -> ◎ | I12: =INDEX('02_能力权限主表'!$H$6:$H$108,MATCH($B12,'02_能力权限主表'!$A$6:$A$108,0)) -> ◎ | J12: =INDEX('02_能力权限主表'!$I$6:$I$108,MATCH($B12,'02_能力权限主表'!$A$6:$A$108,0)) -> ◎ | K12: =INDEX('02_能力权限主表'!$J$6:$J$108,MATCH($B12,'02_能力权限主表'!$A$6:$A$108,0)) -> 专案 | L12: =INDEX('02_能力权限主表'!$L$6:$L$108,MATCH($B12,'02_能力权限主表'!$A$6:$A$108,0)) -> 常规上品起；明确输入、输出、容量不足与失败处理。良品专属标记消费不授权公共状态互转。 | M12: =INDEX('02_能力权限主表'!$M$6:$M$108,MATCH($B12,'02_能力权限主表'!$A$6:$A$108,0)) -> 按具体资产填写参数 | N12: =INDEX('02_能力权限主表'!$N$6:$N$108,MATCH($B12,'02_能力权限主表'!$A$6:$A$108,0)) -> 编制基线；全局规则优先 | O12: =INDEX('02_能力权限主表'!$P$6:$P$108,MATCH($B12,'02_能力权限主表'!$A$6:$A$108,0)) -> R4§七 L252–286；B2§四 L70–165
A13: S1 核心状态 | B13: C043 | C13: =INDEX('02_能力权限主表'!$B$6:$B$108,MATCH($B13,'02_能力权限主表'!$A$6:$A$108,0)) -> 增加明确的状态容量 | D13: =INDEX('02_能力权限主表'!$C$6:$C$108,MATCH($B13,'02_能力权限主表'!$A$6:$A$108,0)) -> 上品 | E13: =INDEX('02_能力权限主表'!$D$6:$D$108,MATCH($B13,'02_能力权限主表'!$A$6:$A$108,0)) -> — | F13: =INDEX('02_能力权限主表'!$E$6:$E$108,MATCH($B13,'02_能力权限主表'!$A$6:$A$108,0)) -> △ | G13: =INDEX('02_能力权限主表'!$F$6:$F$108,MATCH($B13,'02_能力权限主表'!$A$6:$A$108,0)) -> △ | H13: =INDEX('02_能力权限主表'!$G$6:$G$108,MATCH($B13,'02_能力权限主表'!$A$6:$A$108,0)) -> ○ | I13: =INDEX('02_能力权限主表'!$H$6:$H$108,MATCH($B13,'02_能力权限主表'!$A$6:$A$108,0)) -> ◎ | J13: =INDEX('02_能力权限主表'!$I$6:$I$108,MATCH($B13,'02_能力权限主表'!$A$6:$A$108,0)) -> ◎ | K13: =INDEX('02_能力权限主表'!$J$6:$J$108,MATCH($B13,'02_能力权限主表'!$A$6:$A$108,0)) -> 专案 | L13: =INDEX('02_能力权限主表'!$L$6:$L$108,MATCH($B13,'02_能力权限主表'!$A$6:$A$108,0)) -> 凡品可有少量指定容量来源；容量与共鸣分开。禁用仍装备道具固有加成保留，主角换装下降立即截层。 | M13: =INDEX('02_能力权限主表'!$M$6:$M$108,MATCH($B13,'02_能力权限主表'!$A$6:$A$108,0)) -> 按具体资产填写参数 | N13: =INDEX('02_能力权限主表'!$N$6:$N$108,MATCH($B13,'02_能力权限主表'!$A$6:$A$108,0)) -> 编制基线；全局规则优先 | O13: =INDEX('02_能力权限主表'!$P$6:$P$108,MATCH($B13,'02_能力权限主表'!$A$6:$A$108,0)) -> B3§五 L153–194；核心01§1.8
A14: S1 核心状态 | B14: C044 | C14: =INDEX('02_能力权限主表'!$B$6:$B$108,MATCH($B14,'02_能力权限主表'!$A$6:$A$108,0)) -> 修改具体状态运行规则 | D14: =INDEX('02_能力权限主表'!$C$6:$C$108,MATCH($B14,'02_能力权限主表'!$A$6:$A$108,0)) -> 灵品 | E14: =INDEX('02_能力权限主表'!$D$6:$D$108,MATCH($B14,'02_能力权限主表'!$A$6:$A$108,0)) -> — | F14: =INDEX('02_能力权限主表'!$E$6:$E$108,MATCH($B14,'02_能力权限主表'!$A$6:$A$108,0)) -> — | G14: =INDEX('02_能力权限主表'!$F$6:$F$108,MATCH($B14,'02_能力权限主表'!$A$6:$A$108,0)) -> — | H14: =INDEX('02_能力权限主表'!$G$6:$G$108,MATCH($B14,'02_能力权限主表'!$A$6:$A$108,0)) -> △ | I14: =INDEX('02_能力权限主表'!$H$6:$H$108,MATCH($B14,'02_能力权限主表'!$A$6:$A$108,0)) -> ○ | J14: =INDEX('02_能力权限主表'!$I$6:$I$108,MATCH($B14,'02_能力权限主表'!$A$6:$A$108,0)) -> ◎ | K14: =INDEX('02_能力权限主表'!$J$6:$J$108,MATCH($B14,'02_能力权限主表'!$A$6:$A$108,0)) -> 专案 | L14: =INDEX('02_能力权限主表'!$L$6:$L$108,MATCH($B14,'02_能力权限主表'!$A$6:$A$108,0)) -> 上品候选、灵品可针对具体状态，玄品成熟规则权限；须声明准确修改字段，不自动突破全局规则。 | M14: =INDEX('02_能力权限主表'!$M$6:$M$108,MATCH($B14,'02_能力权限主表'!$A$6:$A$108,0)) -> 按具体资产填写参数 | N14: =INDEX('02_能力权限主表'!$N$6:$N$108,MATCH($B14,'02_能力权限主表'!$A$6:$A$108,0)) -> 编制基线；全局规则优先 | O14: =INDEX('02_能力权限主表'!$P$6:$P$108,MATCH($B14,'02_能力权限主表'!$A$6:$A$108,0)) -> B2§十四 L426–445；B3§五 L153–194
A15: S2 通用战术状态 | B15: C010 | C15: =INDEX('02_能力权限主表'!$B$6:$B$108,MATCH($B15,'02_能力权限主表'!$A$6:$A$108,0)) -> 元素攻击与额外状态等独立收益组合 | D15: =INDEX('02_能力权限主表'!$C$6:$C$108,MATCH($B15,'02_能力权限主表'!$A$6:$A$108,0)) -> 凡品 | E15: =INDEX('02_能力权限主表'!$D$6:$D$108,MATCH($B15,'02_能力权限主表'!$A$6:$A$108,0)) -> — | F15: =INDEX('02_能力权限主表'!$E$6:$E$108,MATCH($B15,'02_能力权限主表'!$A$6:$A$108,0)) -> ○ | G15: =INDEX('02_能力权限主表'!$F$6:$F$108,MATCH($B15,'02_能力权限主表'!$A$6:$A$108,0)) -> ○ | H15: =INDEX('02_能力权限主表'!$G$6:$G$108,MATCH($B15,'02_能力权限主表'!$A$6:$A$108,0)) -> ◎ | I15: =INDEX('02_能力权限主表'!$H$6:$H$108,MATCH($B15,'02_能力权限主表'!$A$6:$A$108,0)) -> ◎ | J15: =INDEX('02_能力权限主表'!$I$6:$I$108,MATCH($B15,'02_能力权限主表'!$A$6:$A$108,0)) -> ◎ | K15: =INDEX('02_能力权限主表'!$J$6:$J$108,MATCH($B15,'02_能力权限主表'!$A$6:$A$108,0)) -> 专案 | L15: =INDEX('02_能力权限主表'!$L$6:$L$108,MATCH($B15,'02_能力权限主表'!$A$6:$A$108,0)) -> 凡品常规允许固定单元素＋一种简单状态的组合，仍按各状态已定触发门槛与容量；不顺带开放双状态、复杂监听、来源改写或自由功能槽。其他多份独立收益组合仍须审查。 | M15: =INDEX('02_能力权限主表'!$M$6:$M$108,MATCH($B15,'02_能力权限主表'!$A$6:$A$108,0)) -> 按具体资产填写参数 | N15: =INDEX('02_能力权限主表'!$N$6:$N$108,MATCH($B15,'02_能力权限主表'!$A$6:$A$108,0)) -> 本次08覆盖旧“凡品少量候选、良品常规”口径，许可限本行明确范围。 | O15: =INDEX('02_能力权限主表'!$P$6:$P$108,MATCH($B15,'02_能力权限主表'!$A$6:$A$108,0)) -> R4§七历史口径；t01-08凡品第2／3批与用户直接更正、FP02；2026-09-28
A16: S2 通用战术状态 | B16: C028 | C16: =INDEX('02_能力权限主表'!$B$6:$B$108,MATCH($B16,'02_能力权限主表'!$A$6:$A$108,0)) -> 两个成熟机制实质耦合 | D16: =INDEX('02_能力权限主表'!$C$6:$C$108,MATCH($B16,'02_能力权限主表'!$A$6:$A$108,0)) -> 灵品 | E16: =INDEX('02_能力权限主表'!$D$6:$D$108,MATCH($B16,'02_能力权限主表'!$A$6:$A$108,0)) -> — | F16: =INDEX('02_能力权限主表'!$E$6:$E$108,MATCH($B16,'02_能力权限主表'!$A$6:$A$108,0)) -> — | G16: =INDEX('02_能力权限主表'!$F$6:$F$108,MATCH($B16,'02_能力权限主表'!$A$6:$A$108,0)) -> — | H16: =INDEX('02_能力权限主表'!$G$6:$G$108,MATCH($B16,'02_能力权限主表'!$A$6:$A$108,0)) -> △ | I16: =INDEX('02_能力权限主表'!$H$6:$H$108,MATCH($B16,'02_能力权限主表'!$A$6:$A$108,0)) -> ◎ | J16: =INDEX('02_能力权限主表'!$I$6:$I$108,MATCH($B16,'02_能力权限主表'!$A$6:$A$108,0)) -> ◎ | K16: =INDEX('02_能力权限主表'!$J$6:$J$108,MATCH($B16,'02_能力权限主表'!$A$6:$A$108,0)) -> 专案 | L16: =INDEX('02_能力权限主表'!$L$6:$L$108,MATCH($B16,'02_能力权限主表'!$A$6:$A$108,0)) -> 单向联动、共享取舍、阶段衔接、反馈均可；必须各自具有可管理玩法，不要求A→B→A。上品△仅候选，仍需按两个成熟核心审查。 | M16: =INDEX('02_能力权限主表'!$M$6:$M$108,MATCH($B16,'02_能力权限主表'!$A$6:$A$108,0)) -> 按具体资产填写参数 | N16: =INDEX('02_能力权限主表'!$N$6:$N$108,MATCH($B16,'02_能力权限主表'!$A$6:$A$108,0)) -> 编制基线；全局规则优先 | O16: =INDEX('02_能力权限主表'!$P$6:$P$108,MATCH($B16,'02_能力权限主表'!$A$6:$A$108,0)) -> R4§五 L181–224；B2§十六 L470–491
A17: S2 通用战术状态 | B17: C042 | C17: =INDEX('02_能力权限主表'!$B$6:$B$108,MATCH($B17,'02_能力权限主表'!$A$6:$A$108,0)) -> 公共状态转换／成熟兑现 | D17: =INDEX('02_能力权限主表'!$C$6:$C$108,MATCH($B17,'02_能力权限主表'!$A$6:$A$108,0)) -> 上品 | E17: =INDEX('02_能力权限主表'!$D$6:$D$108,MATCH($B17,'02_能力权限主表'!$A$6:$A$108,0)) -> — | F17: =INDEX('02_能力权限主表'!$E$6:$E$108,MATCH($B17,'02_能力权限主表'!$A$6:$A$108,0)) -> — | G17: =INDEX('02_能力权限主表'!$F$6:$F$108,MATCH($B17,'02_能力权限主表'!$A$6:$A$108,0)) -> ◇ | H17: =INDEX('02_能力权限主表'!$G$6:$G$108,MATCH($B17,'02_能力权限主表'!$A$6:$A$108,0)) -> ◎ | I17: =INDEX('02_能力权限主表'!$H$6:$H$108,MATCH($B17,'02_能力权限主表'!$A$6:$A$108,0)) -> ◎ | J17: =INDEX('02_能力权限主表'!$I$6:$I$108,MATCH($B17,'02_能力权限主表'!$A$6:$A$108,0)) -> ◎ | K17: =INDEX('02_能力权限主表'!$J$6:$J$108,MATCH($B17,'02_能力权限主表'!$A$6:$A$108,0)) -> 专案 | L17: =INDEX('02_能力权限主表'!$L$6:$L$108,MATCH($B17,'02_能力权限主表'!$A$6:$A$108,0)) -> 常规上品起；明确输入、输出、容量不足与失败处理。良品专属标记消费不授权公共状态互转。 | M17: =INDEX('02_能力权限主表'!$M$6:$M$108,MATCH($B17,'02_能力权限主表'!$A$6:$A$108,0)) -> 按具体资产填写参数 | N17: =INDEX('02_能力权限主表'!$N$6:$N$108,MATCH($B17,'02_能力权限主表'!$A$6:$A$108,0)) -> 编制基线；全局规则优先 | O17: =INDEX('02_能力权限主表'!$P$6:$P$108,MATCH($B17,'02_能力权限主表'!$A$6:$A$108,0)) -> R4§七 L252–286；B2§四 L70–165
... A68: OP17 免疫／抵抗 | B68: C065 | C68: =INDEX('02_能力权限主表'!$B$6:$B$108,MATCH($B68,'02_能力权限主表'!$A$6:$A$108,0)) -> 单一免疫／抵抗 | D68: =INDEX('02_能力权限主表'!$C$6:$C$108,MATCH($B68,'02_能力权限主表'!$A$6:$A$108,0)) -> 良品 | E68: =INDEX('02_能力权限主表'!$D$6:$D$108,MATCH($B68,'02_能力权限主表'!$A$6:$A$108,0)) -> — | F68: =INDEX('02_能力权限主表'!$E$6:$E$108,MATCH($B68,'02_能力权限主表'!$A$6:$A$108,0)) -> △ | G68: =INDEX('02_能力权限主表'!$F$6:$F$108,MATCH($B68,'02_能力权限主表'!$A$6:$A$108,0)) -> ○ | H68: =INDEX('02_能力权限主表'!$G$6:$G$108,MATCH($B68,'02_能力权限主表'!$A$6:$A$108,0)) -> ◎ | I68: =INDEX('02_能力权限主表'!$H$6:$H$108,MATCH($B68,'02_能力权限主表'!$A$6:$A$108,0)) -> ◎ | J68: =INDEX('02_能力权限主表'!$I$6:$I$108,MATCH($B68,'02_能力权限主表'!$A$6:$A$108,0)) -> ◎ | K68: =INDEX('02_能力权限主表'!$J$6:$J$108,MATCH($B68,'02_能力权限主表'!$A$6:$A$108,0)) -> 专案 | L68: =INDEX('02_能力权限主表'!$L$6:$L$108,MATCH($B68,'02_能力权限主表'!$A$6:$A$108,0)) -> 明确是阻止施加、降低成功率、减层还是减时间；不因免疫词自动拥有全部权限。 | M68: =INDEX('02_能力权限主表'!$M$6:$M$108,MATCH($B68,'02_能力权限主表'!$A$6:$A$108,0)) -> 按具体资产填写参数 | N68: =INDEX('02_能力权限主表'!$N$6:$N$108,MATCH($B68,'02_能力权限主表'!$A$6:$A$108,0)) -> 编制基线；全局规则优先 | O68: =INDEX('02_能力权限主表'!$P$6:$P$108,MATCH($B68,'02_能力权限主表'!$A$6:$A$108,0)) -> B3§七 L217–260；t01-02 OP17

Sheet 05_空间时序来源权限
A1: T01-03 | 空间时序来源权限
A2: 按能力ID引用02主表；排序不改变对应关系。◎核心 ○常规辅助 △有限候选 ◇明确例外 —非常规 ?待专项；仙品看10表。
A3: 返回说明 | B3: 55 条记录 | 表头可筛选 | 依据中的B1／B2／B3／R4／Q01与原行号可回查12表
A5: 专项 | B5: 能力ID | C5: 能力名称 | D5: 常规最低品级 | E5: 下品 | F5: 凡品 | G5: 良品 | H5: 上品 | I5: 灵品 | J5: 玄品 | K5: 仙品 | L5: 权限边界 | M5: 前置／未决 | N5: 规则状态 | O5: 依据
A6: 空间 | B6: C027 | C6: =INDEX('02_能力权限主表'!$B$6:$B$108,MATCH($B6,'02_能力权限主表'!$A$6:$A$108,0)) -> 局部共享资源池 | D6: =INDEX('02_能力权限主表'!$C$6:$C$108,MATCH($B6,'02_能力权限主表'!$A$6:$A$108,0)) -> 灵品 | E6: =INDEX('02_能力权限主表'!$D$6:$D$108,MATCH($B6,'02_能力权限主表'!$A$6:$A$108,0)) -> — | F6: =INDEX('02_能力权限主表'!$E$6:$E$108,MATCH($B6,'02_能力权限主表'!$A$6:$A$108,0)) -> — | G6: =INDEX('02_能力权限主表'!$F$6:$F$108,MATCH($B6,'02_能力权限主表'!$A$6:$A$108,0)) -> — | H6: =INDEX('02_能力权限主表'!$G$6:$G$108,MATCH($B6,'02_能力权限主表'!$A$6:$A$108,0)) -> ◇ | I6: =INDEX('02_能力权限主表'!$H$6:$H$108,MATCH($B6,'02_能力权限主表'!$A$6:$A$108,0)) -> ○ | J6: =INDEX('02_能力权限主表'!$I$6:$I$108,MATCH($B6,'02_能力权限主表'!$A$6:$A$108,0)) -> ◎ | K6: =INDEX('02_能力权限主表'!$J$6:$J$108,MATCH($B6,'02_能力权限主表'!$A$6:$A$108,0)) -> 专案 | L6: =INDEX('02_能力权限主表'!$L$6:$L$108,MATCH($B6,'02_能力权限主表'!$A$6:$A$108,0)) -> 灵品常规小而明确的绑定／邻接／同领域共享；上品不默认开放，玄品可做成熟网络。 | M6: =INDEX('02_能力权限主表'!$M$6:$M$108,MATCH($B6,'02_能力权限主表'!$A$6:$A$108,0)) -> 按具体资产填写参数 | N6: =INDEX('02_能力权限主表'!$N$6:$N$108,MATCH($B6,'02_能力权限主表'!$A$6:$A$108,0)) -> 编制基线；全局规则优先 | O6: =INDEX('02_能力权限主表'!$P$6:$P$108,MATCH($B6,'02_能力权限主表'!$A$6:$A$108,0)) -> R4§七 L252–286；B2§十三 L398–425
A7: 空间 | B7: C029 | C7: =INDEX('02_能力权限主表'!$B$6:$B$108,MATCH($B7,'02_能力权限主表'!$A$6:$A$108,0)) -> 自身格／直接目标 | D7: =INDEX('02_能力权限主表'!$C$6:$C$108,MATCH($B7,'02_能力权限主表'!$A$6:$A$108,0)) -> 下品 | E7: =INDEX('02_能力权限主表'!$D$6:$D$108,MATCH($B7,'02_能力权限主表'!$A$6:$A$108,0)) -> ◎ | F7: =INDEX('02_能力权限主表'!$E$6:$E$108,MATCH($B7,'02_能力权限主表'!$A$6:$A$108,0)) -> ◎ | G7: =INDEX('02_能力权限主表'!$F$6:$F$108,MATCH($B7,'02_能力权限主表'!$A$6:$A$108,0)) -> ◎ | H7: =INDEX('02_能力权限主表'!$G$6:$G$108,MATCH($B7,'02_能力权限主表'!$A$6:$A$108,0)) -> ◎ | I7: =INDEX('02_能力权限主表'!$H$6:$H$108,MATCH($B7,'02_能力权限主表'!$A$6:$A$108,0)) -> ◎ | J7: =INDEX('02_能力权限主表'!$I$6:$I$108,MATCH($B7,'02_能力权限主表'!$A$6:$A$108,0)) -> ◎ | K7: =INDEX('02_能力权限主表'!$J$6:$J$108,MATCH($B7,'02_能力权限主表'!$A$6:$A$108,0)) -> 专案 | L7: =INDEX('02_能力权限主表'!$L$6:$L$108,MATCH($B7,'02_能力权限主表'!$A$6:$A$108,0)) -> 目标资格与来源资格分别检查。 | M7: =INDEX('02_能力权限主表'!$M$6:$M$108,MATCH($B7,'02_能力权限主表'!$A$6:$A$108,0)) -> 按具体资产填写参数 | N7: =INDEX('02_能力权限主表'!$N$6:$N$108,MATCH($B7,'02_能力权限主表'!$A$6:$A$108,0)) -> 编制基线；全局规则优先 | O7: =INDEX('02_能力权限主表'!$P$6:$P$108,MATCH($B7,'02_能力权限主表'!$A$6:$A$108,0)) -> B3§九 L293–313
A8: 空间 | B8: C030 | C8: =INDEX('02_能力权限主表'!$B$6:$B$108,MATCH($B8,'02_能力权限主表'!$A$6:$A$108,0)) -> 正交邻接 | D8: =INDEX('02_能力权限主表'!$C$6:$C$108,MATCH($B8,'02_能力权限主表'!$A$6:$A$108,0)) -> 良品 | E8: =INDEX('02_能力权限主表'!$D$6:$D$108,MATCH($B8,'02_能力权限主表'!$A$6:$A$108,0)) -> — | F8: =INDEX('02_能力权限主表'!$E$6:$E$108,MATCH($B8,'02_能力权限主表'!$A$6:$A$108,0)) -> — | G8: =INDEX('02_能力权限主表'!$F$6:$F$108,MATCH($B8,'02_能力权限主表'!$A$6:$A$108,0)) -> ◎ | H8: =INDEX('02_能力权限主表'!$G$6:$G$108,MATCH($B8,'02_能力权限主表'!$A$6:$A$108,0)) -> ◎ | I8: =INDEX('02_能力权限主表'!$H$6:$H$108,MATCH($B8,'02_能力权限主表'!$A$6:$A$108,0)) -> ◎ | J8: =INDEX('02_能力权限主表'!$I$6:$I$108,MATCH($B8,'02_能力权限主表'!$A$6:$A$108,0)) -> ◎ | K8: =INDEX('02_能力权限主表'!$J$6:$J$108,MATCH($B8,'02_能力权限主表'!$A$6:$A$108,0)) -> 专案 | L8: =INDEX('02_能力权限主表'!$L$6:$L$108,MATCH($B8,'02_能力权限主表'!$A$6:$A$108,0)) -> 常规简单邻接仍从良品开放；下品两组与凡品三组具名防具联动例外见本行。固定坐标和尺寸按04，摆盘与战斗不可旋转。 | M8: =INDEX('02_能力权限主表'!$M$6:$M$108,MATCH($B8,'02_能力权限主表'!$A$6:$A$108,0)) -> 按具体资产填写参数 | N8: =INDEX('02_能力权限主表'!$N$6:$N$108,MATCH($B8,'02_能力权限主表'!$A$6:$A$108,0)) -> 下品Q01及本批凡品具名例外；常规门槛未整体下放。 | O8: =INDEX('02_能力权限主表'!$P$6:$P$108,MATCH($B8,'02_能力权限主表'!$A$6:$A$108,0)) -> 原编制基线；t01-08下品Q01及后续品级更正；t01-08凡品第2／3批与用户直接更正、FP02；2026-09-28；2026-09-29用户RV05～RV09；docs/t01-08_朋友反馈核对与逐项处理_2026-09-29.md
A9: 空间 | B9: C031 | C9: =INDEX('02_能力权限主表'!$B$6:$B$108,MATCH($B9,'02_能力权限主表'!$A$6:$A$108,0)) -> 定向邻接 | D9: =INDEX('02_能力权限主表'!$C$6:$C$108,MATCH($B9,'02_能力权限主表'!$A$6:$A$108,0)) -> 良品 | E9: =INDEX('02_能力权限主表'!$D$6:$D$108,MATCH($B9,'02_能力权限主表'!$A$6:$A$108,0)) -> — | F9: =INDEX('02_能力权限主表'!$E$6:$E$108,MATCH($B9,'02_能力权限主表'!$A$6:$A$108,0)) -> — | G9: =INDEX('02_能力权限主表'!$F$6:$F$108,MATCH($B9,'02_能力权限主表'!$A$6:$A$108,0)) -> ○ | H9: =INDEX('02_能力权限主表'!$G$6:$G$108,MATCH($B9,'02_能力权限主表'!$A$6:$A$108,0)) -> ◎ | I9: =INDEX('02_能力权限主表'!$H$6:$H$108,MATCH($B9,'02_能力权限主表'!$A$6:$A$108,0)) -> ◎ | J9: =INDEX('02_能力权限主表'!$I$6:$I$108,MATCH($B9,'02_能力权限主表'!$A$6:$A$108,0)) -> ◎ | K9: =INDEX('02_能力权限主表'!$J$6:$J$108,MATCH($B9,'02_能力权限主表'!$A$6:$A$108,0)) -> 专案 | L9: =INDEX('02_能力权限主表'!$L$6:$L$108,MATCH($B9,'02_能力权限主表'!$A$6:$A$108,0)) -> 按阵盘固定坐标明确方向；不可旋转，不隐含连线网络。 | M9: =INDEX('02_能力权限主表'!$M$6:$M$108,MATCH($B9,'02_能力权限主表'!$A$6:$A$108,0)) -> 按具体资产填写参数 | N9: =INDEX('02_能力权限主表'!$N$6:$N$108,MATCH($B9,'02_能力权限主表'!$A$6:$A$108,0)) -> 编制基线；全局规则优先 | O9: =INDEX('02_能力权限主表'!$P$6:$P$108,MATCH($B9,'02_能力权限主表'!$A$6:$A$108,0)) -> B3§九 L293–313
A10: 空间 | B10: C032 | C10: =INDEX('02_能力权限主表'!$B$6:$B$108,MATCH($B10,'02_能力权限主表'!$A$6:$A$108,0)) -> 边缘／角落／同行／同列 | D10: =INDEX('02_能力权限主表'!$C$6:$C$108,MATCH($B10,'02_能力权限主表'!$A$6:$A$108,0)) -> 良品 | E10: =INDEX('02_能力权限主表'!$D$6:$D$108,MATCH($B10,'02_能力权限主表'!$A$6:$A$108,0)) -> — | F10: =INDEX('02_能力权限主表'!$E$6:$E$108,MATCH($B10,'02_能力权限主表'!$A$6:$A$108,0)) -> — | G10: =INDEX('02_能力权限主表'!$F$6:$F$108,MATCH($B10,'02_能力权限主表'!$A$6:$A$108,0)) -> ○ | H10: =INDEX('02_能力权限主表'!$G$6:$G$108,MATCH($B10,'02_能力权限主表'!$A$6:$A$108,0)) -> ◎ | I10: =INDEX('02_能力权限主表'!$H$6:$H$108,MATCH($B10,'02_能力权限主表'!$A$6:$A$108,0)) -> ◎ | J10: =INDEX('02_能力权限主表'!$I$6:$I$108,MATCH($B10,'02_能力权限主表'!$A$6:$A$108,0)) -> ◎ | K10: =INDEX('02_能力权限主表'!$J$6:$J$108,MATCH($B10,'02_能力权限主表'!$A$6:$A$108,0)) -> 专案 | L10: =INDEX('02_能力权限主表'!$L$6:$L$108,MATCH($B10,'02_能力权限主表'!$A$6:$A$108,0)) -> 只作简单位置条件；动态范围与多锚点另查。 | M10: =INDEX('02_能力权限主表'!$M$6:$M$108,MATCH($B10,'02_能力权限主表'!$A$6:$A$108,0)) -> 按具体资产填写参数 | N10: =INDEX('02_能力权限主表'!$N$6:$N$108,MATCH($B10,'02_能力权限主表'!$A$6:$A$108,0)) -> 编制基线；全局规则优先 | O10: =INDEX('02_能力权限主表'!$P$6:$P$108,MATCH($B10,'02_能力权限主表'!$A$6:$A$108,0)) -> B3§九 L293–313
A11: 空间 | B11: C033 | C11: =INDEX('02_能力权限主表'!$B$6:$B$108,MATCH($B11,'02_能力权限主表'!$A$6:$A$108,0)) -> 距离N格条件 | D11: =INDEX('02_能力权限主表'!$C$6:$C$108,MATCH($B11,'02_能力权限主表'!$A$6:$A$108,0)) -> 上品 | E11: =INDEX('02_能力权限主表'!$D$6:$D$108,MATCH($B11,'02_能力权限主表'!$A$6:$A$108,0)) -> — | F11: =INDEX('02_能力权限主表'!$E$6:$E$108,MATCH($B11,'02_能力权限主表'!$A$6:$A$108,0)) -> — | G11: =INDEX('02_能力权限主表'!$F$6:$F$108,MATCH($B11,'02_能力权限主表'!$A$6:$A$108,0)) -> △ | H11: =INDEX('02_能力权限主表'!$G$6:$G$108,MATCH($B11,'02_能力权限主表'!$A$6:$A$108,0)) -> ◎ | I11: =INDEX('02_能力权限主表'!$H$6:$H$108,MATCH($B11,'02_能力权限主表'!$A$6:$A$108,0)) -> ◎ | J11: =INDEX('02_能力权限主表'!$I$6:$I$108,MATCH($B11,'02_能力权限主表'!$A$6:$A$108,0)) -> ◎ | K11: =INDEX('02_能力权限主表'!$J$6:$J$108,MATCH($B11,'02_能力权限主表'!$A$6:$A$108,0)) -> 专案 | L11: =INDEX('02_能力权限主表'!$L$6:$L$108,MATCH($B11,'02_能力权限主表'!$A$6:$A$108,0)) -> 良品少量简单距离条件；距离度量与纳入单元明确。 | M11: =INDEX('02_能力权限主表'!$M$6:$M$108,MATCH($B11,'02_能力权限主表'!$A$6:$A$108,0)) -> 按具体资产填写参数 | N11: =INDEX('02_能力权限主表'!$N$6:$N$108,MATCH($B11,'02_能力权限主表'!$A$6:$A$108,0)) -> 编制基线；全局规则优先 | O11: =INDEX('02_能力权限主表'!$P$6:$P$108,MATCH($B11,'02_能力权限主表'!$A$6:$A$108,0)) -> B3§九 L293–313
A12: 空间 | B12: C034 | C12: =INDEX('02_能力权限主表'!$B$6:$B$108,MATCH($B12,'02_能力权限主表'!$A$6:$A$108,0)) -> 动态领域 | D12: =INDEX('02_能力权限主表'!$C$6:$C$108,MATCH($B12,'02_能力权限主表'!$A$6:$A$108,0)) -> 上品 | E12: =INDEX('02_能力权限主表'!$D$6:$D$108,MATCH($B12,'02_能力权限主表'!$A$6:$A$108,0)) -> — | F12: =INDEX('02_能力权限主表'!$E$6:$E$108,MATCH($B12,'02_能力权限主表'!$A$6:$A$108,0)) -> — | G12: =INDEX('02_能力权限主表'!$F$6:$F$108,MATCH($B12,'02_能力权限主表'!$A$6:$A$108,0)) -> — | H12: =INDEX('02_能力权限主表'!$G$6:$G$108,MATCH($B12,'02_能力权限主表'!$A$6:$A$108,0)) -> ◎ | I12: =INDEX('02_能力权限主表'!$H$6:$H$108,MATCH($B12,'02_能力权限主表'!$A$6:$A$108,0)) -> ◎ | J12: =INDEX('02_能力权限主表'!$I$6:$I$108,MATCH($B12,'02_能力权限主表'!$A$6:$A$108,0)) -> ◎ | K12: =INDEX('02_能力权限主表'!$J$6:$J$108,MATCH($B12,'02_能力权限主表'!$A$6:$A$108,0)) -> 专案 | L12: =INDEX('02_能力权限主表'!$L$6:$L$108,MATCH($B12,'02_能力权限主表'!$A$6:$A$108,0)) -> 上品通常一个作用核心；动态进入／离开、目标快照由具体资产选择。 | M12: =INDEX('02_能力权限主表'!$M$6:$M$108,MATCH($B12,'02_能力权限主表'!$A$6:$A$108,0)) -> 按具体资产填写参数 | N12: =INDEX('02_能力权限主表'!$N$6:$N$108,MATCH($B12,'02_能力权限主表'!$A$6:$A$108,0)) -> 编制基线；全局规则优先 | O12: =INDEX('02_能力权限主表'!$P$6:$P$108,MATCH($B12,'02_能力权限主表'!$A$6:$A$108,0)) -> B2§五 L166–199；B3§九 L293–313
A13: 空间 | B13: C035 | C13: =INDEX('02_能力权限主表'!$B$6:$B$108,MATCH($B13,'02_能力权限主表'!$A$6:$A$108,0)) -> 依附／绑定关系 | D13: =INDEX('02_能力权限主表'!$C$6:$C$108,MATCH($B13,'02_能力权限主表'!$A$6:$A$108,0)) -> 良品 | E13: =INDEX('02_能力权限主表'!$D$6:$D$108,MATCH($B13,'02_能力权限主表'!$A$6:$A$108,0)) -> — | F13: =INDEX('02_能力权限主表'!$E$6:$E$108,MATCH($B13,'02_能力权限主表'!$A$6:$A$108,0)) -> — | G13: =INDEX('02_能力权限主表'!$F$6:$F$108,MATCH($B13,'02_能力权限主表'!$A$6:$A$108,0)) -> ○ | H13: =INDEX('02_能力权限主表'!$G$6:$G$108,MATCH($B13,'02_能力权限主表'!$A$6:$A$108,0)) -> ◎ | I13: =INDEX('02_能力权限主表'!$H$6:$H$108,MATCH($B13,'02_能力权限主表'!$A$6:$A$108,0)) -> ◎ | J13: =INDEX('02_能力权限主表'!$I$6:$I$108,MATCH($B13,'02_能力权限主表'!$A$6:$A$108,0)) -> ◎ | K13: =INDEX('02_能力权限主表'!$J$6:$J$108,MATCH($B13,'02_能力权限主表'!$A$6:$A$108,0)) -> 专案 | L13: =INDEX('02_能力权限主表'!$L$6:$L$108,MATCH($B13,'02_能力权限主表'!$A$6:$A$108,0)) -> 绑定不赋予免费调用权，不自动转移来源或抵消控制。 | M13: =INDEX('02_能力权限主表'!$M$6:$M$108,MATCH($B13,'02_能力权限主表'!$A$6:$A$108,0)) -> 按具体资产填写参数 | N13: =INDEX('02_能力权限主表'!$N$6:$N$108,MATCH($B13,'02_能力权限主表'!$A$6:$A$108,0)) -> 编制基线；全局规则优先 | O13: =INDEX('02_能力权限主表'!$P$6:$P$108,MATCH($B13,'02_能力权限主表'!$A$6:$A$108,0)) -> B3§九 L293–313
A14: 空间 | B14: C036 | C14: =INDEX('02_能力权限主表'!$B$6:$B$108,MATCH($B14,'02_能力权限主表'!$A$6:$A$108,0)) -> 多器具连续结构／连线／阵眼 | D14: =INDEX('02_能力权限主表'!$C$6:$C$108,MATCH($B14,'02_能力权限主表'!$A$6:$A$108,0)) -> 灵品 | E14: =INDEX('02_能力权限主表'!$D$6:$D$108,MATCH($B14,'02_能力权限主表'!$A$6:$A$108,0)) -> — | F14: =INDEX('02_能力权限主表'!$E$6:$E$108,MATCH($B14,'02_能力权限主表'!$A$6:$A$108,0)) -> — | G14: =INDEX('02_能力权限主表'!$F$6:$F$108,MATCH($B14,'02_能力权限主表'!$A$6:$A$108,0)) -> — | H14: =INDEX('02_能力权限主表'!$G$6:$G$108,MATCH($B14,'02_能力权限主表'!$A$6:$A$108,0)) -> △ | I14: =INDEX('02_能力权限主表'!$H$6:$H$108,MATCH($B14,'02_能力权限主表'!$A$6:$A$108,0)) -> ○ | J14: =INDEX('02_能力权限主表'!$I$6:$I$108,MATCH($B14,'02_能力权限主表'!$A$6:$A$108,0)) -> ◎ | K14: =INDEX('02_能力权限主表'!$J$6:$J$108,MATCH($B14,'02_能力权限主表'!$A$6:$A$108,0)) -> 专案 | L14: =INDEX('02_能力权限主表'!$L$6:$L$108,MATCH($B14,'02_能力权限主表'!$A$6:$A$108,0)) -> 上品仅有限候选，灵品小型关系，玄品成熟阵式；T07具体规则未因此完成。 | M14: =INDEX('02_能力权限主表'!$M$6:$M$108,MATCH($B14,'02_能力权限主表'!$A$6:$A$108,0)) -> 按具体资产填写参数 | N14: =INDEX('02_能力权限主表'!$N$6:$N$108,MATCH($B14,'02_能力权限主表'!$A$6:$A$108,0)) -> 编制基线；全局规则优先 | O14: =INDEX('02_能力权限主表'!$P$6:$P$108,MATCH($B14,'02_能力权限主表'!$A$6:$A$108,0)) -> B3§九 L293–313；B2§二十二 L612–638
A15: 空间 | B15: C037 | C15: =INDEX('02_能力权限主表'!$B$6:$B$108,MATCH($B15,'02_能力权限主表'!$A$6:$A$108,0)) -> 改变空间规则本身 | D15: =INDEX('02_能力权限主表'!$C$6:$C$108,MATCH($B15,'02_能力权限主表'!$A$6:$A$108,0)) -> 玄品 | E15: =INDEX('02_能力权限主表'!$D$6:$D$108,MATCH($B15,'02_能力权限主表'!$A$6:$A$108,0)) -> — | F15: =INDEX('02_能力权限主表'!$E$6:$E$108,MATCH($B15,'02_能力权限主表'!$A$6:$A$108,0)) -> — | G15: =INDEX('02_能力权限主表'!$F$6:$F$108,MATCH($B15,'02_能力权限主表'!$A$6:$A$108,0)) -> — | H15: =INDEX('02_能力权限主表'!$G$6:$G$108,MATCH($B15,'02_能力权限主表'!$A$6:$A$108,0)) -> — | I15: =INDEX('02_能力权限主表'!$H$6:$H$108,MATCH($B15,'02_能力权限主表'!$A$6:$A$108,0)) -> △ | J15: =INDEX('02_能力权限主表'!$I$6:$I$108,MATCH($B15,'02_能力权限主表'!$A$6:$A$108,0)) -> ◎ | K15: =INDEX('02_能力权限主表'!$J$6:$J$108,MATCH($B15,'02_能力权限主表'!$A$6:$A$108,0)) -> 专案 | L15: =INDEX('02_能力权限主表'!$L$6:$L$108,MATCH($B15,'02_能力权限主表'!$A$6:$A$108,0)) -> 必须指明改变的空间判定；已有位置、尺寸、路径规则不被品级名自动覆盖。 | M15: =INDEX('02_能力权限主表'!$M$6:$M$108,MATCH($B15,'02_能力权限主表'!$A$6:$A$108,0)) -> 按具体资产填写参数 | N15: =INDEX('02_能力权限主表'!$N$6:$N$108,MATCH($B15,'02_能力权限主表'!$A$6:$A$108,0)) -> 编制基线；全局规则优先 | O15: =INDEX('02_能力权限主表'!$P$6:$P$108,MATCH($B15,'02_能力权限主表'!$A$6:$A$108,0)) -> B3§九 L293–313
A16: 时序 | B16: C003 | C16: =INDEX('02_能力权限主表'!$B$6:$B$108,MATCH($B16,'02_能力权限主表'!$A$6:$A$108,0)) -> 基础轮转与手动／自动模式 | D16: =INDEX('02_能力权限主表'!$C$6:$C$108,MATCH($B16,'02_能力权限主表'!$A$6:$A$108,0)) -> 下品 | E16: =INDEX('02_能力权限主表'!$D$6:$D$108,MATCH($B16,'02_能力权限主表'!$A$6:$A$108,0)) -> ◎ | F16: =INDEX('02_能力权限主表'!$E$6:$E$108,MATCH($B16,'02_能力权限主表'!$A$6:$A$108,0)) -> ◎ | G16: =INDEX('02_能力权限主表'!$F$6:$F$108,MATCH($B16,'02_能力权限主表'!$A$6:$A$108,0)) -> ◎ | H16: =INDEX('02_能力权限主表'!$G$6:$G$108,MATCH($B16,'02_能力权限主表'!$A$6:$A$108,0)) -> ◎ | I16: =INDEX('02_能力权限主表'!$H$6:$H$108,MATCH($B16,'02_能力权限主表'!$A$6:$A$108,0)) -> ◎ | J16: =INDEX('02_能力权限主表'!$I$6:$I$108,MATCH($B16,'02_能力权限主表'!$A$6:$A$108,0)) -> ◎ | K16: =INDEX('02_能力权限主表'!$J$6:$J$108,MATCH($B16,'02_能力权限主表'!$A$6:$A$108,0)) -> 专案 | L16: =INDEX('02_能力权限主表'!$L$6:$L$108,MATCH($B16,'02_能力权限主表'!$A$6:$A$108,0)) -> 正常发动仍检查目标、资源、控制等；不可用低品级理由省略后台判断。 | M16: =INDEX('02_能力权限主表'!$M$6:$M$108,MATCH($B16,'02_能力权限主表'!$A$6:$A$108,0)) -> 按具体资产填写参数 | N16: =INDEX('02_能力权限主表'!$N$6:$N$108,MATCH($B16,'02_能力权限主表'!$A$6:$A$108,0)) -> 编制基线；全局规则优先 | O16: =INDEX('02_能力权限主表'!$P$6:$P$108,MATCH($B16,'02_能力权限主表'!$A$6:$A$108,0)) -> B3§三 L65–128；核心01§1.4
A17: 时序 | B17: C012 | C17: =INDEX('02_能力权限主表'!$B$6:$B$108,MATCH($B17,'02_能力权限主表'!$A$6:$A$108,0)) -> 待发／预备式 | D17: =INDEX('02_能力权限主表'!$C$6:$C$108,MATCH($B17,'02_能力权限主表'!$A$6:$A$108,0)) -> 良品 | E17: =INDEX('02_能力权限主表'!$D$6:$D$108,MATCH($B17,'02_能力权限主表'!$A$6:$A$108,0)) -> — | F17: =INDEX('02_能力权限主表'!$E$6:$E$108,MATCH($B17,'02_能力权限主表'!$A$6:$A$108,0)) -> △ | G17: =INDEX('02_能力权限主表'!$F$6:$F$108,MATCH($B17,'02_能力权限主表'!$A$6:$A$108,0)) -> ○ | H17: =INDEX('02_能力权限主表'!$G$6:$G$108,MATCH($B17,'02_能力权限主表'!$A$6:$A$108,0)) -> ◎ | I17: =INDEX('02_能力权限主表'!$H$6:$H$108,MATCH($B17,'02_能力权限主表'!$A$6:$A$108,0)) -> ◎ | J17: =INDEX('02_能力权限主表'!$I$6:$I$108,MATCH($B17,'02_能力权限主表'!$A$6:$A$108,0)) -> ◎ | K17: =INDEX('02_能力权限主表'!$J$6:$J$108,MATCH($B17,'02_能力权限主表'!$A$6:$A$108,0)) -> 专案 | L17: =INDEX('02_能力权限主表'!$L$6:$L$108,MATCH($B17,'02_能力权限主表'!$A$6:$A$108,0)) -> 等待资格与支付时点按01；已定冻结／禁用／沉默对旧待发资格的处理继续生效。 | M17: =INDEX('02_能力权限主表'!$M$6:$M$108,MATCH($B17,'02_能力权限主表'!$A$6:$A$108,0)) -> 按具体资产填写参数 | N17: =INDEX('02_能力权限主表'!$N$6:$N$108,MATCH($B17,'02_能力权限主表'!$A$6:$A$108,0)) -> 编制基线；全局规则优先 | O17: =INDEX('02_能力权限主表'!$P$6:$P$108,MATCH($B17,'02_能力权限主表'!$A$6:$A$108,0)) -> B3§三 L65–128；核心01§1.4、§1.8
... A60: 基础 | B60: C004 | C60: =INDEX('02_能力权限主表'!$B$6:$B$108,MATCH($B60,'02_能力权限主表'!$A$6:$A$108,0)) -> 标准事件、叠加与资格检查 | D60: =INDEX('02_能力权限主表'!$C$6:$C$108,MATCH($B60,'02_能力权限主表'!$A$6:$A$108,0)) -> 全品级基础 | E60: =INDEX('02_能力权限主表'!$D$6:$D$108,MATCH($B60,'02_能力权限主表'!$A$6:$A$108,0)) -> 基础 | F60: =INDEX('02_能力权限主表'!$E$6:$E$108,MATCH($B60,'02_能力权限主表'!$A$6:$A$108,0)) -> 基础 | G60: =INDEX('02_能力权限主表'!$F$6:$F$108,MATCH($B60,'02_能力权限主表'!$A$6:$A$108,0)) -> 基础 | H60: =INDEX('02_能力权限主表'!$G$6:$G$108,MATCH($B60,'02_能力权限主表'!$A$6:$A$108,0)) -> 基础 | I60: =INDEX('02_能力权限主表'!$H$6:$H$108,MATCH($B60,'02_能力权限主表'!$A$6:$A$108,0)) -> 基础 | J60: =INDEX('02_能力权限主表'!$I$6:$I$108,MATCH($B60,'02_能力权限主表'!$A$6:$A$108,0)) -> 基础 | K60: =INDEX('02_能力权限主表'!$J$6:$J$108,MATCH($B60,'02_能力权限主表'!$A$6:$A$108,0)) -> 基础 | L60: =INDEX('02_能力权限主表'!$L$6:$L$108,MATCH($B60,'02_能力权限主表'!$A$6:$A$108,0)) -> 所有器具都产生合法事件并遵守基础叠加、去重、暴击与命中规则；不等于带特色监听词条。 | M60: =INDEX('02_能力权限主表'!$M$6:$M$108,MATCH($B60,'02_能力权限主表'!$A$6:$A$108,0)) -> 按具体资产填写参数 | N60: =INDEX('02_能力权限主表'!$N$6:$N$108,MATCH($B60,'02_能力权限主表'!$A$6:$A$108,0)) -> 编制基线；全局规则优先 | O60: =INDEX('02_能力权限主表'!$P$6:$P$108,MATCH($B60,'02_能力权限主表'!$A$6:$A$108,0)) -> R4§九 L312–355；B3§三 L65–128

Sheet 06_复杂度与投入
A1: T01-03 | 复杂度与投入
A2: 编制基线 · 2026-09-26 | 第4份复查优先；用户明确答复与全局定案优先 | 设计资料，未接入游戏
A3: 返回说明 | B3: 37 条记录 | 表头可筛选 | 依据中的B1／B2／B3／R4／Q01与原行号可回查12表
A5: 记录ID | B5: 分类 | C5: 标尺／字段 | D5: 设计要求 | E5: 边界与误区 | F5: 性质 | G5: 依据
A6: CX01 | B6: L复杂度 | C6: L0 基础器具层 | D6: 类别基础攻击、防护、恢复；基本参数差异。 | E6: 不是强度公式；不按模块数量、文字长度或效果行数判级。 | F6: 设计标尺 | G6: B1§三 L129–247；R4§五 L181–224
A7: CX02 | B7: L复杂度 | C7: L1 单一附加性质 | D7: 一个直接、容易理解的属性或特殊效果。 | E7: 不是强度公式；不按模块数量、文字长度或效果行数判级。 | F7: 设计标尺 | G7: B1§三 L129–247；R4§五 L181–224
A8: CX03 | B8: L复杂度 | C8: L2 条件机制层 | D8: 简单监听、计数、状态读层、邻接、追击等特色。 | E8: 不是强度公式；不按模块数量、文字长度或效果行数判级。 | F8: 设计标尺 | G8: B1§三 L129–247；R4§五 L181–224
A9: CX04 | B9: L复杂度 | C9: L3 系统操纵层 | D9: 成熟状态消费／转换、领域、他器CD、控制、恢复防护转换。 | E9: 不是强度公式；不按模块数量、文字长度或效果行数判级。 | F9: 设计标尺 | G9: B1§三 L129–247；R4§五 L181–224
A10: CX05 | B10: L复杂度 | C10: L4 双核心耦合层 | D10: 两个成熟机制各有可管理玩法，一个的运行实质性改变另一个；不要求反馈闭环。 | E10: 不是强度公式；不按模块数量、文字长度或效果行数判级。 | F10: 设计标尺 | G10: B1§三 L129–247；R4§五 L181–224
A11: CX06 | B11: L复杂度 | C11: L5 规则改写层 | D11: 限定范围内改变发动、来源、主动／派生身份、连携合法性或成熟阵式规则。数值／窗口辅助另分级。 | E11: 不是强度公式；不按模块数量、文字长度或效果行数判级。 | F11: 设计标尺 | G11: B1§三 L129–247；R4§五 L181–224
A12: CX07 | B12: G判断维度 | C12: G1 机制深度 | D12: 判断与兑现经过几层？ | E12: 同时看实际收益、操作负担、投入和取得条件；选择多不保证价值高。 | F12: 设计标尺 | G12: B1§二 L96–128；R4§六 L225–251
A13: CX08 | B13: G判断维度 | C13: G2 系统跨度 | D13: 连接几个系统、各自是否有独立玩法？ | E13: 同时看实际收益、操作负担、投入和取得条件；选择多不保证价值高。 | F13: 设计标尺 | G13: B1§二 L96–128；R4§六 L225–251
A14: CX09 | B14: G判断维度 | C14: G3 条件复杂度 | D14: 是否监听事件、计数、状态和空间？ | E14: 同时看实际收益、操作负担、投入和取得条件；选择多不保证价值高。 | F14: 设计标尺 | G14: B1§二 L96–128；R4§六 L225–251
A15: CX10 | B15: G判断维度 | C15: G4 战场影响范围 | D15: 自身、邻接、领域或敌方全盘？ | E15: 同时看实际收益、操作负担、投入和取得条件；选择多不保证价值高。 | F15: 设计标尺 | G15: B1§二 L96–128；R4§六 L225–251
A16: CX11 | B16: G判断维度 | C16: G5 构筑中心度 | D16: 是辅助还是可围绕其组织构筑？ | E16: 同时看实际收益、操作负担、投入和取得条件；选择多不保证价值高。 | F16: 设计标尺 | G16: B1§二 L96–128；R4§六 L225–251
... A42: CX37 | B42: 机制中心 | C42: 基础动作与特色中心 | D42: 基础斩击／恢复不加一个中心；单条3次攻击→触发即使调用多个M模块仍可只有一个中心。 | E42: 两条独立数值加成不是两个成熟机制；L4看实质耦合。 | F42: 设计标尺 | G42: B1§五 L266–290～九；R4§五 L181–224

Sheet 07_风险与审核
A1: T01-03 | 风险与审核
A2: 编制基线 · 2026-09-26 | 第4份复查优先；用户明确答复与全局定案优先 | 设计资料，未接入游戏
A3: 返回说明 | B3: 26 条记录 | 表头可筛选 | 依据中的B1／B2／B3／R4／Q01与原行号可回查12表
A5: 检查ID | B5: 分类 | C5: 检查项 | D5: 审查要求 | E5: 边界／所需证据 | F5: 依据
A6: AK01 | B6: 风险标签 | C6: RISK_SOURCE_REWRITE｜来源身份改写 | D6: 枚举获得／保留／不获得的暴击、状态、监听、共鸣、连携资格；检查来源未被抹去。 | E6: 这是审核触发条件，不等于已经发现或禁止该能力。 | F6: B3§十九 L570–598～二十一；R4§十 L356–393
A7: AK02 | B7: 风险标签 | C7: RISK_ACTIVATION_REWRITE｜发动方式改写 | D7: 检查原CD、待发、外部调用、控制、退出模式与已支付费用。 | E7: 这是审核触发条件，不等于已经发现或禁止该能力。 | F7: B3§十九 L570–598～二十一；R4§十 L356–393
A8: AK03 | B8: 风险标签 | C8: RISK_CHAIN_LOOP｜触发循环 | D8: 用真实事件与独立机会检验可终止性；不重复通知、不复制整链，不一刀切吞真实多次机会。 | E8: 这是审核触发条件，不等于已经发现或禁止该能力。 | F8: B3§十九 L570–598～二十一；R4§十 L356–393
A9: AK04 | B9: 风险标签 | C9: RISK_CONTROL_LOCK｜控制长期覆盖 | D9: 按组合后的受控时间、空档、重新施加、解除与抗性检查；单次短不等于组合轻。 | E9: 这是审核触发条件，不等于已经发现或禁止该能力。 | F9: B3§十九 L570–598～二十一；R4§十 L356–393
A10: AK05 | B10: 风险标签 | C10: RISK_RESOURCE_LOOP｜资源反馈与产出 | D10: 净产资源可以成立；查时间／阵位／投入、零时间无限触发、重复收益和绕过支付。 | E10: 这是审核触发条件，不等于已经发现或禁止该能力。 | F10: B3§十九 L570–598～二十一；R4§十 L356–393
A11: AK06 | B11: 风险标签 | C11: RISK_CAPACITY_RULE｜容量与已有层数 | D11: 区分容量主体、变更原因、当前层数与共鸣；主角换装立即截层，禁用保留固有容量。 | E11: 这是审核触发条件，不等于已经发现或禁止该能力。 | F11: B3§十九 L570–598～二十一；R4§十 L356–393
A12: AK07 | B12: 十步流程 | C12: 1 类别与概念投入 | D12: 确认器具类别、基础动作，同时写预期阶段、占格、节奏、费用、范围、材料来源类型。 | E12: 六项粗投入不能全空。 | F12: B3§二十二 L657–673；R4§十 L356–393；R4§十二 L422–446
A13: AK08 | B13: 十步流程 | C13: 2 一句话机制中心 | D13: 写玩家需要理解和管理的核心；分开基础动作与特色机制。 | E13: 区分一个中心、多效果并列与两个成熟核心。 | F13: B3§二十二 L657–673；R4§十 L356–393；R4§十二 L422–446
A14: AK09 | B14: 十步流程 | C14: 3 目标品级与G/L标尺 | D14: 参考品级总纲、L0～L5、G1～G7及同阶段取舍。 | E14: 不以文字长度、数值大小或模块数自动定级。 | F14: B3§二十二 L657–673；R4§十 L356–393；R4§十二 L422–446
A15: AK10 | B15: 十步流程 | C15: 4 M01～M10映射 | D15: 记录使用的能力ID、发动、事件、过滤、积累、目标、效果、时序、成本、叠加、来源。 | E15: 从02主表查，03视图自动引用。 | F15: B3§二十二 L657–673；R4§十 L356–393；R4§十二 L422–446
A16: AK11 | B16: 十步流程 | C16: 5 S与OP映射 | D16: 分别说明生成、读层、消费、转换、控制、清除和规则修改。 | E16: S类不代替目标、范围与清除权限。 | F16: B3§二十二 L657–673；R4§十 L356–393；R4§十二 L422–446
... A32: WING-AK | B32: 仙品专项 | C32: 风雷翅空间与资源回流 | D32: 核对单实例8格、两翼去重、中空点击碰撞、整体移动、CD准确用时2/3、独立时钟和实际灵力收支。 | E32: 不能以大耗灵证明平衡；不得开关白拿削CD／零时间循环；全部游戏验收未运行。 | F32: t01-06第3份审查R3-B；2026-09-27；详见06第10／14表

Sheet 08_例外与待定
A1: T01-03 | 例外与待定
A2: 编制基线 · 2026-09-26 | 第4份复查优先；用户明确答复与全局定案优先 | 设计资料，未接入游戏
A3: 返回说明 | B3: 12 条记录 | 表头可筛选 | 依据中的B1／B2／B3／R4／Q01与原行号可回查12表
A5: 记录ID | B5: 类型 | C5: 事项 | D5: 现有结论／登记内容 | E5: 后续填写范围 | F5: 状态 | G5: 依据
A6: EX01 | B6: 登记字段 | C6: Grade_Exception | D6: 是否越过常规品级权限；TRUE本身不代表已获批准。 | E6: 需填写能力ID、目标品级、理由、限制、确认来源 | F6: 未形成物品实例 | G6: B3§十七 L522–547；R4§十二 L422–446
A7: EX02 | B7: 登记字段 | C7: Global_Rule_Exception | D7: 是否改变已确认全局规则；与品级例外分别审。 | E7: 逐条列出被改规则及适用范围，不能由高品级默认批准 | F7: 未形成物品实例 | G7: R4§十二 L422–446
A8: EX03 | B8: 登记字段 | C8: Exception_Reason／确认依据 | D8: 写为何必要、为何不能使用常规机制、谁何时确认。 | E8: 下品：粗布甲＋布护臂＋布护腿、铁甲＋铁护臂＋铁护腿；凡品：水纹衣＋水纹护臂＋水纹护腿、札甲＋铁护腕＋铁胫甲、雷纹法袍＋雷纹护腕＋雷纹护腿。仅这五组具名基础防具联动，两护具各自正交邻接对应身甲，无Set_ID、无独立CD；RV06～RV09已批准08明确映射的同谱系、同部位跨品级承接，奖励取三件最低品级且只一份；未明配的成员不替代。收益为候选，未实现或平衡验收。 | F8: 五个品级版本的具名例外；同谱系明配成员可混品，参数仍候选 | G8: 2026-09-29用户RV05～RV09；docs/t01-08_朋友反馈核对与逐项处理_2026-09-29.md
A9: EX04 | B9: 登记字段 | C9: 适用对象／时点／次数／费用 | D9: 绑定具体物品或具体阶段，不能跨物品继承例外。 | E9: 明确结束条件、回退及是否影响后续规则 | F9: 模板 | G9: R4§四 L150–180；R4§十二 L422–446
A10: EX05 | B10: 登记字段 | C10: 五层审查结论 | D10: 分别写品级、规则、数值、获取、实现与验证。 | E10: 未完成不得进入正式物品池 | F10: 模板 | G10: R4§十二 L422–446
A11: P01 | B11: 已解决 | C11: 赋予其他武器固定元素的起点 | D11: 用户已选上品常规开放，见能力主表。 | E11: 附加还是替换、持续与费用随具体资产 | F11: 用户已定 | G11: Q01 L3–5
A12: P02 | B12: 已核清 | C12: 炼气对应品级 | D12: 已有正式映射：炼气最高常规良品；复查提及的语音疑点无需重问。 | E12: 仙品新阶段口径与旧实现区分 | F12: 既有记录核清 | G12: 地图储物袋设计 L3–11；R4§八 L287–311
A13: P03 | B13: 随具体资产 | C13: 非仙品自主改换固定配置 | D13: R4增加选择空间维度，但未指定所有此类能力的最低常规品级。 | E13: 主表?保留；开场择相甲仅仙品标杆方向 | F13: 待专项 | G13: R4§二 L38–119；R4§九 L312–355
A14: P04 | B14: 随具体资产 | C14: 良品预留／替代／可变费用 | D14: B3原表“—/△”未收口，不代选成常规许可。 | E14: 主表良品?；先给具体支付方案再审 | F14: 待专项 | G14: B3§三 L65–128
A15: P05 | B15: 随具体资产 | C15: 上品连携窗口辅助 | D15: B3原表“—/△”未收口；保留待审，不等同合法配对改写。 | E15: 主表上品?；灵品○与玄品◎按原专项表 | F15: 待专项 | G15: B3§十三 L391–425；R4§七 L252–286
A16: P06 | B16: 仙品专案 | C16: 开场择相甲细节 | D16: 用户Q05明确本次不设计具体仙甲；最终主元素指定权、原名、初始选项、成长条件、七系覆盖与基础甲值留后续。 | E16: 普通元素聚合继续生效；不得从参考案例自动赋予最终指定权。 | F16: 用户明确延后 | G16: t01-04第3份审查§十／十六；核心01§1.10；Q05明确延后仙甲特殊权限
... A18: WING-EX | B18: 仙品候选／局部空间例外 | C18: 风雷翅固定非连续单实例 | D18: 仅本件：外包6×2，Mask 110011／110011，8实占格，中部可放重甲但不强制；不可旋转。 | E18: CD模式／对象计时器／费用／控制／重复许可／获取成长均待06专项；不进入正式资产池。 | F18: 空间需求明确；运行配置待定 | G18: t01-06第3份审查R3-B；2026-09-27；详见06第10／14表

Sheet 09_概念审查案例
A1: T01-03 | 概念审查案例
A2: 概念审查案例：定位参考、规则、数值、获取、实现和运行分别记录；未进行游戏测试。
A3: 返回说明 | B3: 26 条记录 | 表头可筛选 | 依据中的B1／B2／B3／R4／Q01与原行号可回查12表
A5: 案例ID | B5: 工作名／概念名 | C5: 构思 | D5: 品级适配参考 | E5: 规则完整性 | F5: 数值合理性 | G5: 获取可行性 | H5: 实现状态 | I5: 运行验证 | J5: 修正／待补字段 | K5: 依据
A6: CASE01 | B6: 铁短剑 | C6: 无属性普通斩击 | D6: 下品参考 | E6: HOLD：资产字段未齐 | F6: 待数值审查 | G6: 待获取审查 | H6: 未实现 | I6: 未运行 | J6: 基础类别与参数须填；下品仍有后台命中、CD与费用。 | K6: B3§二十四 L701–718
A7: CASE02 | B7: 霜纹剑／寒霜剑 | C7: 固定水属性攻击＋额外施加寒霜 | D7: 凡品可作为固定水元素＋一种简单寒霜的候选 | E7: HOLD：资产字段未齐 | F7: 待数值审查 | G7: 待获取审查 | H7: 未实现 | I7: 未运行 | J7: 按本次08新口径允许简单组合；完整资产字段、数值和获取仍需各自审查，未实现／未测试。容量按施加者。 | K7: 原R4／B3案例；t01-08凡品第2／3批与用户直接更正、FP02；2026-09-28
A8: CASE03 | B8: 寻隙弓 | C8: 目标有失衡时命中提高 | D8: 良品参考 | E8: HOLD：资产字段未齐 | F8: 待数值审查 | G8: 待获取审查 | H8: 未实现 | I8: 未运行 | J8: 单一状态条件；不重定失衡的既有规则。 | K8: B3§二十四 L701–718
A9: CASE04 | B9: 三击火珠 | C9: 每3次合格火攻发一枚火球 | D9: 良品参考 | E9: HOLD：资产字段未齐 | F9: 待数值审查 | G9: 待获取审查 | H9: 未实现 | I9: 未运行 | J9: 虽映射多个模块，仍可能只有一个中心；派生火球是否计数须明确，不能无限自触发。 | K9: B1§四十 L1146–1213；R4§五 L181–224
A10: CASE05 | B10: 邻接穿刺辅助 | C10: 相邻穿刺武器命中提高 | D10: 良品参考 | E10: HOLD：资产字段未齐 | F10: 待数值审查 | G10: 待获取审查 | H10: 未实现 | I10: 未运行 | J10: 明确正交邻接、增益对象与数值；原＋10%仅举例。 | K10: B1§四十 L1146–1213
A11: CASE06 | B11: 毒蚀条件剑 | C11: 目标有毒蚀时本剑增伤 | D11: 良品参考 | E11: HOLD：资产字段未齐 | F11: 待数值审查 | G11: 待获取审查 | H11: 未实现 | I11: 未运行 | J11: 简单有无读取；原15%是概念例数。 | K11: B2§三十七 L956–1004
A12: CASE07 | B12: 毒蚀兑现器 | C12: 消耗毒蚀造成伤害并生成护盾 | D12: 上品参考 | E12: HOLD：资产字段未齐 | F12: 待数值审查 | G12: 待获取审查 | H12: 未实现 | I12: 未运行 | J12: 输入层数、护盾种类、伤害来源、输出失败与费用待填。 | K12: B2§三十七 L956–1004
A13: CASE08 | B13: 焚痕炉 | C13: 消耗灼烧爆发并回灵 | D13: 上品参考 | E13: HOLD：资产字段未齐 | F13: 待数值审查 | G13: 待获取审查 | H13: 未实现 | I13: 未运行 | J13: 不是已确认爆燃新规则；按独立资产补足消耗与收益。 | K13: B3§二十四 L701–718
A14: CASE09 | B14: 驱散充能器 | C14: 实际拆除增益累计→充能→冻结器具 | D14: 上品或更高参考 | E14: HOLD：资产字段未齐 | F14: 待数值审查 | G14: 待获取审查 | H14: 未实现 | I14: 未运行 | J14: 模块多不自动灵品；消费3点或全部充能、时长与频率不能从例数锁定。 | K14: B1§四十 L1146–1213；B2§三 L46–69
A15: CASE10 | B15: 流焰环／焚天炉 | C15: 充能与灼烧兑现、领域实质联动 | D15: 灵品参考 | E15: HOLD：资产字段未齐 | F15: 待数值审查 | G15: 待获取审查 | H15: 未实现 | I15: 未运行 | J15: 确认两个成熟核心及真实反馈；明确净产量、耗时、受益目标和控制。 | K15: B3§二十四 L701–718；R4§五 L181–224
A16: CASE11 | B16: 领域与CD | C16: 领域发动积累阵势→推进合法目标CD | D16: 灵品候选 | E16: HOLD：资产字段未齐 | F16: 待数值审查 | G16: 待获取审查 | H16: 未实现 | I16: 未运行 | J16: 排除已就绪及带减CD能力目标；核心自身不能默认被推进，检查冻结边界。 | K16: B2§十一 L304–367；R4§十一 L394–421
... A31: CASE26 | B31: 赋予他器固定元素 | C31: 让另一件武器临时获得一种固定元素 | D31: 上品常规权限已定 | E31: HOLD：资产字段未齐 | F31: 待数值审查 | G31: 待获取审查 | H31: 未实现 | I31: 未运行 | J31: 尚未决定附加或替换、持续、费用与命中语义，不能据此生成正式物品。 | K31: Q01 L3–5

Sheet 10_仙品设计对照
A1: T01-03 | 仙品设计对照
A2: 编制基线 · 2026-09-26 | 第4份复查优先；用户明确答复与全局定案优先 | 设计资料，未接入游戏
A3: 返回说明 | B3: 46 条记录 | 表头可筛选 | 依据中的B1／B2／B3／R4／Q01与原行号可回查12表
A5: 记录ID | B5: 分类 | C5: 对照项 | D5: 内容／要求 | E5: 能力边界／非默认项 | F5: 记录性质 | G5: 依据
A6: IM01 | B6: 六项设计对照 | C6: 专属能力 | D6: 一句话说明最特别的本领。 | E6: 单纯更高攻击、护甲、恢复量不足。 | F6: 参考标准 | G6: R4§一 L9–37
A7: IM02 | B7: 六项设计对照 | C7: 战术价值 | D7: 新增了何种选择、组织方式或特殊解法？ | E7: 堆更多普通效果不足。 | F7: 参考标准 | G7: R4§一 L9–37
A8: IM03 | B8: 六项设计对照 | C8: 成长路径 | D8: 修复、培养、事件或试炼如何延续身份？ | E8: 换同名高数值版本不足；提升承载或扩展选择也可成长。 | F8: 参考标准 | G8: R4§一 L9–37
A9: IM04 | B9: 六项设计对照 | C9: 获得身份 | D9: 为何在此地点、剧情或条件下获得？ | E9: 普通商店／普通怪物批量产出不符合常规仙品方向。 | F9: 参考标准 | G9: R4§一 L9–37
A10: IM05 | B10: 六项设计对照 | C10: 能力边界 | D10: 改什么、何时有效、限制是什么？ | E10: 仙品不默认无视全部规则。 | F10: 参考标准 | G10: R4§一 L9–37
A11: IM06 | B11: 六项设计对照 | C11: 同阶段对照 | D11: 对当前可用装备强在哪里、放弃了什么？ | E11: 不要求全场景全面胜出，也不强制扣血反噬。 | F11: 参考标准 | G11: R4§一 L9–37
A12: IM07 | B12: 专案必填 | C12: 代表性能力 | D12: 一句话说明特殊本领。 | E12: 具体数值与资产未定处标待定；本表不是自动批准。 | F12: 档案字段 | G12: R4§四 L150–180
A13: IM08 | B13: 专案必填 | C13: 当前形态 | D13: 列已生效能力和未解锁能力。 | E13: 具体数值与资产未定处标待定；本表不是自动批准。 | F13: 档案字段 | G13: R4§四 L150–180
A14: IM09 | B14: 专案必填 | C14: 阶段数值基准 | D14: 与当前阶段、占格和投入相匹配的装备比较。 | E14: 具体数值与资产未定处标待定；本表不是自动批准。 | F14: 档案字段 | G14: R4§四 L150–180
A15: IM10 | B15: 专案必填 | C15: 特殊权限 | D15: 明确改变哪个参数、判定或操作权限。 | E15: 具体数值与资产未定处标待定；本表不是自动批准。 | F15: 档案字段 | G15: R4§四 L150–180
A16: IM11 | B16: 专案必填 | C16: 不改变的部分 | D16: 逐项排除容易被顺带理解的能力。 | E16: 具体数值与资产未定处标待定；本表不是自动批准。 | F16: 档案字段 | G16: R4§四 L150–180
... A55: IM50 | B55: 风雷翅候选 | C55: 空间行为边界 | D55: 中央可放重甲，不强制也不专限重甲；不自动产生Set或Link。两翼整体移动，中心甲独立。 | E55: 按实占格点击碰撞；器具控制整件不释放占位；未接入游戏。 | F55: 设计需求／未实现 | G55: t01-06第3份审查R3-B；2026-09-27；详见06第10／14表

Sheet 11_复查修正索引
A1: T01-03 | 复查修正索引
A2: 编制基线 · 2026-09-26 | 第4份复查优先；用户明确答复与全局定案优先 | 设计资料，未接入游戏
A3: 返回说明 | B3: 19 条记录 | 表头可筛选 | 依据中的B1／B2／B3／R4／Q01与原行号可回查12表
A5: 修正ID | B5: 复查主题 | C5: 旧说法／缺口 | D5: 现行处理 | E5: 落点 | F5: 处理状态 | G5: 依据
A6: R01 | B6: 仙品标准 | C6: 只写逐件、剧情或成长，缺共同参照。 | D6: 六项对照；专属能力、战术价值、成长、获得身份、边界、同阶段取舍。 | E6: 01／10表 | F6: 已落实编制 | G6: R4§一 L9–37
A7: R02 | B7: 择相甲标杆 | C7: 未将特殊选择权纳入仙品参考。 | D7: 加入玩家战前择相、能力边界、成长候选；工作名与数值仍未定。 | E7: 09／10表 | F7: 已落实编制 | G7: R4§二 L38–119
A8: R03 | B8: 仙品原型 | C8: 仙品容易被理解为玄品多改几条规则。 | D8: 六类候选原型；底层动作可与普通高阶器具共享，不以动作独占定义仙品。 | E8: 10表 | F8: 已落实编制 | G8: R4§三 L120–149
A9: R04 | B9: 仙品统一档案 | C9: 所有矩阵只写逐件，六类物品机械补名额。 | D9: 仙品列引用专案标准，填十项实际字段；不强迫一次性消耗品成为成长器。 | E9: 02～05／10表 | F9: 已落实编制 | G9: R4§四 L150–180
A10: R05 | B10: 灵品与L4 | C10: 要求A→B→A闭环，否则不算灵品。 | D10: 改为两个成熟机制实质耦合；单向联动、共享取舍、阶段衔接、反馈均可。 | E10: 01／02／06／09表 | F10: 已落实编制 | G10: R4§五 L181–224
A11: R06 | B11: 评价维度 | C11: 只有G1～G6；复杂度代替完整价值判断。 | D11: 增G7适应性；同时看收益、操作负担、投入与获取。 | E11: 06／10表 | F11: 已落实编制 | G11: R4§六 L225–251
A12: R07 | B12: 权限交叉 | C12: 状态转换、他器CD、敌器控制等被多张表用“轻”字下放。 | D12: 单一能力主表；上品常规起点。局部共享灵品、成熟阵式玄品；发动及来源改写玄品；连携拆项。 | E12: 02主表／03～05公式视图／13覆盖 | F12: 已落实编制 | G12: R4§七 L252–286
A13: R08 | B13: 使用与获取 | C13: 以投放未定为由不记录境界使用门槛。 | D13: 常规门槛沿已有映射；仙品按阶段；系统解锁与获取另查。旧原型统一仙品门槛尚未调整。 | E13: 01／06／08表 | F13: 已落实编制 | G13: R4§八 L287–311
A14: R09 | B14: 基础与特色／属性 | C14: 基础规则被当特色；高品强迫有元素；固定属性与赋予混行。 | D14: 分别维护后台基础、固定自带、临时赋予、自主选择。高品级仍可无属性。 | E14: 00／02／05／06表 | F14: 已落实编制 | G14: R4§九 L312–355
A15: R10 | B15: 投入与资源风险 | C15: 所有数值／获取最后再考虑，净产出视作漏洞。 | D15: 概念阶段同步六项粗投入；净产出允许，检查耗时、阵位、重复结算、支付与数量补给。 | E15: 06／07／09表 | F15: 已落实编制 | G15: R4§十 L356–393
A16: R11 | B16: 两条错误示例 | C16: 冻结时虚构错过发动；领域加速循环直接PASS。 | D16: 冻结例REWORK；可监听真实解控。CD领域仅候选，排除不合法被推进对象并查冻结限制。 | E16: 09表 | F16: 已落实编制 | G16: R4§十一 L394–421
... A24: Q01 | B24: 对他器临时赋固定元素 | C24: 复查要求拆项但未给常规起点。 | D24: 用户本轮选择：从上品常规开放。具体附加／替换与费用另定。 | E24: 02／05／08表 | F24: 用户已定 | G24: Q01 L3–5

Sheet 12_原文与出处
A1: T01-03 | 原文与出处
A2: 历史原文逐行保留，不覆盖现行规则。原始行号对应docs/sources档案；R4为复查，Q01为本轮用户答复。
A3: 返回说明 | B3: 2068 条记录 | 表头可筛选 | 依据中的B1／B2／B3／R4／Q01与原行号可回查12表
A5: 来源ID | B5: 来源名称 | C5: 原始行号 | D5: 原文／档案信息 | E5: 适用性质
A6: B1 | B6: 第1批原文 | C6: 档案 | D6: 文件：docs/sources/t01-03-品级机制权限矩阵_第1批原文_2026-09-26.txt SHA-256：f535ae9daee1a607030f33f90caa2b7f3cb73562d8d5fb1bc2771d837d932e7d | E6: Q01为本轮用户明确答复；B1～B3为历史讨论，R4优先修订；不直接等于生产配置。
A7: B1 | B7: 第1批原文 | C7: 1 | D7: 好。`t01-03` 这一份我会把它当成**“物品设计的分级宪法”**来做，而不是简单写“下品弱、仙品强”。它必须能约束后面几百件物品，否则前两个词典做得再细，批量设计时还是会逐渐失控。 | E7: 原文保留；现行口径查02主表／11修正索引。
A8: B1 | B8: 第1批原文 | C8: 3 | D8: 我建议这一份分三批完成： | E8: 原文保留；现行口径查02主表／11修正索引。
A9: B1 | B9: 第1批原文 | C9: 5 | D9: > **第1批：品级总纲＋复杂度分层＋下品/凡品/良品** | E9: 原文保留；现行口径查02主表／11修正索引。
A10: B1 | B10: 第1批原文 | C10: 6 | D10: > 第2批：上品/灵品/玄品/仙品 | E10: 原文保留；现行口径查02主表／11修正索引。
A11: B1 | B11: 第1批原文 | C11: 7 | D11: > 第3批：M01～M10、S1～S5完整权限矩阵＋跨品级审查 | E11: 原文保留；现行口径查02主表／11修正索引。
A12: B1 | B12: 第1批原文 | C12: 9 | D12: 这一条先正式做第1批。 | E12: 原文保留；现行口径查02主表／11修正索引。
A13: B1 | B13: 第1批原文 | C13: 11 | D13: # t01-03｜品级机制权限矩阵 | E13: 原文保留；现行口径查02主表／11修正索引。
A14: B1 | B14: 第1批原文 | C14: 12 | D14: ## 第1批：总纲＋复杂度分层＋下品／凡品／良品 v0.9 | E14: 原文保留；现行口径查02主表／11修正索引。
A15: B1 | B15: 第1批原文 | C15: 14 | D15: --- | E15: 原文保留；现行口径查02主表／11修正索引。
A16: B1 | B16: 第1批原文 | C16: 16 | D16: # 一、首先必须把“品级”与另外三件事分开 | E16: 原文保留；现行口径查02主表／11修正索引。
A17: B1 | B17: 第1批原文 | C17: 18 | D17: 否则后面一定会混。 | E17: 原文保留；现行口径查02主表／11修正索引。
A18: B1 | B18: 第1批原文 | C18: 20 | D18: ## 1. 品级 ≠ 境界 | E18: 原文保留；现行口径查02主表／11修正索引。
... A696: B1 | B696: 第1批原文 | C696: 1231 | D696: 这四层会决定整个后期装备体系到底能不能既丰富又不失控。 | E696: 原文保留；现行口径查02主表／11修正索引。
A697: B2 | B697: 第2批原文 | C697: 档案 | D697: 文件：docs/sources/t01-03-品级机制权限矩阵_第2批原文_2026-09-26.txt SHA-256：2508fea9d93658b6c9d9f64cef3b8e08b23b6fc3df19b9939a35f42104d2b0e2 | E697: Q01为本轮用户明确答复；B1～B3为历史讨论，R4优先修订；不直接等于生产配置。
A698: B2 | B698: 第2批原文 | C698: 1 | D698: 好，这一批就把 **上品、灵品、玄品、仙品** 拉开，而且重点不再是“能不能加一个状态”，而是： | E698: 原文保留；现行口径查02主表／11修正索引。
A699: B2 | B699: 第2批原文 | C699: 3 | D699: > **它能在多大程度上成为构筑核心，以及它有没有资格开始修改战斗系统本身。** | E699: 原文保留；现行口径查02主表／11修正索引。
A700: B2 | B700: 第2批原文 | C700: 5 | D700: 我会继续沿用上一批的六层复杂度 L0～L5，不另造新标尺。 | E700: 原文保留；现行口径查02主表／11修正索引。
A701: B2 | B701: 第2批原文 | C701: 7 | D701: # t01-03｜品级机制权限矩阵 | E701: 原文保留；现行口径查02主表／11修正索引。
A702: B2 | B702: 第2批原文 | C702: 8 | D702: ## 第2批：上品／灵品／玄品／仙品 v0.9 | E702: 原文保留；现行口径查02主表／11修正索引。
A703: B2 | B703: 第2批原文 | C703: 10 | D703: --- | E703: 原文保留；现行口径查02主表／11修正索引。
A704: B2 | B704: 第2批原文 | C704: 12 | D704: # 一、先把四个高阶品级的一句话定位锁住 | E704: 原文保留；现行口径查02主表／11修正索引。
A705: B2 | B705: 第2批原文 | C705: 14 | D705: 我建议正式用下面这四句话： | E705: 原文保留；现行口径查02主表／11修正索引。
A706: B2 | B706: 第2批原文 | C706: 16 | D706: | 品级 | 一句话定位 | | E706: 原文保留；现行口径查02主表／11修正索引。
A707: B2 | B707: 第2批原文 | C707: 17 | D707: |---|---| | E707: 原文保留；现行口径查02主表／11修正索引。
A708: B2 | B708: 第2批原文 | C708: 18 | D708: | **上品** | **一个成熟机制足以支撑一套局部构筑。** | | E708: 原文保留；现行口径查02主表／11修正索引。
A709: B2 | B709: 第2批原文 | C709: 19 | D709: | **灵品** | **两个成熟机制真正互相驱动。** | | E709: 原文保留；现行口径查02主表／11修正索引。
... A1270: B2 | B1270: 第2批原文 | C1270: 1031 | D1270: 下一批就是 `t01-03` 最后一批，也是最实用的一批：把 **M01～M10、S1～S5、OP操作、S5控制、空间、CD、来源、Combo等** 全部横向排进七个品级，形成真正可供Codex和以后批量设计物品使用的**完整权限矩阵＋审核流程**。 | E1270: 原文保留；现行口径查02主表／11修正索引。
A1271: B3 | B1271: 第3批原文 | C1271: 档案 | D1271: 文件：docs/sources/t01-03-品级机制权限矩阵_第3批原文_2026-09-26.txt SHA-256：d796f46adcb4970c3436fab877b0560a659ff3d903e184dc22d6635adad65c6f | E1271: Q01为本轮用户明确答复；B1～B3为历史讨论，R4优先修订；不直接等于生产配置。
A1272: B3 | B1272: 第3批原文 | C1272: 1 | D1272: 好。第三批我会把前两批真正压成一套**可执行的设计检查表**。这一批重点不是继续增加机制，而是解决三个问题： | E1272: 原文保留；现行口径查02主表／11修正索引。
A1273: B3 | B1273: 第3批原文 | C1273: 3 | D1273: > **每个品级到底能把 M01～M10 用到多深？** | E1273: 原文保留；现行口径查02主表／11修正索引。
A1274: B3 | B1274: 第3批原文 | C1274: 4 | D1274: > **S1～S5、状态操作、空间/CD/来源/连携分别从哪一级开始成为常规设计？** | E1274: 原文保留；现行口径查02主表／11修正索引。
A1275: B3 | B1275: 第3批原文 | C1275: 5 | D1275: > **以后拿到一件新物品，怎样判断它有没有“越级”、机制堆叠或者偷偷突破已有规则？** | E1275: 原文保留；现行口径查02主表／11修正索引。
A1276: B3 | B1276: 第3批原文 | C1276: 7 | D1276: 同时先修正一个容易误解的地方： | E1276: 原文保留；现行口径查02主表／11修正索引。
A1277: B3 | B1277: 第3批原文 | C1277: 9 | D1277: > **`t01-03`是“品级机制权限矩阵”，不是完整的物品强度分级公式。** | E1277: 原文保留；现行口径查02主表／11修正索引。
A1278: B3 | B1278: 第3批原文 | C1278: 11 | D1278: 它主要管“机制权力和复杂度”。高品级通常也应该有更高的数值/资源价值，但具体攻击、CD、费用、护甲等**数值预算**要等后面的平衡阶段建立。不能仅凭这张表得出“攻击100一定是玄品”或“只有一个效果就不能是高品级”。 | E1278: 原文保留；现行口径查02主表／11修正索引。
A1279: B3 | B1279: 第3批原文 | C1279: 13 | D1279: --- | E1279: 原文保留；现行口径查02主表／11修正索引。
A1280: B3 | B1280: 第3批原文 | C1280: 15 | D1280: # t01-03｜品级机制权限矩阵 | E1280: 原文保留；现行口径查02主表／11修正索引。
A1281: B3 | B1281: 第3批原文 | C1281: 16 | D1281: ## 第3批：完整权限矩阵＋审核流程＋整体终审 v0.9 | E1281: 原文保留；现行口径查02主表／11修正索引。
A1282: B3 | B1282: 第3批原文 | C1282: 18 | D1282: ## 一、先统一矩阵符号 | E1282: 原文保留；现行口径查02主表／11修正索引。
A1283: B3 | B1283: 第3批原文 | C1283: 20 | D1283: 后面的表全部使用同一套含义： | E1283: 原文保留；现行口径查02主表／11修正索引。
... A1789: B3 | B1789: 第3批原文 | C1789: 835 | D1789: 不过 `t01-04` 我会建议先确认一个小问题：是直接做**「材料与打造规则」**，还是先做一个更基础的**「器具类别与规格词典」**（武器类型、防具类型、法器定位、尺寸/占格、基础字段），因为这会决定材料配方表的颗粒度。 | E1789: 原文保留；现行口径查02主表／11修正索引。
A1790: R4 | B1790: 第4份复查原文 | C1790: 档案 | D1790: 文件：docs/sources/t01-03-品级机制权限矩阵_第4份复查原文_2026-09-26.txt SHA-256：f8977b80d59a25c3a77b0c9bf497cdf3569f0f9272a9ff1301e7ff220e269746 | E1790: Q01为本轮用户明确答复；B1～B3为历史讨论，R4优先修订；不直接等于生产配置。
A1791: R4 | B1791: 第4份复查原文 | C1791: 1 | D1791: 你指出了03里一个实质性的缺口：**“仙品逐件设计”只能说明制作方式，不能代替设计标准。**如果没有共同参照，以后我们很容易把“效果很多”“数值特别大”或者“有剧情背景”的物品都叫仙品。 | E1791: 原文保留；现行口径查02主表／11修正索引。
A1792: R4 | B1792: 第4份复查原文 | C1792: 3 | D1792: 你提到的那件**开场可以选择元素属性的甲**，恰好是一个很好的标杆：**它的特殊之处不是更硬，而是把普通装备固定的属性，变成了玩家可以针对战场作出的选择。** | E1792: 原文保留；现行口径查02主表／11修正索引。
A1793: R4 | B1793: 第4份复查原文 | C1793: 5 | D1793: 那件甲的原名，我在目前可检索的记录和参考表里没有核实到。下面先称为**“开场择相甲”——仅作工作名**，不冒认以前的名称。 | E1793: 原文保留；现行口径查02主表／11修正索引。
A1794: R4 | B1794: 第4份复查原文 | C1794: 7 | D1794: 这次我分成两部分：先补齐仙品参考，再审查03三批内容中需要修正的地方。以下新增方案仍是设计建议，不自动当作已经确认的物品配置。 | E1794: 原文保留；现行口径查02主表／11修正索引。
A1795: R4 | B1795: 第4份复查原文 | C1795: 9 | D1795: # 一、仙品应当有明确标准，而不是一个“全部例外”的等级 | E1795: 原文保留；现行口径查02主表／11修正索引。
A1796: R4 | B1796: 第4份复查原文 | C1796: 11 | D1796: 我建议把仙品定位补充为： | E1796: 原文保留；现行口径查02主表／11修正索引。
A1797: R4 | B1797: 第4份复查原文 | C1797: 13 | D1797: > **具有鲜明专属能力、通过特定机缘获得、能够长期成长，并在某个明确领域赋予玩家额外选择或特殊规则权限的器物。** | E1797: 原文保留；现行口径查02主表／11修正索引。
A1798: R4 | B1798: 第4份复查原文 | C1798: 15 | D1798: 这里的关键词是：**某个明确领域**。 | E1798: 原文保留；现行口径查02主表／11修正索引。
A1799: R4 | B1799: 第4份复查原文 | C1799: 17 | D1799: 不是所有领域都最强，也不是每件仙品都要改变半套战斗系统。一件仙品可以只解决一个问题，但解决方式足够独特，值得玩家长期携带和培养。 | E1799: 原文保留；现行口径查02主表／11修正索引。
A1800: R4 | B1800: 第4份复查原文 | C1800: 19 | D1800: ## 仙品的六项设计对照 | E1800: 原文保留；现行口径查02主表／11修正索引。
A1801: R4 | B1801: 第4份复查原文 | C1801: 21 | D1801: | 对照项 | 需要回答的问题 | 不足以单独成为仙品的情况 | | E1801: 原文保留；现行口径查02主表／11修正索引。
A1802: R4 | B1802: 第4份复查原文 | C1802: 22 | D1802: |---|---|---| | E1802: 原文保留；现行口径查02主表／11修正索引。
... A2068: R4 | B2068: 第4份复查原文 | C2068: 481 | D2068: **仙品不需要是一张更长的说明书。它需要的是一个值得获得、值得培养、也值得反复使用的独特本领。** | E2068: 原文保留；现行口径查02主表／11修正索引。
A2069: Q01 | B2069: 用户逐项确认 | C2069: 档案 | D2069: 文件：docs/sources/t01-03-品级机制权限矩阵_逐项确认_2026-09-26.txt SHA-256：d8375ba589e4dbf9f3e3399924a805ed89176ca710362f6be7b0a62af056efda | E2069: Q01为本轮用户明确答复；B1～B3为历史讨论，R4优先修订；不直接等于生产配置。
A2070: Q01 | B2070: 用户逐项确认 | C2070: 1 | D2070: 2026-09-26｜t01-03逐项确认 | E2070: 用户明确答复及边界记录。
A2071: Q01 | B2071: 用户逐项确认 | C2071: 3 | D2071: Q01：让另一件武器临时获得一种固定元素属性，这类能力本次怎样记录？ | E2071: 用户明确答复及边界记录。
A2072: Q01 | B2072: 用户逐项确认 | C2072: 4 | D2072: 用户选择：从上品常规开放。 | E2072: 用户明确答复及边界记录。
A2073: Q01 | B2073: 用户逐项确认 | C2073: 5 | D2073: 记录口径：仅确认常规品级起点；属性附加或替换、持续时间、资源、成功条件仍由具体资产定义。不自动改写攻击来源、主动／派生身份或连携资格。 | E2073: 用户明确答复及边界记录。

Sheet 13_覆盖核对
A1: T01-03 | 覆盖核对
A2: 编制基线 · 2026-09-26 | 第4份复查优先；用户明确答复与全局定案优先 | 设计资料，未接入游戏
A3: 返回说明 | B3: 269 条记录 | 表头可筛选 | 依据中的B1／B2／B3／R4／Q01与原行号可回查12表
A5: 核对ID | B5: 来源ID | C5: 原位置 | D5: 章节／原矩阵行 | E5: 现行落点／能力ID | F5: 处理口径 | G5: 依据
A6: B1-S01 | B6: B1 | C6: §一 L16 | D6: 首先必须把“品级”与另外三件事分开 | E6: 00_使用说明 | F6: 已归入现行主题；冲突按11表修正，原文保留。 | G6: B1§一 L16–95
A7: B1-S02 | B7: B1 | C7: §二 L96 | D7: 品级究竟衡量什么？ | E7: 06_复杂度与投入 | F7: 已归入现行主题；冲突按11表修正，原文保留。 | G7: B1§二 L96–128
A8: B1-S03 | B8: B1 | C8: §三 L129 | D8: 建立六层“机制复杂度” | E8: 06_复杂度与投入 | F8: 已归入现行主题；冲突按11表修正，原文保留。 | G8: B1§三 L129–247
A9: B1-S04 | B9: B1 | C9: §四 L248 | D9: 七品级与六层复杂度的总体映射 | E9: 01_品级总纲 | F9: 已归入现行主题；冲突按11表修正，原文保留。 | G9: B1§四 L248–265
A10: B1-S05 | B10: B1 | C10: §五 L266 | D10: “主要复杂度层”不是硬性的模块禁用表 | E10: 06_复杂度与投入 | F10: 已归入现行主题；冲突按11表修正，原文保留。 | G10: B1§五 L266–290
A11: B1-S06 | B11: B1 | C11: §六 L295 | D11: 什么叫“机制中心” | E11: 06_复杂度与投入 | F11: 已归入现行主题；冲突按11表修正，原文保留。 | G11: B1§六 L295–340
A12: B1-S07 | B12: B1 | C12: §七 L341 | D12: 基础动作不计入“机制中心” | E12: 06_复杂度与投入 | F12: 已归入现行主题；冲突按11表修正，原文保留。 | G12: B1§七 L341–370
A13: B1-S08 | B13: B1 | C13: §八 L371 | D13: 数值差异不自动产生机制中心 | E13: 06_复杂度与投入 | F13: 已归入现行主题；冲突按11表修正，原文保留。 | G13: B1§八 L371–398
A14: B1-S09 | B14: B1 | C14: §九 L399 | D14: 品级越高，不等于效果条数必须越多 | E14: 06_复杂度与投入 | F14: 已归入现行主题；冲突按11表修正，原文保留。 | G14: B1§九 L399–422
A15: B1-S10 | B15: B1 | C15: §十 L423 | D15: 品级权限是“上限”，不是“必须全部使用” | E15: 00_使用说明 | F15: 已归入现行主题；冲突按11表修正，原文保留。 | G15: B1§十 L423–442
A16: B1-S11 | B16: B1 | C16: §十一 L443 | D16: 先正式设计【下品】 | E16: 01_品级总纲 | F16: 已归入现行主题；冲突按11表修正，原文保留。 | G16: B1§十一 L443–466
... A274: MX150 | B274: B3 | C274: §十三 L404 | D274: 改变节点来源资格｜原符号：— / — / ◇ / ◎ | E274: C101 改变连携节点来源资格 | F274: 原符号只作历史；现行符号从相同能力ID读取。 | G274: B3 L404
