Workbook

Sheet 使用说明
A1: 《口袋修仙》有效物品效果清单
A2: 当前 Demo 0.1.4 SDK 中 effectList 非空的 1691 件公开物品；一个工作簿内含主清单、逐条效果明细和统计汇总。
A4: 数据版本 | B4: 0.1.4
A5: 生成时间 | B5: 2026-09-24 22:30:03
A6: 物品数量 | B6: 1691
A7: 筛选规则 | B7: 只收录 effectList 非空的物品；空效果的材料、配方、储物袋等未纳入。
A8: 来源文件 | B8: D:\SteamLibrary\steamapps\common\口袋修仙 Demo\ModSDK\reference\domains\items\base-item-public-catalog.json
A9: 来源 SHA-256 | B9: bc235fc8b3753e4e656ab89731336b73107b5b4802e07cd41aa86b6f07a7b2ea
A10: 主清单 | B10: 一行一件物品，适合按 ID、类别、品阶、元素、效果类型和摘要筛选。
A11: 效果明细 | B11: 一行一条基础效果或一条功法成长层效果；保留对应 JSON，便于核对精确字段。
A12: 统计汇总 | B12: 类别、品阶、元素和效果类型的数量统计；打开 Excel 后自动重算公式。
A13: 字段说明 | B13: 品阶保留 SDK 原始代码，避免对未在文档中明确公布的中文名称进行猜译。
A14: 注意 | B14: 这是 SDK 对外公开目录，不代表游戏内部未公开/未发布内容。

Sheet 物品清单
A1: 序号 | B1: 物品ID | C1: 名称 | D1: 类别 | E1: 类别代码 | F1: 品阶代码 | G1: 元素 | H1: 元素代码 | I1: 尺寸 | J1: 占格数 | K1: 价格 | L1: 可获得 | M1: 获取渠道 | N1: 效果数 | O1: 效果类型 | P1: 效果类型代码 | Q1: 效果摘要 | R1: 标签 | S1: 物品描述 | T1: 图标名 | U1: 覆写策略
A2: 1 | B2: 100001 | C2: 炼体术 | D2: 功法 | E2: scripture | F2: common | G2: 无 | H2: none | I2: 1×1 | J2: 1 | K2: 35 | L2: 是 | M2: bazaar | N2: 2 | O2: 被动效果；功法成长 | P2: passive；scriptureProgression | Q2: 被动效果：每消耗 1 点体力，获得 1 点修为 | 功法成长：第1层（无）：每消耗 1 点体力，获得 1 点修为 | 第2层（修为≥120）：每消耗 1 点体力，获得 2 点修为 | 第3层（修为≥760；境界≥炼气4层）：每消耗 1 点体力，获得 3 点修为 | 第4层（修为≥2450；境界≥炼气4层）：每消耗 1 点体力，获得 4 点修为 | S2: 麻绳束起的旧竹简外覆符纹封皮，字迹不尚玄奥，却处处透着打熬筋骨的笨功夫。 | T2: scripture_bound_bamboo_scroll_1x1 | U2: onboardingProtected
A3: 2 | B3: 100002 | C3: 云字养气册 | D3: 功法 | E3: scripture | F3: common | G3: 木 | H3: wood | I3: 1×1 | J3: 1 | K3: 35 | L3: 是 | M3: bazaar | N3: 2 | O3: 条件触发；功法成长 | P3: triggered；scriptureProgression | Q3: 条件触发：每获得 1 点气血，获得 3 点修为 | 功法成长：第1层（无）：每获得 1 点气血，获得 3 点修为 | 第2层（修为≥210）：每获得 1 点气血，获得 6 点修为 | 第3层（修为≥540）：每获得 1 点气血，获得 9 点修为 | 第4层（修为≥2950）：每获得 1 点气血，获得 12 点修为 | S3: 青润玉简卷筒上云纹鎏金细密，展开时清气如云字舒卷，像宗门内门才许借阅的养气灵简。 | T3: scripture_cloudseal_manual_1x1 | U3: allowed
A4: 3 | B4: 100003 | C4: 聚气册 | D4: 功法 | E4: scripture | F4: common | G4: 火 | H4: fire | I4: 1×1 | J4: 1 | K4: 35 | L4: 是 | M4: bazaar | N4: 3 | O4: 周期触发；条件触发；功法成长 | P4: periodicPulse；triggered；scriptureProgression | Q4: 周期触发：获得 10 点修为 | 条件触发：每当有丹药耗尽时，获得 10 点修为 | 功法成长：第1层（无）：获得 10 点修为；每当有丹药耗尽时，获得 10 点修为 | 第2层（修为≥210）：获得 25 点修为；每当有丹药耗尽时，获得 20 点修为 | 第3层（修为≥760）：获得 40 点修为；每当有丹药耗尽时，获得 30 点修为 | S4: 厚册封面云纹回旋，纸页间藏着温和灵息，读来像把散乱真气一圈圈收回丹田。 | T4: scripture_qi_growth_manual_1x1 | U4: allowed
A5: 4 | B5: 100004 | C5: 月痕养息册 | D5: 功法 | E5: scripture | F5: common | G5: 无 | H5: none | I5: 1×2 | J5: 2 | K5: 35 | L5: 是 | M5: bazaar | N5: 3 | O5: 条件触发；被动效果；功法成长 | P5: triggered；passive；scriptureProgression | Q5: 条件触发：每获得 1 点法力，获得 1 点修为 | 被动效果：法力上限 +10 | 功法成长：第1层（无）：每获得 1 点法力，获得 1 点修为；法力上限 +10 | 第2层（修为≥150）：每获得 1 点法力，获得 2 点修为；法力上限 +20 | 第3层（修为≥780）：每获得 1 点法力，获得 3 点修为；法力上限 +30 | 第4层（修为≥3800）：每获得 1 点法力，获得 4 点修为；法力上限 +40 | S5: 竖长厚册封着一弯淡月痕，夜色下翻页时清辉入息，最能安顿浮躁心神。 | T5: scripture_moon_mark_codex_1x2 | U5: allowed
A6: 5 | B6: 100010 | C6: 五行入门篇 | D6: 功法 | E6: scripture | F6: common | G6: 无 | H6: none | I6: 1×1 | J6: 1 | K6: 35 | L6: 是 | M6: bazaar | N6: 2 | O6: 被动效果；功法成长 | P6: passive；scriptureProgression | Q6: 被动效果：每消耗 1 点法力，获得 1 点修为 | 功法成长：第1层（无）：每消耗 1 点法力，获得 1 点修为 | 第2层（修为≥140；境界≥炼气4层）：每消耗 1 点法力，获得 2 点修为 | 第3层（修为≥1000）：每消耗 1 点法力，获得 3 点修为 | 第4层（修为≥6000）：每消耗 1 点法力，获得 4 点修为 | S6: 米黄竹简以细绳整齐束起，五色细线隐约贯穿其间，像初入山门时领到的第一册传功简。 | T6: scripture_bound_bamboo_slips_1x1 | U6: allowed
A7: 6 | B7: 100011 | C7: 烈阳诀 | D7: 功法 | E7: scripture | F7: common | G7: 火 | H7: fire | I7: 1×1 | J7: 1 | K7: 35 | L7: 是 | M7: bazaar；beastDrop | N7: 3 | O7: 条件触发；被动效果；功法成长 | P7: triggered；passive；scriptureProgression | Q7: 条件触发：每获得 1 层炎热，获得 2 点修为 | 被动效果：炎热层数上限 +3 | 功法成长：第1层（无）：每获得 1 层炎热，获得 2 点修为；炎热层数上限 +3 | 第2层（修为≥160）：每获得 1 层炎热，获得 4 点修为；炎热层数上限 +6 | 第3层（修为≥840）：每获得 1 层炎热，获得 6 点修为；炎热层数上限 +9 | 第4层（修为≥2900）：每获得 1 层炎热，获得 8 点修为；炎热层数上限 +15 | S7: 卷轴正面日芒灼灼，金纹映得纸面微暖，展开时仿佛晨阳越过云海照进静室。 | T7: scripture_sunflare_scroll_1x1 | U7: allowed
A8: 7 | B8: 100012 | C8: 玄水雷纹诀 | D8: 功法 | E8: scripture | F8: common | G8: 雷 | H8: thunder | I8: 1×1 | J8: 1 | K8: 45 | L8: 是 | M8: bazaar | N8: 3 | O8: 说明/执行器；被动效果；功法成长 | P8: effectNote；passive；scriptureProgression | Q8: 说明/执行器：每获得 1 层引雷，获得 3 点修为 | 被动效果：引雷层数上限 +3 | 功法成长：第1层（无）：每获得 1 层引雷，获得 3 点修为；引雷层数上限 +3 | 第2层（修为≥200）：每获得 1 层引雷，获得 6 点修为；引雷层数上限 +6 | 第3层（修为≥920）：每获得 1 层引雷，获得 9 点修为；引雷层数上限 +9 | 第4层（修为≥1880）：每获得 1 层引雷，获得 12 点修为；引雷层数上限 +12 | R8: early_map_market | S8: 蓝金卷面雷纹与水流缠绕，冰晶碎芒沿卷轴边缘闪没，如深潭之下暗藏远雷。 | T8: scripture_waterthunder_scroll_1x1 | U8: allowed
A9: 8 | B9: 100013 | C9: 纳元印诀 | D9: 功法 | E9: scripture | F9: common | G9: 无 | H9: none | I9: 1×1 | J9: 1 | K9: 35 | L9: 是 | M9: bazaar | N9: 3 | O9: 被动效果；条件触发；功法成长 | P9: passive；triggered；scriptureProgression | Q9: 被动效果：法力上限 +0，任意功法突破后效果升级。；法力上限 | 条件触发：任意招式使用时，获得 10 点修为 | 功法成长：第1层（无）：法力上限 +0，任意功法突破后效果升级。；法力上限；任意招式使用时，获得 10 点修为 | 第2层（修为≥180）：法力上限 +0，任意功法突破后效果升级。；法力上限；任意招式使用时，获得 20 点修为 | 第3层（修为≥800）：法力上限 +0，任意功法突破后效果升级。；法力上限；任意招式使用时，获得 30 点修为 | 第4层（修为≥3500）：法力上限 +0，任意功法突破后效果升级。；法力上限；任意招式使用时，获得 40 点修为 | S9: 方形玉印牌层层收束云纹，印心一点灵光内敛，像把纳元心法压成可随身参悟的印诀。 | T9: implement_jade_tally_slips_1x1 | U9: allowed
A10: 9 | B10: 100014 | C10: 悟道玉简 | D10: 功法 | E10: scripture | F10: common | G10: 无 | H10: none | I10: 1×2 | J10: 2 | K10: 40 | L10: 是 | M10: bazaar | N10: 2 | O10: 条件触发；功法成长 | P10: triggered；scriptureProgression | Q10: 条件触发：每当其他功法累计获得 10 点修为时，本功法获得 1 点修为 | 功法成长：第1层（无）：每当其他功法累计获得 10 点修为时，本功法获得 1 点修为 | 第2层（修为≥190）：每当其他功法累计获得 10 点修为时，本功法获得 2 点修为 | 第3层（修为≥780）：每当其他功法累计获得 10 点修为时，本功法获得 3 点修为 | 第4层（修为≥2100）：每当其他功法累计获得 10 点修为时，本功法获得 4 点修为 | S10: 修长玉简并合成册，温白简面篆痕若隐若现，静置案头便有久经讲席的澄明气韵。 | T10: scripture_jade_slip_codex_f2315v1_1x2 | U10: allowed
A11: 10 | B11: 100015 | C11: 焰纹秘卷 | D11: 功法 | E11: scripture | F11: spirit | G11: 火 | H11: fire | I11: 1×1 | J11: 1 | K11: 70 | L11: 否 | M11: bazaar | N11: 3 | O11: 条件触发；被动效果；功法成长 | P11: triggered；passive；scriptureProgression | Q11: 条件触发：将每 1 层炎热转化为 4 点修为 | 被动效果：炎热层数上限 +6 | 功法成长：第1层（无）：将每 1 层炎热转化为 4 点修为；炎热层数上限 +6 | 第2层（修为≥15400）：将每 1 层炎热转化为 8 点修为；炎热层数上限 +12 | 第3层（修为≥44700）：将每 1 层炎热转化为 12 点修为；炎热层数上限 +18 | 第4层（修为≥52500）：将每 1 层炎热转化为 16 点修为；炎热层数上限 +24 | S11: 卷轴之上燃起赤焰纹路，似封存火行法诀。 | T11: scripture_flamecrest_scroll_1x1 | U11: allowed
A12: 11 | B12: 100016 | C12: 青木引灵简 | D12: 功法 | E12: scripture | F12: common | G12: 木 | H12: wood | I12: 1×1 | J12: 1 | K12: 35 | L12: 是 | M12: bazaar | N12: 3 | O12: 条件触发；被动效果；功法成长 | P12: triggered；passive；scriptureProgression | Q12: 条件触发：每当获得 1 层再生时，获得 2 点修为 | 被动效果：再生层数上限 +3 | 功法成长：第1层（无）：每当获得 1 层再生时，获得 2 点修为；再生层数上限 +3 | 第2层（修为≥95）：每当获得 1 层再生时，获得 4 点修为；再生层数上限 +6 | 第3层（修为≥920）：每当获得 1 层再生时，获得 6 点修为；再生层数上限 +9 | 第4层（修为≥2300）：每当获得 1 层再生时，获得 8 点修为；再生层数上限 +12 | S12: 成册竹简刻有叶纹，专擅引动青木灵息。 | T12: scripture_greenwood_spirit_slips_1x1 | U12: allowed
A13: 12 | B13: 100017 | C13: 寒波调息诀 | D13: 功法 | E13: scripture | F13: common | G13: 水 | H13: water | I13: 1×2 | J13: 2 | K13: 35 | L13: 是 | M13: bazaar | N13: 4 | O13: 说明/执行器；被动效果；功法成长 | P13: effectNote；passive；scriptureProgression | Q13: 说明/执行器：每获得 1 层寒冷或露水，获得 2 点修为 | 被动效果：寒冷层数上限 +5 | 被动效果：露水层数上限 +5 | 功法成长：第1层（无）：每获得 1 层寒冷或露水，获得 2 点修为；寒冷层数上限 +5；露水层数上限 +5 | 第2层（修为≥180）：每获得 1 层寒冷或露水，获得 4 点修为；寒冷层数上限 +10；露水层数上限 +10 | 第3层（修为≥840）：每获得 1 层寒冷或露水，获得 6 点修为；寒冷层数上限 +15；露水层数上限 +15 | 第4层（修为≥2350）：每获得 1 层寒冷或露水，获得 8 点修为；寒冷层数上限 +20；露水层数上限 +20 | S13: 蓝白卷页似有寒波细纹起伏，修行时能借寒意回纳法力。 | T13: scripture_bluejade_slip_1x2 | U13: allowed
A14: 13 | B14: 100018 | C14: 凝金阵诀 | D14: 功法 | E14: scripture | F14: common | G14: 金 | H14: metal | I14: 1×1 | J14: 1 | K14: 35 | L14: 是 | M14: questStoryReward | N14: 3 | O14: 条件触发；被动效果；功法成长 | P14: triggered；passive；scriptureProgression | Q14: 条件触发：每获得 1 层凝金，获得 2 点修为 | 被动效果：凝金层数上限 +3 | 功法成长：第1层（无）：每获得 1 层凝金，获得 2 点修为；凝金层数上限 +3 | 第2层（修为≥160）：每获得 1 层凝金，获得 4 点修为；凝金层数上限 +6 | 第3层（修为≥960）：每获得 1 层凝金，获得 6 点修为；凝金层数上限 +9 | 第4层（修为≥3500）：每获得 1 层凝金，获得 8 点修为；凝金层数上限 +12 | S14: 金纹短卷记着凝金阵列的入门法，需借周遭金气才会稳定运转。 | T14: scripture_crimson_talisman_scroll_1x1 | U14: allowed
A15: 14 | B15: 100020 | C15: 沉息归元诀 | D15: 功法 | E15: scripture | F15: common | G15: 土 | H15: earth | I15: 1×2 | J15: 2 | K15: 35 | L15: 是 | M15: bazaar；beastDrop | N15: 3 | O15: 条件触发；被动效果；功法成长 | P15: triggered；passive；scriptureProgression | Q15: 条件触发：每获得 1 层蓄势，获得 2 点修为 | 被动效果：蓄势层数上限 +3 | 功法成长：第1层（无）：每获得 1 层蓄势，获得 2 点修为；蓄势层数上限 +3 | 第2层（修为≥130）：每获得 1 层蓄势，获得 4 点修为；蓄势层数上限 +6 | 第3层（修为≥1120）：每获得 1 层蓄势，获得 6 点修为；蓄势层数上限 +9 | 第4层（修为≥1900）：每获得 1 层蓄势，获得 8 点修为；蓄势层数上限 +12 | S15: 土色册页沉稳厚重，字里行间像把重压一点点炼回体魄。 | T15: scripture_mountain_warding_stele_1x2 | U15: allowed
A16: 15 | B16: 100022 | C16: 搬山运气诀 | D16: 功法 | E16: scripture | F16: common | G16: 土 | H16: earth | I16: 1×1 | J16: 1 | K16: 35 | L16: 是 | M16: bazaar；beastDrop | N16: 4 | O16: 条件触发；被动效果；功法成长 | P16: triggered；passive；scriptureProgression | Q16: 条件触发：每获得 1 点体力，获得 1 点修为 | 被动效果：蓄势层数上限 +3 | 被动效果：体力上限 +10 | 功法成长：第1层（无）：每获得 1 点体力，获得 1 点修为；蓄势层数上限 +3；体力上限 +10 | 第2层（修为≥190）：每获得 1 点体力，获得 2 点修为；蓄势层数上限 +6；体力上限 +20 | 第3层（修为≥860）：每获得 1 点体力，获得 3 点修为；蓄势层数上限 +9；体力上限 +30 | 第4层（修为≥1940）：每获得 1 点体力，获得 4 点修为；蓄势层数上限 +12；体力上限 +40 | S16: 旧卷上绘着搬山行气的小人图，笔势沉稳，像把筋骨余力一点点转入丹田。 | T16: scripture_bamboo_cloud_scroll_1x1 | U16: allowed
A17: 16 | B17: 100023 | C17: 丹霞养火诀 | D17: 功法 | E17: scripture | F17: common | G17: 火 | H17: fire | I17: 2×2 | J17: 4 | K17: 70 | L17: 是 | M17: questStoryReward | N17: 3 | O17: 说明/执行器；被动效果；功法成长 | P17: effectNote；passive；scriptureProgression | Q17: 说明/执行器：每成功炼制 1 颗丹药，获得 200 点修为 | 被动效果：炼丹成功率 +5% | 功法成长：第1层（无）：每成功炼制 1 颗丹药，获得 200 点修为；炼丹成功率 +5% | 第2层（修为≥2150）：每成功炼制 1 颗丹药，获得 300 点修为；炼丹成功率 +10% | 第3层（修为≥5100）：每成功炼制 1 颗丹药，获得 400 点修为；炼丹成功率 +15% | 第4层（修为≥19100）：每成功炼制 1 颗丹药，获得 500 点修为；炼丹成功率 +20% | S17: 丹霞外院入门功法，重在以细火养息，先稳体力，再引火气入周天。 | T17: scripture_crimson_blaze_scroll_2x2 | U17: allowed
A18: 17 | B18: 100024 | C18: 青阙符旗诀 | D18: 功法 | E18: scripture | F18: common | G18: 土 | H18: earth | I18: 2×2 | J18: 4 | K18: 70 | L18: 是 | M18: questStoryReward | N18: 3 | O18: 条件触发；被动效果；功法成长 | P18: triggered；passive；scriptureProgression | Q18: 条件触发：每消耗 1 层蓄势时，获得 4 点修为 | 被动效果：蓄势层数上限 +15 | 功法成长：第1层（无）：每消耗 1 层蓄势时，获得 4 点修为；蓄势层数上限 +15 | 第2层（修为≥1640）：每消耗 1 层蓄势时，获得 8 点修为；蓄势层数上限 +20 | 第3层（修为≥6200）：每消耗 1 层蓄势时，获得 12 点修为；蓄势层数上限 +25 | 第4层（修为≥17500）：每消耗 1 层蓄势时，获得 16 点修为；蓄势层数上限 +30 | R18: scripture_100024 | S18: 青阙门入门功法，讲究以符意镇息，先立根基，再借阵势行气。 | T18: scripture_jade_hidden_scroll_2x2 | U18: allowed
A19: 18 | B19: 100025 | C19: 水月调息篇 | D19: 功法 | E19: scripture | F19: common | G19: 水 | H19: water | I19: 1×1 | J19: 1 | K19: 70 | L19: 是 | M19: questStoryReward | N19: 3 | O19: 条件触发；被动效果；功法成长 | P19: triggered；passive；scriptureProgression | Q19: 条件触发：每层露水恢复气血时，获得 4 点修为 | 被动效果：露水层数上限 +10 | 功法成长：第1层（无）：每层露水恢复气血时，获得 4 点修为；露水层数上限 +10 | 第2层（修为≥1840）：每层露水恢复气血时，获得 8 点修为；露水层数上限 +20 | 第3层（修为≥4600）：每层露水恢复气血时，获得 12 点修为；露水层数上限 +30 | 第4层（修为≥19800）：每层露水恢复气血时，获得 16 点修为；露水层数上限 +40 | S19: 水月别院入门功法，取月照静水之意，重在调息、回气与久战不乱。 | T19: scripture_astrolabe_scroll_1x1 | U19: allowed
A20: 19 | B20: 100027 | C20: 金刃诀 | D20: 功法 | E20: scripture | F20: common | G20: 金 | H20: metal | I20: 1×1 | J20: 1 | K20: 35 | L20: 是 | M20: bazaar | N20: 3 | O20: 条件触发；被动效果；功法成长 | P20: triggered；passive；scriptureProgression | Q20: 条件触发：每消耗 1 层凝金时，获得 2 点修为 | 被动效果：凝金层数上限 +3 | 功法成长：第1层（无）：每消耗 1 层凝金时，获得 2 点修为；凝金层数上限 +3 | 第2层（修为≥110）：每消耗 1 层凝金时，获得 4 点修为；凝金层数上限 +6 | 第3层（修为≥900）：每消耗 1 层凝金时，获得 6 点修为；凝金层数上限 +9 | 第4层（修为≥2450）：每消耗 1 层凝金时，获得 8 点修为；凝金层数上限 +12 | S20: 青绿秘册内页压着细密金纹，行气篇章如刀锋层叠，教人凝金养刃、借锋破敌。 | T20: scripture_jinrenjue_1x1 | U20: allowed
A21: 20 | B21: 100028 | C21: 铁甲诀 | D21: 功法 | E21: scripture | F21: common | G21: 无 | H21: none | I21: 1×1 | J21: 1 | K21: 35 | L21: 是 | M21: bazaar | N21: 3 | O21: 周期触发；被动效果；功法成长 | P21: periodicPulse；passive；scriptureProgression | Q21: 周期触发：消耗所有护甲，每消耗 1 层护甲，获得 1 点修为；每层护甲消耗时，获得 1 点修为 | 被动效果：护甲层数上限 +5 | 功法成长：第1层（无）：消耗所有护甲，每消耗 1 层护甲，获得 1 点修为；每层护甲消耗时，获得 1 点修为；护甲层数上限 +5 | 第2层（修为≥150）：消耗所有护甲，每消耗 1 层护甲，获得 2 点修为；每层护甲消耗时，获得 2 点修为；护甲层数上限 +10 | 第3层（修为≥470；境界≥炼气4层）：消耗所有护甲，每消耗 1 层护甲，获得 3 点修为；每层护甲消耗时，获得 3 点修为；护甲层数上限 +15 | 第4层（修为≥3150；境界≥炼气4层）：消耗所有护甲，每消耗 1 层护甲，获得 4 点修为；每层护甲消耗时，获得 4 点修为；护甲层数上限 +20 | S21: 青绿秘册绘满披甲负重的小人图，笔势厚拙，讲究以沉身磨力、以甲势护体。 | T21: scripture_tiejiajue_1x1 | U21: allowed
A22: 21 | B22: 100029 | C22: 青河听潮篇 | D22: 功法 | E22: scripture | F22: common | G22: 水 | H22: water | I22: 1×1 | J22: 1 | K22: 35 | L22: 是 | M22: bazaar | N22: 3 | O22: 条件触发；被动效果；功法成长 | P22: triggered；passive；scriptureProgression | Q22: 条件触发：每消耗 1 层露水时，获得 2 点修为 | 被动效果：露水层数上限 +3 | 功法成长：第1层（无）：每消耗 1 层露水时，获得 2 点修为；露水层数上限 +3 | 第2层（修为≥120；境界≥炼气层）：每消耗 1 层露水时，获得 4 点修为；露水层数上限 +6 | 第3层（修为≥760；境界≥炼气层）：每消耗 1 层露水时，获得 6 点修为；露水层数上限 +9 | 第4层（修为≥3950；境界≥炼气层）：每消耗 1 层露水时，获得 8 点修为；露水层数上限 +12 | S22: 潮声入息，辨微澜以静心。卷页含青河宗传承的水纹与旧印，静置时仍似能听见远处河声。 | T22: scripture_qinghe_tingchao_1x1 | U22: allowed
A23: 22 | B23: 100030 | C23: 伏流追息诀 | D23: 功法 | E23: scripture | F23: common | G23: 风 | H23: wind | I23: 1×1 | J23: 1 | K23: 35 | L23: 是 | M23: bazaar | N23: 4 | O23: 条件触发；被动效果；功法成长 | P23: triggered；passive；scriptureProgression | Q23: 条件触发：每获得 1 层敏捷或闪避时，获得 3 点修为 | 条件触发：每获得 1 层敏捷或闪避时，获得 3 点修为 | 被动效果：敏捷层数上限 +3 | 功法成长：第1层（无）：每获得 1 层敏捷或闪避时，获得 3 点修为；敏捷层数上限 +3 | 第2层（修为≥210；境界≥炼气层）：每获得 1 层敏捷或闪避时，获得 6 点修为；敏捷层数上限 +6 | 第3层（修为≥640；境界≥炼气层）：每获得 1 层敏捷或闪避时，获得 9 点修为；敏捷层数上限 +9 | 第4层（修为≥3200；境界≥炼气层）：每获得 1 层敏捷或闪避时，获得 12 点修为；敏捷层数上限 +12 | S23: 循伏流残痕，追索未绝之息。卷页含青河宗传承的水纹与旧印，静置时仍似能听见远处河声。 | T23: scripture_fuliu_zhuixi_1x1 | U23: allowed
A24: 23 | B24: 100031 | C24: 回澜牵机诀 | D24: 功法 | E24: scripture | F24: common | G24: 水 | H24: water | I24: 1×1 | J24: 1 | K24: 35 | L24: 是 | M24: bazaar | N24: 4 | O24: 条件触发；被动效果；功法成长 | P24: triggered；passive；scriptureProgression | Q24: 条件触发：每层露水恢复体力时，获得 1 点修为 | 被动效果：露水层数上限 +3 | 被动效果：体力上限 +10 | 功法成长：第1层（无）：每层露水恢复体力时，获得 1 点修为；露水层数上限 +3；体力上限 +10 | 第2层（修为≥210；境界≥炼气层）：每层露水恢复体力时，获得 2 点修为；露水层数上限 +6；体力上限 +20 | 第3层（修为≥680；境界≥炼气层）：每层露水恢复体力时，获得 3 点修为；露水层数上限 +9；体力上限 +30 | 第4层（修为≥4300；境界≥炼气层）：每层露水恢复体力时，获得 4 点修为；露水层数上限 +12；体力上限 +40 | S24: 借舟索阵钉卸力转势。卷页含青河宗传承的水纹与旧印，静置时仍似能听见远处河声。 | T24: scripture_huilan_qianji_1x1 | U24: allowed
A25: 24 | B25: 100042 | C25: 九川归海经 | D25: 功法 | E25: scripture | F25: common | G25: 水 | H25: water | I25: 2×3 | J25: 6 | K25: 50 | L25: 是 | M25: bazaar | N25: 3 | O25: 周期触发；被动效果；功法成长 | P25: periodicPulse；passive；scriptureProgression | Q25: 周期触发：消耗所有露水，每消耗 1 层获得 1 点修为 | 被动效果：露水层数上限 +10 | 功法成长：第1层（无）：消耗所有露水，每消耗 1 层获得 1 点修为；露水层数上限 +10 | 第2层（修为≥160；境界≥炼气4层）：消耗所有露水，每消耗 1 层获得 2 点修为；露水层数上限 +15 | 第3层（修为≥840；境界≥炼气6层）：消耗所有露水，每消耗 1 层获得 3 点修为；露水层数上限 +20 | 第4层（修为≥2250；境界≥筑基1层）：消耗所有露水，每消耗 1 层获得 4 点修为；露水层数上限 +25 | 第5层（修为≥10600；境界≥筑基2层）：消耗所有露水，每消耗 1 层获得 5 点修为；露水层数上限 +30 | 第6层（修为≥36700；境界≥筑基3层）：消耗所有露水，每消耗 1 层获得 6 点修为；露水层数上限 +35 | S25: 玉溪阁分汊水工以支流疏导总势的行气图谱，页间水线层层分合。 | T25: scripture_yuxi_jiuchuan_guihai_2x3 | U25: allowed
A26: 25 | B26: 100043 | C26: 青木引风诀 | D26: 功法 | E26: scripture | F26: common | G26: 木 | H26: wood | I26: 2×3 | J26: 6 | K26: 50 | L26: 是 | M26: bazaar；questStoryReward | N26: 5 | O26: 周期触发；条件触发；被动效果；功法成长 | P26: periodicPulse；triggered；passive；scriptureProgression | Q26: 周期触发：消耗所有再生，每消耗 1 层获得 2 点修为 | 条件触发：每当消耗 1 层敏捷时，获得 2 点修为 | 被动效果：再生层数上限 +2 | 被动效果：敏捷层数上限 +2 | 功法成长：第1层（无）：消耗所有再生，每消耗 1 层获得 2 点修为；每当消耗 1 层敏捷时，获得 2 点修为；再生层数上限 +2；敏捷层数上限 +2 | 第2层（修为≥170；境界≥炼气4层）：消耗所有再生，每消耗 1 层获得 4 点修为；每当消耗 1 层敏捷时，获得 4 点修为；再生层数上限 +4；敏捷层数上限 +4 | 第3层（修为≥800；境界≥炼气6层）：消耗所有再生，每消耗 1 层获得 6 点修为；每当消耗 1 层敏捷时，获得 6 点修为；再生层数上限 +6；敏捷层数上限 +6 | 第4层（修为≥2550；境界≥炼气10层）：消耗所有再生，每消耗 1 层获得 8 点修为；每当消耗 1 层敏捷时，获得 8 点修为；再生层数上限 +8；敏捷层数上限 +8 | 第5层（修为≥10800；境界≥筑基2层）：消耗所有再生，每消耗 1 层获得 10 点修为；每当消耗 1 层敏捷时，获得 10 点修为；再生层数上限 +10；敏捷层数上限 +10 | 第6层（修为≥32100；境界≥筑基3层）：消耗所有再生，每消耗 1 层获得 12 点修为；每当消耗 1 层敏捷时，获得 12 点修为；再生层数上限 +12；敏捷层数上限 +12 | S26: 以水息养木，以风势引灵；行气如舟，不与逆流争先。 | T26: scripture_yuxi_jiefeng_xingzhou_2x3 | U26: allowed
A27: 26 | B27: 100044 | C27: 金契封河十二章 | D27: 功法 | E27: scripture | F27: common | G27: 金 | H27: metal | I27: 2×3 | J27: 6 | K27: 50 | L27: 是 | M27: bazaar | N27: 2 | O27: 周期触发；功法成长 | P27: periodicPulse；scriptureProgression | Q27: 周期触发：消耗所有凝金，每消耗 1 层凝金，获得 4 点修为 | 功法成长：第1层（无）：消耗所有凝金，每消耗 1 层凝金，获得 4 点修为 | 第2层（修为≥210；境界≥炼气4层）：消耗所有凝金，每消耗 1 层凝金，获得 8 点修为 | 第3层（修为≥620；境界≥炼气6层）：消耗所有凝金，每消耗 1 层凝金，获得 12 点修为 | 第4层（修为≥2900；境界≥筑基1层）：消耗所有凝金，每消耗 1 层凝金，获得 16 点修为 | 第5层（修为≥12100；境界≥筑基2层）：消耗所有凝金，每消耗 1 层凝金，获得 20 点修为 | 第6层（修为≥40500；境界≥筑基3层）：消耗所有凝金，每消耗 1 层凝金，获得 24 点修为 | S27: 玉溪阁检校河契与器印的旧录，金线批注如水尺般严整分明。 | T27: scripture_yuxi_jinqi_fenghe_shierzhang_2x3 | U27: allowed
A28: 27 | B28: 100045 | C28: 炉火照寒潭 | D28: 功法 | E28: scripture | F28: common | G28: 火 | H28: fire | I28: 2×3 | J28: 6 | K28: 50 | L28: 是 | M28: bazaar | N28: 3 | O28: 周期触发；被动效果；功法成长 | P28: periodicPulse；passive；scriptureProgression | Q28: 周期触发：消耗所有炎热，每消耗 1 层炎热，获得 4 点修为 | 被动效果：炎热层数上限 +3 | 功法成长：第1层（无）：消耗所有炎热，每消耗 1 层炎热，获得 4 点修为；消耗所有炎热，每消耗 1 层炎热，获得 8 点修为；炎热层数上限 +3 | 第2层（修为≥140；境界≥炼气4层）：消耗所有炎热，每消耗 1 层炎热，获得 8 点修为；消耗所有炎热，每消耗 1 层炎热，获得 12 点修为；炎热层数上限 +6 | 第3层（修为≥640；境界≥炼气6层）：消耗所有炎热，每消耗 1 层炎热，获得 12 点修为；消耗所有炎热，每消耗 1 层炎热，获得 16 点修为；炎热层数上限 +9 | 第4层（修为≥2750；境界≥筑基1层）：消耗所有炎热，每消耗 1 层炎热，获得 16 点修为；炎热层数上限 +12 | 第5层（修为≥10900；境界≥筑基2层）：消耗所有炎热，每消耗 1 层炎热，获得 20 点修为；炎热层数上限 +15 | 第6层（修为≥27500；境界≥筑基3层）：消耗所有炎热，每消耗 1 层炎热，获得 24 点修为；炎热层数上限 +18 | S28: 玉溪阁百炉同开时收束冷热余势的秘诀，朱墨炉记之间留有冷蓝水痕。 | T28: scripture_yuxi_luhuo_zhao_hantan_2x3 | U28: allowed
A29: 28 | B29: 100046 | C29: 镇澜功 | D29: 功法 | E29: scripture | F29: common | G29: 土 | H29: earth | I29: 2×3 | J29: 6 | K29: 50 | L29: 是 | M29: bazaar | N29: 4 | O29: 周期触发；被动效果；功法成长 | P29: periodicPulse；passive；scriptureProgression | Q29: 周期触发：消耗所有蓄势，每消耗 1 层蓄势，获得 3 点修为 | 被动效果：护甲层数上限 +3 | 被动效果：蓄势层数上限 +2 | 功法成长：第1层（无）：消耗所有蓄势，每消耗 1 层蓄势，获得 3 点修为；护甲层数上限 +3；蓄势层数上限 +2 | 第2层（修为≥140；境界≥炼气4层）：消耗所有蓄势，每消耗 1 层蓄势，获得 6 点修为；护甲层数上限 +6；蓄势层数上限 +4 | 第3层（修为≥740；境界≥炼气6层）：消耗所有蓄势，每消耗 1 层蓄势，获得 9 点修为；护甲层数上限 +9；蓄势层数上限 +6 | 第4层（修为≥2900；境界≥筑基1层）：消耗所有蓄势，每消耗 1 层蓄势，获得 12 点修为；护甲层数上限 +12；蓄势层数上限 +8 | 第5层（修为≥11100；境界≥筑基2层）：消耗所有蓄势，每消耗 1 层蓄势，获得 15 点修为；护甲层数上限 +15；蓄势层数上限 +10 | 第6层（修为≥35900；境界≥筑基3层）：消耗所有蓄势，每消耗 1 层蓄势，获得 18 点修为；护甲层数上限 +18；蓄势层数上限 +12 | S29: 玉溪阁门闸承压与回澜的阵图，厚重闸线围住层层倒卷的水纹。 | T29: scripture_yuxi_zhenlan_gong_2x3 | U29: allowed
A30: 29 | B30: 100047 | C30: 太阴玄霜诀 | D30: 功法 | E30: scripture | F30: common | G30: 冰 | H30: ice | I30: 1×2 | J30: 2 | K30: 35 | L30: 是 | M30: bazaar | N30: 3 | O30: 条件触发；被动效果；功法成长 | P30: triggered；passive；scriptureProgression | Q30: 条件触发：每消耗 1 层寒冷，获得 2 点修为 | 被动效果：寒冷层数上限 +5 | 功法成长：第1层（无）：每消耗 1 层寒冷，获得 2 点修为；寒冷层数上限 +5 | 第2层（修为≥120；境界≥炼气层）：每消耗 1 层寒冷，获得 4 点修为；寒冷层数上限 +10 | 第3层（修为≥740；境界≥炼气层）：每消耗 1 层寒冷，获得 6 点修为；寒冷层数上限 +15 | 第4层（修为≥3550；境界≥炼气层）：每消耗 1 层寒冷，获得 8 点修为；寒冷层数上限 +20 | S30: 月白绢册以冰蚕丝装订，卷中水脉与霜纹交叠，讲究先蓄寒、再渡霜、终以万籁冰封镇住敌阵。 | T30: scripture_lunar_mystic_frost_art_1x2 | U30: allowed
A31: 30 | B31: 300001 | C31: 硬气丹 | D31: 丹药 | E31: pill | F31: common | G31: 土 | H31: earth | I31: 1×1 | J31: 1 | K31: 5 | L31: 是 | M31: bazaar；alchemyCrafting；dynamicRandomReward | N31: 1 | O31: 消耗品效果 | P31: consumable | Q31: 消耗品效果：坚硬上限永久 +1 | R31: buff_upper_limit | S31: 土金阵纹压在沉色丹丸表面，药气不浮不躁，入口后像把散劲慢慢坠进筋骨。 | T31: pill_hard_qi_pill_1x1 | U31: allowed
A32: 31 | B32: 300002 | C32: 温炉丹 | D32: 丹药 | E32: pill | F32: common | G32: 火 | H32: fire | I32: 1×1 | J32: 1 | K32: 2 | L32: 是 | M32: bazaar；alchemyCrafting；dynamicRandomReward | N32: 1 | O32: 消耗品效果 | P32: consumable | Q32: 消耗品效果：炎热上限永久 +1 | R32: buff_upper_limit | S32: 温润丹胚里封着一缕细火，热意不急不烈，只在靠近炉烟时显出柔和的助燃气。 | T32: pill_wenling_core_pellet_1x1 | U32: allowed
A33: 32 | B33: 300003 | C33: 温脉露丸 | D33: 丹药 | E33: pill | F33: common | G33: 无 | H33: none | I33: 1×1 | J33: 1 | K33: 3 | L33: 是 | M33: bazaar；alchemyCrafting；dynamicRandomReward | N33: 1 | O33: 消耗品效果 | P33: consumable | Q33: 消耗品效果：气血上限永久 +3 | R33: stat_upper_limit | S33: 青绿小瓶晶润轻盈，瓶中药露贴壁流转，开塞便有温脉回气的草木清香。 | T33: pill_verdant_dew_vial_1x1 | U33: allowed
A34: 33 | B34: 300004 | C34: 固元丸 | D34: 丹药 | E34: pill | F34: common | G34: 无 | H34: none | I34: 1×1 | J34: 1 | K34: 5 | L34: 是 | M34: bazaar；beastDrop；alchemyCrafting；dynamicRandomReward | N34: 1 | O34: 消耗品效果 | P34: consumable | Q34: 消耗品效果：体力上限永久 +3 | R34: stat_upper_limit | S34: 米白丹丸厚润如玉，金纹伏在表层不散，含入口中有一股稳稳固住根基的暖意。 | T34: pill_golden_pattern_foundation_dan_1x1 | U34: allowed
A35: 34 | B35: 300005 | C35: 聚气丹 | D35: 丹药 | E35: pill | F35: common | G35: 无 | H35: none | I35: 1×1 | J35: 1 | K35: 5 | L35: 是 | M35: bazaar；alchemyCrafting；dynamicRandomReward | N35: 1 | O35: 消耗品效果 | P35: consumable | Q35: 消耗品效果：法力上限永久 +3 | R35: stat_upper_limit | S35: 碧绿丹珠通透圆满，金纹细绕如聚拢云气，静置时也像在缓缓收纳游离灵息。 | T35: pill_qi_gathering_dan_1x1 | U35: allowed
A36: 35 | B36: 300011 | C36: 云纹聚气丹 | D36: 丹药 | E36: pill | F36: spirit | G36: 无 | H36: none | I36: 1×1 | J36: 1 | K36: 50 | L36: 是 | M36: bazaar；alchemyCrafting；dynamicRandomReward | N36: 1 | O36: 消耗品效果 | P36: consumable | Q36: 消耗品效果：法力上限永久 +30；法力上限 +30 | R36: stat_upper_limit | S36: 金黄丹珠外绕云气，珠体浑圆厚润，掌心一托便似晨雾凝成的温亮灵核。 | T36: pill_cloudpattern_golden_dan_1x1 | U36: allowed
A37: 36 | B37: 300012 | C37: 固元壮体丹 | D37: 丹药 | E37: pill | F37: spirit | G37: 无 | H37: none | I37: 1×1 | J37: 1 | K37: 50 | L37: 是 | M37: bazaar；beastDrop；alchemyCrafting；dynamicRandomReward | N37: 1 | O37: 消耗品效果 | P37: consumable | Q37: 消耗品效果：体力上限永久 +30；体力上限 +30 | R37: stat_upper_limit | S37: 暗红褐色丹丸置于厚实木碗，表面锻纹朴拙，药香沉入筋骨而不外扬。 | T37: pill_body_strengthening_pill_1x1 | U37: allowed
A38: 37 | B38: 300013 | C38: 凝血丹 | D38: 丹药 | E38: pill | F38: spirit | G38: 无 | H38: none | I38: 1×1 | J38: 1 | K38: 75 | L38: 是 | M38: bazaar；alchemyCrafting；dynamicRandomReward | N38: 1 | O38: 消耗品效果 | P38: consumable | Q38: 消耗品效果：精血上限永久 +6；精血上限 +6 | R38: stat_upper_limit | S38: 圆盒半启，赤金丹丸柔光内敛，药香中透出温厚血气。 | T38: pill_goldcore_case_1x1 | U38: allowed
A39: 38 | B39: 300015 | C39: 紫极蕴神丹 | D39: 丹药 | E39: pill | F39: spirit | G39: 无 | H39: none | I39: 1×1 | J39: 1 | K39: 75 | L39: 是 | M39: bazaar；alchemyCrafting；dynamicRandomReward | N39: 1 | O39: 消耗品效果 | P39: consumable | Q39: 消耗品效果：神识上限永久 +6；神识上限 +6 | R39: stat_upper_limit | S39: 深紫丹丸卧在细口瓷瓶旁，丹壳神纹细密如星，气息沉静而凝定，适合温养神识。 | T39: pill_purple_apex_spirit_nurturing_pill_1x1 | U39: allowed
A40: 39 | B40: 300016 | C40: 通玄丹 | D40: 丹药 | E40: pill | F40: spirit | G40: 无 | H40: none | I40: 1×1 | J40: 1 | K40: 75 | L40: 否 | M40: bazaar；alchemyCrafting | N40: 1 | O40: 消耗品效果 | P40: consumable | Q40: 消耗品效果：精血上限永久 +6；精血上限 +6 | R40: stat_upper_limit | S40: 蓝青丹丸置于细长瓷盘中央，纹理多向交织而不乱，像把纷繁灵思梳成一线清明。 | T40: pill_mystic_insight_pill_1x1 | U40: allowed
A41: 40 | B41: 300017 | C41: 续力丸 | D41: 丹药 | E41: pill | F41: common | G41: 无 | H41: none | I41: 1×1 | J41: 1 | K41: 2 | L41: 是 | M41: bazaar；beastDrop；journeyChest；alchemyCrafting；dynamicRandomReward | N41: 1 | O41: 消耗品效果 | P41: consumable | Q41: 消耗品效果：恢复 20 点体力 | R41: gain_stat | S41: 棕褐小丸藏在浅木匣中，药气朴实，入口后只求迅速接上一口余力。 | T41: pill_stamina_restoring_pellet_1x1 | U41: allowed
A42: 41 | B42: 300018 | C42: 回法丹 | D42: 丹药 | E42: pill | F42: common | G42: 无 | H42: none | I42: 1×1 | J42: 1 | K42: 2 | L42: 是 | M42: bazaar；beastDrop；journeyChest；alchemyCrafting；dynamicRandomReward | N42: 1 | O42: 消耗品效果 | P42: consumable | Q42: 消耗品效果：恢复 10 点法力 | R42: gain_stat | S42: 淡蓝药丸卧在白瓷小盏中，丹纹像回旋的细流，专为短促回纳法力而炼。 | T42: pill_spirit_restoring_pill_1x1 | U42: allowed
... A48: 47 | B48: 300024 | C48: 守脉膏 | D48: 丹药 | E48: pill | F48: common | G48: 无 | H48: none | I48: 1×1 | J48: 1 | K48: 2 | L48: 是 | M48: bazaar；beastDrop；alchemyCrafting；dynamicRandomReward | N48: 1 | O48: 消耗品效果 | P48: consumable | Q48: 消耗品效果：获得 5 层坚硬 | R48: gain_buff | S48: 白玉小匣里盛着淡金药膏，膏面平滑如脂，贴近时能闻到柔和药香。 | T48: pill_meridian_guarding_pill_1x1 | U48: allowed
A49: 48 | B49: 300025 | C49: 清浊丸 | D49: 丹药 | E49: pill | F49: common | G49: 无 | H49: none | I49: 1×1 | J49: 1 | K49: 2 | L49: 是 | M49: bazaar；beastDrop；journeyChest；alchemyCrafting；dynamicRandomReward | N49: 1 | O49: 消耗品效果 | P49: consumable | Q49: 消耗品效果：随机移除 5 层负面效果 | S49: 黑白两色药纹在丹面交错分明，握久了却渐渐沉静下来，像浊气被滤去。 | T49: pill_clarity_turbidity_pellet_1x1 | U49: allowed
A50: 49 | B50: 300026 | C50: 玉露瓶 | D50: 丹药 | E50: pill | F50: common | G50: 水 | H50: water | I50: 1×1 | J50: 1 | K50: 4 | L50: 是 | M50: bazaar；beastDrop；journeyChest；alchemyCrafting；dynamicRandomReward | N50: 1 | O50: 消耗品效果 | P50: consumable | Q50: 消耗品效果：获得 10 层露水 | R50: gain_buff | S50: 透明小瓶中凝着一泓玉色露液，瓶口封蜡晶亮，药香清甜而不浮散。 | T50: pill_batch11_046_1x1 | U50: allowed
A51: 50 | B51: 300027 | C51: 固息丹 | D51: 丹药 | E51: pill | F51: common | G51: 无 | H51: none | I51: 1×1 | J51: 1 | K51: 2 | L51: 是 | M51: bazaar；beastDrop；journeyChest；alchemyCrafting；dynamicRandomReward | N51: 1 | O51: 消耗品效果 | P51: consumable | Q51: 消耗品效果：本局内体力上限 +20 | R51: temp_stat_upper_limit | S51: 浅青圆丸静置于薄碟中，丸面细点如凝息纹，像把躁动气机稳稳压回丹心。 | T51: pill_asthma_calming_pellet_1x1 | U51: allowed
A52: 51 | B52: 300028 | C52: 暖髓丸 | D52: 丹药 | E52: pill | F52: common | G52: 无 | H52: none | I52: 1×1 | J52: 1 | K52: 2 | L52: 是 | M52: bazaar；alchemyCrafting；dynamicRandomReward | N52: 1 | O52: 消耗品效果 | P52: consumable | Q52: 消耗品效果：本局内法力上限 +20 | R52: temp_stat_upper_limit | S52: 赭色丹丸带着温润光泽，丹心隐有细金浮点，贴近掌心便泛起绵长暖意。 | T52: pill_marrow_warming_pill_1x1 | U52: allowed
A53: 52 | B53: 300029 | C53: 青鳞寿果 | D53: 丹药 | E53: pill | F53: common | G53: 无 | H53: none | I53: 1×1 | J53: 1 | K53: 4 | L53: 是 | M53: beastDrop | N53: 1 | O53: 消耗品效果 | P53: consumable | Q53: 消耗品效果：寿元增加 1~2 年 | R53: life_extend | S53: 青碧果皮层叠如鳞，叶隙间凝着晨露，入口清甜而微带草木香。 | T53: material_batch14_008_1x1 | U53: allowed
A54: 53 | B54: 300030 | C54: 秋赤寿果 | D54: 丹药 | E54: pill | F54: common | G54: 无 | H54: none | I54: 1×1 | J54: 1 | K54: 7 | L54: 是 | M54: beastDrop | N54: 1 | O54: 消耗品效果 | P54: consumable | Q54: 消耗品效果：寿元增加 1~3 年 | R54: life_extend | S54: 赤红果皮上留着细密秋纹，果肉温润，咽下后余香久久不散。 | T54: material_pale_down_leaf_1x1 | U54: allowed
A55: 54 | B55: 300031 | C55: 回纹寿果 | D55: 丹药 | E55: pill | F55: common | G55: 无 | H55: none | I55: 1×1 | J55: 1 | K55: 10 | L55: 是 | M55: beastDrop | N55: 1 | O55: 消耗品效果 | P55: consumable | Q55: 消耗品效果：寿元增加 2~4 年 | R55: life_extend | S55: 暗红果皮盘绕着层层回纹，轻轻转动便有细微灵光沿沟纹流过。 | T55: material_frost_crystal_cluster_1x1 | U55: allowed
A56: 55 | B56: 300032 | C56: 赤阳寿果 | D56: 丹药 | E56: pill | F56: spirit | G56: 无 | H56: none | I56: 1×1 | J56: 1 | K56: 45 | L56: 是 | M56: bazaar；dynamicRandomReward | N56: 1 | O56: 消耗品效果 | P56: consumable | Q56: 消耗品效果：寿元增加 18~34 年 | R56: life_extend | S56: 果心如藏微阳，赤色果皮映出柔和暖光，握久了掌心也不觉灼热。 | T56: material_duskleaf_cloudmark_1x1 | U56: allowed
A57: 56 | B57: 300037 | C57: 庚金养根丹 | D57: 丹药 | E57: pill | F57: common | G57: 金 | H57: metal | I57: 1×1 | J57: 1 | K57: 100 | L57: 是 | M57: bazaar；dynamicRandomReward | N57: 1 | O57: 消耗品效果 | P57: consumable | Q57: 消耗品效果：拥有金灵根时，金灵根永久 +1；金灵根永久 +1 | R57: spirit_root_nurture | S57: 淡金丹丸上刻一线庚金锋纹，药壳坚实细润，内蕴的锐气收束如针。 | T57: pill_gengjin_root_nourishing_1x1 | U57: allowed
A58: 57 | B58: 300038 | C58: 乙木养根丹 | D58: 丹药 | E58: pill | F58: common | G58: 木 | H58: wood | I58: 1×1 | J58: 1 | K58: 100 | L58: 是 | M58: bazaar；dynamicRandomReward | N58: 1 | O58: 消耗品效果 | P58: consumable | Q58: 消耗品效果：拥有木灵根时，木灵根永久 +1；木灵根永久 +1 | R58: spirit_root_nurture | S58: 青碧丹丸裹着细密叶脉，草木清香凝而不散，丹心透出柔韧生机。 | T58: pill_yimu_root_nourishing_1x1 | U58: allowed
A59: 58 | B59: 300039 | C59: 癸水养根丹 | D59: 丹药 | E59: pill | F59: common | G59: 水 | H59: water | I59: 1×1 | J59: 1 | K59: 100 | L59: 是 | M59: bazaar；dynamicRandomReward | N59: 1 | O59: 消耗品效果 | P59: consumable | Q59: 消耗品效果：拥有水灵根时，水灵根永久 +1；水灵根永久 +1 | R59: spirit_root_nurture | S59: 深蓝丹丸表面浮着细小水纹，触手清凉，药气如静泉般缓缓回旋。 | T59: pill_guishui_root_nourishing_1x1 | U59: allowed
A60: 59 | B60: 300040 | C60: 丙火养根丹 | D60: 丹药 | E60: pill | F60: common | G60: 火 | H60: fire | I60: 1×1 | J60: 1 | K60: 100 | L60: 是 | M60: bazaar；dynamicRandomReward | N60: 1 | O60: 消耗品效果 | P60: consumable | Q60: 消耗品效果：拥有火灵根时，火灵根永久 +1；火灵根永久 +1 | R60: spirit_root_nurture | S60: 赤红丹丸内藏一点明亮火心，暖意均匀透出，丹衣却不见焦痕。 | T60: pill_binghuo_root_nourishing_1x1 | U60: allowed
A61: 60 | B61: 300041 | C61: 戊土养根丹 | D61: 丹药 | E61: pill | F61: common | G61: 土 | H61: earth | I61: 1×1 | J61: 1 | K61: 100 | L61: 是 | M61: bazaar；dynamicRandomReward | N61: 1 | O61: 消耗品效果 | P61: consumable | Q61: 消耗品效果：拥有土灵根时，土灵根永久 +1；土灵根永久 +1 | R61: spirit_root_nurture | S61: 赭黄丹丸厚重圆实，表面有层叠山纹，药香沉稳得如同新翻沃土。 | T61: pill_wutu_root_nourishing_1x1 | U61: allowed
... A79: 78 | B79: 300059 | C79: 回灵丹 | D79: 丹药 | E79: pill | F79: spirit | G79: 水 | H79: water | I79: 1×1 | J79: 1 | K79: 25 | L79: 是 | M79: bazaar；alchemyCrafting；dynamicRandomReward | N79: 1 | O79: 消耗品效果 | P79: consumable | Q79: 消耗品效果：恢复 300 点法力 | R79: qingque_special | S79: 青瓷小瓶中浮着一丸清凉丹气，拔塞时仿佛有月下水汽漫上眉心。 | T79: pill_leaf_talisman_sheet_1x1 | U79: allowed
A80: 79 | B80: 300060 | C80: 凡品残丹 | D80: 丹药 | E80: pill | F80: common | G80: 无 | H80: none | I80: 1×1 | J80: 1 | K80: 0 | L80: 是 | M80: alchemyCrafting | N80: 1 | O80: 消耗品效果 | P80: consumable | Q80: 消耗品效果：恢复 3 点法力 | S80: 炼制失败后留下的凡品残丹，裂纹间还留着一点温吞药性，勉强可作行路时的回气之用。 | T80: pill_alchemy_residual_common_1x1 | U80: allowed
A81: 80 | B81: 300061 | C81: 灵品残丹 | D81: 丹药 | E81: pill | F81: spirit | G81: 无 | H81: none | I81: 1×1 | J81: 1 | K81: 0 | L81: 是 | M81: bazaar；dynamicRandomReward | N81: 1 | O81: 消耗品效果 | P81: consumable | Q81: 消耗品效果：恢复 30 点法力 | S81: 灵火收束时略偏一线，紫青丹壳虽裂，内里仍封着可供回纳的一缕灵息。 | T81: pill_alchemy_residual_spirit_1x1 | U81: allowed
A82: 81 | B82: 300062 | C82: 筑基丹 | D82: 丹药 | E82: pill | F82: common | G82: 无 | H82: none | I82: 1×1 | J82: 1 | K82: 240 | L82: 是 | M82: alchemyCrafting；questStoryReward | N82: 1 | O82: 消耗品效果 | P82: consumable | Q82: 消耗品效果：服下此丹，助力筑基破境 | S82: 金纹收束在青黑丹皮里，丹心像一枚尚未点亮的地脉星火；从仓库服下后，药力便会沉入经脉，留下可核验的破境印记。 | T82: pill_foundation_breakthrough_dan_1x1 | U82: allowed
A83: 82 | B83: 300063 | C83: 凝寒丹 | D83: 丹药 | E83: pill | F83: common | G83: 水 | H83: water | I83: 1×1 | J83: 1 | K83: 2 | L83: 是 | M83: bazaar；dynamicRandomReward | N83: 1 | O83: 消耗品效果 | P83: consumable | Q83: 消耗品效果：寒冷上限永久 +1 | R83: buff_upper_limit | S83: 冰蓝丹丸封着一圈细霜，丹心清凉如晨雪初融。 | T83: pill_jade_void_life_returning_pill_1x1 | U83: allowed
A84: 83 | B84: 300064 | C84: 负岳丹 | D84: 丹药 | E84: pill | F84: common | G84: 土 | H84: earth | I84: 1×1 | J84: 1 | K84: 2 | L84: 是 | M84: bazaar；dynamicRandomReward | N84: 1 | O84: 消耗品效果 | P84: consumable | Q84: 消耗品效果：蓄势上限永久 +1 | R84: buff_upper_limit | S84: 土黄厚丸沉稳如石，药纹层层叠起，入口便有坠地之感。 | T84: pill_condensed_earth_powder_1x1 | U84: allowed
A85: 84 | B85: 300065 | C85: 轻身丹 | D85: 丹药 | E85: pill | F85: common | G85: 风 | H85: wind | I85: 1×1 | J85: 1 | K85: 5 | L85: 是 | M85: bazaar；dynamicRandomReward | N85: 1 | O85: 消耗品效果 | P85: consumable | Q85: 消耗品效果：敏捷上限永久 +1 | R85: buff_upper_limit | S85: 青碧小丹浮着细叶纹，药气轻灵，仿佛一口风贴过脚踝。 | T85: pill_breath_concealing_pellet_1x1 | U85: allowed
A86: 85 | B86: 300066 | C86: 露华丹 | D86: 丹药 | E86: pill | F86: common | G86: 水 | H86: water | I86: 1×1 | J86: 1 | K86: 2 | L86: 是 | M86: bazaar；dynamicRandomReward | N86: 1 | O86: 消耗品效果 | P86: consumable | Q86: 消耗品效果：露水上限永久 +1 | R86: buff_upper_limit | S86: 水润丹壳透出一线青光，摇动时像有晨露在丹心凝聚。 | T86: pill_nine_blossom_jade_dew_pill_1x1 | U86: allowed
A87: 86 | B87: 300067 | C87: 凝金丹 | D87: 丹药 | E87: pill | F87: common | G87: 金 | H87: metal | I87: 1×1 | J87: 1 | K87: 2 | L87: 是 | M87: bazaar；dynamicRandomReward | N87: 1 | O87: 消耗品效果 | P87: consumable | Q87: 消耗品效果：凝金上限永久 +1 | R87: buff_upper_limit | S87: 银灰丹珠边缘泛起金属冷辉，药纹细密得像新铸的鳞片。 | T87: pill_jade_dew_pill_1x1 | U87: allowed
A88: 87 | B88: 300068 | C88: 护甲丹 | D88: 丹药 | E88: pill | F88: common | G88: 无 | H88: none | I88: 1×1 | J88: 1 | K88: 2 | L88: 是 | M88: bazaar；dynamicRandomReward | N88: 1 | O88: 消耗品效果 | P88: consumable | Q88: 消耗品效果：护甲上限永久 +2 | R88: buff_upper_limit | S88: 灰白丹丸裹着硬亮药膜，触手微凉，像一枚收拢的甲片。 | T88: pill_iron_skin_pill_1x1 | U88: allowed
A89: 88 | B89: 300069 | C89: 逐影丹 | D89: 丹药 | E89: pill | F89: common | G89: 无 | H89: none | I89: 1×1 | J89: 1 | K89: 5 | L89: 是 | M89: bazaar；dynamicRandomReward | N89: 1 | O89: 消耗品效果 | P89: consumable | Q89: 消耗品效果：闪避上限永久 +1 | R89: buff_upper_limit | S89: 无色小丹映着淡淡残影，丹面光泽一转，便似退入暗处。 | T89: pill_mind_concentrating_pill_1x1 | U89: allowed
A90: 89 | B90: 300070 | C90: 青木回春丹 | D90: 丹药 | E90: pill | F90: common | G90: 木 | H90: wood | I90: 1×1 | J90: 1 | K90: 5 | L90: 是 | M90: bazaar；dynamicRandomReward | N90: 1 | O90: 消耗品效果 | P90: consumable | Q90: 消耗品效果：再生上限永久 +1 | R90: buff_upper_limit | S90: 青翠丹衣带着木纹药痕，捧在掌中便有细微生机回环。 | T90: pill_vitality_regenerating_pill_1x1 | U90: allowed
A91: 90 | B91: 300071 | C91: 坚元丹 | D91: 丹药 | E91: pill | F91: common | G91: 土 | H91: earth | I91: 1×1 | J91: 1 | K91: 2 | L91: 是 | M91: bazaar；dynamicRandomReward | N91: 1 | O91: 消耗品效果 | P91: consumable | Q91: 消耗品效果：获得 3 层坚硬 | R91: gain_buff | S91: 土色小丸压着厚重纹路，药香沉静，像把筋骨重新钉牢。 | T91: pill_bone_forging_pill_1x1 | U91: allowed
A92: 91 | B92: 300072 | C92: 炎息丹 | D92: 丹药 | E92: pill | F92: common | G92: 火 | H92: fire | I92: 1×1 | J92: 1 | K92: 1 | L92: 是 | M92: bazaar；dynamicRandomReward | N92: 1 | O92: 消耗品效果 | P92: consumable | Q92: 消耗品效果：获得 10 层炎热 | R92: gain_buff | S92: 赤红丹壳里有微光游走，靠近时能感到一丝温热吐息。 | T92: pill_blazing_origin_pill_1x1 | U92: allowed
A93: 92 | B93: 300073 | C93: 寒息丹 | D93: 丹药 | E93: pill | F93: common | G93: 水 | H93: water | I93: 1×1 | J93: 1 | K93: 1 | L93: 是 | M93: bazaar；dynamicRandomReward | N93: 1 | O93: 消耗品效果 | P93: consumable | Q93: 消耗品效果：获得 10 层寒冷 | R93: gain_buff | S93: 蓝白药霜沿丹面缓慢舒展，入口时如寒雾从喉间散开。 | T93: pill_cold_dispelling_pellet_1x1 | U93: allowed
A94: 93 | B94: 300074 | C94: 负岳丸 | D94: 丹药 | E94: pill | F94: common | G94: 土 | H94: earth | I94: 1×1 | J94: 1 | K94: 2 | L94: 是 | M94: bazaar；dynamicRandomReward | N94: 1 | O94: 消耗品效果 | P94: consumable | Q94: 消耗品效果：获得 3 层蓄势 | R94: gain_buff | S94: 暗黄药丸厚实低沉，轻敲丹壳便有闷闷回声。 | T94: pill_bone_tempering_pill_1x1 | U94: allowed
... A134: 133 | B134: 300114 | C134: 双生护脉丹 | D134: 丹药 | E134: pill | F134: spirit | G134: 无 | H134: none | I134: 1×1 | J134: 1 | K134: 30 | L134: 是 | M134: bazaar；alchemyCrafting；dynamicRandomReward | N134: 1 | O134: 消耗品效果 | P134: consumable | Q134: 消耗品效果：本局内气血上限 +300 | R134: temp_stat_upper_limit | S134: 圆匣中并列两枚棕金丹丸，回纹围住匣心，药香温厚，像两道相扣的护脉环。 | T134: pill_twinpearl_casket_1x1 | U134: allowed
A135: 134 | B135: 300115 | C135: 化龙丹 | D135: 丹药 | E135: pill | F135: spirit | G135: 火 | H135: fire | I135: 1×1 | J135: 1 | K135: 1200 | L135: 是 | M135: questStoryReward；bazaar；alchemyCrafting | N135: 1 | O135: 消耗品效果 | P135: consumable | Q135: 消耗品效果：服下此丹，助力结丹破境 | S135: 青金与赤金龙鳞纹在丹皮上交缠收束。依自身木、火灵根配量从仓库服下，方能引气蜕变。 | T135: pill_core_formation_dragon_1x1 | U135: allowed
A136: 135 | B136: 300116 | C136: 伏虎丹 | D136: 丹药 | E136: pill | F136: spirit | G136: 水 | H136: water | I136: 1×1 | J136: 1 | K136: 1200 | L136: 是 | M136: questStoryReward；bazaar；alchemyCrafting | N136: 1 | O136: 消耗品效果 | P136: consumable | Q136: 消耗品效果：服下此丹，助力结丹破境 | S136: 白金虎纹伏于深蓝丹皮之上。依自身金、水灵根配量从仓库服下，方能镇伏躁动气机。 | T136: pill_core_formation_tiger_1x1 | U136: allowed
A137: 136 | B137: 300117 | C137: 抱一丹 | D137: 丹药 | E137: pill | F137: spirit | G137: 土 | H137: earth | I137: 1×1 | J137: 1 | K137: 1200 | L137: 是 | M137: questStoryReward；bazaar；alchemyCrafting | N137: 1 | O137: 消耗品效果 | P137: consumable | Q137: 消耗品效果：服下此丹，助力结丹破境 | S137: 沉金山环层层抱合玄褐丹心。依自身土灵根配量从仓库服下，方能使五气归一、丹基自固。 | T137: pill_core_formation_unity_1x1 | U137: allowed
A138: 137 | B138: 400001 | C138: 活血石 | D138: 法器 | E138: implement | F138: common | G138: 无 | H138: none | I138: 1×1 | J138: 1 | K138: 3 | L138: 是 | M138: bazaar；beastDrop；dynamicRandomReward；itemReforge | N138: 1 | O138: 周期触发 | P138: periodicPulse | Q138: 周期触发：体力低于 50% 时，恢复 1 点体力；体力低于 50% 时，恢复 2 点体力；体力低于 50% 时，恢复 3 点体力；体力低于 50% 时，恢复 4 点体力 | R138: starter_yangzhen | S138: 赤褐玉牌中央螺纹缓缓收拢，细砂般的表面带着温热触感，像能把散血重新引回脉中。 | T138: implement_spiral_jade_talisman_1x1 | U138: onboardingProtected
A139: 138 | B139: 400002 | C139: 沉重石锤 | D139: 法器 | E139: implement | F139: common | G139: 无 | H139: none | I139: 1×1 | J139: 1 | K139: 3 | L139: 是 | M139: bazaar；dynamicRandomReward；itemReforge | N139: 1 | O139: 周期触发 | P139: periodicPulse | Q139: 周期触发：消耗 1 点体力，对敌人造成 1 点伤害；消耗 2 点体力，对敌人造成 2 点伤害；消耗 3 点体力，对敌人造成 3 点伤害；消耗 4 点体力，对敌人造成 4 点伤害 | S139: 石制重锤带着金属包边与缠带木柄，握久了臂骨发沉，浊气也被迫压入筋肉。 | T139: implement_stone_war_hammer_1x1 | U139: onboardingProtected
A140: 139 | B140: 400003 | C140: 转灵佩 | D140: 法器 | E140: implement | F140: common | G140: 无 | H140: none | I140: 1×2 | J140: 2 | K140: 10 | L140: 是 | M140: bazaar；dynamicRandomReward；itemReforge | N140: 1 | O140: 周期触发 | P140: periodicPulse | Q140: 周期触发：体力未满时，将 1 块灵石转化为 8 点体力；体力未满时，将 1 块灵石转化为 16 点体力；体力未满时，将 1 块灵石转化为 24 点体力；体力未满时，将 1 块灵石转化为 32 点体力 | S140: 狭长石佩刻着盘绕道纹，贴近心口时微微发凉，仿佛把游散灵机牵回一条稳线。 | T140: scripture_dao_stone_tablet_1x2 | U140: allowed
A141: 140 | B141: 400004 | C141: 铁砂绑腿 | D141: 法器 | E141: implement | F141: common | G141: 无 | H141: none | I141: 1×2 | J141: 2 | K141: 1 | L141: 是 | M141: bazaar；dynamicRandomReward；itemReforge | N141: 1 | O141: 被动效果 | P141: passive | Q141: 被动效果：位于储物袋底部时，体力上限 +2；位于储物袋底部时，体力上限 +4；位于储物袋底部时，体力上限 +6；位于储物袋底部时，体力上限 +8 | S141: 深色束扣卷带里灌着细铁砂，系紧后每一步都沉坠踏实，久行反而稳住脚底气息。 | T141: implement_iron_sand_legwraps_1x2 | U141: onboardingProtected
A142: 141 | B142: 400005 | C142: 铜皮腰带 | D142: 法器 | E142: implement | F142: common | G142: 无 | H142: none | I142: 1×1 | J142: 1 | K142: 1 | L142: 是 | M142: bazaar；dynamicRandomReward；itemReforge | N142: 1 | O142: 被动效果 | P142: passive | Q142: 被动效果：未贴住储物袋边缘时，体力上限 +3；未贴住储物袋边缘时，体力上限 +6；未贴住储物袋边缘时，体力上限 +9；未贴住储物袋边缘时，体力上限 +12 | S142: 厚皮环带缀着铜扣与铆钉，束上腰身略显拘束，却能把松散力气重新箍回躯壳。 | T142: implement_leather_restraint_collar_1x1 | U142: onboardingProtected
A143: 142 | B143: 400006 | C143: 引火匣 | D143: 法器 | E143: implement | F143: common | G143: 火 | H143: fire | I143: 2×2 | J143: 4 | K143: 5 | L143: 是 | M143: bazaar；dynamicRandomReward；itemReforge | N143: 1 | O143: 条件触发 | P143: triggered | Q143: 条件触发：右侧相邻火属性道具获得炎热时，额外获得 3 层炎热；右侧相邻火属性道具获得炎热时，额外获得 5 层炎热；右侧相邻火属性道具获得炎热时，额外获得 7 层炎热；右侧相邻火属性道具获得炎热时，额外获得 9 层炎热 | R143: starter_yangzhen | S143: 暗红鎏金匣中藏着一缕偏火，焰光不烈，却总沿匣缝往丹室深处钻。 | T143: implement_yinhuo_bias_box_2x2 | U143: allowed
A144: 143 | B144: 400007 | C144: 回元壶 | D144: 法器 | E144: implement | F144: common | G144: 无 | H144: none | I144: 1×2 | J144: 2 | K144: 3 | L144: 是 | M144: bazaar；journeyChest；dynamicRandomReward；itemReforge | N144: 1 | O144: 周期触发 | P144: periodicPulse | Q144: 周期触发：将 1 点法力转化为 2 点体力；将 2 点法力转化为 4 点体力；将 3 点法力转化为 6 点体力；将 4 点法力转化为 8 点体力 | R144: starter_yangzhen | S144: 青玉葫芦接着竹管滴露，药液温润如新雨，壶口常有回气的湿意不散。 | T144: implement_huiyuan_drip_1x2 | U144: allowed
A145: 144 | B145: 400009 | C145: 养魄筹 | D145: 法器 | E145: implement | F145: common | G145: 无 | H145: none | I145: 3×1 | J145: 3 | K145: 6 | L145: 是 | M145: bazaar；dynamicRandomReward；itemReforge | N145: 1 | O145: 周期触发 | P145: periodicPulse | Q145: 周期触发：和功法相邻时，恢复 4 点体力；和功法相邻时，恢复 5 点体力；和功法相邻时，恢复 6 点体力；和功法相邻时，恢复 7 点体力 | R145: starter_yangzhen | S145: 褐色木筹刻满金纹符字，浸过苦药的纹理温沉，握在手里会把气血慢慢拢稳。 | T145: implement_yangpo_wood_tally_3x1 | U145: allowed
A146: 145 | B146: 400010 | C146: 回响小铃 | D146: 法器 | E146: implement | F146: common | G146: 无 | H146: none | I146: 1×1 | J146: 1 | K146: 7 | L146: 是 | M146: bazaar；dynamicRandomReward；itemReforge | N146: 1 | O146: 条件触发 | P146: triggered | Q146: 条件触发：主动释放招式时，恢复 3 点法力；主动释放招式时，恢复 4 点法力；主动释放招式时，恢复 5 点法力；主动释放招式时，恢复 6 点法力 | S146: 小铃清亮而壁薄，轻振时灵音层层回返，像能把散开的心神召回耳畔。 | T146: implement_echospirit_bell_1x1 | U146: allowed
A147: 146 | B147: 400011 | C147: 护心小镜 | D147: 法器 | E147: implement | F147: common | G147: 无 | H147: none | I147: 1×1 | J147: 1 | K147: 2 | L147: 是 | M147: bazaar；dynamicRandomReward；itemReforge | N147: 1 | O147: 周期触发 | P147: periodicPulse | Q147: 周期触发：开局：如果上方相邻装备，获得 4 层护甲；开局：如果上方相邻装备，获得 8 层护甲；开局：如果上方相邻装备，获得 12 层护甲；开局：如果上方相邻装备，获得 16 层护甲 | S147: 圆镜金属外沿厚重，镜背旧纹细密，照面时光色安静，像替心口挡下一缕浮邪。 | T147: implement_guardward_mirror_1x1 | U147: allowed
A148: 147 | B148: 400012 | C148: 青壶露瓶 | D148: 法器 | E148: implement | F148: common | G148: 无 | H148: none | I148: 1×2 | J148: 2 | K148: 10 | L148: 是 | M148: bazaar；dynamicRandomReward；itemReforge | N148: 1 | O148: 条件触发 | P148: triggered | Q148: 条件触发：相邻 2x2 道具使用时，恢复 1 点法力；相邻 2x2 道具使用时，恢复 2 点法力；相邻 2x2 道具使用时，恢复 3 点法力；相邻 2x2 道具使用时，恢复 4 点法力 | S148: 青绿开片葫芦瓶温润如玉，瓶腹常凝细露，久置静处便积出一圈清润水气。 | T148: pill_emerald_gourd_vial_1x2 | U148: allowed
A149: 148 | B149: 400013 | C149: 小丹匣 | D149: 宝箱 | E149: chest | F149: common | G149: 无 | H149: none | I149: 1×1 | J149: 1 | K149: 4 | L149: 否 | M149: bazaar；beastDrop | N149: 1 | O149: 消耗品效果 | P149: consumable | Q149: 消耗品效果：获得 5 个聚气丹 | S149: 浅色方盒分作六格，白色丹丸各安其位，合盖后仍有细细药香藏在木缝里。 | T149: chest_pill_box_1x1 | U149: allowed
A150: 149 | B150: 400014 | C150: 初阶丹炉 | D150: 法器 | E150: implement | F150: common | G150: 无 | H150: none | I150: 2×2 | J150: 4 | K150: 30 | L150: 是 | M150: bazaar；itemReforge | N150: 1 | O150: 周期触发 | P150: periodicPulse | Q150: 周期触发：适用于凡品丹方，成功率 +25%，大成功率 +5% | R150: basic_pill_furnace | S150: 凡铁旧炉火痕斑驳，炉腹常带余温，像散修静室里用过多年的老炉。 | T150: implement_emberheart_censer_2x2 | U150: allowed
A151: 150 | B151: 400015 | C151: 聚气石盆 | D151: 法器 | E151: implement | F151: common | G151: 水 | H151: water | I151: 2×2 | J151: 4 | K151: 10 | L151: 是 | M151: bazaar；dynamicRandomReward；itemReforge | N151: 1 | O151: 条件触发 | P151: triggered | Q151: 条件触发：累计生成 30 层露水后，恢复 20 点法力；累计生成 30 层露水后，恢复 30 点法力；累计生成 30 层露水后，恢复 40 点法力；累计生成 30 层露水后，恢复 50 点法力 | S151: 原石半凿成盆，内里灵液回旋不散，周遭散气落到盆沿便像被轻轻收住。 | T151: implement_jade_spirit_basin_2x2 | U151: allowed
A152: 151 | B152: 400016 | C152: 青铜丹炉 | D152: 法器 | E152: implement | F152: common | G152: 无 | H152: none | I152: 2×2 | J152: 4 | K152: 60 | L152: 是 | M152: bazaar；itemReforge | N152: 1 | O152: 周期触发 | P152: periodicPulse | Q152: 周期触发：适用于凡品丹方，成功率 +45%，大成功率 +5% | S152: 青铜炉身厚实朴拙，双耳与炉足皆有长期温养留下的暗润火色。 | T152: implement_bronze_alchemy_furnace_2x2 | U152: allowed
A153: 152 | B153: 400017 | C153: 养火丹炉 | D153: 法器 | E153: implement | F153: common | G153: 火 | H153: fire | I153: 2×3 | J153: 6 | K153: 30 | L153: 是 | M153: bazaar；itemReforge | N153: 1 | O153: 周期触发 | P153: periodicPulse | Q153: 周期触发：适用于凡品丹方，成功率 +25%，大成功率 +5% | S153: 细长炉腹内铺着耐火陶胆，炉门常开一线，使旺盛火气能够迅速穿行。 | T153: implement_fire_nurturing_alchemy_furnace_2x3 | U153: allowed
A154: 153 | B154: 400018 | C154: 宽腹丹炉 | D154: 法器 | E154: implement | F154: spirit | G154: 无 | H154: none | I154: 3×3 | J154: 9 | K154: 188 | L154: 是 | M154: bazaar；dynamicRandomReward；itemReforge | N154: 1 | O154: 周期触发 | P154: periodicPulse | Q154: 周期触发：成功率 +63%，大成功率 +10%（适用于灵品以下丹方） | S154: 宽阔炉腹由整片熟铁围成，内壁分层承火，足以容下形制复杂的凡品、灵品丹方与灵材。 | T154: implement_wide_bellied_alchemy_furnace_3x3 | U154: allowed
A155: 154 | B155: 400019 | C155: 玄铜定灵炉 | D155: 法器 | E155: implement | F155: spirit | G155: 无 | H155: none | I155: 3×3 | J155: 9 | K155: 200 | L155: 是 | M155: bazaar；dynamicRandomReward；itemReforge | N155: 1 | O155: 周期触发 | P155: periodicPulse | Q155: 周期触发：成功率 +50%，大成功率 +17%（适用于灵品以下丹方） | S155: 深青玄铜炉腹由三道镇灵铜箍收紧，云雷纹与压火铆钉把炉火稳稳锁在厚重炉盖之下。 | T155: implement_xuantong_spirit_stabilizing_furnace_3x3 | U155: allowed
A156: 155 | B156: 400020 | C156: 流焰丹炉 | D156: 法器 | E156: implement | F156: spirit | G156: 火 | H156: fire | I156: 3×3 | J156: 9 | K156: 280 | L156: 是 | M156: bazaar；dynamicRandomReward；itemReforge | N156: 1 | O156: 周期触发 | P156: periodicPulse | Q156: 周期触发：成功率 +30%，大成功率 +30%（适用于灵品以下丹方） | S156: 赤铜导火槽绕着暗红陶胆回旋，通风鳍片与小火门令炉腹里的热流始终奔走不息。 | T156: implement_flowing_flame_alchemy_furnace_3x3 | U156: allowed
A157: 156 | B157: 400021 | C157: 龙首焰戒 | D157: 法器 | E157: implement | F157: common | G157: 火 | H157: fire | I157: 1×1 | J157: 1 | K157: 5 | L157: 是 | M157: bazaar；dynamicRandomReward；itemReforge | N157: 1 | O157: 周期触发 | P157: periodicPulse | Q157: 周期触发：每相邻 1 件火属性饰品，获得 3 层炎热；每相邻 1 件火属性饰品，获得 6 层炎热；每相邻 1 件火属性饰品，获得 9 层炎热；每相邻 1 件火属性饰品，获得 12 层炎热 | S157: 金属龙首盘绕成戒，鳞角间赤金暗光内敛，似有余焰蛰伏在眼眶深处。 | T157: implement_dragon_ring_1x1 | U157: allowed
A158: 157 | B158: 400022 | C158: 玄纹束带 | D158: 法器 | E158: implement | F158: common | G158: 无 | H158: none | I158: 3×1 | J158: 3 | K158: 25 | L158: 是 | M158: bazaar；dynamicRandomReward；itemReforge | N158: 1 | O158: 周期触发 | P158: periodicPulse | Q158: 周期触发：每有 1 层炎热，使上方相邻装备获得 0.1 秒加速（最多计算 50 层）；每有 1 层炎热，使上方相邻装备获得 0.2 秒加速（最多计算 50 层）；每有 1 层炎热，使上方相邻装备获得 0.3 秒加速（最多计算 50 层）；每有 1 层炎热，使上方相邻装备获得 0.4 秒加速（最多计算 50 层） | S158: 黑灰编纹腰带配着冷银扣件，横束时线纹层层咬合，像把奔散火息拢成一线。 | T158: implement_dark_braided_belt_3x1 | U158: allowed
A159: 158 | B159: 400023 | C159: 沉岳锤 | D159: 法器 | E159: implement | F159: common | G159: 土 | H159: earth | I159: 2×2 | J159: 4 | K159: 6 | L159: 是 | M159: bazaar；dynamicRandomReward；itemReforge | N159: 1 | O159: 周期触发 | P159: periodicPulse | Q159: 周期触发：消耗 10 点体力，对敌人造成 10 点伤害；消耗 15 点体力，对敌人造成 15 点伤害；消耗 20 点体力，对敌人造成 20 点伤害；消耗 25 点体力，对敌人造成 25 点伤害 | S159: 银白刺锤垂着黑链与青缨，锤头沉猛压尘，未挥动时便已有镇煞破阵之势。 | T159: implement_exorcist_meteor_hammer_2x2 | U159: allowed
A160: 159 | B160: 400024 | C160: 回元佩 | D160: 法器 | E160: implement | F160: common | G160: 木 | H160: wood | I160: 1×1 | J160: 1 | K160: 12 | L160: 是 | M160: bazaar；dynamicRandomReward；itemReforge | N160: 1 | O160: 周期触发 | P160: periodicPulse | Q160: 周期触发：恢复 5 法力；恢复 6 法力；恢复 7 法力；恢复 8 法力 | S160: 青碧玉佩嵌着灵珠，浅纹如水波在心处回环，贴近时有雨后玉石的清凉气。 | T160: implement_azureheart_pendant_1x1 | U160: allowed
A161: 160 | B161: 400026 | C161: 羽纹护臂 | D161: 法器 | E161: implement | F161: common | G161: 无 | H161: none | I161: 2×1 | J161: 2 | K161: 10 | L161: 是 | M161: bazaar；dynamicRandomReward；itemReforge | N161: 1 | O161: 周期触发 | P161: periodicPulse | Q161: 周期触发：获得 2 层护甲；获得 3 层护甲；获得 4 层护甲；获得 5 层护甲 | S161: 金羽外展的护臂轻贴腕侧，银灰边线如风掠袖口，抬手时有羽影相随。 | T161: implement_feather_bracer_2x1 | U161: allowed
...

Sheet 效果明细
A1: 物品ID | B1: 名称 | C1: 类别 | D1: 品阶代码 | E1: 元素代码 | F1: 顶层效果序号 | G1: 作用层级 | H1: 功法层数 | I1: 突破要求 | J1: 突破目标 | K1: 限时(秒) | L1: 冷却(秒) | M1: 效果类型 | N1: 效果类型代码 | O1: 效果文字 | P1: 触发器代码 | Q1: 机制类型代码 | R1: 效果JSON
A2: 100001 | B2: 炼体术 | C2: 功法 | D2: common | E2: none | F2: 1 | G2: 基础/顶层 | M2: 被动效果 | N2: passive | O2: 每消耗 1 点体力，获得 1 点修为 | Q2: staminaConsumedToCultivation | R2: {"kind":"passive","label":"每消耗 1 点体力，获得 1 点修为","passiveEffect":{"type":"staminaConsumedToCultivation","value":1,"label":"每消耗 1 点体力，获得 1 点修为"}}
A3: 100001 | B3: 炼体术 | C3: 功法 | D3: common | E3: none | F3: 2 | G3: 功法成长层 | H3: 1 | I3: 无 | L3: 15 | M3: 被动效果 | N3: passive | O3: 每消耗 1 点体力，获得 1 点修为 | Q3: staminaConsumedToCultivation | R3: {"kind":"passive","label":"每消耗 1 点体力，获得 1 点修为","passiveEffect":{"type":"staminaConsumedToCultivation","value":1,"label":"每消耗 1 点体力，获得 1 点修为"}}
A4: 100001 | B4: 炼体术 | C4: 功法 | D4: common | E4: none | F4: 2 | G4: 功法成长层 | H4: 2 | I4: 修为≥120 | J4: 120 | K4: 190 | L4: 15 | M4: 被动效果 | N4: passive | O4: 每消耗 1 点体力，获得 2 点修为 | Q4: staminaConsumedToCultivation | R4: {"kind":"passive","label":"每消耗 1 点体力，获得 2 点修为","passiveEffect":{"type":"staminaConsumedToCultivation","value":2,"label":"每消耗 1 点体力，获得 2 点修为"}}
A5: 100001 | B5: 炼体术 | C5: 功法 | D5: common | E5: none | F5: 2 | G5: 功法成长层 | H5: 3 | I5: 修为≥760；境界≥炼气4层 | J5: 760 | K5: 230 | L5: 60 | M5: 被动效果 | N5: passive | O5: 每消耗 1 点体力，获得 3 点修为 | Q5: staminaConsumedToCultivation | R5: {"kind":"passive","label":"每消耗 1 点体力，获得 3 点修为","passiveEffect":{"type":"staminaConsumedToCultivation","value":3,"label":"每消耗 1 点体力，获得 3 点修为"}}
A6: 100001 | B6: 炼体术 | C6: 功法 | D6: common | E6: none | F6: 2 | G6: 功法成长层 | H6: 4 | I6: 修为≥2450；境界≥炼气4层 | J6: 2450 | K6: 230 | L6: 120 | M6: 被动效果 | N6: passive | O6: 每消耗 1 点体力，获得 4 点修为 | Q6: staminaConsumedToCultivation | R6: {"kind":"passive","label":"每消耗 1 点体力，获得 4 点修为","passiveEffect":{"type":"staminaConsumedToCultivation","value":4,"label":"每消耗 1 点体力，获得 4 点修为"}}
A7: 100002 | B7: 云字养气册 | C7: 功法 | D7: common | E7: wood | F7: 1 | G7: 基础/顶层 | M7: 条件触发 | N7: triggered | O7: 每获得 1 点气血，获得 3 点修为 | P7: onPrimaryStatGain | Q7: gainCultivation | R7: {"kind":"triggered","label":"每获得 1 点气血，获得 3 点修为","triggeredEffect":{"trigger":"onPrimaryStatGain","type":"gainCultivation","amount":2,"amountPerEventPrimaryStatGain":1,"eventPrimaryStatGainFilter":["health"]}}
A8: 100002 | B8: 云字养气册 | C8: 功法 | D8: common | E8: wood | F8: 2 | G8: 功法成长层 | H8: 1 | I8: 无 | L8: 15 | M8: 条件触发 | N8: triggered | O8: 每获得 1 点气血，获得 3 点修为 | P8: onPrimaryStatGain | Q8: gainCultivation | R8: {"kind":"triggered","label":"每获得 1 点气血，获得 3 点修为","triggeredEffect":{"trigger":"onPrimaryStatGain","type":"gainCultivation","amount":2,"amountPerEventPrimaryStatGain":1,"eventPrimaryStatGainFilter":["health"]}}
A9: 100002 | B9: 云字养气册 | C9: 功法 | D9: common | E9: wood | F9: 2 | G9: 功法成长层 | H9: 2 | I9: 修为≥210 | J9: 210 | K9: 275 | L9: 30 | M9: 条件触发 | N9: triggered | O9: 每获得 1 点气血，获得 6 点修为 | P9: onPrimaryStatGain | Q9: gainCultivation | R9: {"kind":"triggered","label":"每获得 1 点气血，获得 6 点修为","triggeredEffect":{"trigger":"onPrimaryStatGain","type":"gainCultivation","amount":4,"amountPerEventPrimaryStatGain":2,"eventPrimaryStatGainFilter":["health"]}}
A10: 100002 | B10: 云字养气册 | C10: 功法 | D10: common | E10: wood | F10: 2 | G10: 功法成长层 | H10: 3 | I10: 修为≥540 | J10: 540 | K10: 195 | L10: 90 | M10: 条件触发 | N10: triggered | O10: 每获得 1 点气血，获得 9 点修为 | P10: onPrimaryStatGain | Q10: gainCultivation | R10: {"kind":"triggered","label":"每获得 1 点气血，获得 9 点修为","triggeredEffect":{"trigger":"onPrimaryStatGain","type":"gainCultivation","amount":6,"amountPerEventPrimaryStatGain":3,"eventPrimaryStatGainFilter":["health"]}}
A11: 100002 | B11: 云字养气册 | C11: 功法 | D11: common | E11: wood | F11: 2 | G11: 功法成长层 | H11: 4 | I11: 修为≥2950 | J11: 2950 | K11: 240 | L11: 240 | M11: 条件触发 | N11: triggered | O11: 每获得 1 点气血，获得 12 点修为 | P11: onPrimaryStatGain | Q11: gainCultivation | R11: {"kind":"triggered","label":"每获得 1 点气血，获得 12 点修为","triggeredEffect":{"trigger":"onPrimaryStatGain","type":"gainCultivation","amount":8,"amountPerEventPrimaryStatGain":4,"eventPrimaryStatGainFilter":["health"]}}
A12: 100003 | B12: 聚气册 | C12: 功法 | D12: common | E12: fire | F12: 1 | G12: 基础/顶层 | M12: 周期触发 | N12: periodicPulse | O12: 获得 10 点修为 | R12: {"kind":"periodicPulse","periodicPulse":{"intervalSec":30,"label":"获得 10 点修为","cultivationGain":10}}
A13: 100003 | B13: 聚气册 | C13: 功法 | D13: common | E13: fire | F13: 2 | G13: 基础/顶层 | M13: 条件触发 | N13: triggered | O13: 每当有丹药耗尽时，获得 10 点修为 | P13: onConsumableExhausted | Q13: grantResources；cultivation；any | R13: {"kind":"triggered","label":"每当有丹药耗尽时，获得 10 点修为","triggeredEffect":{"trigger":"onConsumableExhausted","type":"grantResources","grants":[{"type":"cultivation","amount":10}],"support":"cultivationOnly","eventSource":{"target":{"type":"any"},"filter":{"categories":["pill"]}}}}
A14: 100003 | B14: 聚气册 | C14: 功法 | D14: common | E14: fire | F14: 3 | G14: 功法成长层 | H14: 1 | I14: 无 | L14: 15 | M14: 周期触发 | N14: periodicPulse | O14: 获得 10 点修为 | R14: {"kind":"periodicPulse","periodicPulse":{"intervalSec":30,"label":"获得 10 点修为","cultivationGain":10}}
A15: 100003 | B15: 聚气册 | C15: 功法 | D15: common | E15: fire | F15: 3 | G15: 功法成长层 | H15: 1 | I15: 无 | L15: 15 | M15: 条件触发 | N15: triggered | O15: 每当有丹药耗尽时，获得 10 点修为 | P15: onConsumableExhausted | Q15: grantResources；cultivation；any | R15: {"kind":"triggered","label":"每当有丹药耗尽时，获得 10 点修为","triggeredEffect":{"trigger":"onConsumableExhausted","type":"grantResources","grants":[{"type":"cultivation","amount":10}],"support":"cultivationOnly","eventSource":{"target":{"type":"any"},"filter":{"categories":["pill"]}}}}
A16: 100003 | B16: 聚气册 | C16: 功法 | D16: common | E16: fire | F16: 3 | G16: 功法成长层 | H16: 2 | I16: 修为≥210 | J16: 210 | K16: 290 | L16: 30 | M16: 周期触发 | N16: periodicPulse | O16: 获得 25 点修为 | R16: {"kind":"periodicPulse","periodicPulse":{"intervalSec":20,"label":"获得 25 点修为","cultivationGain":25}}
A17: 100003 | B17: 聚气册 | C17: 功法 | D17: common | E17: fire | F17: 3 | G17: 功法成长层 | H17: 2 | I17: 修为≥210 | J17: 210 | K17: 290 | L17: 30 | M17: 条件触发 | N17: triggered | O17: 每当有丹药耗尽时，获得 20 点修为 | P17: onConsumableExhausted | Q17: grantResources；cultivation；any | R17: {"kind":"triggered","label":"每当有丹药耗尽时，获得 20 点修为","triggeredEffect":{"trigger":"onConsumableExhausted","type":"grantResources","grants":[{"type":"cultivation","amount":20}],"support":"cultivationOnly","eventSource":{"target":{"type":"any"},"filter":{"categories":["pill"]}}}}
A18: 100003 | B18: 聚气册 | C18: 功法 | D18: common | E18: fire | F18: 3 | G18: 功法成长层 | H18: 3 | I18: 修为≥760 | J18: 760 | K18: 195 | L18: 120 | M18: 周期触发 | N18: periodicPulse | O18: 获得 40 点修为 | R18: {"kind":"periodicPulse","periodicPulse":{"intervalSec":15,"label":"获得 40 点修为","cultivationGain":40}}
A19: 100003 | B19: 聚气册 | C19: 功法 | D19: common | E19: fire | F19: 3 | G19: 功法成长层 | H19: 3 | I19: 修为≥760 | J19: 760 | K19: 195 | L19: 120 | M19: 条件触发 | N19: triggered | O19: 每当有丹药耗尽时，获得 30 点修为 | P19: onConsumableExhausted | Q19: grantResources；cultivation；any | R19: {"kind":"triggered","label":"每当有丹药耗尽时，获得 30 点修为","triggeredEffect":{"trigger":"onConsumableExhausted","type":"grantResources","grants":[{"type":"cultivation","amount":30}],"support":"cultivationOnly","eventSource":{"target":{"type":"any"},"filter":{"categories":["pill"]}}}}
A20: 100004 | B20: 月痕养息册 | C20: 功法 | D20: common | E20: none | F20: 1 | G20: 基础/顶层 | M20: 条件触发 | N20: triggered | O20: 每获得 1 点法力，获得 1 点修为 | P20: onPrimaryStatGain | Q20: gainCultivation | R20: {"kind":"triggered","label":"<cultivation>每获得 1 点法力，获得 1 点修为</cultivation>","triggeredEffect":{"trigger":"onPrimaryStatGain","type":"gainCultivation","amount":0,"amountPerEventPrimaryStatGain":1,"eventPrimaryStatGainFilter":["mana"]}}
A21: 100004 | B21: 月痕养息册 | C21: 功法 | D21: common | E21: none | F21: 2 | G21: 基础/顶层 | M21: 被动效果 | N21: passive | O21: 法力上限 +10 | Q21: primaryStatMaxFlatBonus | R21: {"kind":"passive","label":"法力上限 +10","passiveEffect":{"type":"primaryStatMaxFlatBonus","stat":"mana","value":10,"label":"法力上限 +10"}}
A22: 100004 | B22: 月痕养息册 | C22: 功法 | D22: common | E22: none | F22: 3 | G22: 功法成长层 | H22: 1 | I22: 无 | L22: 15 | M22: 条件触发 | N22: triggered | O22: 每获得 1 点法力，获得 1 点修为 | P22: onPrimaryStatGain | Q22: gainCultivation | R22: {"kind":"triggered","label":"<cultivation>每获得 1 点法力，获得 1 点修为</cultivation>","triggeredEffect":{"trigger":"onPrimaryStatGain","type":"gainCultivation","amount":0,"amountPerEventPrimaryStatGain":1,"eventPrimaryStatGainFilter":["mana"]}}
A23: 100004 | B23: 月痕养息册 | C23: 功法 | D23: common | E23: none | F23: 3 | G23: 功法成长层 | H23: 1 | I23: 无 | L23: 15 | M23: 被动效果 | N23: passive | O23: 法力上限 +10 | Q23: primaryStatMaxFlatBonus | R23: {"kind":"passive","label":"法力上限 +10","passiveEffect":{"type":"primaryStatMaxFlatBonus","stat":"mana","value":10,"label":"法力上限 +10"}}
A24: 100004 | B24: 月痕养息册 | C24: 功法 | D24: common | E24: none | F24: 3 | G24: 功法成长层 | H24: 2 | I24: 修为≥150 | J24: 150 | K24: 195 | L24: 30 | M24: 条件触发 | N24: triggered | O24: 每获得 1 点法力，获得 2 点修为 | P24: onPrimaryStatGain | Q24: gainCultivation | R24: {"kind":"triggered","label":"<cultivation>每获得 1 点法力，获得 2 点修为</cultivation>","triggeredEffect":{"trigger":"onPrimaryStatGain","type":"gainCultivation","amount":0,"amountPerEventPrimaryStatGain":2,"eventPrimaryStatGainFilter":["mana"]}}
A25: 100004 | B25: 月痕养息册 | C25: 功法 | D25: common | E25: none | F25: 3 | G25: 功法成长层 | H25: 2 | I25: 修为≥150 | J25: 150 | K25: 195 | L25: 30 | M25: 被动效果 | N25: passive | O25: 法力上限 +20 | Q25: primaryStatMaxFlatBonus | R25: {"kind":"passive","label":"法力上限 +20","passiveEffect":{"type":"primaryStatMaxFlatBonus","stat":"mana","value":20,"label":"法力上限 +20"}}
A26: 100004 | B26: 月痕养息册 | C26: 功法 | D26: common | E26: none | F26: 3 | G26: 功法成长层 | H26: 3 | I26: 修为≥780 | J26: 780 | K26: 205 | L26: 90 | M26: 条件触发 | N26: triggered | O26: 每获得 1 点法力，获得 3 点修为 | P26: onPrimaryStatGain | Q26: gainCultivation | R26: {"kind":"triggered","label":"<cultivation>每获得 1 点法力，获得 3 点修为</cultivation>","triggeredEffect":{"trigger":"onPrimaryStatGain","type":"gainCultivation","amount":0,"amountPerEventPrimaryStatGain":3,"eventPrimaryStatGainFilter":["mana"]}}
A27: 100004 | B27: 月痕养息册 | C27: 功法 | D27: common | E27: none | F27: 3 | G27: 功法成长层 | H27: 3 | I27: 修为≥780 | J27: 780 | K27: 205 | L27: 90 | M27: 被动效果 | N27: passive | O27: 法力上限 +30 | Q27: primaryStatMaxFlatBonus | R27: {"kind":"passive","label":"法力上限 +30","passiveEffect":{"type":"primaryStatMaxFlatBonus","stat":"mana","value":30,"label":"法力上限 +30"}}
A28: 100004 | B28: 月痕养息册 | C28: 功法 | D28: common | E28: none | F28: 3 | G28: 功法成长层 | H28: 4 | I28: 修为≥3800 | J28: 3800 | K28: 275 | L28: 120 | M28: 条件触发 | N28: triggered | O28: 每获得 1 点法力，获得 4 点修为 | P28: onPrimaryStatGain | Q28: gainCultivation | R28: {"kind":"triggered","label":"<cultivation>每获得 1 点法力，获得 4 点修为</cultivation>","triggeredEffect":{"trigger":"onPrimaryStatGain","type":"gainCultivation","amount":0,"amountPerEventPrimaryStatGain":4,"eventPrimaryStatGainFilter":["mana"]}}
A29: 100004 | B29: 月痕养息册 | C29: 功法 | D29: common | E29: none | F29: 3 | G29: 功法成长层 | H29: 4 | I29: 修为≥3800 | J29: 3800 | K29: 275 | L29: 120 | M29: 被动效果 | N29: passive | O29: 法力上限 +40 | Q29: primaryStatMaxFlatBonus | R29: {"kind":"passive","label":"法力上限 +40","passiveEffect":{"type":"primaryStatMaxFlatBonus","stat":"mana","value":40,"label":"法力上限 +40"}}
A30: 100010 | B30: 五行入门篇 | C30: 功法 | D30: common | E30: none | F30: 1 | G30: 基础/顶层 | M30: 被动效果 | N30: passive | O30: 每消耗 1 点法力，获得 1 点修为 | Q30: primaryStatConsumedToCultivation | R30: {"kind":"passive","passiveEffect":{"type":"primaryStatConsumedToCultivation","stat":"mana","cost":1,"gain":1,"label":"每消耗 1 点法力，获得 1 点修为"}}
A31: 100010 | B31: 五行入门篇 | C31: 功法 | D31: common | E31: none | F31: 2 | G31: 功法成长层 | H31: 1 | I31: 无 | L31: 15 | M31: 被动效果 | N31: passive | O31: 每消耗 1 点法力，获得 1 点修为 | Q31: primaryStatConsumedToCultivation | R31: {"kind":"passive","passiveEffect":{"type":"primaryStatConsumedToCultivation","stat":"mana","cost":1,"gain":1,"label":"每消耗 1 点法力，获得 1 点修为"}}
A32: 100010 | B32: 五行入门篇 | C32: 功法 | D32: common | E32: none | F32: 2 | G32: 功法成长层 | H32: 2 | I32: 修为≥140；境界≥炼气4层 | J32: 140 | K32: 210 | L32: 30 | M32: 被动效果 | N32: passive | O32: 每消耗 1 点法力，获得 2 点修为 | Q32: primaryStatConsumedToCultivation | R32: {"kind":"passive","passiveEffect":{"type":"primaryStatConsumedToCultivation","stat":"mana","cost":1,"gain":2,"label":"每消耗 1 点法力，获得 2 点修为"}}
A33: 100010 | B33: 五行入门篇 | C33: 功法 | D33: common | E33: none | F33: 2 | G33: 功法成长层 | H33: 3 | I33: 修为≥1000 | J33: 1000 | K33: 300 | L33: 60 | M33: 被动效果 | N33: passive | O33: 每消耗 1 点法力，获得 3 点修为 | Q33: primaryStatConsumedToCultivation | R33: {"kind":"passive","passiveEffect":{"type":"primaryStatConsumedToCultivation","stat":"mana","cost":1,"gain":3,"label":"每消耗 1 点法力，获得 3 点修为"}}
A34: 100010 | B34: 五行入门篇 | C34: 功法 | D34: common | E34: none | F34: 2 | G34: 功法成长层 | H34: 4 | I34: 修为≥6000 | J34: 6000 | K34: 285 | L34: 90 | M34: 被动效果 | N34: passive | O34: 每消耗 1 点法力，获得 4 点修为 | Q34: primaryStatConsumedToCultivation | R34: {"kind":"passive","passiveEffect":{"type":"primaryStatConsumedToCultivation","stat":"mana","cost":1,"gain":4,"label":"每消耗 1 点法力，获得 4 点修为"}}
A35: 100011 | B35: 烈阳诀 | C35: 功法 | D35: common | E35: fire | F35: 1 | G35: 基础/顶层 | M35: 条件触发 | N35: triggered | O35: 每获得 1 层炎热，获得 2 点修为 | P35: onBuffGain | Q35: gainCultivation | R35: {"kind":"triggered","label":"每获得 1 层炎热，获得 2 点修为","triggeredEffect":{"trigger":"onBuffGain","type":"gainCultivation","amount":0,"amountPerEventBuffStack":2,"eventBuffId":"heat"}}
A36: 100011 | B36: 烈阳诀 | C36: 功法 | D36: common | E36: fire | F36: 2 | G36: 基础/顶层 | M36: 被动效果 | N36: passive | O36: 炎热层数上限 +3 | Q36: buffStackCapBonus | R36: {"kind":"passive","label":"炎热层数上限 +3","passiveEffect":{"type":"buffStackCapBonus","buffId":"heat","value":3,"label":"炎热层数上限 +3"}}
A37: 100011 | B37: 烈阳诀 | C37: 功法 | D37: common | E37: fire | F37: 3 | G37: 功法成长层 | H37: 1 | I37: 无 | L37: 15 | M37: 条件触发 | N37: triggered | O37: 每获得 1 层炎热，获得 2 点修为 | P37: onBuffGain | Q37: gainCultivation | R37: {"kind":"triggered","label":"每获得 1 层炎热，获得 2 点修为","triggeredEffect":{"trigger":"onBuffGain","type":"gainCultivation","amount":0,"amountPerEventBuffStack":2,"eventBuffId":"heat"}}
A38: 100011 | B38: 烈阳诀 | C38: 功法 | D38: common | E38: fire | F38: 3 | G38: 功法成长层 | H38: 1 | I38: 无 | L38: 15 | M38: 被动效果 | N38: passive | O38: 炎热层数上限 +3 | Q38: buffStackCapBonus | R38: {"kind":"passive","label":"炎热层数上限 +3","passiveEffect":{"type":"buffStackCapBonus","buffId":"heat","value":3,"label":"炎热层数上限 +3"}}
A39: 100011 | B39: 烈阳诀 | C39: 功法 | D39: common | E39: fire | F39: 3 | G39: 功法成长层 | H39: 2 | I39: 修为≥160 | J39: 160 | K39: 230 | L39: 60 | M39: 条件触发 | N39: triggered | O39: 每获得 1 层炎热，获得 4 点修为 | P39: onBuffGain | Q39: gainCultivation | R39: {"kind":"triggered","label":"每获得 1 层炎热，获得 4 点修为","triggeredEffect":{"trigger":"onBuffGain","type":"gainCultivation","amount":0,"amountPerEventBuffStack":4,"eventBuffId":"heat"}}
A40: 100011 | B40: 烈阳诀 | C40: 功法 | D40: common | E40: fire | F40: 3 | G40: 功法成长层 | H40: 2 | I40: 修为≥160 | J40: 160 | K40: 230 | L40: 60 | M40: 被动效果 | N40: passive | O40: 炎热层数上限 +6 | Q40: buffStackCapBonus | R40: {"kind":"passive","label":"炎热层数上限 +6","passiveEffect":{"type":"buffStackCapBonus","buffId":"heat","value":6,"label":"炎热层数上限 +6"}}
A41: 100011 | B41: 烈阳诀 | C41: 功法 | D41: common | E41: fire | F41: 3 | G41: 功法成长层 | H41: 3 | I41: 修为≥840 | J41: 840 | K41: 230 | L41: 90 | M41: 条件触发 | N41: triggered | O41: 每获得 1 层炎热，获得 6 点修为 | P41: onBuffGain | Q41: gainCultivation | R41: {"kind":"triggered","label":"每获得 1 层炎热，获得 6 点修为","triggeredEffect":{"trigger":"onBuffGain","type":"gainCultivation","amount":0,"amountPerEventBuffStack":6,"eventBuffId":"heat"}}
A42: 100011 | B42: 烈阳诀 | C42: 功法 | D42: common | E42: fire | F42: 3 | G42: 功法成长层 | H42: 3 | I42: 修为≥840 | J42: 840 | K42: 230 | L42: 90 | M42: 被动效果 | N42: passive | O42: 炎热层数上限 +9 | Q42: buffStackCapBonus | R42: {"kind":"passive","label":"炎热层数上限 +9","passiveEffect":{"type":"buffStackCapBonus","buffId":"heat","value":9,"label":"炎热层数上限 +9"}}
A43: 100011 | B43: 烈阳诀 | C43: 功法 | D43: common | E43: fire | F43: 3 | G43: 功法成长层 | H43: 4 | I43: 修为≥2900 | J43: 2900 | K43: 265 | L43: 180 | M43: 条件触发 | N43: triggered | O43: 每获得 1 层炎热，获得 8 点修为 | P43: onBuffGain | Q43: gainCultivation | R43: {"kind":"triggered","label":"每获得 1 层炎热，获得 8 点修为","triggeredEffect":{"trigger":"onBuffGain","type":"gainCultivation","amount":0,"amountPerEventBuffStack":8,"eventBuffId":"heat"}}
A44: 100011 | B44: 烈阳诀 | C44: 功法 | D44: common | E44: fire | F44: 3 | G44: 功法成长层 | H44: 4 | I44: 修为≥2900 | J44: 2900 | K44: 265 | L44: 180 | M44: 被动效果 | N44: passive | O44: 炎热层数上限 +15 | Q44: buffStackCapBonus | R44: {"kind":"passive","label":"炎热层数上限 +15","passiveEffect":{"type":"buffStackCapBonus","buffId":"heat","value":15,"label":"炎热层数上限 +15"}}
A45: 100012 | B45: 玄水雷纹诀 | C45: 功法 | D45: common | E45: thunder | F45: 1 | G45: 基础/顶层 | M45: 说明/执行器 | N45: effectNote | O45: 每获得 1 层引雷，获得 3 点修为 | P45: onBuffGain | Q45: gainCultivation | R45: {"kind":"effectNote","label":"<cultivation>每获得 1 层引雷，获得 3 点修为</cultivation>","executors":[{"trigger":"onBuffGain","type":"gainCultivation","amount":0,"amountPerEventBuffStack":3,"eventBuffId":"lightningCharge","label":"<cultivation>每获得 1 层引雷，获得 3 点修为</cultivation>"}]}
A46: 100012 | B46: 玄水雷纹诀 | C46: 功法 | D46: common | E46: thunder | F46: 2 | G46: 基础/顶层 | M46: 被动效果 | N46: passive | O46: 引雷层数上限 +3 | Q46: buffStackCapBonus | R46: {"kind":"passive","label":"引雷层数上限 +3","passiveEffect":{"type":"buffStackCapBonus","buffId":"lightningCharge","value":3,"label":"引雷层数上限 +3"}}
A47: 100012 | B47: 玄水雷纹诀 | C47: 功法 | D47: common | E47: thunder | F47: 3 | G47: 功法成长层 | H47: 1 | I47: 无 | L47: 15 | M47: 说明/执行器 | N47: effectNote | O47: 每获得 1 层引雷，获得 3 点修为 | P47: onBuffGain | Q47: gainCultivation | R47: {"kind":"effectNote","label":"<cultivation>每获得 1 层引雷，获得 3 点修为</cultivation>","executors":[{"trigger":"onBuffGain","type":"gainCultivation","amount":0,"amountPerEventBuffStack":3,"eventBuffId":"lightningCharge","label":"<cultivation>每获得 1 层引雷，获得 3 点修为</cultivation>"}]}
A48: 100012 | B48: 玄水雷纹诀 | C48: 功法 | D48: common | E48: thunder | F48: 3 | G48: 功法成长层 | H48: 1 | I48: 无 | L48: 15 | M48: 被动效果 | N48: passive | O48: 引雷层数上限 +3 | Q48: buffStackCapBonus | R48: {"kind":"passive","label":"引雷层数上限 +3","passiveEffect":{"type":"buffStackCapBonus","buffId":"lightningCharge","value":3,"label":"引雷层数上限 +3"}}
A49: 100012 | B49: 玄水雷纹诀 | C49: 功法 | D49: common | E49: thunder | F49: 3 | G49: 功法成长层 | H49: 2 | I49: 修为≥200 | J49: 200 | K49: 265 | L49: 60 | M49: 说明/执行器 | N49: effectNote | O49: 每获得 1 层引雷，获得 6 点修为 | P49: onBuffGain | Q49: gainCultivation | R49: {"kind":"effectNote","label":"<cultivation>每获得 1 层引雷，获得 6 点修为</cultivation>","executors":[{"trigger":"onBuffGain","type":"gainCultivation","amount":0,"amountPerEventBuffStack":6,"eventBuffId":"lightningCharge","label":"<cultivation>每获得 1 层引雷，获得 6 点修为</cultivation>"}]}
A50: 100012 | B50: 玄水雷纹诀 | C50: 功法 | D50: common | E50: thunder | F50: 3 | G50: 功法成长层 | H50: 2 | I50: 修为≥200 | J50: 200 | K50: 265 | L50: 60 | M50: 被动效果 | N50: passive | O50: 引雷层数上限 +6 | Q50: buffStackCapBonus | R50: {"kind":"passive","label":"引雷层数上限 +6","passiveEffect":{"type":"buffStackCapBonus","buffId":"lightningCharge","value":6,"label":"引雷层数上限 +6"}}
A51: 100012 | B51: 玄水雷纹诀 | C51: 功法 | D51: common | E51: thunder | F51: 3 | G51: 功法成长层 | H51: 3 | I51: 修为≥920 | J51: 920 | K51: 240 | L51: 90 | M51: 说明/执行器 | N51: effectNote | O51: 每获得 1 层引雷，获得 9 点修为 | P51: onBuffGain | Q51: gainCultivation | R51: {"kind":"effectNote","label":"<cultivation>每获得 1 层引雷，获得 9 点修为</cultivation>","executors":[{"trigger":"onBuffGain","type":"gainCultivation","amount":0,"amountPerEventBuffStack":9,"eventBuffId":"lightningCharge","label":"<cultivation>每获得 1 层引雷，获得 9 点修为</cultivation>"}]}
A52: 100012 | B52: 玄水雷纹诀 | C52: 功法 | D52: common | E52: thunder | F52: 3 | G52: 功法成长层 | H52: 3 | I52: 修为≥920 | J52: 920 | K52: 240 | L52: 90 | M52: 被动效果 | N52: passive | O52: 引雷层数上限 +9 | Q52: buffStackCapBonus | R52: {"kind":"passive","label":"引雷层数上限 +9","passiveEffect":{"type":"buffStackCapBonus","buffId":"lightningCharge","value":9,"label":"引雷层数上限 +9"}}
A53: 100012 | B53: 玄水雷纹诀 | C53: 功法 | D53: common | E53: thunder | F53: 3 | G53: 功法成长层 | H53: 4 | I53: 修为≥1880 | J53: 1880 | K53: 195 | L53: 180 | M53: 说明/执行器 | N53: effectNote | O53: 每获得 1 层引雷，获得 12 点修为 | P53: onBuffGain | Q53: gainCultivation | R53: {"kind":"effectNote","label":"<cultivation>每获得 1 层引雷，获得 12 点修为</cultivation>","executors":[{"trigger":"onBuffGain","type":"gainCultivation","amount":0,"amountPerEventBuffStack":12,"eventBuffId":"lightningCharge","label":"<cultivation>每获得 1 层引雷，获得 12 点修为</cultivation>"}]}
A54: 100012 | B54: 玄水雷纹诀 | C54: 功法 | D54: common | E54: thunder | F54: 3 | G54: 功法成长层 | H54: 4 | I54: 修为≥1880 | J54: 1880 | K54: 195 | L54: 180 | M54: 被动效果 | N54: passive | O54: 引雷层数上限 +12 | Q54: buffStackCapBonus | R54: {"kind":"passive","label":"引雷层数上限 +12","passiveEffect":{"type":"buffStackCapBonus","buffId":"lightningCharge","value":12,"label":"引雷层数上限 +12"}}
A55: 100013 | B55: 纳元印诀 | C55: 功法 | D55: common | E55: none | F55: 1 | G55: 基础/顶层 | M55: 被动效果 | N55: passive | O55: 法力上限 +0，任意功法突破后效果升级。；法力上限 | P55: onScriptureLayerBreakthrough | Q55: primaryStatMaxFlatBonus | R55: {"kind":"passive","label":"法力上限 +0，任意功法突破后效果升级。","passiveEffect":{"type":"primaryStatMaxFlatBonus","stat":"mana","value":0,"label":"法力上限 +0，任意功法突破后效果升级。"},"growth":{"lifecycle":"permanent","trigger":"onScriptureLayerBreakthrough","bindings":[{"path":"passiveEffect.value","delta":3,"maxValue":200,"label":"法力上限","textOccurrence":0}],"support":"cultivationOnly"}}
A56: 100013 | B56: 纳元印诀 | C56: 功法 | D56: common | E56: none | F56: 2 | G56: 基础/顶层 | M56: 条件触发 | N56: triggered | O56: 任意招式使用时，获得 10 点修为 | P56: onItemUse | Q56: gainCultivation；any | R56: {"kind":"triggered","label":"任意招式使用时，获得 10 点修为","triggeredEffect":{"trigger":"onItemUse","type":"gainCultivation","amount":10,"eventSource":{"target":{"type":"any"},"filter":{"categories":["spell"]}}}}
A57: 100013 | B57: 纳元印诀 | C57: 功法 | D57: common | E57: none | F57: 3 | G57: 功法成长层 | H57: 1 | I57: 无 | L57: 15 | M57: 被动效果 | N57: passive | O57: 法力上限 +0，任意功法突破后效果升级。；法力上限 | P57: onScriptureLayerBreakthrough | Q57: primaryStatMaxFlatBonus | R57: {"kind":"passive","label":"法力上限 +0，任意功法突破后效果升级。","passiveEffect":{"type":"primaryStatMaxFlatBonus","stat":"mana","value":0,"label":"法力上限 +0，任意功法突破后效果升级。"},"growth":{"lifecycle":"permanent","trigger":"onScriptureLayerBreakthrough","bindings":[{"path":"passiveEffect.value","delta":3,"maxValue":200,"label":"法力上限","textOccurrence":0}],"support":"cultivationOnly"}}
A58: 100013 | B58: 纳元印诀 | C58: 功法 | D58: common | E58: none | F58: 3 | G58: 功法成长层 | H58: 1 | I58: 无 | L58: 15 | M58: 条件触发 | N58: triggered | O58: 任意招式使用时，获得 10 点修为 | P58: onItemUse | Q58: gainCultivation；any | R58: {"kind":"triggered","label":"任意招式使用时，获得 10 点修为","triggeredEffect":{"trigger":"onItemUse","type":"gainCultivation","amount":10,"eventSource":{"target":{"type":"any"},"filter":{"categories":["spell"]}}}}
A59: 100013 | B59: 纳元印诀 | C59: 功法 | D59: common | E59: none | F59: 3 | G59: 功法成长层 | H59: 2 | I59: 修为≥180 | J59: 180 | K59: 235 | L59: 60 | M59: 被动效果 | N59: passive | O59: 法力上限 +0，任意功法突破后效果升级。；法力上限 | P59: onScriptureLayerBreakthrough | Q59: primaryStatMaxFlatBonus | R59: {"kind":"passive","label":"法力上限 +0，任意功法突破后效果升级。","passiveEffect":{"type":"primaryStatMaxFlatBonus","stat":"mana","value":0,"label":"法力上限 +0，任意功法突破后效果升级。"},"growth":{"lifecycle":"permanent","trigger":"onScriptureLayerBreakthrough","bindings":[{"path":"passiveEffect.value","delta":6,"maxValue":200,"label":"法力上限","textOccurrence":0}],"support":"cultivationOnly"}}
A60: 100013 | B60: 纳元印诀 | C60: 功法 | D60: common | E60: none | F60: 3 | G60: 功法成长层 | H60: 2 | I60: 修为≥180 | J60: 180 | K60: 235 | L60: 60 | M60: 条件触发 | N60: triggered | O60: 任意招式使用时，获得 20 点修为 | P60: onItemUse | Q60: gainCultivation；any | R60: {"kind":"triggered","label":"任意招式使用时，获得 20 点修为","triggeredEffect":{"trigger":"onItemUse","type":"gainCultivation","amount":20,"eventSource":{"target":{"type":"any"},"filter":{"categories":["spell"]}}}}
A61: 100013 | B61: 纳元印诀 | C61: 功法 | D61: common | E61: none | F61: 3 | G61: 功法成长层 | H61: 3 | I61: 修为≥800 | J61: 800 | K61: 260 | L61: 90 | M61: 被动效果 | N61: passive | O61: 法力上限 +0，任意功法突破后效果升级。；法力上限 | P61: onScriptureLayerBreakthrough | Q61: primaryStatMaxFlatBonus | R61: {"kind":"passive","label":"法力上限 +0，任意功法突破后效果升级。","passiveEffect":{"type":"primaryStatMaxFlatBonus","stat":"mana","value":0,"label":"法力上限 +0，任意功法突破后效果升级。"},"growth":{"lifecycle":"permanent","trigger":"onScriptureLayerBreakthrough","bindings":[{"path":"passiveEffect.value","delta":9,"maxValue":200,"label":"法力上限","textOccurrence":0}],"support":"cultivationOnly"}}
A62: 100013 | B62: 纳元印诀 | C62: 功法 | D62: common | E62: none | F62: 3 | G62: 功法成长层 | H62: 3 | I62: 修为≥800 | J62: 800 | K62: 260 | L62: 90 | M62: 条件触发 | N62: triggered | O62: 任意招式使用时，获得 30 点修为 | P62: onItemUse | Q62: gainCultivation；any | R62: {"kind":"triggered","label":"任意招式使用时，获得 30 点修为","triggeredEffect":{"trigger":"onItemUse","type":"gainCultivation","amount":30,"eventSource":{"target":{"type":"any"},"filter":{"categories":["spell"]}}}}
A63: 100013 | B63: 纳元印诀 | C63: 功法 | D63: common | E63: none | F63: 3 | G63: 功法成长层 | H63: 4 | I63: 修为≥3500 | J63: 3500 | K63: 305 | L63: 180 | M63: 被动效果 | N63: passive | O63: 法力上限 +0，任意功法突破后效果升级。；法力上限 | P63: onScriptureLayerBreakthrough | Q63: primaryStatMaxFlatBonus | R63: {"kind":"passive","label":"法力上限 +0，任意功法突破后效果升级。","passiveEffect":{"type":"primaryStatMaxFlatBonus","stat":"mana","value":0,"label":"法力上限 +0，任意功法突破后效果升级。"},"growth":{"lifecycle":"permanent","trigger":"onScriptureLayerBreakthrough","bindings":[{"path":"passiveEffect.value","delta":12,"maxValue":200,"label":"法力上限","textOccurrence":0}],"support":"cultivationOnly"}}
A64: 100013 | B64: 纳元印诀 | C64: 功法 | D64: common | E64: none | F64: 3 | G64: 功法成长层 | H64: 4 | I64: 修为≥3500 | J64: 3500 | K64: 305 | L64: 180 | M64: 条件触发 | N64: triggered | O64: 任意招式使用时，获得 40 点修为 | P64: onItemUse | Q64: gainCultivation；any | R64: {"kind":"triggered","label":"任意招式使用时，获得 40 点修为","triggeredEffect":{"trigger":"onItemUse","type":"gainCultivation","amount":40,"eventSource":{"target":{"type":"any"},"filter":{"categories":["spell"]}}}}
A65: 100014 | B65: 悟道玉简 | C65: 功法 | D65: common | E65: none | F65: 1 | G65: 基础/顶层 | M65: 条件触发 | N65: triggered | O65: 每当其他功法累计获得 10 点修为时，本功法获得 1 点修为 | P65: onCultivationGain | Q65: gainCultivation；other | R65: {"kind":"triggered","label":"<cultivation>每当其他功法累计获得 10 点修为时，本功法获得 1 点修为</cultivation>","triggeredEffect":{"trigger":"onCultivationGain","type":"gainCultivation","amount":1,"eventSource":{"target":{"type":"other"},"filter":{"categories":["scripture"]}},"charge":{"threshold":10,"source":{"trigger":"onCultivationGain"}}}}
A66: 100014 | B66: 悟道玉简 | C66: 功法 | D66: common | E66: none | F66: 2 | G66: 功法成长层 | H66: 1 | I66: 无 | L66: 15 | M66: 条件触发 | N66: triggered | O66: 每当其他功法累计获得 10 点修为时，本功法获得 1 点修为 | P66: onCultivationGain | Q66: gainCultivation；other | R66: {"kind":"triggered","label":"<cultivation>每当其他功法累计获得 10 点修为时，本功法获得 1 点修为</cultivation>","triggeredEffect":{"trigger":"onCultivationGain","type":"gainCultivation","amount":1,"eventSource":{"target":{"type":"other"},"filter":{"categories":["scripture"]}},"charge":{"threshold":10,"source":{"trigger":"onCultivationGain"}}}}
A67: 100014 | B67: 悟道玉简 | C67: 功法 | D67: common | E67: none | F67: 2 | G67: 功法成长层 | H67: 2 | I67: 修为≥190 | J67: 190 | K67: 250 | L67: 60 | M67: 条件触发 | N67: triggered | O67: 每当其他功法累计获得 10 点修为时，本功法获得 2 点修为 | P67: onCultivationGain | Q67: gainCultivation；other | R67: {"kind":"triggered","label":"<cultivation>每当其他功法累计获得 10 点修为时，本功法获得 2 点修为</cultivation>","triggeredEffect":{"trigger":"onCultivationGain","type":"gainCultivation","amount":2,"eventSource":{"target":{"type":"other"},"filter":{"categories":["scripture"]}},"charge":{"threshold":10,"source":{"trigger":"onCultivationGain"}}}}
A68: 100014 | B68: 悟道玉简 | C68: 功法 | D68: common | E68: none | F68: 2 | G68: 功法成长层 | H68: 3 | I68: 修为≥780 | J68: 780 | K68: 240 | L68: 90 | M68: 条件触发 | N68: triggered | O68: 每当其他功法累计获得 10 点修为时，本功法获得 3 点修为 | P68: onCultivationGain | Q68: gainCultivation；other | R68: {"kind":"triggered","label":"<cultivation>每当其他功法累计获得 10 点修为时，本功法获得 3 点修为</cultivation>","triggeredEffect":{"trigger":"onCultivationGain","type":"gainCultivation","amount":3,"eventSource":{"target":{"type":"other"},"filter":{"categories":["scripture"]}},"charge":{"threshold":10,"source":{"trigger":"onCultivationGain"}}}}
A69: 100014 | B69: 悟道玉简 | C69: 功法 | D69: common | E69: none | F69: 2 | G69: 功法成长层 | H69: 4 | I69: 修为≥2100 | J69: 2100 | K69: 215 | L69: 180 | M69: 条件触发 | N69: triggered | O69: 每当其他功法累计获得 10 点修为时，本功法获得 4 点修为 | P69: onCultivationGain | Q69: gainCultivation；other | R69: {"kind":"triggered","label":"<cultivation>每当其他功法累计获得 10 点修为时，本功法获得 4 点修为</cultivation>","triggeredEffect":{"trigger":"onCultivationGain","type":"gainCultivation","amount":4,"eventSource":{"target":{"type":"other"},"filter":{"categories":["scripture"]}},"charge":{"threshold":10,"source":{"trigger":"onCultivationGain"}}}}
A70: 100015 | B70: 焰纹秘卷 | C70: 功法 | D70: spirit | E70: fire | F70: 1 | G70: 基础/顶层 | M70: 条件触发 | N70: triggered | O70: 将每 1 层炎热转化为 4 点修为 | P70: onBuffConsumed | Q70: gainCultivation | R70: {"kind":"triggered","label":"<cultivation>将每 1 层炎热转化为 4 点修为</cultivation>","triggeredEffect":{"trigger":"onBuffConsumed","eventBuffId":"heat","type":"gainCultivation","amount":0,"amountPerEventBuffStack":4}}
A71: 100015 | B71: 焰纹秘卷 | C71: 功法 | D71: spirit | E71: fire | F71: 2 | G71: 基础/顶层 | M71: 被动效果 | N71: passive | O71: 炎热层数上限 +6 | Q71: buffStackCapBonus | R71: {"kind":"passive","label":"炎热层数上限 +6","passiveEffect":{"type":"buffStackCapBonus","buffId":"heat","value":6,"label":"炎热层数上限 +6"}}
A72: 100015 | B72: 焰纹秘卷 | C72: 功法 | D72: spirit | E72: fire | F72: 3 | G72: 功法成长层 | H72: 1 | I72: 无 | L72: 15 | M72: 条件触发 | N72: triggered | O72: 将每 1 层炎热转化为 4 点修为 | P72: onBuffConsumed | Q72: gainCultivation | R72: {"kind":"triggered","label":"<cultivation>将每 1 层炎热转化为 4 点修为</cultivation>","triggeredEffect":{"trigger":"onBuffConsumed","eventBuffId":"heat","type":"gainCultivation","amount":0,"amountPerEventBuffStack":4}}
A73: 100015 | B73: 焰纹秘卷 | C73: 功法 | D73: spirit | E73: fire | F73: 3 | G73: 功法成长层 | H73: 1 | I73: 无 | L73: 15 | M73: 被动效果 | N73: passive | O73: 炎热层数上限 +6 | Q73: buffStackCapBonus | R73: {"kind":"passive","label":"炎热层数上限 +6","passiveEffect":{"type":"buffStackCapBonus","buffId":"heat","value":6,"label":"炎热层数上限 +6"}}
A74: 100015 | B74: 焰纹秘卷 | C74: 功法 | D74: spirit | E74: fire | F74: 3 | G74: 功法成长层 | H74: 2 | I74: 修为≥15400 | J74: 15400 | K74: 365 | L74: 60 | M74: 条件触发 | N74: triggered | O74: 将每 1 层炎热转化为 8 点修为 | P74: onBuffConsumed | Q74: gainCultivation | R74: {"kind":"triggered","label":"<cultivation>将每 1 层炎热转化为 8 点修为</cultivation>","triggeredEffect":{"trigger":"onBuffConsumed","eventBuffId":"heat","type":"gainCultivation","amount":0,"amountPerEventBuffStack":8}}
A75: 100015 | B75: 焰纹秘卷 | C75: 功法 | D75: spirit | E75: fire | F75: 3 | G75: 功法成长层 | H75: 2 | I75: 修为≥15400 | J75: 15400 | K75: 365 | L75: 60 | M75: 被动效果 | N75: passive | O75: 炎热层数上限 +12 | Q75: buffStackCapBonus | R75: {"kind":"passive","label":"炎热层数上限 +12","passiveEffect":{"type":"buffStackCapBonus","buffId":"heat","value":12,"label":"炎热层数上限 +12"}}
A76: 100015 | B76: 焰纹秘卷 | C76: 功法 | D76: spirit | E76: fire | F76: 3 | G76: 功法成长层 | H76: 3 | I76: 修为≥44700 | J76: 44700 | K76: 395 | L76: 90 | M76: 条件触发 | N76: triggered | O76: 将每 1 层炎热转化为 12 点修为 | P76: onBuffConsumed | Q76: gainCultivation | R76: {"kind":"triggered","label":"<cultivation>将每 1 层炎热转化为 12 点修为</cultivation>","triggeredEffect":{"trigger":"onBuffConsumed","eventBuffId":"heat","type":"gainCultivation","amount":0,"amountPerEventBuffStack":12}}
A77: 100015 | B77: 焰纹秘卷 | C77: 功法 | D77: spirit | E77: fire | F77: 3 | G77: 功法成长层 | H77: 3 | I77: 修为≥44700 | J77: 44700 | K77: 395 | L77: 90 | M77: 被动效果 | N77: passive | O77: 炎热层数上限 +18 | Q77: buffStackCapBonus | R77: {"kind":"passive","label":"炎热层数上限 +18","passiveEffect":{"type":"buffStackCapBonus","buffId":"heat","value":18,"label":"炎热层数上限 +18"}}
A78: 100015 | B78: 焰纹秘卷 | C78: 功法 | D78: spirit | E78: fire | F78: 3 | G78: 功法成长层 | H78: 4 | I78: 修为≥52500 | J78: 52500 | K78: 375 | L78: 180 | M78: 条件触发 | N78: triggered | O78: 将每 1 层炎热转化为 16 点修为 | P78: onBuffConsumed | Q78: gainCultivation | R78: {"kind":"triggered","label":"<cultivation>将每 1 层炎热转化为 16 点修为</cultivation>","triggeredEffect":{"trigger":"onBuffConsumed","eventBuffId":"heat","type":"gainCultivation","amount":0,"amountPerEventBuffStack":16}}
A79: 100015 | B79: 焰纹秘卷 | C79: 功法 | D79: spirit | E79: fire | F79: 3 | G79: 功法成长层 | H79: 4 | I79: 修为≥52500 | J79: 52500 | K79: 375 | L79: 180 | M79: 被动效果 | N79: passive | O79: 炎热层数上限 +24 | Q79: buffStackCapBonus | R79: {"kind":"passive","label":"炎热层数上限 +24","passiveEffect":{"type":"buffStackCapBonus","buffId":"heat","value":24,"label":"炎热层数上限 +24"}}
A80: 100016 | B80: 青木引灵简 | C80: 功法 | D80: common | E80: wood | F80: 1 | G80: 基础/顶层 | M80: 条件触发 | N80: triggered | O80: 每当获得 1 层再生时，获得 2 点修为 | P80: onBuffGain | Q80: gainCultivation | R80: {"kind":"triggered","label":"每当获得 1 层再生时，获得 2 点修为","triggeredEffect":{"trigger":"onBuffGain","type":"gainCultivation","amount":0,"amountPerEventBuffStack":2,"eventBuffId":"regeneration","label":"每当获得 1 层再生时，获得 2 点修为"}}
A81: 100016 | B81: 青木引灵简 | C81: 功法 | D81: common | E81: wood | F81: 2 | G81: 基础/顶层 | M81: 被动效果 | N81: passive | O81: 再生层数上限 +3 | Q81: buffStackCapBonus | R81: {"kind":"passive","label":"再生层数上限 +3","passiveEffect":{"type":"buffStackCapBonus","buffId":"regeneration","value":3,"label":"再生层数上限 +3"}}
A82: 100016 | B82: 青木引灵简 | C82: 功法 | D82: common | E82: wood | F82: 3 | G82: 功法成长层 | H82: 1 | I82: 无 | L82: 15 | M82: 条件触发 | N82: triggered | O82: 每当获得 1 层再生时，获得 2 点修为 | P82: onBuffGain | Q82: gainCultivation | R82: {"kind":"triggered","label":"每当获得 1 层再生时，获得 2 点修为","triggeredEffect":{"trigger":"onBuffGain","type":"gainCultivation","amount":0,"amountPerEventBuffStack":2,"eventBuffId":"regeneration","label":"每当获得 1 层再生时，获得 2 点修为"}}
A83: 100016 | B83: 青木引灵简 | C83: 功法 | D83: common | E83: wood | F83: 3 | G83: 功法成长层 | H83: 1 | I83: 无 | L83: 15 | M83: 被动效果 | N83: passive | O83: 再生层数上限 +3 | Q83: buffStackCapBonus | R83: {"kind":"passive","label":"再生层数上限 +3","passiveEffect":{"type":"buffStackCapBonus","buffId":"regeneration","value":3,"label":"再生层数上限 +3"}}
A84: 100016 | B84: 青木引灵简 | C84: 功法 | D84: common | E84: wood | F84: 3 | G84: 功法成长层 | H84: 2 | I84: 修为≥95 | J84: 95 | K84: 170 | L84: 60 | M84: 条件触发 | N84: triggered | O84: 每当获得 1 层再生时，获得 4 点修为 | P84: onBuffGain | Q84: gainCultivation | R84: {"kind":"triggered","label":"每当获得 1 层再生时，获得 4 点修为","triggeredEffect":{"trigger":"onBuffGain","type":"gainCultivation","amount":0,"amountPerEventBuffStack":4,"eventBuffId":"regeneration","label":"每当获得 1 层再生时，获得 4 点修为"}}
A85: 100016 | B85: 青木引灵简 | C85: 功法 | D85: common | E85: wood | F85: 3 | G85: 功法成长层 | H85: 2 | I85: 修为≥95 | J85: 95 | K85: 170 | L85: 60 | M85: 被动效果 | N85: passive | O85: 再生层数上限 +6 | Q85: buffStackCapBonus | R85: {"kind":"passive","label":"再生层数上限 +6","passiveEffect":{"type":"buffStackCapBonus","buffId":"regeneration","value":6,"label":"再生层数上限 +6"}}
A86: 100016 | B86: 青木引灵简 | C86: 功法 | D86: common | E86: wood | F86: 3 | G86: 功法成长层 | H86: 3 | I86: 修为≥920 | J86: 920 | K86: 295 | L86: 90 | M86: 条件触发 | N86: triggered | O86: 每当获得 1 层再生时，获得 6 点修为 | P86: onBuffGain | Q86: gainCultivation | R86: {"kind":"triggered","label":"每当获得 1 层再生时，获得 6 点修为","triggeredEffect":{"trigger":"onBuffGain","type":"gainCultivation","amount":0,"amountPerEventBuffStack":6,"eventBuffId":"regeneration","label":"每当获得 1 层再生时，获得 6 点修为"}}
A87: 100016 | B87: 青木引灵简 | C87: 功法 | D87: common | E87: wood | F87: 3 | G87: 功法成长层 | H87: 3 | I87: 修为≥920 | J87: 920 | K87: 295 | L87: 90 | M87: 被动效果 | N87: passive | O87: 再生层数上限 +9 | Q87: buffStackCapBonus | R87: {"kind":"passive","label":"再生层数上限 +9","passiveEffect":{"type":"buffStackCapBonus","buffId":"regeneration","value":9,"label":"再生层数上限 +9"}}
A88: 100016 | B88: 青木引灵简 | C88: 功法 | D88: common | E88: wood | F88: 3 | G88: 功法成长层 | H88: 4 | I88: 修为≥2300 | J88: 2300 | K88: 210 | L88: 180 | M88: 条件触发 | N88: triggered | O88: 每当获得 1 层再生时，获得 8 点修为 | P88: onBuffGain | Q88: gainCultivation | R88: {"kind":"triggered","label":"每当获得 1 层再生时，获得 8 点修为","triggeredEffect":{"trigger":"onBuffGain","type":"gainCultivation","amount":0,"amountPerEventBuffStack":8,"eventBuffId":"regeneration","label":"每当获得 1 层再生时，获得 8 点修为"}}
A89: 100016 | B89: 青木引灵简 | C89: 功法 | D89: common | E89: wood | F89: 3 | G89: 功法成长层 | H89: 4 | I89: 修为≥2300 | J89: 2300 | K89: 210 | L89: 180 | M89: 被动效果 | N89: passive | O89: 再生层数上限 +12 | Q89: buffStackCapBonus | R89: {"kind":"passive","label":"再生层数上限 +12","passiveEffect":{"type":"buffStackCapBonus","buffId":"regeneration","value":12,"label":"再生层数上限 +12"}}
A90: 100017 | B90: 寒波调息诀 | C90: 功法 | D90: common | E90: water | F90: 1 | G90: 基础/顶层 | M90: 说明/执行器 | N90: effectNote | O90: 每获得 1 层寒冷或露水，获得 2 点修为 | P90: onBuffGain | Q90: gainCultivation | R90: {"kind":"effectNote","label":"每获得 1 层寒冷或露水，<cultivation>获得 2 点修为</cultivation>","executors":[{"trigger":"onBuffGain","eventBuffId":"cold","type":"gainCultivation","amount":0,"amountPerEventBuffStack":2,"label":"每获得 1 层寒冷或露水，<cultivation>获得 2 点修为</cultivation>"},{"trigger":"onBuffGain","eventBuffId":"dew","type":"gainCultivation","amount":0,"amountPerEventBuffStack":2,"label":"每获得 1 层寒冷或露水，<cultivation>获得 2 点修为</cultivation>"}]}
A91: 100017 | B91: 寒波调息诀 | C91: 功法 | D91: common | E91: water | F91: 2 | G91: 基础/顶层 | M91: 被动效果 | N91: passive | O91: 寒冷层数上限 +5 | Q91: buffStackCapBonus | R91: {"kind":"passive","label":"寒冷层数上限 +5","passiveEffect":{"type":"buffStackCapBonus","buffId":"cold","value":5,"label":"寒冷层数上限 +5"}}
A92: 100017 | B92: 寒波调息诀 | C92: 功法 | D92: common | E92: water | F92: 3 | G92: 基础/顶层 | M92: 被动效果 | N92: passive | O92: 露水层数上限 +5 | Q92: buffStackCapBonus | R92: {"kind":"passive","label":"露水层数上限 +5","passiveEffect":{"type":"buffStackCapBonus","buffId":"dew","value":5,"label":"露水层数上限 +5"}}
A93: 100017 | B93: 寒波调息诀 | C93: 功法 | D93: common | E93: water | F93: 4 | G93: 功法成长层 | H93: 1 | I93: 无 | L93: 15 | M93: 说明/执行器 | N93: effectNote | O93: 每获得 1 层寒冷或露水，获得 2 点修为 | P93: onBuffGain | Q93: gainCultivation | R93: {"kind":"effectNote","label":"每获得 1 层寒冷或露水，<cultivation>获得 2 点修为</cultivation>","executors":[{"trigger":"onBuffGain","eventBuffId":"cold","type":"gainCultivation","amount":0,"amountPerEventBuffStack":2,"label":"每获得 1 层寒冷或露水，<cultivation>获得 2 点修为</cultivation>"},{"trigger":"onBuffGain","eventBuffId":"dew","type":"gainCultivation","amount":0,"amountPerEventBuffStack":2,"label":"每获得 1 层寒冷或露水，<cultivation>获得 2 点修为</cultivation>"}]}
A94: 100017 | B94: 寒波调息诀 | C94: 功法 | D94: common | E94: water | F94: 4 | G94: 功法成长层 | H94: 1 | I94: 无 | L94: 15 | M94: 被动效果 | N94: passive | O94: 寒冷层数上限 +5 | Q94: buffStackCapBonus | R94: {"kind":"passive","label":"寒冷层数上限 +5","passiveEffect":{"type":"buffStackCapBonus","buffId":"cold","value":5,"label":"寒冷层数上限 +5"}}
A95: 100017 | B95: 寒波调息诀 | C95: 功法 | D95: common | E95: water | F95: 4 | G95: 功法成长层 | H95: 1 | I95: 无 | L95: 15 | M95: 被动效果 | N95: passive | O95: 露水层数上限 +5 | Q95: buffStackCapBonus | R95: {"kind":"passive","label":"露水层数上限 +5","passiveEffect":{"type":"buffStackCapBonus","buffId":"dew","value":5,"label":"露水层数上限 +5"}}
A96: 100017 | B96: 寒波调息诀 | C96: 功法 | D96: common | E96: water | F96: 4 | G96: 功法成长层 | H96: 2 | I96: 修为≥180 | J96: 180 | K96: 255 | L96: 60 | M96: 说明/执行器 | N96: effectNote | O96: 每获得 1 层寒冷或露水，获得 4 点修为 | P96: onBuffGain | Q96: gainCultivation | R96: {"kind":"effectNote","label":"每获得 1 层寒冷或露水，<cultivation>获得 4 点修为</cultivation>","executors":[{"trigger":"onBuffGain","eventBuffId":"cold","type":"gainCultivation","amount":0,"amountPerEventBuffStack":4,"label":"每获得 1 层寒冷或露水，<cultivation>获得 4 点修为</cultivation>"},{"trigger":"onBuffGain","eventBuffId":"dew","type":"gainCultivation","amount":0,"amountPerEventBuffStack":4,"label":"每获得 1 层寒冷或露水，<cultivation>获得 4 点修为</cultivation>"}]}
A97: 100017 | B97: 寒波调息诀 | C97: 功法 | D97: common | E97: water | F97: 4 | G97: 功法成长层 | H97: 2 | I97: 修为≥180 | J97: 180 | K97: 255 | L97: 60 | M97: 被动效果 | N97: passive | O97: 寒冷层数上限 +10 | Q97: buffStackCapBonus | R97: {"kind":"passive","label":"寒冷层数上限 +10","passiveEffect":{"type":"buffStackCapBonus","buffId":"cold","value":10,"label":"寒冷层数上限 +10"}}
A98: 100017 | B98: 寒波调息诀 | C98: 功法 | D98: common | E98: water | F98: 4 | G98: 功法成长层 | H98: 2 | I98: 修为≥180 | J98: 180 | K98: 255 | L98: 60 | M98: 被动效果 | N98: passive | O98: 露水层数上限 +10 | Q98: buffStackCapBonus | R98: {"kind":"passive","label":"露水层数上限 +10","passiveEffect":{"type":"buffStackCapBonus","buffId":"dew","value":10,"label":"露水层数上限 +10"}}
A99: 100017 | B99: 寒波调息诀 | C99: 功法 | D99: common | E99: water | F99: 4 | G99: 功法成长层 | H99: 3 | I99: 修为≥840 | J99: 840 | K99: 250 | L99: 90 | M99: 说明/执行器 | N99: effectNote | O99: 每获得 1 层寒冷或露水，获得 6 点修为 | P99: onBuffGain | Q99: gainCultivation | R99: {"kind":"effectNote","label":"每获得 1 层寒冷或露水，<cultivation>获得 6 点修为</cultivation>","executors":[{"trigger":"onBuffGain","eventBuffId":"cold","type":"gainCultivation","amount":0,"amountPerEventBuffStack":6,"label":"每获得 1 层寒冷或露水，<cultivation>获得 6 点修为</cultivation>"},{"trigger":"onBuffGain","eventBuffId":"dew","type":"gainCultivation","amount":0,"amountPerEventBuffStack":6,"label":"每获得 1 层寒冷或露水，<cultivation>获得 6 点修为</cultivation>"}]}
A100: 100017 | B100: 寒波调息诀 | C100: 功法 | D100: common | E100: water | F100: 4 | G100: 功法成长层 | H100: 3 | I100: 修为≥840 | J100: 840 | K100: 250 | L100: 90 | M100: 被动效果 | N100: passive | O100: 寒冷层数上限 +15 | Q100: buffStackCapBonus | R100: {"kind":"passive","label":"寒冷层数上限 +15","passiveEffect":{"type":"buffStackCapBonus","buffId":"cold","value":15,"label":"寒冷层数上限 +15"}}
...

Sheet 统计汇总
A1: 统计汇总
A2: 所有数量由“物品清单”工作表公式计算；一个物品可以同时含多种效果类型。
A4: 关键指标
A5: 有效物品总数 | B5: =COUNTA('物品清单'!$B:$B)-1
A6: 效果明细行数 | B6: 2064
E8: 类别 | F8: 代码 | G8: 数量 | H8: 品阶 | I8: 代码 | J8: 数量
E9: 法器 | F9: implement | G9: =COUNTIF('物品清单'!$E:$E,"implement") | H9: common | I9: common | J9: =COUNTIF('物品清单'!$F:$F,"common")
E10: 材料 | F10: material | G10: =COUNTIF('物品清单'!$E:$E,"material") | H10: spirit | I10: spirit | J10: =COUNTIF('物品清单'!$F:$F,"spirit")
E11: 招式 | F11: spell | G11: =COUNTIF('物品清单'!$E:$E,"spell") | H11: mystic | I11: mystic | J11: =COUNTIF('物品清单'!$F:$F,"mystic")
E12: 丹药 | F12: pill | G12: =COUNTIF('物品清单'!$E:$E,"pill") | H12: earth | I12: earth | J12: =COUNTIF('物品清单'!$F:$F,"earth")
E13: 阵法 | F13: formation | G13: =COUNTIF('物品清单'!$E:$E,"formation")
E14: 符箓 | F14: talisman | G14: =COUNTIF('物品清单'!$E:$E,"talisman")
E15: 投掷物 | F15: throwable | G15: =COUNTIF('物品清单'!$E:$E,"throwable")
E16: 功法 | F16: scripture | G16: =COUNTIF('物品清单'!$E:$E,"scripture")
E17: 占卜 | F17: divination | G17: =COUNTIF('物品清单'!$E:$E,"divination")
E18: 宝箱 | F18: chest | G18: =COUNTIF('物品清单'!$E:$E,"chest")
A25: 元素 | B25: 代码 | C25: 数量 | E25: 效果类型（按含该类型的物品数） | F25: 代码 | G25: 数量
A26: 水 | B26: water | C26: =COUNTIF('物品清单'!$H:$H,"water") | E26: 周期触发 | F26: periodicPulse | G26: =COUNTIF('物品清单'!$P:$P,"*periodicPulse*")
A27: 火 | B27: fire | C27: =COUNTIF('物品清单'!$H:$H,"fire") | E27: 条件触发 | F27: triggered | G27: =COUNTIF('物品清单'!$P:$P,"*triggered*")
A28: 金 | B28: metal | C28: =COUNTIF('物品清单'!$H:$H,"metal") | E28: 说明/执行器 | F28: effectNote | G28: =COUNTIF('物品清单'!$P:$P,"*effectNote*")
A29: 土 | B29: earth | C29: =COUNTIF('物品清单'!$H:$H,"earth") | E29: 消耗品效果 | F29: consumable | G29: =COUNTIF('物品清单'!$P:$P,"*consumable*")
A30: 木 | B30: wood | C30: =COUNTIF('物品清单'!$H:$H,"wood") | E30: 被动效果 | F30: passive | G30: =COUNTIF('物品清单'!$P:$P,"*passive*")
A31: 无 | B31: none | C31: =COUNTIF('物品清单'!$H:$H,"none") | E31: 功法成长 | F31: scriptureProgression | G31: =COUNTIF('物品清单'!$P:$P,"*scriptureProgression*")
A32: 风 | B32: wind | C32: =COUNTIF('物品清单'!$H:$H,"wind")
A33: 雷 | B33: thunder | C33: =COUNTIF('物品清单'!$H:$H,"thunder")
A34: 冰 | B34: ice | C34: =COUNTIF('物品清单'!$H:$H,"ice")
A35: poison | B35: poison | C35: =COUNTIF('物品清单'!$H:$H,"poison")
