Workbook

Sheet 00_使用说明
A1: t01-08｜使用说明
A2: 2026-09-28 · 27下品＋88凡品＝115件 · 候选数值／当前规则／游戏实现分列 · 不含平衡测试结论
A5: 记录ID | B5: 主题 | C5: 内容 | D5: 边界／状态 | E5: 依据
A6: U01 | B6: 组织方式 | C6: 六类别各自维护跨品级正文；总索引和统计由分类表派生。 | D6: 不另建下品副本作为第二份正文；以后新增品级仍进原类别表。 | E6: 用户本次问题；编制安排
A7: U02 | B7: 本批品级 | C7: 既有27件下品＋新增88件凡品＝115件；六类别正文跨品级维护。 | D7: 下品批次更正不适用于本次新增凡品；本次候选数值与旧基准分开。 | E7: 用户最新品级更正，2026-09-28；资料A/B/C
A8: U03 | B8: 最终数量 | C8: 累计36武器＋36防具＋22法器＋16丹药＋0符箓＋5暗器＝115。 | D8: 本批27武器＋28防具＋18法器＋10丹药＋5暗器＝88；退出编号不复用。 | E8: 资料A/B/C
A9: U04 | B9: 数值性质 | C9: 原下品武器绝对值仍未定；本批凡品88件已有候选数值。已有10件游戏配置单列参考。 | D9: 原资料称已测试≠本轮跑过游戏；参考配置不自动成为下品最终平衡。 | E9: 资料B；当前配置只读
A10: U05 | B10: 识别与引用 | C10: t01.asset.*为资产主表记录ID，不是新游戏注册ID；已有游戏ID保留映射。 | D10: 一件正式资产尚需合法机制、数值、制作／获取链及实现条件；不可把此表直接视作可运行JSON。 | E10: 项目工程约束；01～07
A11: U06 | B11: 公式与派生 | C11: 占格、名义回复率、组合上限和统计使用公式；公式缓存由独立输入计算后写入。 | D11: 无Excel引擎重新计算／真实渲染；名义比值不含资源、上限、控制、命中或战斗长度，不是平衡验证。 | E11: 编制验证口径
A12: U07 | B12: 当前确认 | C12: 下品Q01～Q04及本次FP01～FP06均已确认；当前没有待答题。普通灵障模板见19表。 | D12: 常规邻接仍从良品；限定下品两组、凡品三组基础联动。数值未试跑，升品承接延后。 | E12: 两批逐项答复；本轮凡品合并，2026-09-28
A13: U08 | B13: 实现范围 | C13: 本次编制资产主表及文档衔接，游戏配置只读。 | D13: 已有10件游戏配置仍为下品；本批新增凡品尚未注册游戏。旧配置差异见12表。 | E13: data/maps/inventory_items.json
A14: U09 | B14: 查阅 | C14: 01总索引；02～07分类；08数量；09联动；10甲型元素；11获取；12旧配置；13跨词典；14确认；15案例；16来源；17效果；18状态覆盖；19凡品规则；20试算；21修订停列。22元素／状态分开统计。 | D14: 所有无资产类别只有空模板行，不作为真实物品计数。 | E14: 本次编制

Sheet 01_总索引
A1: t01-08｜总索引
A2: 2026-09-28 · 27下品＋88凡品＝115件 · 候选数值／当前规则／游戏实现分列 · 不含平衡测试结论
A5: 资产ID | B5: 名称_分类表引用 | C5: 品级_分类表引用 | D5: 类别 | E5: 正文位置 | F5: 设计阶段 | G5: 实现核对 | H5: 资料依据
A6: t01.asset.0001 | B6: ='02_武器'!B6 -> 青石短剑 | C6: ='02_武器'!C6 -> 下品 | D6: 武器 | E6: 02_武器!A6 | F6: 骨架登记；绝对数值待平衡 | G6: 已有同名配置／品级一致；其他差异见12表 | H6: A；用户最新更正为下品
A7: t01.asset.0002 | B7: ='02_武器'!B7 -> 铁刀 | C7: ='02_武器'!C7 -> 下品 | D7: 武器 | E7: 02_武器!A7 | F7: 骨架登记；绝对数值待平衡 | G7: 尚无正式游戏配置 | H7: A；用户最新更正为下品
A8: t01.asset.0003 | B8: ='02_武器'!B8 -> 柴斧 | C8: ='02_武器'!C8 -> 下品 | D8: 武器 | E8: 02_武器!A8 | F8: 骨架登记；绝对数值待平衡 | G8: 尚无正式游戏配置 | H8: A；用户最新更正为下品
A9: t01.asset.0004 | B9: ='02_武器'!B9 -> 猎弓 | C9: ='02_武器'!C9 -> 下品 | D9: 武器 | E9: 02_武器!A9 | F9: 骨架登记；绝对数值待平衡 | G9: 已有同名配置／品级一致；其他差异见12表 | H9: A；用户最新更正为下品
A10: t01.asset.0005 | B10: ='02_武器'!B10 -> 匕首 | C10: ='02_武器'!C10 -> 下品 | D10: 武器 | E10: 02_武器!A10 | F10: 骨架登记；绝对数值待平衡 | G10: 尚无正式游戏配置 | H10: A；用户最新更正为下品
A11: t01.asset.0006 | B11: ='02_武器'!B11 -> 长枪 | C11: ='02_武器'!C11 -> 下品 | D11: 武器 | E11: 02_武器!A11 | F11: 骨架登记；绝对数值待平衡 | G11: 尚无正式游戏配置 | H11: A；用户最新更正为下品
A12: t01.asset.0007 | B12: ='02_武器'!B12 -> 短柄铁锤 | C12: ='02_武器'!C12 -> 下品 | D12: 武器 | E12: 02_武器!A12 | F12: 骨架登记；绝对数值待平衡 | G12: 已有同名配置／品级一致；其他差异见12表 | H12: A；用户最新更正为下品
A13: t01.asset.0008 | B13: ='02_武器'!B13 -> 石印 | C13: ='02_武器'!C13 -> 下品 | D13: 武器 | E13: 02_武器!A13 | F13: 骨架登记；绝对数值待平衡 | G13: 尚无正式游戏配置 | H13: A；用户最新更正为下品
A14: t01.asset.0009 | B14: ='02_武器'!B14 -> 皮鞭 | C14: ='02_武器'!C14 -> 下品 | D14: 武器 | E14: 02_武器!A14 | F14: 骨架登记；绝对数值待平衡 | G14: 尚无正式游戏配置 | H14: A；用户最新更正为下品
A15: t01.asset.0010 | B15: ='03_防具'!B6 -> 粗布甲 | C15: ='03_防具'!C6 -> 下品 | D15: 防具 | E15: 03_防具!A6 | F15: 保留资料已有值 | G15: 已有同名配置／品级一致；其他差异见12表 | H15: B2；C覆盖
A16: t01.asset.0011 | B16: ='03_防具'!B7 -> 铁甲 | C16: ='03_防具'!C7 -> 下品 | D16: 防具 | E16: 03_防具!A7 | F16: 新增试玩候选；本体6秒 | G16: 尚无正式游戏配置 | H16: B2；C覆盖
A17: t01.asset.0012 | B17: ='03_防具'!B8 -> 旧铁盔 | C17: ='03_防具'!C8 -> 下品 | D17: 防具 | E17: 03_防具!A8 | F17: 保留资料已有值；补甲型 | G17: 已有同名配置／品级一致；其他差异见12表 | H17: B2；C覆盖
A18: t01.asset.0013 | B18: ='03_防具'!B9 -> 木圆盾 | C18: ='03_防具'!C9 -> 下品 | D18: 防具 | E18: 03_防具!A9 | F18: 保留资料已有值；补甲型 | G18: 已有同名配置／品级一致；其他差异见12表 | H18: B2；C覆盖
A19: t01.asset.0014 | B19: ='03_防具'!B10 -> 布护臂 | C19: ='03_防具'!C10 -> 下品 | D19: 防具 | E19: 03_防具!A10 | F19: 新增试玩候选 | G19: 尚无正式游戏配置 | H19: B2；C覆盖
A20: t01.asset.0015 | B20: ='03_防具'!B11 -> 布护腿 | C20: ='03_防具'!C11 -> 下品 | D20: 防具 | E20: 03_防具!A11 | F20: 新增试玩候选 | G20: 尚无正式游戏配置 | H20: B2；C覆盖
A21: t01.asset.0016 | B21: ='03_防具'!B12 -> 铁护臂 | C21: ='03_防具'!C12 -> 下品 | D21: 防具 | E21: 03_防具!A12 | F21: C新增试玩候选 | G21: 尚无正式游戏配置 | H21: C
A22: t01.asset.0017 | B22: ='03_防具'!B13 -> 铁护腿 | C22: ='03_防具'!C13 -> 下品 | D22: 防具 | E22: 03_防具!A13 | F22: C新增试玩候选 | G22: 尚无正式游戏配置 | H22: C
A23: t01.asset.0018 | B23: ='04_法器'!B6 -> 温玉佩 | C23: ='04_法器'!C6 -> 下品 | D23: 法器 | E23: 04_法器!A6 | F23: 保留已有值 | G23: 已有同名配置／品级一致；其他差异见12表 | H23: B3
A24: t01.asset.0019 | B24: ='04_法器'!B7 -> 回春玉 | C24: ='04_法器'!C7 -> 下品 | D24: 法器 | E24: 04_法器!A7 | F24: 新增试玩候选 | G24: 尚无正式游戏配置 | H24: B3
A25: t01.asset.0020 | B25: ='04_法器'!B8 -> 养息珠 | C25: ='04_法器'!C8 -> 下品 | D25: 法器 | E25: 04_法器!A8 | F25: 新增试玩候选 | G25: 尚无正式游戏配置 | H25: B3
A26: t01.asset.0021 | B26: ='04_法器'!B9 -> 聚灵珠 | C26: ='04_法器'!C9 -> 下品 | D26: 法器 | E26: 04_法器!A9 | F26: 新增试玩候选 | G26: 尚无正式游戏配置 | H26: B3
A27: t01.asset.0022 | B27: ='05_丹药'!B6 -> 止血丹 | C27: ='05_丹药'!C6 -> 下品 | D27: 丹药 | E27: 05_丹药!A6 | F27: 保留资料已有值 | G27: 已有同名配置／品级一致；其他差异见12表 | H27: B4
A28: t01.asset.0023 | B28: ='05_丹药'!B7 -> 强筋丸 | C28: ='05_丹药'!C7 -> 下品 | D28: 丹药 | E28: 05_丹药!A7 | F28: 保留资料已有值 | G28: 已有同名配置／品级一致；其他差异见12表 | H28: B4
A29: t01.asset.0024 | B29: ='05_丹药'!B8 -> 消毒散 | C29: ='05_丹药'!C8 -> 下品 | D29: 丹药 | E29: 05_丹药!A8 | F29: 保留资料已有值 | G29: 已有同名配置／品级一致；其他差异见12表 | H29: B4
A30: t01.asset.0025 | B30: ='05_丹药'!B9 -> 回灵丹 | C30: ='05_丹药'!C9 -> 下品 | D30: 丹药 | E30: 05_丹药!A9 | F30: 新增试玩候选 | G30: 尚无正式游戏配置 | H30: B4
A31: t01.asset.0026 | B31: ='05_丹药'!B10 -> 金疮散 | C31: ='05_丹药'!C10 -> 下品 | D31: 丹药 | E31: 05_丹药!A10 | F31: 新增试玩候选 | G31: 尚无正式游戏配置 | H31: B4
A32: t01.asset.0027 | B32: ='05_丹药'!B11 -> 回元散 | C32: ='05_丹药'!C11 -> 下品 | D32: 丹药 | E32: 05_丹药!A11 | F32: 新增试玩候选 | G32: 尚无正式游戏配置 | H32: B4
A33: t01.asset.0028 | B33: ='02_武器'!B15 -> 铁剑 | C33: ='02_武器'!C15 -> 凡品 | D33: 武器 | E33: 02_武器!A15 | F33: 候选数值，未试跑 | G33: 未实现；无游戏注册ID | H33: 第1批基础；第2批微调；第3批复查；用户直接更正优先；W01
A34: t01.asset.0029 | B34: ='02_武器'!B16 -> 赤纹剑 | C34: ='02_武器'!C16 -> 凡品 | D34: 武器 | E34: 02_武器!A16 | F34: 候选数值，未试跑 | G34: 未实现；无游戏注册ID | H34: 第1批基础；第2批微调；第3批复查；用户直接更正优先；W02
A35: t01.asset.0030 | B35: ='02_武器'!B17 -> 寒水剑 | C35: ='02_武器'!C17 -> 凡品 | D35: 武器 | E35: 02_武器!A17 | F35: 候选数值，未试跑 | G35: 未实现；无游戏注册ID | H35: 第1批基础；第2批微调；第3批复查；用户直接更正优先；W03
A36: t01.asset.0031 | B36: ='02_武器'!B18 -> 钢刀 | C36: ='02_武器'!C18 -> 凡品 | D36: 武器 | E36: 02_武器!A18 | F36: 候选数值，未试跑 | G36: 未实现；无游戏注册ID | H36: 第1批基础；第2批微调；第3批复查；用户直接更正优先；W05
A37: t01.asset.0032 | B37: ='02_武器'!B19 -> 金纹刀 | C37: ='02_武器'!C19 -> 凡品 | D37: 武器 | E37: 02_武器!A19 | F37: 候选数值，未试跑 | G37: 未实现；无游戏注册ID | H37: 第1批基础；第2批微调；第3批复查；用户直接更正优先；W06
A38: t01.asset.0033 | B38: ='02_武器'!B20 -> 赤焰刀 | C38: ='02_武器'!C20 -> 凡品 | D38: 武器 | E38: 02_武器!A20 | F38: 候选数值，未试跑 | G38: 未实现；无游戏注册ID | H38: 第1批基础；第2批微调；第3批复查；用户直接更正优先；W07
A39: t01.asset.0034 | B39: ='02_武器'!B21 -> 开山斧 | C39: ='02_武器'!C21 -> 凡品 | D39: 武器 | E39: 02_武器!A21 | F39: 候选数值，未试跑 | G39: 未实现；无游戏注册ID | H39: 第1批基础；第2批微调；第3批复查；用户直接更正优先；W08
A40: t01.asset.0035 | B40: ='02_武器'!B22 -> 金刚斧 | C40: ='02_武器'!C22 -> 凡品 | D40: 武器 | E40: 02_武器!A22 | F40: 候选数值，未试跑 | G40: 未实现；无游戏注册ID | H40: 第1批基础；第2批微调；第3批复查；用户直接更正优先；W09
A41: t01.asset.0036 | B41: ='02_武器'!B23 -> 厚土斧 | C41: ='02_武器'!C23 -> 凡品 | D41: 武器 | E41: 02_武器!A23 | F41: 候选数值，未试跑 | G41: 未实现；无游戏注册ID | H41: 第1批基础；第2批微调；第3批复查；用户直接更正优先；W10
A42: t01.asset.0037 | B42: ='02_武器'!B24 -> 桑木弓 | C42: ='02_武器'!C24 -> 凡品 | D42: 武器 | E42: 02_武器!A24 | F42: 候选数值，未试跑 | G42: 未实现；无游戏注册ID | H42: 第1批基础；第2批微调；第3批复查；用户直接更正优先；W11
A43: t01.asset.0038 | B43: ='02_武器'!B25 -> 水纹弓 | C43: ='02_武器'!C25 -> 凡品 | D43: 武器 | E43: 02_武器!A25 | F43: 候选数值，未试跑 | G43: 未实现；无游戏注册ID | H43: 第1批基础；第2批微调；第3批复查；用户直接更正优先；W12
A44: t01.asset.0039 | B44: ='02_武器'!B26 -> 雷纹弓 | C44: ='02_武器'!C26 -> 凡品 | D44: 武器 | E44: 02_武器!A26 | F44: 候选数值，未试跑 | G44: 未实现；无游戏注册ID | H44: 第1批基础；第2批微调；第3批复查；用户直接更正优先；W14
... A59: t01.asset.0054 | B59: ='02_武器'!B41 -> 赤焰枪 | C59: ='02_武器'!C41 -> 凡品 | D59: 武器 | E59: 02_武器!A41 | F59: 候选数值，未试跑 | G59: 未实现；无游戏注册ID | H59: 第1批基础；第2批微调；第3批复查；用户直接更正优先；W33
A60: t01.asset.0055 | B60: ='03_防具'!B14 -> 细布衣 | C60: ='03_防具'!C14 -> 凡品 | D60: 防具 | E60: 03_防具!A14 | F60: 候选数值，未试跑 | G60: 未实现；无游戏注册ID | H60: 第1批基础；第2批微调；第3批复查；用户直接更正优先；A01
A61: t01.asset.0056 | B61: ='03_防具'!B15 -> 水纹衣 | C61: ='03_防具'!C15 -> 凡品 | D61: 防具 | E61: 03_防具!A15 | F61: 候选数值，未试跑 | G61: 未实现；无游戏注册ID | H61: 第1批基础；第2批微调；第3批复查；用户直接更正优先；A02
A62: t01.asset.0057 | B62: ='03_防具'!B16 -> 札甲 | C62: ='03_防具'!C16 -> 凡品 | D62: 防具 | E62: 03_防具!A16 | F62: 候选数值，未试跑 | G62: 未实现；无游戏注册ID | H62: 第1批基础；第2批微调；第3批复查；用户直接更正优先；A03
A63: t01.asset.0058 | B63: ='03_防具'!B17 -> 赤铜甲 | C63: ='03_防具'!C17 -> 凡品 | D63: 防具 | E63: 03_防具!A17 | F63: 候选数值，未试跑 | G63: 未实现；无游戏注册ID | H63: 第1批基础；第2批微调；第3批复查；用户直接更正优先；A04
A64: t01.asset.0059 | B64: ='03_防具'!B18 -> 雷纹法袍 | C64: ='03_防具'!C18 -> 凡品 | D64: 防具 | E64: 03_防具!A18 | F64: 候选数值，未试跑 | G64: 未实现；无游戏注册ID | H64: 第1批基础；第2批微调；第3批复查；用户直接更正优先；A06
A65: t01.asset.0060 | B65: ='03_防具'!B19 -> 皮帽 | C65: ='03_防具'!C19 -> 凡品 | D65: 防具 | E65: 03_防具!A19 | F65: 候选数值，未试跑 | G65: 未实现；无游戏注册ID | H65: 第1批基础；第2批微调；第3批复查；用户直接更正优先；A07
A66: t01.asset.0061 | B66: ='03_防具'!B20 -> 铁盔 | C66: ='03_防具'!C20 -> 凡品 | D66: 防具 | E66: 03_防具!A20 | F66: 候选数值，未试跑 | G66: 未实现；无游戏注册ID | H66: 第1批基础；第2批微调；第3批复查；用户直接更正优先；A08
A67: t01.asset.0062 | B67: ='03_防具'!B21 -> 木纹冠 | C67: ='03_防具'!C21 -> 凡品 | D67: 防具 | E67: 03_防具!A21 | F67: 候选数值，未试跑 | G67: 未实现；无游戏注册ID | H67: 第1批基础；第2批微调；第3批复查；用户直接更正优先；A09
A68: t01.asset.0063 | B68: ='03_防具'!B22 -> 风纹冠 | C68: ='03_防具'!C22 -> 凡品 | D68: 防具 | E68: 03_防具!A22 | F68: 候选数值，未试跑 | G68: 未实现；无游戏注册ID | H68: 第1批基础；第2批微调；第3批复查；用户直接更正优先；A10
A69: t01.asset.0064 | B69: ='03_防具'!B23 -> 皮护臂 | C69: ='03_防具'!C23 -> 凡品 | D69: 防具 | E69: 03_防具!A23 | F69: 候选数值，未试跑 | G69: 未实现；无游戏注册ID | H69: 第1批基础；第2批微调；第3批复查；用户直接更正优先；A11
A70: t01.asset.0065 | B70: ='03_防具'!B24 -> 铁护腕 | C70: ='03_防具'!C24 -> 凡品 | D70: 防具 | E70: 03_防具!A24 | F70: 候选数值，未试跑 | G70: 未实现；无游戏注册ID | H70: 第1批基础；第2批微调；第3批复查；用户直接更正优先；A12
A71: t01.asset.0066 | B71: ='03_防具'!B25 -> 水纹护臂 | C71: ='03_防具'!C25 -> 凡品 | D71: 防具 | E71: 03_防具!A25 | F71: 候选数值，未试跑 | G71: 未实现；无游戏注册ID | H71: 第1批基础；第2批微调；第3批复查；用户直接更正优先；A13
... A87: t01.asset.0082 | B87: ='03_防具'!B41 -> 润脉腰带 | C87: ='03_防具'!C41 -> 凡品 | D87: 防具 | E87: 03_防具!A41 | F87: 候选数值，未试跑 | G87: 未实现；无游戏注册ID | H87: 第1批基础；第2批微调；第3批复查；用户直接更正优先；A31
A88: t01.asset.0083 | B88: ='04_法器'!B10 -> 回春佩 | C88: ='04_法器'!C10 -> 凡品 | D88: 法器 | E88: 04_法器!A10 | F88: 候选数值，未试跑 | G88: 未实现；无游戏注册ID | H88: 第1批基础；第2批微调；第3批复查；用户直接更正优先；F01
A89: t01.asset.0084 | B89: ='04_法器'!B11 -> 行气珠 | C89: ='04_法器'!C11 -> 凡品 | D89: 法器 | E89: 04_法器!A11 | F89: 候选数值，未试跑 | G89: 未实现；无游戏注册ID | H89: 第1批基础；第2批微调；第3批复查；用户直接更正优先；F02
A90: t01.asset.0085 | B90: ='04_法器'!B12 -> 聚元环 | C90: ='04_法器'!C12 -> 凡品 | D90: 法器 | E90: 04_法器!A12 | F90: 候选数值，未试跑 | G90: 未实现；无游戏注册ID | H90: 第1批基础；第2批微调；第3批复查；用户直接更正优先；F03
A91: t01.asset.0086 | B91: ='04_法器'!B13 -> 调息玉 | C91: ='04_法器'!C13 -> 凡品 | D91: 法器 | E91: 04_法器!A13 | F91: 候选数值，未试跑 | G91: 未实现；无游戏注册ID | H91: 第1批基础；第2批微调；第3批复查；用户直接更正优先；F04
A92: t01.asset.0087 | B92: ='04_法器'!B14 -> 金光镜 | C92: ='04_法器'!C14 -> 凡品 | D92: 法器 | E92: 04_法器!A14 | F92: 候选数值，未试跑 | G92: 未实现；无游戏注册ID | H92: 第1批基础；第2批微调；第3批复查；用户直接更正优先；F05
A93: t01.asset.0088 | B93: ='04_法器'!B15 -> 青木铃 | C93: ='04_法器'!C15 -> 凡品 | D93: 法器 | E93: 04_法器!A15 | F93: 候选数值，未试跑 | G93: 未实现；无游戏注册ID | H93: 第1批基础；第2批微调；第3批复查；用户直接更正优先；F06
A94: t01.asset.0089 | B94: ='04_法器'!B16 -> 寒水珠 | C94: ='04_法器'!C16 -> 凡品 | D94: 法器 | E94: 04_法器!A16 | F94: 候选数值，未试跑 | G94: 未实现；无游戏注册ID | H94: 第1批基础；第2批微调；第3批复查；用户直接更正优先；F07
A95: t01.asset.0090 | B95: ='04_法器'!B17 -> 火灵珠 | C95: ='04_法器'!C17 -> 凡品 | D95: 法器 | E95: 04_法器!A17 | F95: 候选数值，未试跑 | G95: 未实现；无游戏注册ID | H95: 第1批基础；第2批微调；第3批复查；用户直接更正优先；F08
A96: t01.asset.0091 | B96: ='04_法器'!B18 -> 坤土珠 | C96: ='04_法器'!C18 -> 凡品 | D96: 法器 | E96: 04_法器!A18 | F96: 候选数值，未试跑 | G96: 未实现；无游戏注册ID | H96: 第1批基础；第2批微调；第3批复查；用户直接更正优先；F09
A97: t01.asset.0092 | B97: ='04_法器'!B19 -> 逐风旗 | C97: ='04_法器'!C19 -> 凡品 | D97: 法器 | E97: 04_法器!A19 | F97: 候选数值，未试跑 | G97: 未实现；无游戏注册ID | H97: 第1批基础；第2批微调；第3批复查；用户直接更正优先；F10
A98: t01.asset.0093 | B98: ='04_法器'!B20 -> 引雷珠 | C98: ='04_法器'!C20 -> 凡品 | D98: 法器 | E98: 04_法器!A20 | F98: 候选数值，未试跑 | G98: 未实现；无游戏注册ID | H98: 第1批基础；第2批微调；第3批复查；用户直接更正优先；F11
A99: t01.asset.0094 | B99: ='04_法器'!B21 -> 护心镜 | C99: ='04_法器'!C21 -> 凡品 | D99: 法器 | E99: 04_法器!A21 | F99: 候选数值，未试跑 | G99: 未实现；无游戏注册ID | H99: 第1批基础；第2批微调；第3批复查；用户直接更正优先；F12
... A105: t01.asset.0100 | B105: ='04_法器'!B27 -> 蕴雷铃 | C105: ='04_法器'!C27 -> 凡品 | D105: 法器 | E105: 04_法器!A27 | F105: 候选数值，未试跑 | G105: 未实现；无游戏注册ID | H105: 第1批基础；第2批微调；第3批复查；用户直接更正优先；F18
A106: t01.asset.0101 | B106: ='05_丹药'!B12 -> 回春丹 | C106: ='05_丹药'!C12 -> 凡品 | D106: 丹药 | E106: 05_丹药!A12 | F106: 候选数值，未试跑 | G106: 未实现；无游戏注册ID | H106: 本次Q01用户补充丹药完整表；用户首瓶机制修正；P01
A107: t01.asset.0102 | B107: ='05_丹药'!B13 -> 益气丹 | C107: ='05_丹药'!C13 -> 凡品 | D107: 丹药 | E107: 05_丹药!A13 | F107: 候选数值，未试跑 | G107: 未实现；无游戏注册ID | H107: 本次Q01用户补充丹药完整表；用户首瓶机制修正；P02
A108: t01.asset.0103 | B108: ='05_丹药'!B14 -> 聚灵丹 | C108: ='05_丹药'!C14 -> 凡品 | D108: 丹药 | E108: 05_丹药!A14 | F108: 候选数值，未试跑 | G108: 未实现；无游戏注册ID | H108: 本次Q01用户补充丹药完整表；用户首瓶机制修正；P03
A109: t01.asset.0104 | B109: ='05_丹药'!B15 -> 培元丹 | C109: ='05_丹药'!C15 -> 凡品 | D109: 丹药 | E109: 05_丹药!A15 | F109: 候选数值，未试跑 | G109: 未实现；无游戏注册ID | H109: 本次Q01用户补充丹药完整表；用户首瓶机制修正；P04
A110: t01.asset.0105 | B110: ='05_丹药'!B16 -> 铁骨丸 | C110: ='05_丹药'!C16 -> 凡品 | D110: 丹药 | E110: 05_丹药!A16 | F110: 候选数值，未试跑 | G110: 未实现；无游戏注册ID | H110: 本次Q01用户补充丹药完整表；用户首瓶机制修正；P05
A111: t01.asset.0106 | B111: ='05_丹药'!B17 -> 避火丹 | C111: ='05_丹药'!C17 -> 凡品 | D111: 丹药 | E111: 05_丹药!A17 | F111: 候选数值，未试跑 | G111: 未实现；无游戏注册ID | H111: 本次Q01用户补充丹药完整表；用户首瓶机制修正；P06
A112: t01.asset.0107 | B112: ='05_丹药'!B18 -> 辟寒丹 | C112: ='05_丹药'!C18 -> 凡品 | D112: 丹药 | E112: 05_丹药!A18 | F112: 候选数值，未试跑 | G112: 未实现；无游戏注册ID | H112: 本次Q01用户补充丹药完整表；用户首瓶机制修正；P07
A113: t01.asset.0108 | B113: ='05_丹药'!B19 -> 辟金丹 | C113: ='05_丹药'!C19 -> 凡品 | D113: 丹药 | E113: 05_丹药!A19 | F113: 候选数值，未试跑 | G113: 未实现；无游戏注册ID | H113: 本次Q01用户补充丹药完整表；用户首瓶机制修正；P08
A114: t01.asset.0109 | B114: ='05_丹药'!B20 -> 御木丹 | C114: ='05_丹药'!C20 -> 凡品 | D114: 丹药 | E114: 05_丹药!A20 | F114: 候选数值，未试跑 | G114: 未实现；无游戏注册ID | H114: 本次Q01用户补充丹药完整表；用户首瓶机制修正；P09
A115: t01.asset.0110 | B115: ='05_丹药'!B21 -> 镇土丹 | C115: ='05_丹药'!C21 -> 凡品 | D115: 丹药 | E115: 05_丹药!A21 | F115: 候选数值，未试跑 | G115: 未实现；无游戏注册ID | H115: 本次Q01用户补充丹药完整表；用户首瓶机制修正；P10
A116: t01.asset.0111 | B116: ='07_暗器'!B6 -> 飞针 | C116: ='07_暗器'!C6 -> 凡品 | D116: 暗器 | E116: 07_暗器!A6 | F116: 候选数值，未试跑 | G116: 未实现；无游戏注册ID | H116: 第1批基础；第2批微调；第3批复查；用户直接更正优先；H01
A117: t01.asset.0112 | B117: ='07_暗器'!B7 -> 柳叶镖 | C117: ='07_暗器'!C7 -> 凡品 | D117: 暗器 | E117: 07_暗器!A7 | F117: 候选数值，未试跑 | G117: 未实现；无游戏注册ID | H117: 第1批基础；第2批微调；第3批复查；用户直接更正优先；H02
A118: t01.asset.0113 | B118: ='07_暗器'!B8 -> 铁丸 | C118: ='07_暗器'!C8 -> 凡品 | D118: 暗器 | E118: 07_暗器!A8 | F118: 候选数值，未试跑 | G118: 未实现；无游戏注册ID | H118: 第1批基础；第2批微调；第3批复查；用户直接更正优先；H03
A119: t01.asset.0114 | B119: ='07_暗器'!B9 -> 毒针 | C119: ='07_暗器'!C9 -> 凡品 | D119: 暗器 | E119: 07_暗器!A9 | F119: 候选数值，未试跑 | G119: 未实现；无游戏注册ID | H119: 第1批基础；第2批微调；第3批复查；用户直接更正优先；H04
A120: t01.asset.0115 | B120: ='07_暗器'!B10 -> 火砂 | C120: ='07_暗器'!C10 -> 凡品 | D120: 暗器 | E120: 07_暗器!A10 | F120: 候选数值，未试跑 | G120: 未实现；无游戏注册ID | H120: 第1批基础；第2批微调；第3批复查；用户直接更正优先；H05

Sheet 02_武器
A1: t01-08｜武器
A2: 2026-09-28 · 27下品＋88凡品＝115件 · 候选数值／当前规则／游戏实现分列 · 不含平衡测试结论
A5: 资产ID | B5: 名称 | C5: 品级 | D5: 元素 | E5: 器型 | F5: Attack Type | G5: 宽_格 | H5: 高_格 | I5: 实际占格 | J5: 设计伤害 | K5: 设计CD_秒 | L5: 设计体力费 | M5: 伤害相对档 | N5: CD相对档 | O5: 体力相对档 | P5: 基础战斗性格 | Q5: 后续元素倾向_非本件 | R5: 边界 | S5: 机制引用 | T5: 现有游戏ID | U5: 设计状态 | V5: 来源 | W5: 来源编号 | X5: 状态 | Y5: 施加层数 | Z5: 状态时机与目标 | AA5: 灵力费 | AB5: 数量消耗 | AC5: 效果引用 | AD5: 本批元素规则
A6: t01.asset.0001 | B6: 青石短剑 | C6: 下品 | D6: NONE | E6: 剑 | F6: 斩击 | G6: 1 | H6: 2 | I6: =G6*H6 -> 2 | M6: 中 | N6: 中 | O6: 中 | P6: 均衡斩击基准 | Q6: 火、水 | R6: 不带状态／控制／邻接；无射程，猎弓不耗箭；石印为武器。 | S6: 01 M01/M06/M08；03权限；04九器型 | T6: base.map_item.qingshi_short_sword | U6: 待绝对数值；非生产配置 | V6: A；U
A7: t01.asset.0002 | B7: 铁刀 | C7: 下品 | D7: NONE | E7: 佩刀 | F7: 斩击 | G7: 1 | H7: 1 | I7: =G7*H7 -> 1 | M7: 中低 | N7: 中短 | O7: 中低 | P7: 紧凑、以空间换单击收益 | Q7: 金、火 | R7: 不带状态／控制／邻接；无射程，猎弓不耗箭；石印为武器。 | S7: 01 M01/M06/M08；03权限；04九器型 | T7: 未配置 | U7: 待绝对数值；非生产配置 | V7: A；U
A8: t01.asset.0003 | B8: 柴斧 | C8: 下品 | D8: NONE | E8: 斧 | F8: 斩击 | G8: 2 | H8: 1 | I8: =G8*H8 -> 2 | M8: 高 | N8: 中长 | O8: 高 | P8: 重斩、强调单次爆发 | Q8: 金、土 | R8: 不带状态／控制／邻接；无射程，猎弓不耗箭；石印为武器。 | S8: 01 M01/M06/M08；03权限；04九器型 | T8: 未配置 | U8: 待绝对数值；非生产配置 | V8: A；U
A9: t01.asset.0004 | B9: 猎弓 | C9: 下品 | D9: NONE | E9: 弓 | F9: 穿刺 | G9: 1 | H9: 2 | I9: =G9*H9 -> 2 | M9: 中 | N9: 中长 | O9: 中低 | P9: 稳节奏穿刺；耗力较轻为本批方向 | Q9: 木、水；兼容面广 | R9: 不带状态／控制／邻接；无射程，猎弓不耗箭；石印为武器。 | S9: 01 M01/M06/M08；03权限；04九器型 | T9: base.map_item.hunting_bow | U9: 待绝对数值；非生产配置 | V9: A；U
A10: t01.asset.0005 | B10: 匕首 | C10: 下品 | D10: NONE | E10: 短刃 | F10: 穿刺 | G10: 1 | H10: 1 | I10: =G10*H10 -> 1 | M10: 低 | N10: 短 | O10: 低 | P10: 小占格、快循环 | Q10: 金、风 | R10: 不带状态／控制／邻接；无射程，猎弓不耗箭；石印为武器。 | S10: 01 M01/M06/M08；03权限；04九器型 | T10: 未配置 | U10: 待绝对数值；非生产配置 | V10: A；U
A11: t01.asset.0006 | B11: 长枪 | C11: 下品 | D11: NONE | E11: 枪 | F11: 穿刺 | G11: 3 | H11: 1 | I11: =G11*H11 -> 3 | M11: 高 | N11: 长 | O11: 中高 | P11: 大占格换高单击 | Q11: 雷、金、木 | R11: 不带状态／控制／邻接；无射程，猎弓不耗箭；石印为武器。 | S11: 01 M01/M06/M08；03权限；04九器型 | T11: 未配置 | U11: 待绝对数值；非生产配置 | V11: A；U
A12: t01.asset.0007 | B12: 短柄铁锤 | C12: 下品 | D12: NONE | E12: 锤 | F12: 钝击 | G12: 1 | H12: 2 | I12: =G12*H12 -> 2 | M12: 中高 | N12: 中长 | O12: 中高 | P12: 偏沉重的钝击基准 | Q12: 土、火 | R12: 不带状态／控制／邻接；无射程，猎弓不耗箭；石印为武器。 | S12: 01 M01/M06/M08；03权限；04九器型 | T12: base.map_item.short_iron_hammer | U12: 待绝对数值；非生产配置 | V12: A；U
A13: t01.asset.0008 | B13: 石印 | C13: 下品 | D13: NONE | E13: 印 | F13: 钝击 | G13: 1 | H13: 1 | I13: =G13*H13 -> 1 | M13: 中低 | N13: 中 | O13: 中 | P13: 紧凑钝击，不追求快攻 | Q13: 土、雷 | R13: 不带状态／控制／邻接；无射程，猎弓不耗箭；石印为武器。 | S13: 01 M01/M06/M08；03权限；04九器型 | T13: 未配置 | U13: 待绝对数值；非生产配置 | V13: A；U
A14: t01.asset.0009 | B14: 皮鞭 | C14: 下品 | D14: NONE | E14: 鞭 | F14: 钝击 | G14: 3 | H14: 1 | I14: =G14*H14 -> 3 | M14: 低 | N14: 短 | O14: 中低 | P14: 大占格换高轮转频率 | Q14: 雷、木 | R14: 不带状态／控制／邻接；无射程，猎弓不耗箭；石印为武器。 | S14: 01 M01/M06/M08；03权限；04九器型 | T14: 未配置 | U14: 待绝对数值；非生产配置 | V14: A；U
A15: t01.asset.0028 | B15: 铁剑 | C15: 凡品 | D15: NONE | E15: 剑 | F15: 斩击 | G15: 1 | H15: 2 | I15: =G15*H15 -> 2 | J15: 18 | K15: 5.5 | L15: 3 | P15: 基础数值与元素 | R15: 不耗本体；体力为单把基础，多武器加算另查19／20表；无射程、弓不耗普通箭 | S15: 01 M01/M06/M08；03 C010；04武器 | U15: 候选数值，未试跑 | V15: 第1批基础；第2批微调；第3批复查；用户直接更正优先 | W15: W01 | Z15: 无；敌方 | AA15: 0 | AB15: 0 | AC15: t01.asset.0028.effect.01 | AD15: 固定元素与单状态匹配；不是运行时由状态改变元素
A16: t01.asset.0029 | B16: 赤纹剑 | C16: 凡品 | D16: 火 | E16: 剑 | F16: 斩击 | G16: 1 | H16: 2 | I16: =G16*H16 -> 2 | J16: 16 | K16: 5.5 | L16: 4 | P16: 基础＋单状态 | R16: 不耗本体；体力为单把基础，多武器加算另查19／20表；无射程、弓不耗普通箭；具体效果与施加时序依02和核心01，不由七系标签自动增加额外伤害。 | S16: 01 M01/M06/M08；03 C010；04武器 | U16: 候选数值，未试跑 | V16: 第1批基础；第2批微调；第3批复查；用户直接更正优先 | W16: W02 | X16: 灼烧 | Y16: 1 | Z16: 命中；敌方 | AA16: 0 | AB16: 0 | AC16: t01.asset.0029.effect.01；t01.asset.0029.effect.02 | AD16: 固定元素与单状态匹配；不是运行时由状态改变元素
A17: t01.asset.0030 | B17: 寒水剑 | C17: 凡品 | D17: 水 | E17: 剑 | F17: 斩击 | G17: 1 | H17: 2 | I17: =G17*H17 -> 2 | J17: 17 | K17: 6 | L17: 4 | P17: 基础＋单状态 | R17: 不耗本体；体力为单把基础，多武器加算另查19／20表；无射程、弓不耗普通箭；寒霜正常新层先施加、后由本次合格主动水攻触发；初霜专属额外层例外留后次。 | S17: 01 M01/M06/M08；03 C010；04武器 | U17: 候选数值，未试跑 | V17: 第1批基础；第2批微调；第3批复查；用户直接更正优先 | W17: W03 | X17: 寒霜 | Y17: 1 | Z17: 命中；敌方 | AA17: 0 | AB17: 0 | AC17: t01.asset.0030.effect.01；t01.asset.0030.effect.02 | AD17: 固定元素与单状态匹配；不是运行时由状态改变元素
A18: t01.asset.0031 | B18: 钢刀 | C18: 凡品 | D18: 金 | E18: 佩刀 | F18: 斩击 | G18: 1 | H18: 1 | I18: =G18*H18 -> 1 | J18: 10 | K18: 4.5 | L18: 2 | P18: 基础＋单状态 | R18: 不耗本体；体力为单把基础，多武器加算另查19／20表；无射程、弓不耗普通箭；本件流血须本次攻击实际伤及气血；只命中或只扣盾甲不足。 | S18: 01 M01/M06/M08；03 C010；04武器 | U18: 候选数值，未试跑 | V18: 第1批基础；第2批微调；第3批复查；用户直接更正优先 | W18: W05 | X18: 流血 | Y18: 1 | Z18: 实际伤到气血；敌方 | AA18: 0 | AB18: 0 | AC18: t01.asset.0031.effect.01；t01.asset.0031.effect.02 | AD18: 固定元素与单状态匹配；不是运行时由状态改变元素
A19: t01.asset.0032 | B19: 金纹刀 | C19: 凡品 | D19: 金 | E19: 佩刀 | F19: 斩击 | G19: 1 | H19: 1 | I19: =G19*H19 -> 1 | J19: 12 | K19: 5.5 | L19: 3 | P19: 基础＋单状态 | R19: 不耗本体；体力为单把基础，多武器加算另查19／20表；无射程、弓不耗普通箭；锋痕由合格武器攻击兑现；金光镜仍是法器来源，不因金元素或SPELL攻击类型取得武器资格。 | S19: 01 M01/M06/M08；03 C010；04武器 | U19: 候选数值，未试跑 | V19: 第1批基础；第2批微调；第3批复查；用户直接更正优先 | W19: W06 | X19: 锋痕 | Y19: 1 | Z19: 命中；敌方 | AA19: 0 | AB19: 0 | AC19: t01.asset.0032.effect.01；t01.asset.0032.effect.02 | AD19: 固定元素与单状态匹配；不是运行时由状态改变元素
A20: t01.asset.0033 | B20: 赤焰刀 | C20: 凡品 | D20: 火 | E20: 佩刀 | F20: 斩击 | G20: 1 | H20: 1 | I20: =G20*H20 -> 1 | J20: 11 | K20: 5.5 | L20: 3 | P20: 基础＋单状态 | R20: 不耗本体；体力为单把基础，多武器加算另查19／20表；无射程、弓不耗普通箭；具体效果与施加时序依02和核心01，不由七系标签自动增加额外伤害。 | S20: 01 M01/M06/M08；03 C010；04武器 | U20: 候选数值，未试跑 | V20: 第1批基础；第2批微调；第3批复查；用户直接更正优先 | W20: W07 | X20: 破甲 | Y20: 1 | Z20: 命中；敌方 | AA20: 0 | AB20: 0 | AC20: t01.asset.0033.effect.01；t01.asset.0033.effect.02 | AD20: 固定元素与单状态匹配；不是运行时由状态改变元素
A21: t01.asset.0034 | B21: 开山斧 | C21: 凡品 | D21: 土 | E21: 斧 | F21: 斩击 | G21: 2 | H21: 1 | I21: =G21*H21 -> 2 | J21: 30 | K21: 8.5 | L21: 6 | P21: 基础＋单状态 | R21: 不耗本体；体力为单把基础，多武器加算另查19／20表；无射程、弓不耗普通箭；具体效果与施加时序依02和核心01，不由七系标签自动增加额外伤害。 | S21: 01 M01/M06/M08；03 C010；04武器 | U21: 候选数值，未试跑 | V21: 第1批基础；第2批微调；第3批复查；用户直接更正优先 | W21: W08 | X21: 疲惫 | Y21: 2 | Z21: 命中；敌方 | AA21: 0 | AB21: 0 | AC21: t01.asset.0034.effect.01；t01.asset.0034.effect.02 | AD21: 固定元素与单状态匹配；不是运行时由状态改变元素
A22: t01.asset.0035 | B22: 金刚斧 | C22: 凡品 | D22: 金 | E22: 斧 | F22: 斩击 | G22: 2 | H22: 1 | I22: =G22*H22 -> 2 | J22: 28 | K22: 8.5 | L22: 6 | P22: 基础＋单状态 | R22: 不耗本体；体力为单把基础，多武器加算另查19／20表；无射程、弓不耗普通箭；锋痕由合格武器攻击兑现；金光镜仍是法器来源，不因金元素或SPELL攻击类型取得武器资格。 | S22: 01 M01/M06/M08；03 C010；04武器 | U22: 候选数值，未试跑 | V22: 第1批基础；第2批微调；第3批复查；用户直接更正优先 | W22: W09 | X22: 锋痕 | Y22: 2 | Z22: 命中；敌方 | AA22: 0 | AB22: 0 | AC22: t01.asset.0035.effect.01；t01.asset.0035.effect.02 | AD22: 固定元素与单状态匹配；不是运行时由状态改变元素
A23: t01.asset.0036 | B23: 厚土斧 | C23: 凡品 | D23: 土 | E23: 斧 | F23: 斩击 | G23: 2 | H23: 1 | I23: =G23*H23 -> 2 | J23: 28 | K23: 8.5 | L23: 6 | P23: 基础＋单状态 | R23: 不耗本体；体力为单把基础，多武器加算另查19／20表；无射程、弓不耗普通箭；具体效果与施加时序依02和核心01，不由七系标签自动增加额外伤害。 | S23: 01 M01/M06/M08；03 C010；04武器 | U23: 候选数值，未试跑 | V23: 第1批基础；第2批微调；第3批复查；用户直接更正优先 | W23: W10 | X23: 重伤 | Y23: 2 | Z23: 命中；敌方 | AA23: 0 | AB23: 0 | AC23: t01.asset.0036.effect.01；t01.asset.0036.effect.02 | AD23: 固定元素与单状态匹配；不是运行时由状态改变元素
A24: t01.asset.0037 | B24: 桑木弓 | C24: 凡品 | D24: 木 | E24: 弓 | F24: 穿刺 | G24: 1 | H24: 2 | I24: =G24*H24 -> 2 | J24: 24 | K24: 7 | L24: 5 | P24: 基础数值与元素 | R24: 不耗本体；体力为单把基础，多武器加算另查19／20表；无射程、弓不耗普通箭 | S24: 01 M01/M06/M08；03 C010；04武器 | U24: 候选数值，未试跑 | V24: 第1批基础；第2批微调；第3批复查；用户直接更正优先 | W24: W11 | Z24: 无；敌方 | AA24: 0 | AB24: 0 | AC24: t01.asset.0037.effect.01 | AD24: 固定元素与单状态匹配；不是运行时由状态改变元素
A25: t01.asset.0038 | B25: 水纹弓 | C25: 凡品 | D25: 水 | E25: 弓 | F25: 穿刺 | G25: 1 | H25: 2 | I25: =G25*H25 -> 2 | J25: 20 | K25: 7 | L25: 5 | P25: 基础＋单状态 | R25: 不耗本体；体力为单把基础，多武器加算另查19／20表；无射程、弓不耗普通箭；具体效果与施加时序依02和核心01，不由七系标签自动增加额外伤害。 | S25: 01 M01/M06/M08；03 C010；04武器 | U25: 候选数值，未试跑 | V25: 第1批基础；第2批微调；第3批复查；用户直接更正优先 | W25: W12 | X25: 枯脉 | Y25: 1 | Z25: 命中；敌方 | AA25: 0 | AB25: 0 | AC25: t01.asset.0038.effect.01；t01.asset.0038.effect.02 | AD25: 固定元素与单状态匹配；不是运行时由状态改变元素
A26: t01.asset.0039 | B26: 雷纹弓 | C26: 凡品 | D26: 雷 | E26: 弓 | F26: 穿刺 | G26: 1 | H26: 2 | I26: =G26*H26 -> 2 | J26: 22 | K26: 7 | L26: 6 | P26: 基础＋单状态 | R26: 不耗本体；体力为单把基础，多武器加算另查19／20表；无射程、弓不耗普通箭；连环供后续合格雷攻击利用；锁雷环无本体攻击，不直接制造雷击或闪电。 | S26: 01 M01/M06/M08；03 C010；04武器 | U26: 候选数值，未试跑 | V26: 第1批基础；第2批微调；第3批复查；用户直接更正优先 | W26: W14 | X26: 连环 | Y26: 1 | Z26: 命中；敌方 | AA26: 0 | AB26: 0 | AC26: t01.asset.0039.effect.01；t01.asset.0039.effect.02 | AD26: 固定元素与单状态匹配；不是运行时由状态改变元素
A27: t01.asset.0040 | B27: 精铁匕 | C27: 凡品 | D27: 金 | E27: 短刃 | F27: 穿刺 | G27: 1 | H27: 1 | I27: =G27*H27 -> 1 | J27: 8 | K27: 3.5 | L27: 2 | P27: 基础＋单状态 | R27: 不耗本体；体力为单把基础，多武器加算另查19／20表；无射程、弓不耗普通箭；本件流血须本次攻击实际伤及气血；只命中或只扣盾甲不足。 | S27: 01 M01/M06/M08；03 C010；04武器 | U27: 候选数值，未试跑 | V27: 第1批基础；第2批微调；第3批复查；用户直接更正优先 | W27: W15 | X27: 流血 | Y27: 1 | Z27: 实际伤到气血；敌方 | AA27: 0 | AB27: 0 | AC27: t01.asset.0040.effect.01；t01.asset.0040.effect.02 | AD27: 固定元素与单状态匹配；不是运行时由状态改变元素
A28: t01.asset.0041 | B28: 风刃匕 | C28: 凡品 | D28: 风 | E28: 短刃 | F28: 穿刺 | G28: 1 | H28: 1 | I28: =G28*H28 -> 1 | J28: 7 | K28: 3 | L28: 2 | P28: 基础＋单状态 | R28: 不耗本体；体力为单把基础，多武器加算另查19／20表；无射程、弓不耗普通箭；具体效果与施加时序依02和核心01，不由七系标签自动增加额外伤害。 | S28: 01 M01/M06/M08；03 C010；04武器 | U28: 候选数值，未试跑 | V28: 第1批基础；第2批微调；第3批复查；用户直接更正优先 | W28: W16 | X28: 失衡 | Y28: 1 | Z28: 命中；敌方 | AA28: 0 | AB28: 0 | AC28: t01.asset.0041.effect.01；t01.asset.0041.effect.02 | AD28: 固定元素与单状态匹配；不是运行时由状态改变元素
A29: t01.asset.0042 | B29: 青木枪 | C29: 凡品 | D29: 木 | E29: 枪 | F29: 穿刺 | G29: 3 | H29: 1 | I29: =G29*H29 -> 3 | J29: 34 | K29: 8.5 | L29: 7 | P29: 基础＋单状态 | R29: 不耗本体；体力为单把基础，多武器加算另查19／20表；无射程、弓不耗普通箭；缠绕由后续合格火、雷伤害利用；木攻击本身不因此获得火雷增幅。 | S29: 01 M01/M06/M08；03 C010；04武器 | U29: 候选数值，未试跑 | V29: 第1批基础；第2批微调；第3批复查；用户直接更正优先 | W29: W17 | X29: 缠绕 | Y29: 2 | Z29: 命中；敌方 | AA29: 0 | AB29: 0 | AC29: t01.asset.0042.effect.01；t01.asset.0042.effect.02 | AD29: 固定元素与单状态匹配；不是运行时由状态改变元素
A30: t01.asset.0043 | B30: 雷纹枪 | C30: 凡品 | D30: 雷 | E30: 枪 | F30: 穿刺 | G30: 3 | H30: 1 | I30: =G30*H30 -> 3 | J30: 38 | K30: 9.5 | L30: 8 | P30: 基础＋单状态 | R30: 不耗本体；体力为单把基础，多武器加算另查19／20表；无射程、弓不耗普通箭；雷印新层在本击伤后加入，供后续合格雷攻；无本体雷攻击的施层器具不直接引雷。 | S30: 01 M01/M06/M08；03 C010；04武器 | U30: 候选数值，未试跑 | V30: 第1批基础；第2批微调；第3批复查；用户直接更正优先 | W30: W19 | X30: 雷印 | Y30: 2 | Z30: 命中；敌方 | AA30: 0 | AB30: 0 | AC30: t01.asset.0043.effect.01；t01.asset.0043.effect.02 | AD30: 固定元素与单状态匹配；不是运行时由状态改变元素
A31: t01.asset.0044 | B31: 炎纹锤 | C31: 凡品 | D31: 火 | E31: 锤 | F31: 钝击 | G31: 1 | H31: 2 | I31: =G31*H31 -> 2 | J31: 20 | K31: 6 | L31: 4 | P31: 基础＋单状态 | R31: 不耗本体；体力为单把基础，多武器加算另查19／20表；无射程、弓不耗普通箭；具体效果与施加时序依02和核心01，不由七系标签自动增加额外伤害。 | S31: 01 M01/M06/M08；03 C010；04武器 | U31: 候选数值，未试跑 | V31: 第1批基础；第2批微调；第3批复查；用户直接更正优先 | W31: W20 | X31: 破甲 | Y31: 1 | Z31: 命中；敌方 | AA31: 0 | AB31: 0 | AC31: t01.asset.0044.effect.01；t01.asset.0044.effect.02 | AD31: 固定元素与单状态匹配；不是运行时由状态改变元素
A32: t01.asset.0045 | B32: 石骨锤 | C32: 凡品 | D32: 土 | E32: 锤 | F32: 钝击 | G32: 1 | H32: 2 | I32: =G32*H32 -> 2 | J32: 26 | K32: 7 | L32: 5 | P32: 基础数值与元素 | R32: 不耗本体；体力为单把基础，多武器加算另查19／20表；无射程、弓不耗普通箭 | S32: 01 M01/M06/M08；03 C010；04武器 | U32: 候选数值，未试跑 | V32: 第1批基础；第2批微调；第3批复查；用户直接更正优先 | W32: W21 | Z32: 无；敌方 | AA32: 0 | AB32: 0 | AC32: t01.asset.0045.effect.01 | AD32: 固定元素与单状态匹配；不是运行时由状态改变元素
A33: t01.asset.0046 | B33: 镇土印 | C33: 凡品 | D33: 土 | E33: 印 | F33: 钝击 | G33: 1 | H33: 1 | I33: =G33*H33 -> 1 | J33: 16 | K33: 7 | L33: 3 | P33: 基础＋单状态 | R33: 不耗本体；体力为单把基础，多武器加算另查19／20表；无射程、弓不耗普通箭；具体效果与施加时序依02和核心01，不由七系标签自动增加额外伤害。 | S33: 01 M01/M06/M08；03 C010；04武器 | U33: 候选数值，未试跑 | V33: 第1批基础；第2批微调；第3批复查；用户直接更正优先 | W33: W22 | X33: 疲惫 | Y33: 1 | Z33: 命中；敌方 | AA33: 0 | AB33: 0 | AC33: t01.asset.0046.effect.01；t01.asset.0046.effect.02 | AD33: 固定元素与单状态匹配；不是运行时由状态改变元素
A34: t01.asset.0047 | B34: 雷纹印 | C34: 凡品 | D34: 雷 | E34: 印 | F34: 钝击 | G34: 1 | H34: 1 | I34: =G34*H34 -> 1 | J34: 14 | K34: 6 | L34: 3 | P34: 基础＋单状态 | R34: 不耗本体；体力为单把基础，多武器加算另查19／20表；无射程、弓不耗普通箭；具体效果与施加时序依02和核心01，不由七系标签自动增加额外伤害。 | S34: 01 M01/M06/M08；03 C010；04武器 | U34: 候选数值，未试跑 | V34: 第1批基础；第2批微调；第3批复查；用户直接更正优先 | W34: W23 | X34: 雷蕴 | Y34: 1 | Z34: 命中；自身 | AA34: 0 | AB34: 0 | AC34: t01.asset.0047.effect.01；t01.asset.0047.effect.02 | AD34: 固定元素与单状态匹配；不是运行时由状态改变元素
A35: t01.asset.0048 | B35: 藤鞭 | C35: 凡品 | D35: 木 | E35: 鞭 | F35: 钝击 | G35: 3 | H35: 1 | I35: =G35*H35 -> 3 | J35: 14 | K35: 4 | L35: 3 | P35: 基础＋单状态 | R35: 不耗本体；体力为单把基础，多武器加算另查19／20表；无射程、弓不耗普通箭；具体效果与施加时序依02和核心01，不由七系标签自动增加额外伤害。 | S35: 01 M01/M06/M08；03 C010；04武器 | U35: 候选数值，未试跑 | V35: 第1批基础；第2批微调；第3批复查；用户直接更正优先 | W35: W24 | X35: 毒蚀 | Y35: 1 | Z35: 命中；敌方 | AA35: 0 | AB35: 0 | AC35: t01.asset.0048.effect.01；t01.asset.0048.effect.02 | AD35: 固定元素与单状态匹配；不是运行时由状态改变元素
A36: t01.asset.0049 | B36: 雷鞭 | C36: 凡品 | D36: 雷 | E36: 鞭 | F36: 钝击 | G36: 3 | H36: 1 | I36: =G36*H36 -> 3 | J36: 15 | K36: 4.5 | L36: 4 | P36: 基础＋单状态 | R36: 不耗本体；体力为单把基础，多武器加算另查19／20表；无射程、弓不耗普通箭；雷印新层在本击伤后加入，供后续合格雷攻；无本体雷攻击的施层器具不直接引雷。 | S36: 01 M01/M06/M08；03 C010；04武器 | U36: 候选数值，未试跑 | V36: 第1批基础；第2批微调；第3批复查；用户直接更正优先 | W36: W25 | X36: 雷印 | Y36: 1 | Z36: 命中；敌方 | AA36: 0 | AB36: 0 | AC36: t01.asset.0049.effect.01；t01.asset.0049.effect.02 | AD36: 固定元素与单状态匹配；不是运行时由状态改变元素
A37: t01.asset.0050 | B37: 刺血匕 | C37: 凡品 | D37: 金 | E37: 短刃 | F37: 穿刺 | G37: 1 | H37: 1 | I37: =G37*H37 -> 1 | J37: 8 | K37: 4.5 | L37: 2 | P37: 基础＋单状态 | R37: 不耗本体；体力为单把基础，多武器加算另查19／20表；无射程、弓不耗普通箭；本件流血须本次攻击实际伤及气血；只命中或只扣盾甲不足。 | S37: 01 M01/M06/M08；03 C010；04武器 | U37: 候选数值，未试跑 | V37: 第1批基础；第2批微调；第3批复查；用户直接更正优先 | W37: W28 | X37: 流血 | Y37: 2 | Z37: 实际伤到气血；敌方 | AA37: 0 | AB37: 0 | AC37: t01.asset.0050.effect.01；t01.asset.0050.effect.02 | AD37: 固定元素与单状态匹配；不是运行时由状态改变元素
A38: t01.asset.0051 | B38: 震骨锤 | C38: 凡品 | D38: 土 | E38: 锤 | F38: 钝击 | G38: 1 | H38: 2 | I38: =G38*H38 -> 2 | J38: 32 | K38: 9 | L38: 7 | P38: 基础＋单状态 | R38: 不耗本体；体力为单把基础，多武器加算另查19／20表；无射程、弓不耗普通箭；具体效果与施加时序依02和核心01，不由七系标签自动增加额外伤害。 | S38: 01 M01/M06/M08；03 C010；04武器 | U38: 候选数值，未试跑 | V38: 第1批基础；第2批微调；第3批复查；用户直接更正优先 | W38: W30 | X38: 重伤 | Y38: 2 | Z38: 命中；敌方 | AA38: 0 | AB38: 0 | AC38: t01.asset.0051.effect.01；t01.asset.0051.effect.02 | AD38: 固定元素与单状态匹配；不是运行时由状态改变元素
A39: t01.asset.0052 | B39: 清风印 | C39: 凡品 | D39: 风 | E39: 印 | F39: 钝击 | G39: 1 | H39: 1 | I39: =G39*H39 -> 1 | J39: 13 | K39: 7 | L39: 3 | P39: 基础＋单状态 | R39: 不耗本体；体力为单把基础，多武器加算另查19／20表；无射程、弓不耗普通箭；具体效果与施加时序依02和核心01，不由七系标签自动增加额外伤害。 | S39: 01 M01/M06/M08；03 C010；04武器 | U39: 候选数值，未试跑 | V39: 第1批基础；第2批微调；第3批复查；用户直接更正优先 | W39: W31 | X39: 驱散 | Y39: 1 | Z39: 命中；敌方 | AA39: 0 | AB39: 0 | AC39: t01.asset.0052.effect.01；t01.asset.0052.effect.02 | AD39: 固定元素与单状态匹配；不是运行时由状态改变元素
A40: t01.asset.0053 | B40: 荆鞭 | C40: 凡品 | D40: 木 | E40: 鞭 | F40: 钝击 | G40: 3 | H40: 1 | I40: =G40*H40 -> 3 | J40: 16 | K40: 4.5 | L40: 3 | P40: 基础＋单状态 | R40: 不耗本体；体力为单把基础，多武器加算另查19／20表；无射程、弓不耗普通箭；缠绕由后续合格火、雷伤害利用；木攻击本身不因此获得火雷增幅。 | S40: 01 M01/M06/M08；03 C010；04武器 | U40: 候选数值，未试跑 | V40: 第1批基础；第2批微调；第3批复查；用户直接更正优先 | W40: W32 | X40: 缠绕 | Y40: 1 | Z40: 命中；敌方 | AA40: 0 | AB40: 0 | AC40: t01.asset.0053.effect.01；t01.asset.0053.effect.02 | AD40: 固定元素与单状态匹配；不是运行时由状态改变元素
A41: t01.asset.0054 | B41: 赤焰枪 | C41: 凡品 | D41: 火 | E41: 枪 | F41: 穿刺 | G41: 3 | H41: 1 | I41: =G41*H41 -> 3 | J41: 36 | K41: 9 | L41: 8 | P41: 基础＋单状态 | R41: 不耗本体；体力为单把基础，多武器加算另查19／20表；无射程、弓不耗普通箭；具体效果与施加时序依02和核心01，不由七系标签自动增加额外伤害。 | S41: 01 M01/M06/M08；03 C010；04武器 | U41: 候选数值，未试跑 | V41: 第1批基础；第2批微调；第3批复查；用户直接更正优先 | W41: W33 | X41: 灼烧 | Y41: 2 | Z41: 命中；敌方 | AA41: 0 | AB41: 0 | AC41: t01.asset.0054.effect.01；t01.asset.0054.effect.02 | AD41: 固定元素与单状态匹配；不是运行时由状态改变元素

Sheet 03_防具
A1: t01-08｜防具
A2: 2026-09-28 · 27下品＋88凡品＝115件 · 候选数值／当前规则／游戏实现分列 · 不含平衡测试结论
A5: 资产ID | B5: 名称 | C5: 品级 | D5: 元素 | E5: 部位 | F5: 甲型 | G5: 宽_格 | H5: 高_格 | I5: 实际占格 | J5: CD_秒 | K5: 护甲上限贡献 | L5: 单次回甲 | M5: 名义回甲每秒 | N5: 甲型权重倍率 | O5: 甲型统计权重 | P5: 上阵部位限制 | Q5: 基础联动 | R5: 费用／数量 | S5: 机制引用 | T5: 现有游戏ID | U5: 设计状态 | V5: 来源 | W5: 来源编号 | X5: 状态 | Y5: 层数 | Z5: 状态触发 | AA5: 受击状态独立CD_秒 | AB5: 防御元素权重 | AC5: 效果引用
A6: t01.asset.0010 | B6: 粗布甲 | C6: 下品 | D6: NONE | E6: 身甲 | F6: 轻甲 | G6: 1 | H6: 2 | I6: =G6*H6 -> 2 | J6: 4 | K6: 7 | L6: 3 | M6: =L6/J6 -> 0.75 | N6: 2 | O6: =I6*N6 -> 4 | P6: 同一部位最多1件；护臂／护腿分别计限（Q03） | Q6: 布甲联动 | R6: 零体力沿用防具基线；数量不消耗 | S6: 01 C01/I11；04防具；06 Link | T6: base.map_item.coarse_cloth_armor | U6: 保留资料已有值；甲型加权Q02已确认 | V6: B2/C；U | AB6: =O6 -> 4
A7: t01.asset.0011 | B7: 铁甲 | C7: 下品 | D7: NONE | E7: 身甲 | F7: 重甲 | G7: 1 | H7: 2 | I7: =G7*H7 -> 2 | J7: 6 | K7: 10 | L7: 4 | M7: =L7/J7 -> 0.66666667 | N7: 2 | O7: =I7*N7 -> 4 | P7: 同一部位最多1件；护臂／护腿分别计限（Q03） | Q7: 铁甲联动 | R7: 零体力沿用防具基线；数量不消耗 | S7: 01 C01/I11；04防具；06 Link | T7: 未配置 | U7: 新增试玩候选；本体6秒；甲型加权Q02已确认 | V7: B2/C；U | AB7: =O7 -> 4
A8: t01.asset.0012 | B8: 旧铁盔 | C8: 下品 | D8: NONE | E8: 头具 | F8: 重甲 | G8: 1 | H8: 1 | I8: =G8*H8 -> 1 | J8: 5 | K8: 2 | L8: 1 | M8: =L8/J8 -> 0.2 | N8: 1 | O8: =I8*N8 -> 1 | P8: 同一部位最多1件；护臂／护腿分别计限（Q03） | Q8: 无 | R8: 零体力沿用防具基线；数量不消耗 | S8: 01 C01/I11；04防具；06 Link | T8: base.map_item.old_iron_helmet | U8: 保留资料已有值；补甲型；甲型加权Q02已确认 | V8: B2/C；U | AB8: =O8 -> 1
A9: t01.asset.0013 | B9: 木圆盾 | C9: 下品 | D9: NONE | E9: 盾 | F9: 轻甲 | G9: 1 | H9: 2 | I9: =G9*H9 -> 2 | J9: 5 | K9: 2 | L9: 3 | M9: =L9/J9 -> 0.6 | N9: 1 | O9: =I9*N9 -> 2 | P9: 可多件上阵，仅受阵盘空间限制（Q03） | Q9: 无 | R9: 零体力沿用防具基线；数量不消耗 | S9: 01 C01/I11；04防具；06 Link | T9: base.map_item.round_wood_shield | U9: 保留资料已有值；补甲型；甲型加权Q02已确认 | V9: B2/C；U | AB9: =O9 -> 2
A10: t01.asset.0014 | B10: 布护臂 | C10: 下品 | D10: NONE | E10: 护具·臂 | F10: 轻甲 | G10: 1 | H10: 1 | I10: =G10*H10 -> 1 | J10: 5 | K10: 1 | L10: 1 | M10: =L10/J10 -> 0.2 | N10: 1 | O10: =I10*N10 -> 1 | P10: 同一部位最多1件；护臂／护腿分别计限（Q03） | Q10: 布甲联动 | R10: 零体力沿用防具基线；数量不消耗 | S10: 01 C01/I11；04防具；06 Link | T10: 未配置 | U10: 新增试玩候选；甲型加权Q02已确认 | V10: B2/C；U | AB10: =O10 -> 1
A11: t01.asset.0015 | B11: 布护腿 | C11: 下品 | D11: NONE | E11: 护具·腿 | F11: 轻甲 | G11: 1 | H11: 1 | I11: =G11*H11 -> 1 | J11: 6 | K11: 2 | L11: 1 | M11: =L11/J11 -> 0.16666667 | N11: 1 | O11: =I11*N11 -> 1 | P11: 同一部位最多1件；护臂／护腿分别计限（Q03） | Q11: 布甲联动 | R11: 零体力沿用防具基线；数量不消耗 | S11: 01 C01/I11；04防具；06 Link | T11: 未配置 | U11: 新增试玩候选；甲型加权Q02已确认 | V11: B2/C；U | AB11: =O11 -> 1
A12: t01.asset.0016 | B12: 铁护臂 | C12: 下品 | D12: NONE | E12: 护具·臂 | F12: 重甲 | G12: 1 | H12: 1 | I12: =G12*H12 -> 1 | J12: 5 | K12: 2 | L12: 2 | M12: =L12/J12 -> 0.4 | N12: 1 | O12: =I12*N12 -> 1 | P12: 同一部位最多1件；护臂／护腿分别计限（Q03） | Q12: 铁甲联动 | R12: 零体力沿用防具基线；数量不消耗 | S12: 01 C01/I11；04防具；06 Link | T12: 未配置 | U12: C新增试玩候选；甲型加权Q02已确认 | V12: C | AB12: =O12 -> 1
A13: t01.asset.0017 | B13: 铁护腿 | C13: 下品 | D13: NONE | E13: 护具·腿 | F13: 重甲 | G13: 1 | H13: 1 | I13: =G13*H13 -> 1 | J13: 6 | K13: 3 | L13: 3 | M13: =L13/J13 -> 0.5 | N13: 1 | O13: =I13*N13 -> 1 | P13: 同一部位最多1件；护臂／护腿分别计限（Q03） | Q13: 铁甲联动 | R13: 零体力沿用防具基线；数量不消耗 | S13: 01 C01/I11；04防具；06 Link | T13: 未配置 | U13: C新增试玩候选；甲型加权Q02已确认 | V13: C | AB13: =O13 -> 1
A14: t01.asset.0055 | B14: 细布衣 | C14: 凡品 | D14: NONE | E14: 身甲 | F14: 轻甲 | G14: 1 | H14: 2 | I14: =G14*H14 -> 2 | J14: 6 | K14: 13 | L14: 7 | M14: =IF(OR(J14="",J14=0),0,L14/J14) -> 1.1666667 | N14: 2 | O14: =I14*N14 -> 4 | P14: 盾可多件；其他同一部位最多1件 | Q14: 无 | R14: 体力0／灵力0／数量0 | S14: 01 C01/I11；02状态；04；06 Link | U14: 候选数值，未试跑 | V14: 第1批基础；第2批微调；第3批复查；用户直接更正优先 | W14: A01 | Z14: 无 | AB14: =O14 -> 4 | AC14: t01.asset.0055.effect.01；t01.asset.0055.effect.02
A15: t01.asset.0056 | B15: 水纹衣 | C15: 凡品 | D15: 水 | E15: 身甲 | F15: 轻甲 | G15: 1 | H15: 2 | I15: =G15*H15 -> 2 | J15: 7 | K15: 12 | L15: 6 | M15: =IF(OR(J15="",J15=0),0,L15/J15) -> 0.85714286 | N15: 2 | O15: =I15*N15 -> 4 | P15: 盾可多件；其他同一部位最多1件 | Q15: 水纹三件 | R15: 体力0／灵力0／数量0 | S15: 01 C01/I11；02状态；04；06 Link | U15: 候选数值，未试跑 | V15: 第1批基础；第2批微调；第3批复查；用户直接更正优先 | W15: A02 | X15: 润脉 | Y15: 1 | Z15: 轮转 | AB15: =O15 -> 4 | AC15: t01.asset.0056.effect.01；t01.asset.0056.effect.02；t01.asset.0056.effect.03
A16: t01.asset.0057 | B16: 札甲 | C16: 凡品 | D16: NONE | E16: 身甲 | F16: 重甲 | G16: 1 | H16: 2 | I16: =G16*H16 -> 2 | J16: 8.5 | K16: 18 | L16: 8 | M16: =IF(OR(J16="",J16=0),0,L16/J16) -> 0.94117647 | N16: 2 | O16: =I16*N16 -> 4 | P16: 盾可多件；其他同一部位最多1件 | Q16: 铁甲三件_凡品 | R16: 体力0／灵力0／数量0 | S16: 01 C01/I11；02状态；04；06 Link | U16: 候选数值，未试跑 | V16: 第1批基础；第2批微调；第3批复查；用户直接更正优先 | W16: A03 | Z16: 无 | AB16: =O16 -> 4 | AC16: t01.asset.0057.effect.01；t01.asset.0057.effect.02
A17: t01.asset.0058 | B17: 赤铜甲 | C17: 凡品 | D17: 火 | E17: 身甲 | F17: 重甲 | G17: 1 | H17: 2 | I17: =G17*H17 -> 2 | J17: 8.5 | K17: 16 | L17: 6 | M17: =IF(OR(J17="",J17=0),0,L17/J17) -> 0.70588235 | N17: 2 | O17: =I17*N17 -> 4 | P17: 盾可多件；其他同一部位最多1件 | Q17: 无 | R17: 体力0／灵力0／数量0 | S17: 01 C01/I11；02状态；04；06 Link | U17: 候选数值，未试跑 | V17: 第1批基础；第2批微调；第3批复查；用户直接更正优先 | W17: A04 | X17: 附炎 | Y17: 2 | Z17: 受击 | AA17: 9 | AB17: =O17 -> 4 | AC17: t01.asset.0058.effect.01；t01.asset.0058.effect.02；t01.asset.0058.effect.03
A18: t01.asset.0059 | B18: 雷纹法袍 | C18: 凡品 | D18: 雷 | E18: 身甲 | F18: 灵甲 | G18: 1 | H18: 2 | I18: =G18*H18 -> 2 | J18: 9 | K18: 14 | L18: 6 | M18: =IF(OR(J18="",J18=0),0,L18/J18) -> 0.66666667 | N18: 2 | O18: =I18*N18 -> 4 | P18: 盾可多件；其他同一部位最多1件 | Q18: 雷纹三件 | R18: 体力0／灵力0／数量0 | S18: 01 C01/I11；02状态；04；06 Link | U18: 候选数值，未试跑 | V18: 第1批基础；第2批微调；第3批复查；用户直接更正优先 | W18: A06 | X18: 雷蕴 | Y18: 2 | Z18: 轮转 | AB18: =O18 -> 4 | AC18: t01.asset.0059.effect.01；t01.asset.0059.effect.02；t01.asset.0059.effect.03
A19: t01.asset.0060 | B19: 皮帽 | C19: 凡品 | D19: 风 | E19: 头具 | F19: 轻甲 | G19: 1 | H19: 1 | I19: =G19*H19 -> 1 | J19: 7 | K19: 4 | L19: 2 | M19: =IF(OR(J19="",J19=0),0,L19/J19) -> 0.28571429 | N19: 1 | O19: =I19*N19 -> 1 | P19: 盾可多件；其他同一部位最多1件 | Q19: 无 | R19: 体力0／灵力0／数量0 | S19: 01 C01/I11；02状态；04；06 Link | U19: 候选数值，未试跑 | V19: 第1批基础；第2批微调；第3批复查；用户直接更正优先 | W19: A07 | X19: 轻灵 | Y19: 1 | Z19: 受击 | AA19: 9 | AB19: =O19 -> 1 | AC19: t01.asset.0060.effect.01；t01.asset.0060.effect.02；t01.asset.0060.effect.03
A20: t01.asset.0061 | B20: 铁盔 | C20: 凡品 | D20: 土 | E20: 头具 | F20: 重甲 | G20: 1 | H20: 1 | I20: =G20*H20 -> 1 | J20: 7.5 | K20: 4 | L20: 3 | M20: =IF(OR(J20="",J20=0),0,L20/J20) -> 0.4 | N20: 1 | O20: =I20*N20 -> 1 | P20: 盾可多件；其他同一部位最多1件 | Q20: 无 | R20: 体力0／灵力0／数量0 | S20: 01 C01/I11；02状态；04；06 Link | U20: 候选数值，未试跑 | V20: 第1批基础；第2批微调；第3批复查；用户直接更正优先 | W20: A08 | X20: 坚韧 | Y20: 1 | Z20: 受击 | AA20: 9 | AB20: =O20 -> 1 | AC20: t01.asset.0061.effect.01；t01.asset.0061.effect.02；t01.asset.0061.effect.03
A21: t01.asset.0062 | B21: 木纹冠 | C21: 凡品 | D21: 木 | E21: 头具 | F21: 灵甲 | G21: 1 | H21: 1 | I21: =G21*H21 -> 1 | J21: 9 | K21: 4 | L21: 2 | M21: =IF(OR(J21="",J21=0),0,L21/J21) -> 0.22222222 | N21: 1 | O21: =I21*N21 -> 1 | P21: 盾可多件；其他同一部位最多1件 | Q21: 无 | R21: 体力0／灵力0／数量0 | S21: 01 C01/I11；02状态；04；06 Link | U21: 候选数值，未试跑 | V21: 第1批基础；第2批微调；第3批复查；用户直接更正优先 | W21: A09 | X21: 生机 | Y21: 1 | Z21: 轮转 | AB21: =O21 -> 1 | AC21: t01.asset.0062.effect.01；t01.asset.0062.effect.02；t01.asset.0062.effect.03
A22: t01.asset.0063 | B22: 风纹冠 | C22: 凡品 | D22: 风 | E22: 头具 | F22: 灵甲 | G22: 1 | H22: 1 | I22: =G22*H22 -> 1 | J22: 8.5 | K22: 3 | L22: 2 | M22: =IF(OR(J22="",J22=0),0,L22/J22) -> 0.23529412 | N22: 1 | O22: =I22*N22 -> 1 | P22: 盾可多件；其他同一部位最多1件 | Q22: 无 | R22: 体力0／灵力0／数量0 | S22: 01 C01/I11；02状态；04；06 Link | U22: 候选数值，未试跑 | V22: 第1批基础；第2批微调；第3批复查；用户直接更正优先 | W22: A10 | X22: 轻灵 | Y22: 1 | Z22: 轮转 | AB22: =O22 -> 1 | AC22: t01.asset.0063.effect.01；t01.asset.0063.effect.02；t01.asset.0063.effect.03
A23: t01.asset.0064 | B23: 皮护臂 | C23: 凡品 | D23: 金 | E23: 护具·臂 | F23: 轻甲 | G23: 1 | H23: 1 | I23: =G23*H23 -> 1 | J23: 7 | K23: 3 | L23: 2 | M23: =IF(OR(J23="",J23=0),0,L23/J23) -> 0.28571429 | N23: 1 | O23: =I23*N23 -> 1 | P23: 盾可多件；其他同一部位最多1件 | Q23: 无 | R23: 体力0／灵力0／数量0 | S23: 01 C01/I11；02状态；04；06 Link | U23: 候选数值，未试跑 | V23: 第1批基础；第2批微调；第3批复查；用户直接更正优先 | W23: A11 | X23: 反锋 | Y23: 1 | Z23: 受击 | AA23: 9 | AB23: =O23 -> 1 | AC23: t01.asset.0064.effect.01；t01.asset.0064.effect.02；t01.asset.0064.effect.03
A24: t01.asset.0065 | B24: 铁护腕 | C24: 凡品 | D24: 金 | E24: 护具·臂 | F24: 重甲 | G24: 1 | H24: 1 | I24: =G24*H24 -> 1 | J24: 7.5 | K24: 3 | L24: 4 | M24: =IF(OR(J24="",J24=0),0,L24/J24) -> 0.53333333 | N24: 1 | O24: =I24*N24 -> 1 | P24: 盾可多件；其他同一部位最多1件 | Q24: 铁甲三件_凡品 | R24: 体力0／灵力0／数量0 | S24: 01 C01/I11；02状态；04；06 Link | U24: 候选数值，未试跑 | V24: 第1批基础；第2批微调；第3批复查；用户直接更正优先 | W24: A12 | X24: 反锋 | Y24: 1 | Z24: 轮转 | AB24: =O24 -> 1 | AC24: t01.asset.0065.effect.01；t01.asset.0065.effect.02；t01.asset.0065.effect.03
A25: t01.asset.0066 | B25: 水纹护臂 | C25: 凡品 | D25: 水 | E25: 护具·臂 | F25: 轻甲 | G25: 1 | H25: 1 | I25: =G25*H25 -> 1 | J25: 8.5 | K25: 3 | L25: 2 | M25: =IF(OR(J25="",J25=0),0,L25/J25) -> 0.23529412 | N25: 1 | O25: =I25*N25 -> 1 | P25: 盾可多件；其他同一部位最多1件 | Q25: 水纹三件 | R25: 体力0／灵力0／数量0 | S25: 01 C01/I11；02状态；04；06 Link | U25: 候选数值，未试跑 | V25: 第1批基础；第2批微调；第3批复查；用户直接更正优先 | W25: A13 | X25: 润脉 | Y25: 1 | Z25: 受击 | AA25: 9 | AB25: =O25 -> 1 | AC25: t01.asset.0066.effect.01；t01.asset.0066.effect.02；t01.asset.0066.effect.03
A26: t01.asset.0067 | B26: 雷纹护腕 | C26: 凡品 | D26: 雷 | E26: 护具·臂 | F26: 重甲 | G26: 1 | H26: 1 | I26: =G26*H26 -> 1 | J26: 9 | K26: 4 | L26: 3 | M26: =IF(OR(J26="",J26=0),0,L26/J26) -> 0.33333333 | N26: 1 | O26: =I26*N26 -> 1 | P26: 盾可多件；其他同一部位最多1件 | Q26: 雷纹三件 | R26: 体力0／灵力0／数量0 | S26: 01 C01/I11；02状态；04；06 Link | U26: 候选数值，未试跑 | V26: 第1批基础；第2批微调；第3批复查；用户直接更正优先 | W26: A14 | X26: 雷蕴 | Y26: 2 | Z26: 受击 | AA26: 9 | AB26: =O26 -> 1 | AC26: t01.asset.0067.effect.01；t01.asset.0067.effect.02；t01.asset.0067.effect.03
A27: t01.asset.0068 | B27: 皮护腿 | C27: 凡品 | D27: 风 | E27: 护具·腿 | F27: 轻甲 | G27: 1 | H27: 1 | I27: =G27*H27 -> 1 | J27: 9 | K27: 4 | L27: 2 | M27: =IF(OR(J27="",J27=0),0,L27/J27) -> 0.22222222 | N27: 1 | O27: =I27*N27 -> 1 | P27: 盾可多件；其他同一部位最多1件 | Q27: 无 | R27: 体力0／灵力0／数量0 | S27: 01 C01/I11；02状态；04；06 Link | U27: 候选数值，未试跑 | V27: 第1批基础；第2批微调；第3批复查；用户直接更正优先 | W27: A15 | X27: 轻灵 | Y27: 1 | Z27: 轮转 | AB27: =O27 -> 1 | AC27: t01.asset.0068.effect.01；t01.asset.0068.effect.02；t01.asset.0068.effect.03
A28: t01.asset.0069 | B28: 铁胫甲 | C28: 凡品 | D28: 土 | E28: 护具·腿 | F28: 重甲 | G28: 1 | H28: 1 | I28: =G28*H28 -> 1 | J28: 9 | K28: 4 | L28: 5 | M28: =IF(OR(J28="",J28=0),0,L28/J28) -> 0.55555556 | N28: 1 | O28: =I28*N28 -> 1 | P28: 盾可多件；其他同一部位最多1件 | Q28: 铁甲三件_凡品 | R28: 体力0／灵力0／数量0 | S28: 01 C01/I11；02状态；04；06 Link | U28: 候选数值，未试跑 | V28: 第1批基础；第2批微调；第3批复查；用户直接更正优先 | W28: A16 | X28: 坚韧 | Y28: 2 | Z28: 受击 | AA28: 9 | AB28: =O28 -> 1 | AC28: t01.asset.0069.effect.01；t01.asset.0069.effect.02；t01.asset.0069.effect.03
A29: t01.asset.0070 | B29: 水纹护腿 | C29: 凡品 | D29: 水 | E29: 护具·腿 | F29: 轻甲 | G29: 1 | H29: 1 | I29: =G29*H29 -> 1 | J29: 8.5 | K29: 4 | L29: 3 | M29: =IF(OR(J29="",J29=0),0,L29/J29) -> 0.35294118 | N29: 1 | O29: =I29*N29 -> 1 | P29: 盾可多件；其他同一部位最多1件 | Q29: 水纹三件 | R29: 体力0／灵力0／数量0 | S29: 01 C01/I11；02状态；04；06 Link | U29: 候选数值，未试跑 | V29: 第1批基础；第2批微调；第3批复查；用户直接更正优先 | W29: A17 | X29: 润脉 | Y29: 1 | Z29: 轮转 | AB29: =O29 -> 1 | AC29: t01.asset.0070.effect.01；t01.asset.0070.effect.02；t01.asset.0070.effect.03
A30: t01.asset.0071 | B30: 藤甲护腿 | C30: 凡品 | D30: 木 | E30: 护具·腿 | F30: 重甲 | G30: 1 | H30: 1 | I30: =G30*H30 -> 1 | J30: 10.5 | K30: 5 | L30: 4 | M30: =IF(OR(J30="",J30=0),0,L30/J30) -> 0.38095238 | N30: 1 | O30: =I30*N30 -> 1 | P30: 盾可多件；其他同一部位最多1件 | Q30: 无 | R30: 体力0／灵力0／数量0 | S30: 01 C01/I11；02状态；04；06 Link | U30: 候选数值，未试跑 | V30: 第1批基础；第2批微调；第3批复查；用户直接更正优先 | W30: A18 | X30: 生机 | Y30: 2 | Z30: 轮转 | AB30: =O30 -> 1 | AC30: t01.asset.0071.effect.01；t01.asset.0071.effect.02；t01.asset.0071.effect.03
A31: t01.asset.0072 | B31: 皮护肩 | C31: 凡品 | D31: 土 | E31: 护具·肩 | F31: 轻甲 | G31: 1 | H31: 1 | I31: =G31*H31 -> 1 | K31: 8 | L31: 0 | M31: =IF(OR(J31="",J31=0),0,L31/J31) -> 0 | N31: 1 | O31: =I31*N31 -> 1 | P31: 盾可多件；其他同一部位最多1件 | Q31: 无 | R31: 体力0／灵力0／数量0 | S31: 01 C01/I11；02状态；04；06 Link | U31: 候选数值，未试跑 | V31: 第1批基础；第2批微调；第3批复查；用户直接更正优先 | W31: A19 | X31: 坚韧 | Y31: 1 | Z31: 受击 | AA31: 9 | AB31: =O31 -> 1 | AC31: t01.asset.0072.effect.01；t01.asset.0072.effect.02
A32: t01.asset.0073 | B32: 金纹护肩 | C32: 凡品 | D32: 金 | E32: 护具·肩 | F32: 重甲 | G32: 1 | H32: 1 | I32: =G32*H32 -> 1 | J32: 9 | K32: 6 | L32: 3 | M32: =IF(OR(J32="",J32=0),0,L32/J32) -> 0.33333333 | N32: 1 | O32: =I32*N32 -> 1 | P32: 盾可多件；其他同一部位最多1件 | Q32: 无 | R32: 体力0／灵力0／数量0 | S32: 01 C01/I11；02状态；04；06 Link | U32: 候选数值，未试跑 | V32: 第1批基础；第2批微调；第3批复查；用户直接更正优先 | W32: A20 | X32: 反锋 | Y32: 2 | Z32: 受击 | AA32: 9 | AB32: =O32 -> 1 | AC32: t01.asset.0073.effect.01；t01.asset.0073.effect.02；t01.asset.0073.effect.03
A33: t01.asset.0074 | B33: 灵丝腰带 | C33: 凡品 | D33: 风 | E33: 护具·腰 | F33: 灵甲 | G33: 1 | H33: 1 | I33: =G33*H33 -> 1 | J33: 9 | K33: 3 | L33: 0 | M33: =IF(OR(J33="",J33=0),0,L33/J33) -> 0 | N33: 1 | O33: =I33*N33 -> 1 | P33: 盾可多件；其他同一部位最多1件 | Q33: 无 | R33: 体力0／灵力0／数量0 | S33: 01 C01/I11；02状态；04；06 Link | U33: 候选数值，未试跑 | V33: 第1批基础；第2批微调；第3批复查；用户直接更正优先 | W33: A21 | X33: 轻灵 | Y33: 2 | Z33: 轮转 | AB33: =O33 -> 1 | AC33: t01.asset.0074.effect.01；t01.asset.0074.effect.02
A34: t01.asset.0075 | B34: 包铁木盾 | C34: 凡品 | D34: 木 | E34: 盾 | F34: 轻甲 | G34: 1 | H34: 2 | I34: =G34*H34 -> 2 | J34: 7.5 | K34: 5 | L34: 6 | M34: =IF(OR(J34="",J34=0),0,L34/J34) -> 0.8 | N34: 1 | O34: =I34*N34 -> 2 | P34: 盾可多件；其他同一部位最多1件 | Q34: 无 | R34: 体力0／灵力0／数量0 | S34: 01 C01/I11；02状态；04；06 Link | U34: 候选数值，未试跑 | V34: 第1批基础；第2批微调；第3批复查；用户直接更正优先 | W34: A22 | X34: 生机 | Y34: 1 | Z34: 轮转 | AB34: =O34 -> 2 | AC34: t01.asset.0075.effect.01；t01.asset.0075.effect.02；t01.asset.0075.effect.03
A35: t01.asset.0076 | B35: 铁盾 | C35: 凡品 | D35: 金 | E35: 盾 | F35: 重甲 | G35: 1 | H35: 2 | I35: =G35*H35 -> 2 | J35: 9 | K35: 8 | L35: 5 | M35: =IF(OR(J35="",J35=0),0,L35/J35) -> 0.55555556 | N35: 1 | O35: =I35*N35 -> 2 | P35: 盾可多件；其他同一部位最多1件 | Q35: 无 | R35: 体力0／灵力0／数量0 | S35: 01 C01/I11；02状态；04；06 Link | U35: 候选数值，未试跑 | V35: 第1批基础；第2批微调；第3批复查；用户直接更正优先 | W35: A23 | X35: 反锋 | Y35: 2 | Z35: 受击 | AA35: 9 | AB35: =O35 -> 2 | AC35: t01.asset.0076.effect.01；t01.asset.0076.effect.02；t01.asset.0076.effect.03
A36: t01.asset.0077 | B36: 水纹盾 | C36: 凡品 | D36: 水 | E36: 盾 | F36: 轻甲 | G36: 1 | H36: 2 | I36: =G36*H36 -> 2 | J36: 8.5 | K36: 6 | L36: 5 | M36: =IF(OR(J36="",J36=0),0,L36/J36) -> 0.58823529 | N36: 1 | O36: =I36*N36 -> 2 | P36: 盾可多件；其他同一部位最多1件 | Q36: 无 | R36: 体力0／灵力0／数量0 | S36: 01 C01/I11；02状态；04；06 Link | U36: 候选数值，未试跑 | V36: 第1批基础；第2批微调；第3批复查；用户直接更正优先 | W36: A24 | X36: 润脉 | Y36: 1 | Z36: 轮转 | AB36: =O36 -> 2 | AC36: t01.asset.0077.effect.01；t01.asset.0077.effect.02；t01.asset.0077.effect.03
A37: t01.asset.0078 | B37: 束甲带 | C37: 凡品 | D37: NONE | E37: 护具·腰 | F37: 重甲 | G37: 1 | H37: 1 | I37: =G37*H37 -> 1 | K37: 12 | L37: 0 | M37: =IF(OR(J37="",J37=0),0,L37/J37) -> 0 | N37: 1 | O37: =I37*N37 -> 1 | P37: 盾可多件；其他同一部位最多1件 | Q37: 无 | R37: 体力0／灵力0／数量0 | S37: 01 C01/I11；02状态；04；06 Link | U37: 候选数值，未试跑 | V37: 第1批基础；第2批微调；第3批复查；用户直接更正优先 | W37: A26 | Z37: 无 | AB37: =O37 -> 1 | AC37: t01.asset.0078.effect.01
A38: t01.asset.0079 | B38: 燎火护臂 | C38: 凡品 | D38: 火 | E38: 护具·臂 | F38: 轻甲 | G38: 1 | H38: 1 | I38: =G38*H38 -> 1 | J38: 8 | K38: 4 | L38: 2 | M38: =IF(OR(J38="",J38=0),0,L38/J38) -> 0.25 | N38: 1 | O38: =I38*N38 -> 1 | P38: 盾可多件；其他同一部位最多1件 | Q38: 无 | R38: 体力0／灵力0／数量0 | S38: 01 C01/I11；02状态；04；06 Link | U38: 候选数值，未试跑 | V38: 第1批基础；第2批微调；第3批复查；用户直接更正优先 | W38: A28 | X38: 附炎 | Y38: 1 | Z38: 轮转 | AB38: =O38 -> 1 | AC38: t01.asset.0079.effect.01；t01.asset.0079.effect.02；t01.asset.0079.effect.03
A39: t01.asset.0080 | B39: 雷纹护腿 | C39: 凡品 | D39: 雷 | E39: 护具·腿 | F39: 灵甲 | G39: 1 | H39: 1 | I39: =G39*H39 -> 1 | J39: 9 | K39: 4 | L39: 2 | M39: =IF(OR(J39="",J39=0),0,L39/J39) -> 0.22222222 | N39: 1 | O39: =I39*N39 -> 1 | P39: 盾可多件；其他同一部位最多1件 | Q39: 雷纹三件 | R39: 体力0／灵力0／数量0 | S39: 01 C01/I11；02状态；04；06 Link | U39: 候选数值，未试跑 | V39: 第1批基础；第2批微调；第3批复查；用户直接更正优先 | W39: A29 | X39: 雷蕴 | Y39: 1 | Z39: 轮转 | AB39: =O39 -> 1 | AC39: t01.asset.0080.effect.01；t01.asset.0080.effect.02；t01.asset.0080.effect.03
A40: t01.asset.0081 | B40: 炎纹护肩 | C40: 凡品 | D40: 火 | E40: 护具·肩 | F40: 重甲 | G40: 1 | H40: 1 | I40: =G40*H40 -> 1 | J40: 10 | K40: 6 | L40: 2 | M40: =IF(OR(J40="",J40=0),0,L40/J40) -> 0.2 | N40: 1 | O40: =I40*N40 -> 1 | P40: 盾可多件；其他同一部位最多1件 | Q40: 无 | R40: 体力0／灵力0／数量0 | S40: 01 C01/I11；02状态；04；06 Link | U40: 候选数值，未试跑 | V40: 第1批基础；第2批微调；第3批复查；用户直接更正优先 | W40: A30 | X40: 附炎 | Y40: 2 | Z40: 轮转 | AB40: =O40 -> 1 | AC40: t01.asset.0081.effect.01；t01.asset.0081.effect.02；t01.asset.0081.effect.03
A41: t01.asset.0082 | B41: 润脉腰带 | C41: 凡品 | D41: 水 | E41: 护具·腰 | F41: 灵甲 | G41: 1 | H41: 1 | I41: =G41*H41 -> 1 | J41: 9 | K41: 4 | L41: 0 | M41: =IF(OR(J41="",J41=0),0,L41/J41) -> 0 | N41: 1 | O41: =I41*N41 -> 1 | P41: 盾可多件；其他同一部位最多1件 | Q41: 无 | R41: 体力0／灵力0／数量0 | S41: 01 C01/I11；02状态；04；06 Link | U41: 候选数值，未试跑 | V41: 第1批基础；第2批微调；第3批复查；用户直接更正优先 | W41: A31 | X41: 润脉 | Y41: 2 | Z41: 轮转 | AB41: =O41 -> 1 | AC41: t01.asset.0082.effect.01；t01.asset.0082.effect.02

Sheet 04_法器
A1: t01-08｜法器
A2: 2026-09-28 · 27下品＋88凡品＝115件 · 候选数值／当前规则／游戏实现分列 · 不含平衡测试结论
A5: 资产ID | B5: 名称 | C5: 品级 | D5: 元素 | E5: 定位 | F5: 攻击类型 | G5: 宽_格 | H5: 高_格 | I5: 实际占格 | J5: CD_秒 | K5: 气血恢复 | L5: 体力恢复 | M5: 灵力恢复 | N5: 恢复上限分子 | O5: 恢复上限分母 | P5: 恢复上限状态 | Q5: 成本与效果边界 | R5: 机制引用 | S5: 现有游戏ID | T5: 设计状态 | U5: 来源 | V5: 来源编号 | W5: 本体伤害 | X5: 灵力费 | Y5: 体力费 | Z5: 护甲上限贡献 | AA5: 单次回甲 | AB5: 普通灵障生成 | AC5: 状态 | AD5: 层数 | AE5: 施加时机与目标 | AF5: 完整效果 | AG5: 效果引用
A6: t01.asset.0018 | B6: 温玉佩 | C6: 下品 | D6: NONE | E6: 基础资源恢复 | F6: 无攻击 | G6: 1 | H6: 1 | I6: =G6*H6 -> 1 | J6: 4 | K6: 4 | L6: 6 | M6: 0 | N6: 2 | O6: 3 | P6: 已有配置上限2/3；保留 | Q6: 道具消耗0、灵力费0；资料称免费恢复，不附Buff／净化。 | R6: 01资源恢复／上限；04法器 | S6: base.map_item.warm_jade | T6: 保留已有值；具体恢复条件按主表边界 | U6: B3；U
A7: t01.asset.0019 | B7: 回春玉 | C7: 下品 | D7: NONE | E7: 基础资源恢复 | F7: 无攻击 | G7: 1 | H7: 1 | I7: =G7*H7 -> 1 | J7: 5 | K7: 6 | L7: 0 | M7: 0 | N7: 2 | O7: 3 | P7: Q04已确认：最多恢复至对应最大值2/3；已超上限不扣减、不继续恢复 | Q7: 道具消耗0、灵力费0；资料称免费恢复，不附Buff／净化。 | R7: 01资源恢复／上限；04法器 | S7: 未配置 | T7: 新增试玩候选；具体恢复条件按主表边界 | U7: B3；U；Q04用户答复2026-09-28
A8: t01.asset.0020 | B8: 养息珠 | C8: 下品 | D8: NONE | E8: 基础资源恢复 | F8: 无攻击 | G8: 1 | H8: 1 | I8: =G8*H8 -> 1 | J8: 5 | K8: 0 | L8: 9 | M8: 0 | N8: 2 | O8: 3 | P8: Q04已确认：最多恢复至对应最大值2/3；已超上限不扣减、不继续恢复 | Q8: 道具消耗0、灵力费0；资料称免费恢复，不附Buff／净化。 | R8: 01资源恢复／上限；04法器 | S8: 未配置 | T8: 新增试玩候选；具体恢复条件按主表边界 | U8: B3；U；Q04用户答复2026-09-28
A9: t01.asset.0021 | B9: 聚灵珠 | C9: 下品 | D9: NONE | E9: 基础资源恢复 | F9: 无攻击 | G9: 1 | H9: 1 | I9: =G9*H9 -> 1 | J9: 5 | K9: 0 | L9: 0 | M9: 6 | N9: 2 | O9: 3 | P9: Q04已确认：最多恢复至对应最大值2/3；已超上限不扣减、不继续恢复 | Q9: 道具消耗0、灵力费0；资料称免费恢复，不附Buff／净化。 | R9: 01资源恢复／上限；04法器 | S9: 未配置 | T9: 新增试玩候选；具体恢复条件按主表边界 | U9: B3；U；Q04用户答复2026-09-28
A10: t01.asset.0083 | B10: 回春佩 | C10: 凡品 | D10: NONE | E10: 资源恢复 | F10: 无攻击 | G10: 1 | H10: 1 | I10: =G10*H10 -> 1 | J10: 7.5 | K10: 13 | L10: 0 | M10: 0 | N10: 1 | O10: 1 | P10: 正常上限 | Q10: 灵力2／体力0／数量0；元素分类不自动创造攻击 | R10: 01效果；02状态；04法器 | T10: 候选数值，未试跑 | U10: 第1批基础；第2批微调；第3批复查；用户直接更正优先 | V10: F01 | X10: 2 | Y10: 0 | Z10: 0 | AA10: 0 | AB10: 0 | AE10: 轮转；自身 | AF10: 气血＋13，可至正常上限 | AG10: t01.asset.0083.effect.01
A11: t01.asset.0084 | B11: 行气珠 | C11: 凡品 | D11: NONE | E11: 资源恢复 | F11: 无攻击 | G11: 1 | H11: 1 | I11: =G11*H11 -> 1 | J11: 7.5 | K11: 0 | L11: 18 | M11: 0 | N11: 2 | O11: 3 | P11: 2/3向下取整 | Q11: 灵力0／体力0／数量0；元素分类不自动创造攻击 | R11: 01效果；02状态；04法器 | T11: 候选数值，未试跑 | U11: 第1批基础；第2批微调；第3批复查；用户直接更正优先 | V11: F02 | X11: 0 | Y11: 0 | Z11: 0 | AA11: 0 | AB11: 0 | AE11: 轮转；自身 | AF11: 体力＋18，最多至上限2/3 | AG11: t01.asset.0084.effect.01
A12: t01.asset.0085 | B12: 聚元环 | C12: 凡品 | D12: NONE | E12: 资源恢复 | F12: 无攻击 | G12: 1 | H12: 1 | I12: =G12*H12 -> 1 | J12: 7.5 | K12: 0 | L12: 0 | M12: 13 | N12: 2 | O12: 3 | P12: 2/3向下取整 | Q12: 灵力0／体力0／数量0；元素分类不自动创造攻击 | R12: 01效果；02状态；04法器 | T12: 候选数值，未试跑 | U12: 第1批基础；第2批微调；第3批复查；用户直接更正优先 | V12: F03 | X12: 0 | Y12: 0 | Z12: 0 | AA12: 0 | AB12: 0 | AE12: 轮转；自身 | AF12: 灵力＋13，最多至上限2/3 | AG12: t01.asset.0085.effect.01
A13: t01.asset.0086 | B13: 调息玉 | C13: 凡品 | D13: NONE | E13: 资源恢复 | F13: 无攻击 | G13: 1 | H13: 1 | I13: =G13*H13 -> 1 | J13: 8.5 | K13: 7 | L13: 0 | M13: 10 | N13: 2 | O13: 3 | P13: 2/3向下取整 | Q13: 灵力0／体力0／数量0；元素分类不自动创造攻击 | R13: 01效果；02状态；04法器 | T13: 候选数值，未试跑 | U13: 第1批基础；第2批微调；第3批复查；用户直接更正优先 | V13: F04 | X13: 0 | Y13: 0 | Z13: 0 | AA13: 0 | AB13: 0 | AE13: 轮转；自身 | AF13: 气血＋7、灵力＋10，各至上限2/3 | AG13: t01.asset.0086.effect.01；t01.asset.0086.effect.02
A14: t01.asset.0087 | B14: 金光镜 | C14: 凡品 | D14: 金 | E14: 攻击／状态／防护 | F14: 法术型 | G14: 1 | H14: 1 | I14: =G14*H14 -> 1 | J14: 7 | K14: 0 | L14: 0 | M14: 0 | P14: 不适用 | Q14: 灵力6／体力0／数量0；元素分类不自动创造攻击 | R14: 01效果；02状态；04法器 | T14: 候选数值，未试跑 | U14: 第1批基础；第2批微调；第3批复查；用户直接更正优先 | V14: F05 | W14: 22 | X14: 6 | Y14: 0 | Z14: 0 | AA14: 0 | AB14: 0 | AC14: 锋痕 | AD14: 1 | AE14: 命中；敌方 | AF14: 金属性法术攻击22，命中锋痕＋1；锋痕由合格武器攻击兑现；金光镜仍是法器来源，不因金元素或SPELL攻击类型取得武器资格。 | AG14: t01.asset.0087.effect.01；t01.asset.0087.effect.02
A15: t01.asset.0088 | B15: 青木铃 | C15: 凡品 | D15: 木 | E15: 攻击／状态／防护 | F15: 无攻击 | G15: 1 | H15: 1 | I15: =G15*H15 -> 1 | J15: 9 | K15: 0 | L15: 0 | M15: 0 | P15: 不适用 | Q15: 灵力4／体力0／数量0；元素分类不自动创造攻击 | R15: 01效果；02状态；04法器 | T15: 候选数值，未试跑 | U15: 第1批基础；第2批微调；第3批复查；用户直接更正优先 | V15: F06 | X15: 4 | Y15: 0 | Z15: 0 | AA15: 0 | AB15: 0 | AC15: 生机 | AD15: 3 | AE15: 轮转；自身 | AF15: 自身生机＋3；具体效果与施加时序依02和核心01，不由七系标签自动增加额外伤害。 | AG15: t01.asset.0088.effect.01
A16: t01.asset.0089 | B16: 寒水珠 | C16: 凡品 | D16: 水 | E16: 攻击／状态／防护 | F16: 法术型 | G16: 1 | H16: 1 | I16: =G16*H16 -> 1 | J16: 7.5 | K16: 0 | L16: 0 | M16: 0 | P16: 不适用 | Q16: 灵力6／体力0／数量0；元素分类不自动创造攻击 | R16: 01效果；02状态；04法器 | T16: 候选数值，未试跑 | U16: 第1批基础；第2批微调；第3批复查；用户直接更正优先 | V16: F07 | W16: 23 | X16: 6 | Y16: 0 | Z16: 0 | AA16: 0 | AB16: 0 | AC16: 寒霜 | AD16: 1 | AE16: 命中；敌方 | AF16: 水属性法术攻击23，命中寒霜＋1；寒霜正常新层先施加、后由本次合格主动水攻触发；初霜专属额外层例外留后次。 | AG16: t01.asset.0089.effect.01；t01.asset.0089.effect.02
A17: t01.asset.0090 | B17: 火灵珠 | C17: 凡品 | D17: 火 | E17: 攻击／状态／防护 | F17: 无攻击 | G17: 1 | H17: 1 | I17: =G17*H17 -> 1 | J17: 7.5 | K17: 0 | L17: 0 | M17: 0 | P17: 不适用 | Q17: 灵力4／体力0／数量0；元素分类不自动创造攻击 | R17: 01效果；02状态；04法器 | T17: 候选数值，未试跑 | U17: 第1批基础；第2批微调；第3批复查；用户直接更正优先 | V17: F08 | X17: 4 | Y17: 0 | Z17: 0 | AA17: 0 | AB17: 0 | AC17: 附炎 | AD17: 3 | AE17: 轮转；自身 | AF17: 自身附炎＋3；具体效果与施加时序依02和核心01，不由七系标签自动增加额外伤害。 | AG17: t01.asset.0090.effect.01
A18: t01.asset.0091 | B18: 坤土珠 | C18: 凡品 | D18: 土 | E18: 攻击／状态／防护 | F18: 无攻击 | G18: 1 | H18: 1 | I18: =G18*H18 -> 1 | J18: 9 | K18: 0 | L18: 0 | M18: 0 | P18: 不适用 | Q18: 灵力4／体力0／数量0；元素分类不自动创造攻击 | R18: 01效果；02状态；04法器 | T18: 候选数值，未试跑 | U18: 第1批基础；第2批微调；第3批复查；用户直接更正优先 | V18: F09 | X18: 4 | Y18: 0 | Z18: 0 | AA18: 0 | AB18: 0 | AC18: 坚韧 | AD18: 3 | AE18: 轮转；自身 | AF18: 自身坚韧＋3；具体效果与施加时序依02和核心01，不由七系标签自动增加额外伤害。 | AG18: t01.asset.0091.effect.01
A19: t01.asset.0092 | B19: 逐风旗 | C19: 凡品 | D19: 风 | E19: 攻击／状态／防护 | F19: 无攻击 | G19: 1 | H19: 2 | I19: =G19*H19 -> 2 | J19: 7.5 | K19: 0 | L19: 0 | M19: 0 | P19: 不适用 | Q19: 灵力4／体力0／数量0；元素分类不自动创造攻击 | R19: 01效果；02状态；04法器 | T19: 候选数值，未试跑 | U19: 第1批基础；第2批微调；第3批复查；用户直接更正优先 | V19: F10 | X19: 4 | Y19: 0 | Z19: 0 | AA19: 0 | AB19: 0 | AC19: 失衡 | AD19: 4 | AE19: 轮转；敌方 | AF19: 直接向敌方施加失衡＋4；具体效果与施加时序依02和核心01，不由七系标签自动增加额外伤害。 | AG19: t01.asset.0092.effect.01
A20: t01.asset.0093 | B20: 引雷珠 | C20: 凡品 | D20: 雷 | E20: 攻击／状态／防护 | F20: 无攻击 | G20: 1 | H20: 1 | I20: =G20*H20 -> 1 | J20: 9 | K20: 0 | L20: 0 | M20: 0 | P20: 不适用 | Q20: 灵力4／体力0／数量0；元素分类不自动创造攻击 | R20: 01效果；02状态；04法器 | T20: 候选数值，未试跑 | U20: 第1批基础；第2批微调；第3批复查；用户直接更正优先 | V20: F11 | X20: 4 | Y20: 0 | Z20: 0 | AA20: 0 | AB20: 0 | AC20: 雷印 | AD20: 4 | AE20: 轮转；敌方 | AF20: 直接向敌方施加雷印＋4；雷印新层在本击伤后加入，供后续合格雷攻；无本体雷攻击的施层器具不直接引雷。 | AG20: t01.asset.0093.effect.01
A21: t01.asset.0094 | B21: 护心镜 | C21: 凡品 | D21: NONE | E21: 攻击／状态／防护 | F21: 无攻击 | G21: 1 | H21: 1 | I21: =G21*H21 -> 1 | K21: 0 | L21: 0 | M21: 0 | P21: 不适用 | Q21: 灵力0／体力0／数量0；元素分类不自动创造攻击 | R21: 01效果；02状态；04法器 | T21: 候选数值，未试跑 | U21: 第1批基础；第2批微调；第3批复查；用户直接更正优先 | V21: F12 | X21: 0 | Y21: 0 | Z21: 10 | AA21: 0 | AB21: 0 | AE21: 静态；自身 | AF21: 护甲上限＋10，无甲型权重 | AG21: t01.asset.0094.effect.01
A22: t01.asset.0095 | B22: 复甲环 | C22: 凡品 | D22: NONE | E22: 攻击／状态／防护 | F22: 无攻击 | G22: 1 | H22: 1 | I22: =G22*H22 -> 1 | J22: 6 | K22: 0 | L22: 0 | M22: 0 | P22: 不适用 | Q22: 灵力3／体力0／数量0；元素分类不自动创造攻击 | R22: 01效果；02状态；04法器 | T22: 候选数值，未试跑 | U22: 第1批基础；第2批微调；第3批复查；用户直接更正优先 | V22: F13 | X22: 3 | Y22: 0 | Z22: 0 | AA22: 7 | AB22: 0 | AE22: 轮转；自身 | AF22: 当前护甲＋7，不增加上限 | AG22: t01.asset.0095.effect.01
A23: t01.asset.0096 | B23: 灵障珠 | C23: 凡品 | D23: NONE | E23: 攻击／状态／防护 | F23: 无攻击 | G23: 1 | H23: 1 | I23: =G23*H23 -> 1 | J23: 10.5 | K23: 0 | L23: 0 | M23: 0 | P23: 不适用 | Q23: 灵力6／体力0／数量0；满灵障仍发动扣费并重开CD，普通控制和资源资格仍检查。 | R23: 01效果；02状态；04法器 | T23: 候选数值，未试跑 | U23: 第1批基础；第2批微调；第3批复查；用户直接更正优先 | V23: F14 | X23: 6 | Y23: 0 | Z23: 0 | AA23: 0 | AB23: 15 | AE23: 轮转；自身 | AF23: 普通灵障＋15（受当前上限限制）；F14灵障珠满上限仍正常发动，消耗6灵力并重开10.5秒CD，实际增加0；未满时实际增加min(15,容量缺口)，费用仍6。仍检查控制、资源等正常发动资格；费用不足不能发动。此空转支付是F14的已定策略，不自动推广其他资产。 | AG23: t01.asset.0096.effect.01
A24: t01.asset.0097 | B24: 枯脉瓶 | C24: 凡品 | D24: 水 | E24: 攻击／状态／防护 | F24: 无攻击 | G24: 1 | H24: 1 | I24: =G24*H24 -> 1 | J24: 9 | K24: 0 | L24: 0 | M24: 0 | P24: 不适用 | Q24: 灵力4／体力0／数量0；元素分类不自动创造攻击 | R24: 01效果；02状态；04法器 | T24: 候选数值，未试跑 | U24: 第1批基础；第2批微调；第3批复查；用户直接更正优先 | V24: F15 | X24: 4 | Y24: 0 | Z24: 0 | AA24: 0 | AB24: 0 | AC24: 枯脉 | AD24: 3 | AE24: 轮转；敌方 | AF24: 直接向敌方施加枯脉＋3；具体效果与施加时序依02和核心01，不由七系标签自动增加额外伤害。 | AG24: t01.asset.0097.effect.01
A25: t01.asset.0098 | B25: 清风拂 | C25: 凡品 | D25: 风 | E25: 攻击／状态／防护 | F25: 无攻击 | G25: 1 | H25: 2 | I25: =G25*H25 -> 2 | J25: 10.5 | K25: 0 | L25: 0 | M25: 0 | P25: 不适用 | Q25: 灵力4／体力0／数量0；元素分类不自动创造攻击 | R25: 01效果；02状态；04法器 | T25: 候选数值，未试跑 | U25: 第1批基础；第2批微调；第3批复查；用户直接更正优先 | V25: F16 | X25: 4 | Y25: 0 | Z25: 0 | AA25: 0 | AB25: 0 | AC25: 驱散 | AD25: 2 | AE25: 轮转；敌方 | AF25: 直接向敌方施加驱散＋2；具体效果与施加时序依02和核心01，不由七系标签自动增加额外伤害。 | AG25: t01.asset.0098.effect.01
A26: t01.asset.0099 | B26: 锁雷环 | C26: 凡品 | D26: 雷 | E26: 攻击／状态／防护 | F26: 无攻击 | G26: 1 | H26: 1 | I26: =G26*H26 -> 1 | J26: 9 | K26: 0 | L26: 0 | M26: 0 | P26: 不适用 | Q26: 灵力4／体力0／数量0；元素分类不自动创造攻击 | R26: 01效果；02状态；04法器 | T26: 候选数值，未试跑 | U26: 第1批基础；第2批微调；第3批复查；用户直接更正优先 | V26: F17 | X26: 4 | Y26: 0 | Z26: 0 | AA26: 0 | AB26: 0 | AC26: 连环 | AD26: 2 | AE26: 轮转；敌方 | AF26: 直接向敌方施加连环＋2；连环供后续合格雷攻击利用；锁雷环无本体攻击，不直接制造雷击或闪电。 | AG26: t01.asset.0099.effect.01
A27: t01.asset.0100 | B27: 蕴雷铃 | C27: 凡品 | D27: 雷 | E27: 攻击／状态／防护 | F27: 无攻击 | G27: 1 | H27: 1 | I27: =G27*H27 -> 1 | J27: 9 | K27: 0 | L27: 0 | M27: 0 | P27: 不适用 | Q27: 灵力4／体力0／数量0；元素分类不自动创造攻击 | R27: 01效果；02状态；04法器 | T27: 候选数值，未试跑 | U27: 第1批基础；第2批微调；第3批复查；用户直接更正优先 | V27: F18 | X27: 4 | Y27: 0 | Z27: 0 | AA27: 0 | AB27: 0 | AC27: 雷蕴 | AD27: 3 | AE27: 轮转；自身 | AF27: 自身雷蕴＋3；具体效果与施加时序依02和核心01，不由七系标签自动增加额外伤害。 | AG27: t01.asset.0100.effect.01

Sheet 05_丹药
A1: t01-08｜丹药
A2: 2026-09-28 · 27下品＋88凡品＝115件 · 候选数值／当前规则／游戏实现分列 · 不含平衡测试结论
A5: 资产ID | B5: 名称 | C5: 品级 | D5: 元素 | E5: 效果类型 | F5: 宽_格 | G5: 高_格 | H5: 实际占格 | I5: CD_秒 | J5: 每次气血恢复 | K5: 每次体力恢复 | L5: 每次灵力恢复 | M5: 跳间隔_秒 | N5: 次数 | O5: 总气血恢复 | P5: 总体力恢复 | Q5: 总灵力恢复 | R5: 毒蚀免疫_秒 | S5: 发动耗数量 | T5: 单位 | U5: 结算时点 | V5: 效果边界 | W5: 机制引用 | X5: 现有游戏ID | Y5: 设计状态 | Z5: 来源 | AA5: 来源编号 | AB5: 状态 | AC5: 层数 | AD5: 减伤元素 | AE5: 减伤比例 | AF5: 持续_秒 | AG5: 首瓶与CD规则 | AH5: 自动使用条件 | AI5: 效果引用
A6: t01.asset.0022 | B6: 止血丹 | C6: 下品 | D6: NONE | E6: 分次 | F6: 1 | G6: 1 | H6: =F6*G6 -> 1 | I6: 6.5 | J6: 2 | K6: 0 | L6: 0 | M6: 2 | N6: 3 | O6: =IF(N6="",0,J6*N6) -> 6 | P6: =IF(N6="",0,K6*N6) -> 0 | Q6: =IF(N6="",0,L6*N6) -> 0 | R6: 0 | S6: 1 | T6: 瓶 | U6: 第2/4/6秒结算；不是发动即首跳 | V6: 仅消毒散清除毒蚀并免疫毒蚀；不扩为全负面净化。 | W6: 01时序／恢复／免疫；02 OP；03专门用途 | X6: base.map_item.hemostatic_pill | Y6: 保留资料已有值 | Z6: B4；U | AG6: 首瓶开战可用；未用不进入CD；实际使用后重开完整CD
A7: t01.asset.0023 | B7: 强筋丸 | C7: 下品 | D7: NONE | E7: 分次 | F7: 1 | G7: 1 | H7: =F7*G7 -> 1 | I7: 7.5 | J7: 0 | K7: 4 | L7: 0 | M7: 2 | N7: 3 | O7: =IF(N7="",0,J7*N7) -> 0 | P7: =IF(N7="",0,K7*N7) -> 12 | Q7: =IF(N7="",0,L7*N7) -> 0 | R7: 0 | S7: 1 | T7: 瓶 | U7: 第2/4/6秒结算；不是发动即首跳 | V7: 仅消毒散清除毒蚀并免疫毒蚀；不扩为全负面净化。 | W7: 01时序／恢复／免疫；02 OP；03专门用途 | X7: base.map_item.sinew_pill | Y7: 保留资料已有值 | Z7: B4；U | AG7: 首瓶开战可用；未用不进入CD；实际使用后重开完整CD
A8: t01.asset.0024 | B8: 消毒散 | C8: 下品 | D8: NONE | E8: 清毒＋毒蚀免疫 | F8: 1 | G8: 1 | H8: =F8*G8 -> 1 | I8: 5.5 | J8: 0 | K8: 0 | L8: 0 | O8: =IF(N8="",0,J8*N8) -> 0 | P8: =IF(N8="",0,K8*N8) -> 0 | Q8: =IF(N8="",0,L8*N8) -> 0 | R8: 15 | S8: 1 | T8: 瓶 | U8: 发动立即生效 | V8: 仅消毒散清除毒蚀并免疫毒蚀；不扩为全负面净化。 | W8: 01时序／恢复／免疫；02 OP；03专门用途 | X8: base.map_item.detox_powder | Y8: 保留资料已有值 | Z8: B4；U | AG8: 首瓶开战可用；未用不进入CD；实际使用后重开完整CD
A9: t01.asset.0025 | B9: 回灵丹 | C9: 下品 | D9: NONE | E9: 分次 | F9: 1 | G9: 1 | H9: =F9*G9 -> 1 | I9: 7.5 | J9: 0 | K9: 0 | L9: 3 | M9: 2 | N9: 3 | O9: =IF(N9="",0,J9*N9) -> 0 | P9: =IF(N9="",0,K9*N9) -> 0 | Q9: =IF(N9="",0,L9*N9) -> 9 | R9: 0 | S9: 1 | T9: 瓶 | U9: 第2/4/6秒结算；不是发动即首跳 | V9: 仅消毒散清除毒蚀并免疫毒蚀；不扩为全负面净化。 | W9: 01时序／恢复／免疫；02 OP；03专门用途 | X9: 未配置 | Y9: 新增试玩候选 | Z9: B4；U | AG9: 首瓶开战可用；未用不进入CD；实际使用后重开完整CD
A10: t01.asset.0026 | B10: 金疮散 | C10: 下品 | D10: NONE | E10: 即时 | F10: 1 | G10: 1 | H10: =F10*G10 -> 1 | I10: 5.5 | J10: 4 | K10: 0 | L10: 0 | M10: 0 | N10: 1 | O10: =IF(N10="",0,J10*N10) -> 4 | P10: =IF(N10="",0,K10*N10) -> 0 | Q10: =IF(N10="",0,L10*N10) -> 0 | R10: 0 | S10: 1 | T10: 份 | U10: 发动立即生效 | V10: 仅消毒散清除毒蚀并免疫毒蚀；不扩为全负面净化。 | W10: 01时序／恢复／免疫；02 OP；03专门用途 | X10: 未配置 | Y10: 新增试玩候选 | Z10: B4；U | AG10: 首瓶开战可用；未用不进入CD；实际使用后重开完整CD
A11: t01.asset.0027 | B11: 回元散 | C11: 下品 | D11: NONE | E11: 即时 | F11: 1 | G11: 1 | H11: =F11*G11 -> 1 | I11: 7 | J11: 3 | K11: 6 | L11: 0 | M11: 0 | N11: 1 | O11: =IF(N11="",0,J11*N11) -> 3 | P11: =IF(N11="",0,K11*N11) -> 6 | Q11: =IF(N11="",0,L11*N11) -> 0 | R11: 0 | S11: 1 | T11: 份 | U11: 发动立即生效 | V11: 仅消毒散清除毒蚀并免疫毒蚀；不扩为全负面净化。 | W11: 01时序／恢复／免疫；02 OP；03专门用途 | X11: 未配置 | Y11: 新增试玩候选 | Z11: B4；U | AG11: 首瓶开战可用；未用不进入CD；实际使用后重开完整CD
A12: t01.asset.0101 | B12: 回春丹 | C12: 凡品 | D12: NONE | E12: 分次 | F12: 1 | G12: 1 | H12: =F12*G12 -> 1 | I12: 12 | J12: 7 | K12: 0 | L12: 0 | M12: 2 | N12: 3 | O12: =J12*N12 -> 21 | P12: =K12*N12 -> 0 | Q12: =L12*N12 -> 0 | R12: 0 | S12: 1 | T12: 份 | U12: 第2/4/6战斗秒 | V12: 发动后第2、4、6战斗秒各恢复气血7，总21 | W12: 01时序／恢复；02状态／S3；04丹药 | Y12: 候选数值，未试跑 | Z12: 本次Q01用户补充丹药完整表；用户首瓶机制修正 | AA12: P01 | AG12: 首瓶开战可用；未用不进入CD；实际使用后重开完整CD | AH12: 对应资源未缺不自动消耗；同款持续恢复未结束不再自动服用 | AI12: t01.asset.0101.effect.01
A13: t01.asset.0102 | B13: 益气丹 | C13: 凡品 | D13: NONE | E13: 分次 | F13: 1 | G13: 1 | H13: =F13*G13 -> 1 | I13: 13 | J13: 0 | K13: 10 | L13: 0 | M13: 2 | N13: 3 | O13: =J13*N13 -> 0 | P13: =K13*N13 -> 30 | Q13: =L13*N13 -> 0 | R13: 0 | S13: 1 | T13: 份 | U13: 第2/4/6战斗秒 | V13: 发动后第2、4、6战斗秒各恢复体力10，总30 | W13: 01时序／恢复；02状态／S3；04丹药 | Y13: 候选数值，未试跑 | Z13: 本次Q01用户补充丹药完整表；用户首瓶机制修正 | AA13: P02 | AG13: 首瓶开战可用；未用不进入CD；实际使用后重开完整CD | AH13: 对应资源未缺不自动消耗；同款持续恢复未结束不再自动服用 | AI13: t01.asset.0102.effect.01
A14: t01.asset.0103 | B14: 聚灵丹 | C14: 凡品 | D14: NONE | E14: 分次 | F14: 1 | G14: 1 | H14: =F14*G14 -> 1 | I14: 13 | J14: 0 | K14: 0 | L14: 9 | M14: 2 | N14: 3 | O14: =J14*N14 -> 0 | P14: =K14*N14 -> 0 | Q14: =L14*N14 -> 27 | R14: 0 | S14: 1 | T14: 份 | U14: 第2/4/6战斗秒 | V14: 发动后第2、4、6战斗秒各恢复灵力9，总27 | W14: 01时序／恢复；02状态／S3；04丹药 | Y14: 候选数值，未试跑 | Z14: 本次Q01用户补充丹药完整表；用户首瓶机制修正 | AA14: P03 | AG14: 首瓶开战可用；未用不进入CD；实际使用后重开完整CD | AH14: 对应资源未缺不自动消耗；同款持续恢复未结束不再自动服用 | AI14: t01.asset.0103.effect.01
A15: t01.asset.0104 | B15: 培元丹 | C15: 凡品 | D15: NONE | E15: 即时恢复 | F15: 1 | G15: 1 | H15: =F15*G15 -> 1 | I15: 12 | J15: 12 | K15: 18 | L15: 0 | N15: 1 | O15: =J15*N15 -> 12 | P15: =K15*N15 -> 18 | Q15: =L15*N15 -> 0 | R15: 0 | S15: 1 | T15: 份 | U15: 使用当刻 | V15: 立即恢复气血12、体力18 | W15: 01时序／恢复；02状态／S3；04丹药 | Y15: 候选数值，未试跑 | Z15: 本次Q01用户补充丹药完整表；用户首瓶机制修正 | AA15: P04 | AG15: 首瓶开战可用；未用不进入CD；实际使用后重开完整CD | AH15: 对应资源未缺不自动消耗；同款持续恢复未结束不再自动服用 | AI15: t01.asset.0104.effect.01；t01.asset.0104.effect.02
A16: t01.asset.0105 | B16: 铁骨丸 | C16: 凡品 | D16: NONE | E16: 状态 | F16: 1 | G16: 1 | H16: =F16*G16 -> 1 | I16: 18 | J16: 0 | K16: 0 | L16: 0 | N16: 1 | O16: =J16*N16 -> 0 | P16: =K16*N16 -> 0 | Q16: =L16*N16 -> 0 | R16: 0 | S16: 1 | T16: 份 | U16: 使用当刻 | V16: 立即给予自身坚韧＋4层 | W16: 01时序／恢复；02状态／S3；04丹药 | Y16: 候选数值，未试跑 | Z16: 本次Q01用户补充丹药完整表；用户首瓶机制修正 | AA16: P05 | AB16: 坚韧 | AC16: 4 | AG16: 首瓶开战可用；未用不进入CD；实际使用后重开完整CD | AH16: 坚韧仍有新增容量时使用 | AI16: t01.asset.0105.effect.01
A17: t01.asset.0106 | B17: 避火丹 | C17: 凡品 | D17: NONE | E17: 元素减伤 | F17: 1 | G17: 1 | H17: =F17*G17 -> 1 | I17: 22.5 | J17: 0 | K17: 0 | L17: 0 | N17: 1 | O17: =J17*N17 -> 0 | P17: =K17*N17 -> 0 | Q17: =L17*N17 -> 0 | R17: 0 | S17: 1 | T17: 份 | U17: 使用当刻 | V17: 持续12秒，合格直接攻击的火伤分量－10%；同基础百分比加算 | W17: 01时序／恢复；02状态／S3；04丹药 | Y17: 候选数值，未试跑 | Z17: 本次Q01用户补充丹药完整表；用户首瓶机制修正 | AA17: P06 | AD17: 火 | AE17: 0.1 | AF17: 12 | AG17: 首瓶开战可用；未用不进入CD；实际使用后重开完整CD | AH17: 同款幅度不叠加；不同款可并存；不免疫状态／控制，不减持续跳伤 | AI17: t01.asset.0106.effect.01
A18: t01.asset.0107 | B18: 辟寒丹 | C18: 凡品 | D18: NONE | E18: 元素减伤 | F18: 1 | G18: 1 | H18: =F18*G18 -> 1 | I18: 22.5 | J18: 0 | K18: 0 | L18: 0 | N18: 1 | O18: =J18*N18 -> 0 | P18: =K18*N18 -> 0 | Q18: =L18*N18 -> 0 | R18: 0 | S18: 1 | T18: 份 | U18: 使用当刻 | V18: 持续12秒，合格直接攻击的水伤分量－10%；同基础百分比加算 | W18: 01时序／恢复；02状态／S3；04丹药 | Y18: 候选数值，未试跑 | Z18: 本次Q01用户补充丹药完整表；用户首瓶机制修正 | AA18: P07 | AD18: 水 | AE18: 0.1 | AF18: 12 | AG18: 首瓶开战可用；未用不进入CD；实际使用后重开完整CD | AH18: 同款幅度不叠加；不同款可并存；不免疫状态／控制，不减持续跳伤 | AI18: t01.asset.0107.effect.01
A19: t01.asset.0108 | B19: 辟金丹 | C19: 凡品 | D19: NONE | E19: 元素减伤 | F19: 1 | G19: 1 | H19: =F19*G19 -> 1 | I19: 22.5 | J19: 0 | K19: 0 | L19: 0 | N19: 1 | O19: =J19*N19 -> 0 | P19: =K19*N19 -> 0 | Q19: =L19*N19 -> 0 | R19: 0 | S19: 1 | T19: 份 | U19: 使用当刻 | V19: 持续12秒，合格直接攻击的金伤分量－10%；同基础百分比加算 | W19: 01时序／恢复；02状态／S3；04丹药 | Y19: 候选数值，未试跑 | Z19: 本次Q01用户补充丹药完整表；用户首瓶机制修正 | AA19: P08 | AD19: 金 | AE19: 0.1 | AF19: 12 | AG19: 首瓶开战可用；未用不进入CD；实际使用后重开完整CD | AH19: 同款幅度不叠加；不同款可并存；不免疫状态／控制，不减持续跳伤 | AI19: t01.asset.0108.effect.01
A20: t01.asset.0109 | B20: 御木丹 | C20: 凡品 | D20: NONE | E20: 元素减伤 | F20: 1 | G20: 1 | H20: =F20*G20 -> 1 | I20: 22.5 | J20: 0 | K20: 0 | L20: 0 | N20: 1 | O20: =J20*N20 -> 0 | P20: =K20*N20 -> 0 | Q20: =L20*N20 -> 0 | R20: 0 | S20: 1 | T20: 份 | U20: 使用当刻 | V20: 持续12秒，合格直接攻击的木伤分量－10%；同基础百分比加算 | W20: 01时序／恢复；02状态／S3；04丹药 | Y20: 候选数值，未试跑 | Z20: 本次Q01用户补充丹药完整表；用户首瓶机制修正 | AA20: P09 | AD20: 木 | AE20: 0.1 | AF20: 12 | AG20: 首瓶开战可用；未用不进入CD；实际使用后重开完整CD | AH20: 同款幅度不叠加；不同款可并存；不免疫状态／控制，不减持续跳伤 | AI20: t01.asset.0109.effect.01
A21: t01.asset.0110 | B21: 镇土丹 | C21: 凡品 | D21: NONE | E21: 元素减伤 | F21: 1 | G21: 1 | H21: =F21*G21 -> 1 | I21: 22.5 | J21: 0 | K21: 0 | L21: 0 | N21: 1 | O21: =J21*N21 -> 0 | P21: =K21*N21 -> 0 | Q21: =L21*N21 -> 0 | R21: 0 | S21: 1 | T21: 份 | U21: 使用当刻 | V21: 持续12秒，合格直接攻击的土伤分量－10%；同基础百分比加算 | W21: 01时序／恢复；02状态／S3；04丹药 | Y21: 候选数值，未试跑 | Z21: 本次Q01用户补充丹药完整表；用户首瓶机制修正 | AA21: P10 | AD21: 土 | AE21: 0.1 | AF21: 12 | AG21: 首瓶开战可用；未用不进入CD；实际使用后重开完整CD | AH21: 同款幅度不叠加；不同款可并存；不免疫状态／控制，不减持续跳伤 | AI21: t01.asset.0110.effect.01

Sheet 06_符箓
A1: t01-08｜符箓
A2: 2026-09-28 · 27下品＋88凡品＝115件 · 候选数值／当前规则／游戏实现分列 · 不含平衡测试结论
A5: 资产ID | B5: 名称 | C5: 品级 | D5: 元素 | E5: 规格 | F5: 宽_格 | G5: 高_格 | H5: 效果 | I5: CD_秒 | J5: 数量消耗 | K5: 机制引用 | L5: 设计状态 | M5: 来源

Sheet 07_暗器
A1: t01-08｜暗器
A2: 2026-09-28 · 27下品＋88凡品＝115件 · 候选数值／当前规则／游戏实现分列 · 不含平衡测试结论
A5: 资产ID | B5: 名称 | C5: 品级 | D5: 元素 | E5: 规格 | F5: 宽_格 | G5: 高_格 | H5: 效果 | I5: CD_秒 | J5: 数量消耗 | K5: 机制引用 | L5: 设计状态 | M5: 来源 | N5: 来源编号 | O5: 攻击类型 | P5: 基础伤害 | Q5: 体力费 | R5: 灵力费 | S5: 状态 | T5: 层数 | U5: 状态门槛 | V5: 效果引用
A6: t01.asset.0111 | B6: 飞针 | C6: 凡品 | D6: NONE | E6: 1×1，数量消耗；非武器来源 | F6: 1 | G6: 1 | H6: 无 | I6: 6 | J6: 1 | K6: 01伤害；02状态；04暗器 | L6: 候选数值，未试跑 | M6: 第1批基础；第2批微调；第3批复查；用户直接更正优先 | N6: H01 | O6: 穿刺 | P6: 18 | Q6: 0 | R6: 0 | U6: 无 | V6: t01.asset.0111.effect.01
A7: t01.asset.0112 | B7: 柳叶镖 | C7: 凡品 | D7: NONE | E7: 1×1，数量消耗；非武器来源 | F7: 1 | G7: 1 | H7: 无 | I7: 8.5 | J7: 1 | K7: 01伤害；02状态；04暗器 | L7: 候选数值，未试跑 | M7: 第1批基础；第2批微调；第3批复查；用户直接更正优先 | N7: H02 | O7: 斩击 | P7: 26 | Q7: 0 | R7: 0 | U7: 无 | V7: t01.asset.0112.effect.01
A8: t01.asset.0113 | B8: 铁丸 | C8: 凡品 | D8: NONE | E8: 1×1，数量消耗；非武器来源 | F8: 1 | G8: 1 | H8: 无 | I8: 9.5 | J8: 1 | K8: 01伤害；02状态；04暗器 | L8: 候选数值，未试跑 | M8: 第1批基础；第2批微调；第3批复查；用户直接更正优先 | N8: H03 | O8: 钝击 | P8: 32 | Q8: 0 | R8: 0 | U8: 无 | V8: t01.asset.0113.effect.01
A9: t01.asset.0114 | B9: 毒针 | C9: 凡品 | D9: NONE | E9: 1×1，数量消耗；非武器来源 | F9: 1 | G9: 1 | H9: 命中毒蚀＋3 | I9: 7.5 | J9: 1 | K9: 01伤害；02状态；04暗器 | L9: 候选数值，未试跑 | M9: 第1批基础；第2批微调；第3批复查；用户直接更正优先 | N9: H04 | O9: 穿刺 | P9: 12 | Q9: 0 | R9: 0 | S9: 毒蚀 | T9: 3 | U9: 命中 | V9: t01.asset.0114.effect.01；t01.asset.0114.effect.02
A10: t01.asset.0115 | B10: 火砂 | C10: 凡品 | D10: 火 | E10: 1×1，数量消耗；非武器来源 | F10: 1 | G10: 1 | H10: 无 | I10: 9 | J10: 1 | K10: 01伤害；02状态；04暗器 | L10: 候选数值，未试跑 | M10: 第1批基础；第2批微调；第3批复查；用户直接更正优先 | N10: H05 | O10: 法术型 | P10: 30 | Q10: 0 | R10: 0 | U10: 无 | V10: t01.asset.0115.effect.01

Sheet 08_数量统计
A1: t01-08｜数量统计
A2: 2026-09-28 · 27下品＋88凡品＝115件 · 候选数值／当前规则／游戏实现分列 · 不含平衡测试结论
A5: 类别 | B5: 下品 | C5: 凡品 | D5: 良品 | E5: 上品 | F5: 灵品 | G5: 玄品 | H5: 仙品 | I5: 合计
A6: 武器 | B6: =COUNTIF(T08Weapon[品级],B$5) -> 9 | C6: =COUNTIF(T08Weapon[品级],C$5) -> 27 | D6: =COUNTIF(T08Weapon[品级],D$5) -> 0 | E6: =COUNTIF(T08Weapon[品级],E$5) -> 0 | F6: =COUNTIF(T08Weapon[品级],F$5) -> 0 | G6: =COUNTIF(T08Weapon[品级],G$5) -> 0 | H6: =COUNTIF(T08Weapon[品级],H$5) -> 0 | I6: =SUM(B6:H6) -> 36
A7: 防具 | B7: =COUNTIF(T08Armor[品级],B$5) -> 8 | C7: =COUNTIF(T08Armor[品级],C$5) -> 28 | D7: =COUNTIF(T08Armor[品级],D$5) -> 0 | E7: =COUNTIF(T08Armor[品级],E$5) -> 0 | F7: =COUNTIF(T08Armor[品级],F$5) -> 0 | G7: =COUNTIF(T08Armor[品级],G$5) -> 0 | H7: =COUNTIF(T08Armor[品级],H$5) -> 0 | I7: =SUM(B7:H7) -> 36
A8: 法器 | B8: =COUNTIF(T08Artifact[品级],B$5) -> 4 | C8: =COUNTIF(T08Artifact[品级],C$5) -> 18 | D8: =COUNTIF(T08Artifact[品级],D$5) -> 0 | E8: =COUNTIF(T08Artifact[品级],E$5) -> 0 | F8: =COUNTIF(T08Artifact[品级],F$5) -> 0 | G8: =COUNTIF(T08Artifact[品级],G$5) -> 0 | H8: =COUNTIF(T08Artifact[品级],H$5) -> 0 | I8: =SUM(B8:H8) -> 22
A9: 丹药 | B9: =COUNTIF(T08Pill[品级],B$5) -> 6 | C9: =COUNTIF(T08Pill[品级],C$5) -> 10 | D9: =COUNTIF(T08Pill[品级],D$5) -> 0 | E9: =COUNTIF(T08Pill[品级],E$5) -> 0 | F9: =COUNTIF(T08Pill[品级],F$5) -> 0 | G9: =COUNTIF(T08Pill[品级],G$5) -> 0 | H9: =COUNTIF(T08Pill[品级],H$5) -> 0 | I9: =SUM(B9:H9) -> 16
A10: 符箓 | B10: =COUNTIF(T08Talisman[品级],B$5) -> 0 | C10: =COUNTIF(T08Talisman[品级],C$5) -> 0 | D10: =COUNTIF(T08Talisman[品级],D$5) -> 0 | E10: =COUNTIF(T08Talisman[品级],E$5) -> 0 | F10: =COUNTIF(T08Talisman[品级],F$5) -> 0 | G10: =COUNTIF(T08Talisman[品级],G$5) -> 0 | H10: =COUNTIF(T08Talisman[品级],H$5) -> 0 | I10: =SUM(B10:H10) -> 0
A11: 暗器 | B11: =COUNTIF(T08HiddenWeapon[品级],B$5) -> 0 | C11: =COUNTIF(T08HiddenWeapon[品级],C$5) -> 5 | D11: =COUNTIF(T08HiddenWeapon[品级],D$5) -> 0 | E11: =COUNTIF(T08HiddenWeapon[品级],E$5) -> 0 | F11: =COUNTIF(T08HiddenWeapon[品级],F$5) -> 0 | G11: =COUNTIF(T08HiddenWeapon[品级],G$5) -> 0 | H11: =COUNTIF(T08HiddenWeapon[品级],H$5) -> 0 | I11: =SUM(B11:H11) -> 5
A12: 合计 | B12: =SUM(B6:B11) -> 27 | C12: =SUM(C6:C11) -> 88 | D12: =SUM(D6:D11) -> 0 | E12: =SUM(E6:E11) -> 0 | F12: =SUM(F6:F11) -> 0 | G12: =SUM(G6:G11) -> 0 | H12: =SUM(H6:H11) -> 0 | I12: =SUM(I6:I11) -> 115

Sheet 09_基础防具联动
A1: t01-08｜基础防具联动
A2: 2026-09-28 · 27下品＋88凡品＝115件 · 候选数值／当前规则／游戏实现分列 · 不含平衡测试结论
A5: 联动记录ID | B5: 名称 | C5: 主体身甲 | D5: 护臂 | E5: 护腿 | F5: 构型条件 | G5: 关系身份 | H5: 上限额外贡献 | I5: 身甲发动额外回甲 | J5: 组合总上限 | K5: 身甲单次回甲 | L5: 身甲CD_秒 | M5: 总占格 | N5: 运行节奏 | O5: 生命周期边界 | P5: 设计状态 | Q5: 来源
A6: t01.link.cloth_basic | B6: 布甲联动 | C6: 粗布甲 | D6: 布护臂 | E6: 布护腿 | F6: 两护具各自正交邻接同一身甲；不要求两护具彼此相邻。 | G6: 无Set_ID；资料称基础防具联动 | H6: 2 | I6: 1 | J6: =SUM('03_防具'!K6,'03_防具'!K10,'03_防具'!K11)+H6 -> 12 | K6: ='03_防具'!L6+I6 -> 4 | L6: ='03_防具'!J6 -> 4 | M6: =SUM('03_防具'!I6,'03_防具'!I10,'03_防具'!I11) -> 4 | N6: 无额外CD；附加回甲随身甲发动 | O6: 拆联动只撤本贡献，不补满护甲；控制影响按06／02资格判断 | P6: Q01：本组下品邻接限定许可已确认；收益仍为试玩候选 | Q6: B2；C；Q01用户答复2026-09-28
A7: t01.link.iron_basic | B7: 铁甲联动 | C7: 铁甲 | D7: 铁护臂 | E7: 铁护腿 | F7: 两护具各自正交邻接同一身甲；不要求两护具彼此相邻。 | G7: 无Set_ID；资料称基础防具联动 | H7: 3 | I7: 2 | J7: =SUM('03_防具'!K7,'03_防具'!K12,'03_防具'!K13)+H7 -> 18 | K7: ='03_防具'!L7+I7 -> 6 | L7: ='03_防具'!J7 -> 6 | M7: =SUM('03_防具'!I7,'03_防具'!I12,'03_防具'!I13) -> 4 | N7: 无额外CD；附加回甲随身甲发动 | O7: 拆联动只撤本贡献，不补满护甲；控制影响按06／02资格判断 | P7: Q01：本组下品邻接限定许可已确认；收益仍为试玩候选 | Q7: B2；C；Q01用户答复2026-09-28
A8: t01.link.fanpin_water | B8: 水纹三件 | C8: 水纹衣 | D8: 水纹护臂 | E8: 水纹护腿 | F8: 两护具分别正交邻接同一身甲；碰角不算；无两件奖励 | G8: 无Set_ID；仅本批具名基础联动 | H8: 3 | I8: 1 | J8: =SUM('03_防具'!K15,'03_防具'!K25,'03_防具'!K29)+H8 -> 22 | K8: ='03_防具'!L15+I8 -> 7 | L8: ='03_防具'!J15 -> 7 | M8: =SUM('03_防具'!I15,'03_防具'!I25,'03_防具'!I29) -> 4 | N8: 附加回甲并入身甲同一次恢复，无额外CD | O8: 缺员／移开撤本组；超上限截除；重组不回满、不重置CD、不触发受击；控制分项查02／06 | P8: 候选数值；不授权跨品级替代 | Q8: 第1批三组；第2/3批元素修正；铁甲上限按用户调至29
A9: t01.link.fanpin_iron | B9: 铁甲三件_凡品 | C9: 札甲 | D9: 铁护腕 | E9: 铁胫甲 | F9: 两护具分别正交邻接同一身甲；碰角不算；无两件奖励 | G9: 无Set_ID；仅本批具名基础联动 | H9: 4 | I9: 2 | J9: =SUM('03_防具'!K16,'03_防具'!K24,'03_防具'!K28)+H9 -> 29 | K9: ='03_防具'!L16+I9 -> 10 | L9: ='03_防具'!J16 -> 8.5 | M9: =SUM('03_防具'!I16,'03_防具'!I24,'03_防具'!I28) -> 4 | N9: 附加回甲并入身甲同一次恢复，无额外CD | O9: 缺员／移开撤本组；超上限截除；重组不回满、不重置CD、不触发受击；控制分项查02／06 | P9: 候选数值；不授权跨品级替代 | Q9: 第1批三组；第2/3批元素修正；铁甲上限按用户调至29
A10: t01.link.fanpin_thunder | B10: 雷纹三件 | C10: 雷纹法袍 | D10: 雷纹护腕 | E10: 雷纹护腿 | F10: 两护具分别正交邻接同一身甲；碰角不算；无两件奖励 | G10: 无Set_ID；仅本批具名基础联动 | H10: 3 | I10: 1 | J10: =SUM('03_防具'!K18,'03_防具'!K26,'03_防具'!K39)+H10 -> 25 | K10: ='03_防具'!L18+I10 -> 7 | L10: ='03_防具'!J18 -> 9 | M10: =SUM('03_防具'!I18,'03_防具'!I26,'03_防具'!I39) -> 4 | N10: 附加回甲并入身甲同一次恢复，无额外CD | O10: 缺员／移开撤本组；超上限截除；重组不回满、不重置CD、不触发受击；控制分项查02／06 | P10: 候选数值；不授权跨品级替代 | Q10: 第1批三组；第2/3批元素修正；铁甲上限按用户调至29

Sheet 10_甲型与部位规则
A1: t01-08｜甲型规则与部位范围（逐项标记效力）
A2: 2026-09-28 · 27下品＋88凡品＝115件 · 候选数值／当前规则／游戏实现分列 · 不含平衡测试结论
A5: 规则ID | B5: 内容 | C5: 本批处理 | D5: 与旧词典的关系 | E5: 状态
A6: ARM01 | B6: 身甲每实际格×2，其余防具每实际格×1，同甲型加总。 | C6: 分类表N/O列现按已确认规则计算甲型权重；适用双方。 | D6: Q02已覆盖04原等权统计，回填字段、正文、案例与汇总。 | E6: Q02已确认；04已回填
A7: ARM02 | B7: 最高并列含身甲甲型时优先身甲。 | C7: 铁甲重甲4与盾＋布护臂＋布护腿轻甲4并列，优先身甲，取重甲。 | D7: 双方均适用。元素也加权，但元素最高并列使用扫描，不继承甲型身甲优先。 | E7: Q02已确认；04已回填
A8: ARM03 | B8: 无身甲或最高并列不含身甲时：玩家选最高候选；敌方按阵盘从上到下、每行从左到右扫描。 | C8: 敌方首遇最高候选胜出，跳过非候选；不随机。 | D8: 先判断身甲优先，再使用玩家／敌方的后备规则；04已回填。 | E8: Q02已确认；04已回填
A9: ARM04 | B9: 身甲、头具、护臂、护腿、护肩、腰部同部位各限1；盾可多件，仍占阵盘。 | C9: 本批新增肩／腰沿同部位规则；盾例外保持。 | D9: 四大防具形态≠部位唯一性：护臂和护腿可各1件。 | E9: Q03已确认；04已回填
A10: ARM05 | B10: 防御元素也按身甲每格2、其他防具每格1；NONE参与统计。 | C10: 札甲无属性4、金护腕1、土护腿1，最终NONE。 | D10: 覆盖旧等权且排除NONE的元素算法；甲型并列身甲优先与元素并列扫描仍各自独立。 | E10: 本次FP02用户确认

Sheet 11_获取规划
A1: t01-08｜获取规划
A2: 2026-09-28 · 27下品＋88凡品＝115件 · 候选数值／当前规则／游戏实现分列 · 不含平衡测试结论
A5: 规划记录ID | B5: 目标资产ID或类型 | C5: 目标名称 | D5: 渠道 | E5: 具体来源意向 | F5: 方法 | G5: 交付模式 | H5: 目标与成功对象 | I5: 缺失配置 | J5: 节奏／前提 | K5: 状态 | L5: 依据
A6: t01.acquisition.plan.001 | B6: t01.asset.0001 | C6: 青石短剑 | D6: SHOP | E6: 青石镇铁匠铺 | F6: PURCHASE | G6: DIRECT | H6: 固定实物／规格待绝对值 | I6: 数量／价格／库存／资格待配 | J6: 凡人阶段内逐步接触九器型为建议；不等于都已可买。 | K6: 投放建议，非可执行记录 | L6: A；07 D11／R05／Q05
A7: t01.acquisition.plan.002 | B7: t01.asset.0002 | C7: 铁刀 | D7: SHOP | E7: 青石镇铁匠铺 | F7: PURCHASE | G7: DIRECT | H7: 固定实物／规格待绝对值 | I7: 数量／价格／库存／资格待配 | J7: 凡人阶段内逐步接触九器型为建议；不等于都已可买。 | K7: 投放建议，非可执行记录 | L7: A；07 D11／R05／Q05
A8: t01.acquisition.plan.003 | B8: t01.asset.0003 | C8: 柴斧 | D8: SHOP | E8: 青石镇铁匠铺 | F8: PURCHASE | G8: DIRECT | H8: 固定实物／规格待绝对值 | I8: 数量／价格／库存／资格待配 | J8: 凡人阶段内逐步接触九器型为建议；不等于都已可买。 | K8: 投放建议，非可执行记录 | L8: A；07 D11／R05／Q05
A9: t01.acquisition.plan.004 | B9: t01.asset.0004 | C9: 猎弓 | D9: SHOP | E9: 青石镇商铺 | F9: PURCHASE | G9: DIRECT | H9: 固定实物／规格待绝对值 | I9: 数量／价格／库存／资格待配 | J9: 凡人阶段内逐步接触九器型为建议；不等于都已可买。 | K9: 投放建议，非可执行记录 | L9: A；07 D11／R05／Q05
A10: t01.acquisition.plan.005 | B10: t01.asset.0005 | C10: 匕首 | D10: SHOP | E10: 青石镇商铺 | F10: PURCHASE | G10: DIRECT | H10: 固定实物／规格待绝对值 | I10: 数量／价格／库存／资格待配 | J10: 凡人阶段内逐步接触九器型为建议；不等于都已可买。 | K10: 投放建议，非可执行记录 | L10: A；07 D11／R05／Q05
A11: t01.acquisition.plan.006 | B11: t01.asset.0006 | C11: 长枪 | D11: SHOP | E11: 青石镇铁匠铺 | F11: PURCHASE | G11: DIRECT | H11: 固定实物／规格待绝对值 | I11: 数量／价格／库存／资格待配 | J11: 凡人阶段内逐步接触九器型为建议；不等于都已可买。 | K11: 投放建议，非可执行记录 | L11: A；07 D11／R05／Q05
A12: t01.acquisition.plan.007 | B12: t01.asset.0007 | C12: 短柄铁锤 | D12: SHOP | E12: 青石镇铁匠铺 | F12: PURCHASE | G12: DIRECT | H12: 固定实物／规格待绝对值 | I12: 数量／价格／库存／资格待配 | J12: 凡人阶段内逐步接触九器型为建议；不等于都已可买。 | K12: 投放建议，非可执行记录 | L12: A；07 D11／R05／Q05
A13: t01.acquisition.plan.008 | B13: t01.asset.0008 | C13: 石印 | D13: SHOP | E13: 青石镇商铺 | F13: PURCHASE | G13: DIRECT | H13: 固定实物／规格待绝对值 | I13: 数量／价格／库存／资格待配 | J13: 凡人阶段内逐步接触九器型为建议；不等于都已可买。 | K13: 投放建议，非可执行记录 | L13: A；07 D11／R05／Q05
A14: t01.acquisition.plan.009 | B14: t01.asset.0009 | C14: 皮鞭 | D14: SHOP | E14: 青石镇商铺 | F14: PURCHASE | G14: DIRECT | H14: 固定实物／规格待绝对值 | I14: 数量／价格／库存／资格待配 | J14: 凡人阶段内逐步接触九器型为建议；不等于都已可买。 | K14: 投放建议，非可执行记录 | L14: A；07 D11／R05／Q05
A15: t01.acquisition.plan.010 | B15: 来源入口 | C15: 青石镇商铺 | D15: 任务／剧情待配 | E15: 救下商人条件待定义 | F15: 来源开放 | G15: SOURCE_UNLOCK | H15: 商铺入口及开放状态 | I15: 不适用实物数量；具体任务／入口ID待配 | J15: 仅建议，不从正文自行创建剧情。 | K15: 投放建议，非可执行记录 | L15: A；07 D13

Sheet 12_现有配置与迁移
A1: t01-08｜现有配置与迁移
A2: 2026-09-28 · 27下品＋88凡品＝115件 · 候选数值／当前规则／游戏实现分列 · 不含平衡测试结论
A5: 资产ID | B5: 名称 | C5: 现有游戏ID | D5: 现配置品级 | E5: 主表品级 | F5: 现基础伤害 | G5: 现CD_秒 | H5: 现体力费 | I5: 现甲型字段 | J5: 现上限贡献 | K5: 现回甲 | L5: 现effects原值 | M5: 差异与迁移范围 | N5: 验证性质 | O5: 证据
A6: t01.asset.0001 | B6: 青石短剑 | C6: base.map_item.qingshi_short_sword | D6: 下品 | E6: 下品 | F6: 7 | G6: 3.5 | H6: 3 | I6: 未声明 | L6: [] | M6: 主表与现配置均为下品，无品级迁移需求。已有绝对数值仅参考；本批仍以相对档位为设计输入。 | N6: 本轮只读配置；未运行游戏 | O6: data/maps/inventory_items.json
A7: t01.asset.0004 | B7: 猎弓 | C7: base.map_item.hunting_bow | D7: 下品 | E7: 下品 | F7: 9 | G7: 4.5 | H7: 5 | I7: 未声明 | L7: [] | M7: 主表与现配置均为下品，无品级迁移需求。已有绝对数值仅参考；本批仍以相对档位为设计输入。 | N7: 本轮只读配置；未运行游戏 | O7: data/maps/inventory_items.json
A8: t01.asset.0007 | B8: 短柄铁锤 | C8: base.map_item.short_iron_hammer | D8: 下品 | E8: 下品 | F8: 8 | G8: 4 | H8: 4 | I8: 未声明 | L8: [] | M8: 主表与现配置均为下品，无品级迁移需求。已有绝对数值仅参考；本批仍以相对档位为设计输入。 | N8: 本轮只读配置；未运行游戏 | O8: data/maps/inventory_items.json
A9: t01.asset.0010 | B9: 粗布甲 | C9: base.map_item.coarse_cloth_armor | D9: 下品 | E9: 下品 | G9: 4 | I9: 轻甲 | J9: 7 | K9: 3 | L9: [] | M9: 主表与现配置均为下品，无品级迁移需求。 | N9: 本轮只读配置；未运行游戏 | O9: data/maps/inventory_items.json
A10: t01.asset.0012 | B10: 旧铁盔 | C10: base.map_item.old_iron_helmet | D10: 下品 | E10: 下品 | G10: 5 | I10: 未声明 | J10: 2 | K10: 1 | L10: [] | M10: 主表与现配置均为下品，无品级迁移需求。现配置未声明armor_type；本批明确重甲。 | N10: 本轮只读配置；未运行游戏 | O10: data/maps/inventory_items.json
A11: t01.asset.0013 | B11: 木圆盾 | C11: base.map_item.round_wood_shield | D11: 下品 | E11: 下品 | G11: 5 | I11: 未声明 | J11: 2 | K11: 3 | L11: [] | M11: 主表与现配置均为下品，无品级迁移需求。现配置未声明armor_type；本批明确轻甲。 | N11: 本轮只读配置；未运行游戏 | O11: data/maps/inventory_items.json
A12: t01.asset.0018 | B12: 温玉佩 | C12: base.map_item.warm_jade | D12: 下品 | E12: 下品 | G12: 4 | I12: 未声明 | L12: [{"cap_numerator": 2, "resource": "hp", "cap_denominator": 3, "effect": "restore_capped", "value": 4, "trigger": "on_activate"}, {"cap_numerator": 2, "resource": "stamina", "cap_denominator": 3, "effect": "restore_capped", "value": 6, "trigger": "on_activate"}] | M12: 主表与现配置均为下品，无品级迁移需求。 | N12: 本轮只读配置；未运行游戏 | O12: data/maps/inventory_items.json
A13: t01.asset.0022 | B13: 止血丹 | C13: base.map_item.hemostatic_pill | D13: 下品 | E13: 下品 | G13: 6.5 | I13: 未声明 | L13: [{"resource": "hp", "interval": 2.0, "effect": "restore_ticks", "value": 2, "ticks": 3, "trigger": "on_activate"}] | M13: 主表与现配置均为下品，无品级迁移需求。 | N13: 本轮只读配置；未运行游戏 | O13: data/maps/inventory_items.json
A14: t01.asset.0023 | B14: 强筋丸 | C14: base.map_item.sinew_pill | D14: 下品 | E14: 下品 | G14: 7.5 | I14: 未声明 | L14: [{"resource": "stamina", "interval": 2.0, "effect": "restore_ticks", "value": 4, "ticks": 3, "trigger": "on_activate"}] | M14: 主表与现配置均为下品，无品级迁移需求。 | N14: 本轮只读配置；未运行游戏 | O14: data/maps/inventory_items.json
A15: t01.asset.0024 | B15: 消毒散 | C15: base.map_item.detox_powder | D15: 下品 | E15: 下品 | G15: 5.5 | I15: 未声明 | L15: [{"effect": "cleanse_toxin", "duration": 15, "trigger": "on_activate"}] | M15: 主表与现配置均为下品，无品级迁移需求。 | N15: 本轮只读配置；未运行游戏 | O15: data/maps/inventory_items.json

Sheet 13_跨词典联系
A1: t01-08｜跨词典联系
A2: 2026-09-28 · 27下品＋88凡品＝115件 · 候选数值／当前规则／游戏实现分列 · 不含平衡测试结论
A5: 词典 | B5: 接口 | C5: 本批关联 | D5: 边界／实际动作 | E5: 状态
A6: 01 | B6: 发动／支付／恢复／上限 | C6: 基础攻击、状态施加、恢复、上限及灵障分别引用效果；19表补灵障模板，丹药首瓶开战就绪。 | D6: 引用已有词义，不给每件物品建新运行系统。 | E6: 参考
A7: 02 | B7: 毒蚀清除与免疫／控制 | C7: 消毒散专门清毒＋15秒毒蚀免疫；药效和免疫为独立整份实例；Link按控制资格运行。 | D7: 不扩全负面净化、不自动免控；具体重复药效策略按资产/既有规则。 | E7: 参考
A8: 03 | B8: 下品／凡品权限 | C8: 下品两组原例外保留；凡品固定单元素＋一种简单状态开放，本批水纹／铁甲／雷纹三组邻接另列具名例外。 | D8: 对应03 C010和C030及派生视图；不整体放开凡品邻接、双状态或复杂机制。 | E8: 本轮同步03
A9: 04 | B9: 器型、甲型、部位 | C9: 九器型与固定占格；Q02已定身甲每格2、其他1及最高并列身甲优先。 | D9: 防御元素也按身甲2／其他1，含NONE，并列扫描；甲型并列先身甲。各部位限1，盾可多件。 | E9: 下品Q02／Q03及本次FP02
A10: 05 | B10: 制作方／配方 | C10: 当前115件未逐件补齐器方、材料及升品映射；用户明确本次升品稍后考虑。 | D10: 不因下品可制作就虚构实际器方；不恢复蓝图学习或归胚。 | E10: 待具体生产资产
A11: 06 | B11: 基础联动 | C11: 下品两组＋凡品三组固定身甲和两护具正交邻接；无Set_ID、无独立CD，不自动跨品级替代。 | D11: 仍查Link资格、控制、只撤本贡献及不靠重组成套补甲。 | E11: Q01限定许可已确认；资产运行待补齐
A12: 07 | B12: 获取与交付 | C12: 旧下品9武器购入方向保留为规划；本批88凡品暂无正式投放记录。 | D12: 来源覆盖与实际获取覆盖分开；不虚构商品目录、掉率、器方或炼气可达路径。 | E12: 待实际获取链

Sheet 14_确认与后续事项
A1: t01-08｜确认与后续事项
A2: 2026-09-28 · 27下品＋88凡品＝115件 · 候选数值／当前规则／游戏实现分列 · 不含平衡测试结论
A5: 编号 | B5: 主题 | C5: 问题／工作 | D5: 当前状态 | E5: 影响范围
A6: Q01 | B6: 下品邻接权限 | C6: 03从良品常规开放正交邻接，本批两组下品联动是否限定例外？ | D6: 已确认限定两组联动；用户最新将本批品级更正为下品，例外随这两组改为下品；其他物品仍按03原权限。 | E6: 03 C030及两联动许可已同步；数值仍为候选
A7: Q02 | B7: 甲型全局覆盖 | C7: 身甲×2／其他×1、并列优先身甲是否全局替换04？ | D7: 已确认：采用整套规则，更新04（建议） | E7: 历史Q02只改甲型；后由本次FP02进一步确认元素也加权且含NONE，现按10／19表。
A8: Q03 | B8: 部位限制范围 | C8: 盾是否也最多1件；同部位限制与现有阵盘规格需统一。 | D8: 已确认：允许多件盾，只受阵盘空间限制 | E8: 已回填04及08部位限制
A9: Q04 | B9: 新法器恢复上限 | C9: 回春玉、养息珠、聚灵珠是否采用最多至最大值2/3？ | D9: 已确认：三件都采用2/3上限（建议） | E9: 已回填回春玉、养息珠、聚灵珠；温玉佩既有规则不变
A10: A01 | B10: 绝对武器数值 | C10: 九件之间相对伤害／CD／体力档位，待横向平衡。 | D10: 原稿明确后定；保留三已有武器参考值，未擅自代填。 | E10: 未来数值设计
A11: A02 | B11: 候选参数与平衡 | C11: 新增防具、法器、丹药及两联动收益保留试玩候选。 | D11: 未运行战斗；不把新增候选改写为已测试。 | E11: 未来确认与验证
A12: A03 | B12: 生产获取与表现 | C12: 配方、正式来源、价格库存、图标和运行配置未齐。 | D12: 未创建游戏资产；后续按实际选定范围补齐。 | E12: 未来资产落地
A13: A04 | B13: Link具体运行 | C13: 固定匹配结构已有，控制时静态上限／发动修正需与02/06实例策略衔接。 | D13: 不一律控制就断链、不用重新组合免费恢复护甲。 | E13: 未来实际运行模板
A14: FP01 | B14: 丹药缺表 | C14: 补齐10种丹药完整数据 | D14: 已补齐并入表 | E14: 05及18统计
A15: FP02 | B15: 元素权重 | C15: NONE参与，身甲也乘2 | D15: 已确认：元素也采用身甲乘2：无属性4、金1、土1 | E15: 04及10表
A16: FP03 | B16: 灵障重复生成 | C16: 已有10再次生成15 | D16: 已确认：容量足够时加进现有池成为25；来源份额保留 | E16: 01 M06 C04／F14
... A20: FP-LATER | B20: 后续实施 | C20: 平衡试跑、实际游戏ID、配方和获取；升品稍后 | D20: 未实施，不自动猜配方或跨品级承接 | E20: 候选资产后续阶段

Sheet 15_核对场景
A1: t01-08｜核对场景
A2: 2026-09-28 · 27下品＋88凡品＝115件 · 候选数值／当前规则／游戏实现分列 · 不含平衡测试结论
A5: 案例ID | B5: 主题 | C5: 输入 | D5: 预期／边界 | E5: 状态
A6: T01 | B6: 总量 | C6: 下品27保留＋本批凡品88 | D6: 总115＝36武器＋36防具＋22法器＋16丹药＋0符箓＋5暗器 | E6: 文本核对
A7: T02 | B7: 品级覆盖 | C7: 用户更正：“这一批道具全是下品”；覆盖此前误说。 | D7: 更正针对旧27件下品；本次独立新增88件凡品。当前统计下品27、凡品88。 | E7: 文本／结构核对
A8: T03 | B8: 武器数值 | C8: 猎弓已有9伤／4.5秒／5体力，但新稿体力中低 | D8: 保留旧配置证据，不把新相对档位等同旧排序已满足 | E8: 待平衡
A9: T04 | B9: 占格方向 | C9: 剑1×2、斧2×1；枪鞭3×1 | D9: 维持固定方向不可旋转；无射程加成 | E9: 文本核对
A10: T05 | B10: 布甲联动 | C10: 两护具分别贴粗布甲，互不相邻 | D10: 上限12、身甲回甲4／4秒；总4格；Q01已批准本组下品邻接例外。 | E10: 候选计算；未运行
A11: T06 | B11: 铁甲联动 | C11: 铁甲＋铁护臂＋铁护腿合法构型 | D11: 上限18、身甲回甲6／6秒；护臂5秒／腿6秒，非身甲4秒 | E11: 候选计算；未运行
A12: T07 | B12: 甲型并列 | C12: 铁甲重4，盾＋布臂＋布腿轻4 | D12: 权重重4、轻4并列，优先身甲重甲；Q02已定，04已覆盖。 | E12: 已确认规则；文本核对，未运行
A13: T08 | B13: 元素权重 | C13: 札甲2格NONE＋金护腕1格＋土护腿1格 | D13: 本次FP02：身甲乘2，NONE4／金1／土1，最终NONE；元素并列才扫描，不继承甲型身甲优先。 | E13: 已确认；覆盖旧NONE不投票
A14: T09 | B14: 解组 | C14: 布／铁三件构型失效后再成立 | D14: 只撤／恢复对应上限贡献，不凭空补满护甲；控制须查资格 | E14: 文本需求；未运行
A15: T10 | B15: 资源法器 | C15: 新三件免费回复法器接近资源上限 | D15: Q04已确认2/3上限：对应最大值60时最多恢复至40；已高于40不扣减，也不继续恢复。 | E15: 已确认规则；文本核对，未运行
A16: T11 | B16: 分次丹药 | C16: 止血／强筋／回灵在发动后2、4、6秒跳 | D16: 各总6气血／12体力／9灵力；不能发动即先跳一次 | E16: 候选／既有对照；未运行
... A18: T13 | B18: 非实物开放 | C18: 救商人后开放商铺的规划被采纳时 | D18: 按07 SOURCE_UNLOCK成功应用入口，不能为填字段虚构物品×1 | E18: 后续投放需求

Sheet 16_来源与证据
A1: t01-08｜来源与证据
A2: 2026-09-28 · 27下品＋88凡品＝115件 · 候选数值／当前规则／游戏实现分列 · 不含平衡测试结论
A5: 来源ID | B5: 来源位置 | C5: 性质 | D5: 有效范围 | E5: 完整性说明
A6: U/A/B/C | B6: docs\sources\t01-08_三段资料结构化摘录_2026-09-28.md | C6: 用户本轮消息的结构化摘录 | D6: 用户最新更正全为下品；C修正优先；候选与建议保留原性质 | E6: 不是附件原字节／完整逐字转录
A7: GAME10 | B7: data/maps/inventory_items.json | C7: 现行配置只读快照 | D7: 10件同名基准数据；不等于新下品设计已实现 | E7: 684c149bf81c83f6034ffbd6a1f12e52a41de4c0ba1b722e8d6899921f84a528
A8: Q01 | B8: 本轮选择题 | C8: 用户已答，2026-09-28 | D8: 历史Q01原答复：“仅允许这两组凡品防具联动，其他凡品仍按03原权限（建议）”；随后用户更正本批全部下品，现行例外限两组下品。 | E8: 原答复留作历史；现行品级按最新更正，两组限定许可不推广其他下品或凡品，候选数值未定案。
A9: DICT01-07 | B9: output/spreadsheet/t01-01～07正式词典 | C9: 既有规则参考 | D9: 引用具体接口；新全局规则须明确覆盖范围 | E9: 本轮未批准前不改旧词典
A10: FP-S01 | B10: docs/sources/t01-08_凡品第1批原文_2026-09-28.txt | C10: 附件原字节归档 | D10: 78件完整基础数据及三组联动；后续覆盖以第2/3批和用户为准 | E10: 已校验附件SHA256
A11: FP-S02 | B11: 本线程第2批＋第3批＋直接说明 | C11: 内贴资料结构化整理 | D11: 元素13处、2个状态换向、火弓退出／火枪新增；模板、成本、药品首瓶、NONE及铁甲29 | E11: 非逐字原文归档；见编制记录
A12: FP-S03 | B12: 本次FP01丹药补表 | C12: 用户完整文字答复 | D12: 10丹药及自动使用条件、五行直接减伤范围 | E12: 录入数据见05；初版附件未展开该表

Sheet 17_效果与触发
A1: t01-08｜效果与触发
A2: 2026-09-28 · 27下品＋88凡品＝115件 · 候选数值／当前规则／游戏实现分列 · 不含平衡测试结论
A5: 效果记录ID | B5: 资产ID | C5: 来源编号 | D5: 名称 | E5: 行为 | F5: 数值 | G5: 状态 | H5: 触发时机 | I5: 目标 | J5: 来源身份 | K5: 攻击类型 | L5: 元素 | M5: 规则引用 | N5: 边界 | O5: 效力
A6: t01.asset.0028.effect.01 | B6: t01.asset.0028 | C6: W01 | D6: 铁剑 | E6: 直接伤害 | F6: 18 | H6: 合法发动并按命中结算 | I6: 敌方 | J6: WEAPON | K6: 斩击 | L6: 无属性 | M6: 01 M06 A01；04攻击类型 | N6: 单一基础伤害，不额外赠送一份元素伤害；来源身份不因SPELL攻击类型改变 | O6: 候选设计记录；未注册游戏Effect
A7: t01.asset.0029.effect.01 | B7: t01.asset.0029 | C7: W02 | D7: 赤纹剑 | E7: 直接伤害 | F7: 16 | H7: 合法发动并按命中结算 | I7: 敌方 | J7: WEAPON | K7: 斩击 | L7: 火 | M7: 01 M06 A01；04攻击类型 | N7: 单一基础伤害，不额外赠送一份元素伤害；来源身份不因SPELL攻击类型改变 | O7: 候选设计记录；未注册游戏Effect
A8: t01.asset.0029.effect.02 | B8: t01.asset.0029 | C8: W02 | D8: 赤纹剑 | E8: 施加状态 | F8: 1 | G8: 灼烧 | H8: 命中 | I8: 敌方 | J8: WEAPON | K8: 斩击 | L8: 火 | M8: 02核心状态／OP_ADD；01 M02/M03/M07 | N8: 施加结果以合法应用返回值判断，不用状态池净增量；即时转盾不抹去成功施加。具体效果与施加时序依02和核心01，不由七系标签自动增加额外伤害。 | O8: 候选设计记录；未注册游戏Effect
A9: t01.asset.0030.effect.01 | B9: t01.asset.0030 | C9: W03 | D9: 寒水剑 | E9: 直接伤害 | F9: 17 | H9: 合法发动并按命中结算 | I9: 敌方 | J9: WEAPON | K9: 斩击 | L9: 水 | M9: 01 M06 A01；04攻击类型 | N9: 单一基础伤害，不额外赠送一份元素伤害；来源身份不因SPELL攻击类型改变 | O9: 候选设计记录；未注册游戏Effect
A10: t01.asset.0030.effect.02 | B10: t01.asset.0030 | C10: W03 | D10: 寒水剑 | E10: 施加状态 | F10: 1 | G10: 寒霜 | H10: 命中 | I10: 敌方 | J10: WEAPON | K10: 斩击 | L10: 水 | M10: 02核心状态／OP_ADD；01 M02/M03/M07 | N10: 施加结果以合法应用返回值判断，不用状态池净增量；即时转盾不抹去成功施加。寒霜正常新层先施加、后由本次合格主动水攻触发；初霜专属额外层例外留后次。 | O10: 候选设计记录；未注册游戏Effect
A11: t01.asset.0031.effect.01 | B11: t01.asset.0031 | C11: W05 | D11: 钢刀 | E11: 直接伤害 | F11: 10 | H11: 合法发动并按命中结算 | I11: 敌方 | J11: WEAPON | K11: 斩击 | L11: 金 | M11: 01 M06 A01；04攻击类型 | N11: 单一基础伤害，不额外赠送一份元素伤害；来源身份不因SPELL攻击类型改变 | O11: 候选设计记录；未注册游戏Effect
A12: t01.asset.0031.effect.02 | B12: t01.asset.0031 | C12: W05 | D12: 钢刀 | E12: 施加状态 | F12: 1 | G12: 流血 | H12: 实际伤到气血 | I12: 敌方 | J12: WEAPON | K12: 斩击 | L12: 金 | M12: 02核心状态／OP_ADD；01 M02/M03/M07 | N12: 施加结果以合法应用返回值判断，不用状态池净增量；即时转盾不抹去成功施加。本件流血须本次攻击实际伤及气血；只命中或只扣盾甲不足。 | O12: 候选设计记录；未注册游戏Effect
A13: t01.asset.0032.effect.01 | B13: t01.asset.0032 | C13: W06 | D13: 金纹刀 | E13: 直接伤害 | F13: 12 | H13: 合法发动并按命中结算 | I13: 敌方 | J13: WEAPON | K13: 斩击 | L13: 金 | M13: 01 M06 A01；04攻击类型 | N13: 单一基础伤害，不额外赠送一份元素伤害；来源身份不因SPELL攻击类型改变 | O13: 候选设计记录；未注册游戏Effect
A14: t01.asset.0032.effect.02 | B14: t01.asset.0032 | C14: W06 | D14: 金纹刀 | E14: 施加状态 | F14: 1 | G14: 锋痕 | H14: 命中 | I14: 敌方 | J14: WEAPON | K14: 斩击 | L14: 金 | M14: 02核心状态／OP_ADD；01 M02/M03/M07 | N14: 施加结果以合法应用返回值判断，不用状态池净增量；即时转盾不抹去成功施加。锋痕由合格武器攻击兑现；金光镜仍是法器来源，不因金元素或SPELL攻击类型取得武器资格。 | O14: 候选设计记录；未注册游戏Effect
A15: t01.asset.0033.effect.01 | B15: t01.asset.0033 | C15: W07 | D15: 赤焰刀 | E15: 直接伤害 | F15: 11 | H15: 合法发动并按命中结算 | I15: 敌方 | J15: WEAPON | K15: 斩击 | L15: 火 | M15: 01 M06 A01；04攻击类型 | N15: 单一基础伤害，不额外赠送一份元素伤害；来源身份不因SPELL攻击类型改变 | O15: 候选设计记录；未注册游戏Effect
A16: t01.asset.0033.effect.02 | B16: t01.asset.0033 | C16: W07 | D16: 赤焰刀 | E16: 施加状态 | F16: 1 | G16: 破甲 | H16: 命中 | I16: 敌方 | J16: WEAPON | K16: 斩击 | L16: 火 | M16: 02核心状态／OP_ADD；01 M02/M03/M07 | N16: 施加结果以合法应用返回值判断，不用状态池净增量；即时转盾不抹去成功施加。具体效果与施加时序依02和核心01，不由七系标签自动增加额外伤害。 | O16: 候选设计记录；未注册游戏Effect
A17: t01.asset.0034.effect.01 | B17: t01.asset.0034 | C17: W08 | D17: 开山斧 | E17: 直接伤害 | F17: 30 | H17: 合法发动并按命中结算 | I17: 敌方 | J17: WEAPON | K17: 斩击 | L17: 土 | M17: 01 M06 A01；04攻击类型 | N17: 单一基础伤害，不额外赠送一份元素伤害；来源身份不因SPELL攻击类型改变 | O17: 候选设计记录；未注册游戏Effect
A18: t01.asset.0034.effect.02 | B18: t01.asset.0034 | C18: W08 | D18: 开山斧 | E18: 施加状态 | F18: 2 | G18: 疲惫 | H18: 命中 | I18: 敌方 | J18: WEAPON | K18: 斩击 | L18: 土 | M18: 02核心状态／OP_ADD；01 M02/M03/M07 | N18: 施加结果以合法应用返回值判断，不用状态池净增量；即时转盾不抹去成功施加。具体效果与施加时序依02和核心01，不由七系标签自动增加额外伤害。 | O18: 候选设计记录；未注册游戏Effect
A19: t01.asset.0035.effect.01 | B19: t01.asset.0035 | C19: W09 | D19: 金刚斧 | E19: 直接伤害 | F19: 28 | H19: 合法发动并按命中结算 | I19: 敌方 | J19: WEAPON | K19: 斩击 | L19: 金 | M19: 01 M06 A01；04攻击类型 | N19: 单一基础伤害，不额外赠送一份元素伤害；来源身份不因SPELL攻击类型改变 | O19: 候选设计记录；未注册游戏Effect
A20: t01.asset.0035.effect.02 | B20: t01.asset.0035 | C20: W09 | D20: 金刚斧 | E20: 施加状态 | F20: 2 | G20: 锋痕 | H20: 命中 | I20: 敌方 | J20: WEAPON | K20: 斩击 | L20: 金 | M20: 02核心状态／OP_ADD；01 M02/M03/M07 | N20: 施加结果以合法应用返回值判断，不用状态池净增量；即时转盾不抹去成功施加。锋痕由合格武器攻击兑现；金光镜仍是法器来源，不因金元素或SPELL攻击类型取得武器资格。 | O20: 候选设计记录；未注册游戏Effect
A21: t01.asset.0036.effect.01 | B21: t01.asset.0036 | C21: W10 | D21: 厚土斧 | E21: 直接伤害 | F21: 28 | H21: 合法发动并按命中结算 | I21: 敌方 | J21: WEAPON | K21: 斩击 | L21: 土 | M21: 01 M06 A01；04攻击类型 | N21: 单一基础伤害，不额外赠送一份元素伤害；来源身份不因SPELL攻击类型改变 | O21: 候选设计记录；未注册游戏Effect
A22: t01.asset.0036.effect.02 | B22: t01.asset.0036 | C22: W10 | D22: 厚土斧 | E22: 施加状态 | F22: 2 | G22: 重伤 | H22: 命中 | I22: 敌方 | J22: WEAPON | K22: 斩击 | L22: 土 | M22: 02核心状态／OP_ADD；01 M02/M03/M07 | N22: 施加结果以合法应用返回值判断，不用状态池净增量；即时转盾不抹去成功施加。具体效果与施加时序依02和核心01，不由七系标签自动增加额外伤害。 | O22: 候选设计记录；未注册游戏Effect
A23: t01.asset.0037.effect.01 | B23: t01.asset.0037 | C23: W11 | D23: 桑木弓 | E23: 直接伤害 | F23: 24 | H23: 合法发动并按命中结算 | I23: 敌方 | J23: WEAPON | K23: 穿刺 | L23: 木 | M23: 01 M06 A01；04攻击类型 | N23: 单一基础伤害，不额外赠送一份元素伤害；来源身份不因SPELL攻击类型改变 | O23: 候选设计记录；未注册游戏Effect
A24: t01.asset.0038.effect.01 | B24: t01.asset.0038 | C24: W12 | D24: 水纹弓 | E24: 直接伤害 | F24: 20 | H24: 合法发动并按命中结算 | I24: 敌方 | J24: WEAPON | K24: 穿刺 | L24: 水 | M24: 01 M06 A01；04攻击类型 | N24: 单一基础伤害，不额外赠送一份元素伤害；来源身份不因SPELL攻击类型改变 | O24: 候选设计记录；未注册游戏Effect
A25: t01.asset.0038.effect.02 | B25: t01.asset.0038 | C25: W12 | D25: 水纹弓 | E25: 施加状态 | F25: 1 | G25: 枯脉 | H25: 命中 | I25: 敌方 | J25: WEAPON | K25: 穿刺 | L25: 水 | M25: 02核心状态／OP_ADD；01 M02/M03/M07 | N25: 施加结果以合法应用返回值判断，不用状态池净增量；即时转盾不抹去成功施加。具体效果与施加时序依02和核心01，不由七系标签自动增加额外伤害。 | O25: 候选设计记录；未注册游戏Effect
A26: t01.asset.0039.effect.01 | B26: t01.asset.0039 | C26: W14 | D26: 雷纹弓 | E26: 直接伤害 | F26: 22 | H26: 合法发动并按命中结算 | I26: 敌方 | J26: WEAPON | K26: 穿刺 | L26: 雷 | M26: 01 M06 A01；04攻击类型 | N26: 单一基础伤害，不额外赠送一份元素伤害；来源身份不因SPELL攻击类型改变 | O26: 候选设计记录；未注册游戏Effect
A27: t01.asset.0039.effect.02 | B27: t01.asset.0039 | C27: W14 | D27: 雷纹弓 | E27: 施加状态 | F27: 1 | G27: 连环 | H27: 命中 | I27: 敌方 | J27: WEAPON | K27: 穿刺 | L27: 雷 | M27: 02核心状态／OP_ADD；01 M02/M03/M07 | N27: 施加结果以合法应用返回值判断，不用状态池净增量；即时转盾不抹去成功施加。连环供后续合格雷攻击利用；锁雷环无本体攻击，不直接制造雷击或闪电。 | O27: 候选设计记录；未注册游戏Effect
A28: t01.asset.0040.effect.01 | B28: t01.asset.0040 | C28: W15 | D28: 精铁匕 | E28: 直接伤害 | F28: 8 | H28: 合法发动并按命中结算 | I28: 敌方 | J28: WEAPON | K28: 穿刺 | L28: 金 | M28: 01 M06 A01；04攻击类型 | N28: 单一基础伤害，不额外赠送一份元素伤害；来源身份不因SPELL攻击类型改变 | O28: 候选设计记录；未注册游戏Effect
A29: t01.asset.0040.effect.02 | B29: t01.asset.0040 | C29: W15 | D29: 精铁匕 | E29: 施加状态 | F29: 1 | G29: 流血 | H29: 实际伤到气血 | I29: 敌方 | J29: WEAPON | K29: 穿刺 | L29: 金 | M29: 02核心状态／OP_ADD；01 M02/M03/M07 | N29: 施加结果以合法应用返回值判断，不用状态池净增量；即时转盾不抹去成功施加。本件流血须本次攻击实际伤及气血；只命中或只扣盾甲不足。 | O29: 候选设计记录；未注册游戏Effect
A30: t01.asset.0041.effect.01 | B30: t01.asset.0041 | C30: W16 | D30: 风刃匕 | E30: 直接伤害 | F30: 7 | H30: 合法发动并按命中结算 | I30: 敌方 | J30: WEAPON | K30: 穿刺 | L30: 风 | M30: 01 M06 A01；04攻击类型 | N30: 单一基础伤害，不额外赠送一份元素伤害；来源身份不因SPELL攻击类型改变 | O30: 候选设计记录；未注册游戏Effect
A31: t01.asset.0041.effect.02 | B31: t01.asset.0041 | C31: W16 | D31: 风刃匕 | E31: 施加状态 | F31: 1 | G31: 失衡 | H31: 命中 | I31: 敌方 | J31: WEAPON | K31: 穿刺 | L31: 风 | M31: 02核心状态／OP_ADD；01 M02/M03/M07 | N31: 施加结果以合法应用返回值判断，不用状态池净增量；即时转盾不抹去成功施加。具体效果与施加时序依02和核心01，不由七系标签自动增加额外伤害。 | O31: 候选设计记录；未注册游戏Effect
A32: t01.asset.0042.effect.01 | B32: t01.asset.0042 | C32: W17 | D32: 青木枪 | E32: 直接伤害 | F32: 34 | H32: 合法发动并按命中结算 | I32: 敌方 | J32: WEAPON | K32: 穿刺 | L32: 木 | M32: 01 M06 A01；04攻击类型 | N32: 单一基础伤害，不额外赠送一份元素伤害；来源身份不因SPELL攻击类型改变 | O32: 候选设计记录；未注册游戏Effect
A33: t01.asset.0042.effect.02 | B33: t01.asset.0042 | C33: W17 | D33: 青木枪 | E33: 施加状态 | F33: 2 | G33: 缠绕 | H33: 命中 | I33: 敌方 | J33: WEAPON | K33: 穿刺 | L33: 木 | M33: 02核心状态／OP_ADD；01 M02/M03/M07 | N33: 施加结果以合法应用返回值判断，不用状态池净增量；即时转盾不抹去成功施加。缠绕由后续合格火、雷伤害利用；木攻击本身不因此获得火雷增幅。 | O33: 候选设计记录；未注册游戏Effect
A34: t01.asset.0043.effect.01 | B34: t01.asset.0043 | C34: W19 | D34: 雷纹枪 | E34: 直接伤害 | F34: 38 | H34: 合法发动并按命中结算 | I34: 敌方 | J34: WEAPON | K34: 穿刺 | L34: 雷 | M34: 01 M06 A01；04攻击类型 | N34: 单一基础伤害，不额外赠送一份元素伤害；来源身份不因SPELL攻击类型改变 | O34: 候选设计记录；未注册游戏Effect
A35: t01.asset.0043.effect.02 | B35: t01.asset.0043 | C35: W19 | D35: 雷纹枪 | E35: 施加状态 | F35: 2 | G35: 雷印 | H35: 命中 | I35: 敌方 | J35: WEAPON | K35: 穿刺 | L35: 雷 | M35: 02核心状态／OP_ADD；01 M02/M03/M07 | N35: 施加结果以合法应用返回值判断，不用状态池净增量；即时转盾不抹去成功施加。雷印新层在本击伤后加入，供后续合格雷攻；无本体雷攻击的施层器具不直接引雷。 | O35: 候选设计记录；未注册游戏Effect
A36: t01.asset.0044.effect.01 | B36: t01.asset.0044 | C36: W20 | D36: 炎纹锤 | E36: 直接伤害 | F36: 20 | H36: 合法发动并按命中结算 | I36: 敌方 | J36: WEAPON | K36: 钝击 | L36: 火 | M36: 01 M06 A01；04攻击类型 | N36: 单一基础伤害，不额外赠送一份元素伤害；来源身份不因SPELL攻击类型改变 | O36: 候选设计记录；未注册游戏Effect
A37: t01.asset.0044.effect.02 | B37: t01.asset.0044 | C37: W20 | D37: 炎纹锤 | E37: 施加状态 | F37: 1 | G37: 破甲 | H37: 命中 | I37: 敌方 | J37: WEAPON | K37: 钝击 | L37: 火 | M37: 02核心状态／OP_ADD；01 M02/M03/M07 | N37: 施加结果以合法应用返回值判断，不用状态池净增量；即时转盾不抹去成功施加。具体效果与施加时序依02和核心01，不由七系标签自动增加额外伤害。 | O37: 候选设计记录；未注册游戏Effect
A38: t01.asset.0045.effect.01 | B38: t01.asset.0045 | C38: W21 | D38: 石骨锤 | E38: 直接伤害 | F38: 26 | H38: 合法发动并按命中结算 | I38: 敌方 | J38: WEAPON | K38: 钝击 | L38: 土 | M38: 01 M06 A01；04攻击类型 | N38: 单一基础伤害，不额外赠送一份元素伤害；来源身份不因SPELL攻击类型改变 | O38: 候选设计记录；未注册游戏Effect
A39: t01.asset.0046.effect.01 | B39: t01.asset.0046 | C39: W22 | D39: 镇土印 | E39: 直接伤害 | F39: 16 | H39: 合法发动并按命中结算 | I39: 敌方 | J39: WEAPON | K39: 钝击 | L39: 土 | M39: 01 M06 A01；04攻击类型 | N39: 单一基础伤害，不额外赠送一份元素伤害；来源身份不因SPELL攻击类型改变 | O39: 候选设计记录；未注册游戏Effect
A40: t01.asset.0046.effect.02 | B40: t01.asset.0046 | C40: W22 | D40: 镇土印 | E40: 施加状态 | F40: 1 | G40: 疲惫 | H40: 命中 | I40: 敌方 | J40: WEAPON | K40: 钝击 | L40: 土 | M40: 02核心状态／OP_ADD；01 M02/M03/M07 | N40: 施加结果以合法应用返回值判断，不用状态池净增量；即时转盾不抹去成功施加。具体效果与施加时序依02和核心01，不由七系标签自动增加额外伤害。 | O40: 候选设计记录；未注册游戏Effect
A41: t01.asset.0047.effect.01 | B41: t01.asset.0047 | C41: W23 | D41: 雷纹印 | E41: 直接伤害 | F41: 14 | H41: 合法发动并按命中结算 | I41: 敌方 | J41: WEAPON | K41: 钝击 | L41: 雷 | M41: 01 M06 A01；04攻击类型 | N41: 单一基础伤害，不额外赠送一份元素伤害；来源身份不因SPELL攻击类型改变 | O41: 候选设计记录；未注册游戏Effect
A42: t01.asset.0047.effect.02 | B42: t01.asset.0047 | C42: W23 | D42: 雷纹印 | E42: 施加状态 | F42: 1 | G42: 雷蕴 | H42: 命中 | I42: 自身 | J42: WEAPON | K42: 钝击 | L42: 雷 | M42: 02核心状态／OP_ADD；01 M02/M03/M07 | N42: 施加结果以合法应用返回值判断，不用状态池净增量；即时转盾不抹去成功施加。具体效果与施加时序依02和核心01，不由七系标签自动增加额外伤害。 | O42: 候选设计记录；未注册游戏Effect
A43: t01.asset.0048.effect.01 | B43: t01.asset.0048 | C43: W24 | D43: 藤鞭 | E43: 直接伤害 | F43: 14 | H43: 合法发动并按命中结算 | I43: 敌方 | J43: WEAPON | K43: 钝击 | L43: 木 | M43: 01 M06 A01；04攻击类型 | N43: 单一基础伤害，不额外赠送一份元素伤害；来源身份不因SPELL攻击类型改变 | O43: 候选设计记录；未注册游戏Effect
A44: t01.asset.0048.effect.02 | B44: t01.asset.0048 | C44: W24 | D44: 藤鞭 | E44: 施加状态 | F44: 1 | G44: 毒蚀 | H44: 命中 | I44: 敌方 | J44: WEAPON | K44: 钝击 | L44: 木 | M44: 02核心状态／OP_ADD；01 M02/M03/M07 | N44: 施加结果以合法应用返回值判断，不用状态池净增量；即时转盾不抹去成功施加。具体效果与施加时序依02和核心01，不由七系标签自动增加额外伤害。 | O44: 候选设计记录；未注册游戏Effect
A45: t01.asset.0049.effect.01 | B45: t01.asset.0049 | C45: W25 | D45: 雷鞭 | E45: 直接伤害 | F45: 15 | H45: 合法发动并按命中结算 | I45: 敌方 | J45: WEAPON | K45: 钝击 | L45: 雷 | M45: 01 M06 A01；04攻击类型 | N45: 单一基础伤害，不额外赠送一份元素伤害；来源身份不因SPELL攻击类型改变 | O45: 候选设计记录；未注册游戏Effect
A46: t01.asset.0049.effect.02 | B46: t01.asset.0049 | C46: W25 | D46: 雷鞭 | E46: 施加状态 | F46: 1 | G46: 雷印 | H46: 命中 | I46: 敌方 | J46: WEAPON | K46: 钝击 | L46: 雷 | M46: 02核心状态／OP_ADD；01 M02/M03/M07 | N46: 施加结果以合法应用返回值判断，不用状态池净增量；即时转盾不抹去成功施加。雷印新层在本击伤后加入，供后续合格雷攻；无本体雷攻击的施层器具不直接引雷。 | O46: 候选设计记录；未注册游戏Effect
A47: t01.asset.0050.effect.01 | B47: t01.asset.0050 | C47: W28 | D47: 刺血匕 | E47: 直接伤害 | F47: 8 | H47: 合法发动并按命中结算 | I47: 敌方 | J47: WEAPON | K47: 穿刺 | L47: 金 | M47: 01 M06 A01；04攻击类型 | N47: 单一基础伤害，不额外赠送一份元素伤害；来源身份不因SPELL攻击类型改变 | O47: 候选设计记录；未注册游戏Effect
A48: t01.asset.0050.effect.02 | B48: t01.asset.0050 | C48: W28 | D48: 刺血匕 | E48: 施加状态 | F48: 2 | G48: 流血 | H48: 实际伤到气血 | I48: 敌方 | J48: WEAPON | K48: 穿刺 | L48: 金 | M48: 02核心状态／OP_ADD；01 M02/M03/M07 | N48: 施加结果以合法应用返回值判断，不用状态池净增量；即时转盾不抹去成功施加。本件流血须本次攻击实际伤及气血；只命中或只扣盾甲不足。 | O48: 候选设计记录；未注册游戏Effect
A49: t01.asset.0051.effect.01 | B49: t01.asset.0051 | C49: W30 | D49: 震骨锤 | E49: 直接伤害 | F49: 32 | H49: 合法发动并按命中结算 | I49: 敌方 | J49: WEAPON | K49: 钝击 | L49: 土 | M49: 01 M06 A01；04攻击类型 | N49: 单一基础伤害，不额外赠送一份元素伤害；来源身份不因SPELL攻击类型改变 | O49: 候选设计记录；未注册游戏Effect
A50: t01.asset.0051.effect.02 | B50: t01.asset.0051 | C50: W30 | D50: 震骨锤 | E50: 施加状态 | F50: 2 | G50: 重伤 | H50: 命中 | I50: 敌方 | J50: WEAPON | K50: 钝击 | L50: 土 | M50: 02核心状态／OP_ADD；01 M02/M03/M07 | N50: 施加结果以合法应用返回值判断，不用状态池净增量；即时转盾不抹去成功施加。具体效果与施加时序依02和核心01，不由七系标签自动增加额外伤害。 | O50: 候选设计记录；未注册游戏Effect
A51: t01.asset.0052.effect.01 | B51: t01.asset.0052 | C51: W31 | D51: 清风印 | E51: 直接伤害 | F51: 13 | H51: 合法发动并按命中结算 | I51: 敌方 | J51: WEAPON | K51: 钝击 | L51: 风 | M51: 01 M06 A01；04攻击类型 | N51: 单一基础伤害，不额外赠送一份元素伤害；来源身份不因SPELL攻击类型改变 | O51: 候选设计记录；未注册游戏Effect
A52: t01.asset.0052.effect.02 | B52: t01.asset.0052 | C52: W31 | D52: 清风印 | E52: 施加状态 | F52: 1 | G52: 驱散 | H52: 命中 | I52: 敌方 | J52: WEAPON | K52: 钝击 | L52: 风 | M52: 02核心状态／OP_ADD；01 M02/M03/M07 | N52: 施加结果以合法应用返回值判断，不用状态池净增量；即时转盾不抹去成功施加。具体效果与施加时序依02和核心01，不由七系标签自动增加额外伤害。 | O52: 候选设计记录；未注册游戏Effect
A53: t01.asset.0053.effect.01 | B53: t01.asset.0053 | C53: W32 | D53: 荆鞭 | E53: 直接伤害 | F53: 16 | H53: 合法发动并按命中结算 | I53: 敌方 | J53: WEAPON | K53: 钝击 | L53: 木 | M53: 01 M06 A01；04攻击类型 | N53: 单一基础伤害，不额外赠送一份元素伤害；来源身份不因SPELL攻击类型改变 | O53: 候选设计记录；未注册游戏Effect
A54: t01.asset.0053.effect.02 | B54: t01.asset.0053 | C54: W32 | D54: 荆鞭 | E54: 施加状态 | F54: 1 | G54: 缠绕 | H54: 命中 | I54: 敌方 | J54: WEAPON | K54: 钝击 | L54: 木 | M54: 02核心状态／OP_ADD；01 M02/M03/M07 | N54: 施加结果以合法应用返回值判断，不用状态池净增量；即时转盾不抹去成功施加。缠绕由后续合格火、雷伤害利用；木攻击本身不因此获得火雷增幅。 | O54: 候选设计记录；未注册游戏Effect
A55: t01.asset.0054.effect.01 | B55: t01.asset.0054 | C55: W33 | D55: 赤焰枪 | E55: 直接伤害 | F55: 36 | H55: 合法发动并按命中结算 | I55: 敌方 | J55: WEAPON | K55: 穿刺 | L55: 火 | M55: 01 M06 A01；04攻击类型 | N55: 单一基础伤害，不额外赠送一份元素伤害；来源身份不因SPELL攻击类型改变 | O55: 候选设计记录；未注册游戏Effect
A56: t01.asset.0054.effect.02 | B56: t01.asset.0054 | C56: W33 | D56: 赤焰枪 | E56: 施加状态 | F56: 2 | G56: 灼烧 | H56: 命中 | I56: 敌方 | J56: WEAPON | K56: 穿刺 | L56: 火 | M56: 02核心状态／OP_ADD；01 M02/M03/M07 | N56: 施加结果以合法应用返回值判断，不用状态池净增量；即时转盾不抹去成功施加。具体效果与施加时序依02和核心01，不由七系标签自动增加额外伤害。 | O56: 候选设计记录；未注册游戏Effect
A57: t01.asset.0055.effect.01 | B57: t01.asset.0055 | C57: A01 | D57: 细布衣 | E57: 护甲上限贡献 | F57: 13 | H57: 上阵静态贡献 | I57: 自身 | J57: ARMOR | K57: 无攻击 | L57: 无属性 | M57: 01 M06 I11；04防具 | N57: 只加上限，不立即回满；法器不参加甲型或防御元素投票 | O57: 候选设计记录；未注册游戏Effect
A58: t01.asset.0055.effect.02 | B58: t01.asset.0055 | C58: A01 | D58: 细布衣 | E58: 恢复当前护甲 | F58: 7 | H58: 自身轮转CD合法发动 | I58: 自身 | J58: ARMOR | K58: 无攻击 | L58: 无属性 | M58: 01 M06 C01 | N58: 不增加上限；与受击Buff独立计时 | O58: 候选设计记录；未注册游戏Effect
A59: t01.asset.0056.effect.01 | B59: t01.asset.0056 | C59: A02 | D59: 水纹衣 | E59: 护甲上限贡献 | F59: 12 | H59: 上阵静态贡献 | I59: 自身 | J59: ARMOR | K59: 无攻击 | L59: 水 | M59: 01 M06 I11；04防具 | N59: 只加上限，不立即回满；法器不参加甲型或防御元素投票 | O59: 候选设计记录；未注册游戏Effect
A60: t01.asset.0056.effect.02 | B60: t01.asset.0056 | C60: A02 | D60: 水纹衣 | E60: 恢复当前护甲 | F60: 6 | H60: 自身轮转CD合法发动 | I60: 自身 | J60: ARMOR | K60: 无攻击 | L60: 水 | M60: 01 M06 C01 | N60: 不增加上限；与受击Buff独立计时 | O60: 候选设计记录；未注册游戏Effect
A61: t01.asset.0056.effect.03 | B61: t01.asset.0056 | C61: A02 | D61: 水纹衣 | E61: 施加状态 | F61: 1 | G61: 润脉 | H61: 轮转 | I61: 自身 | J61: ARMOR | K61: 无攻击 | L61: 水 | M61: 02核心状态／OP_ADD；01 M02/M03/M07 | N61: 施加结果以合法应用返回值判断，不用状态池净增量；即时转盾不抹去成功施加。具体效果与施加时序依02和核心01，不由七系标签自动增加额外伤害。 | O61: 候选设计记录；未注册游戏Effect
A62: t01.asset.0057.effect.01 | B62: t01.asset.0057 | C62: A03 | D62: 札甲 | E62: 护甲上限贡献 | F62: 18 | H62: 上阵静态贡献 | I62: 自身 | J62: ARMOR | K62: 无攻击 | L62: 无属性 | M62: 01 M06 I11；04防具 | N62: 只加上限，不立即回满；法器不参加甲型或防御元素投票 | O62: 候选设计记录；未注册游戏Effect
A63: t01.asset.0057.effect.02 | B63: t01.asset.0057 | C63: A03 | D63: 札甲 | E63: 恢复当前护甲 | F63: 8 | H63: 自身轮转CD合法发动 | I63: 自身 | J63: ARMOR | K63: 无攻击 | L63: 无属性 | M63: 01 M06 C01 | N63: 不增加上限；与受击Buff独立计时 | O63: 候选设计记录；未注册游戏Effect
A64: t01.asset.0058.effect.01 | B64: t01.asset.0058 | C64: A04 | D64: 赤铜甲 | E64: 护甲上限贡献 | F64: 16 | H64: 上阵静态贡献 | I64: 自身 | J64: ARMOR | K64: 无攻击 | L64: 火 | M64: 01 M06 I11；04防具 | N64: 只加上限，不立即回满；法器不参加甲型或防御元素投票 | O64: 候选设计记录；未注册游戏Effect
A65: t01.asset.0058.effect.02 | B65: t01.asset.0058 | C65: A04 | D65: 赤铜甲 | E65: 恢复当前护甲 | F65: 6 | H65: 自身轮转CD合法发动 | I65: 自身 | J65: ARMOR | K65: 无攻击 | L65: 火 | M65: 01 M06 C01 | N65: 不增加上限；与受击Buff独立计时 | O65: 候选设计记录；未注册游戏Effect
A66: t01.asset.0058.effect.03 | B66: t01.asset.0058 | C66: A04 | D66: 赤铜甲 | E66: 施加状态 | F66: 2 | G66: 附炎 | H66: 受击 | I66: 自身 | J66: ARMOR | K66: 无攻击 | L66: 火 | M66: 02核心状态／OP_ADD；01 M02/M03/M07 | N66: 施加结果以合法应用返回值判断，不用状态池净增量；即时转盾不抹去成功施加。独立9秒；开战先倒数，归零后等待合格受击，成功施加后才重开；回甲CD独立。具体效果与施加时序依02和核心01，不由七系标签自动增加额外伤害。 | O66: 候选设计记录；未注册游戏Effect
A67: t01.asset.0059.effect.01 | B67: t01.asset.0059 | C67: A06 | D67: 雷纹法袍 | E67: 护甲上限贡献 | F67: 14 | H67: 上阵静态贡献 | I67: 自身 | J67: ARMOR | K67: 无攻击 | L67: 雷 | M67: 01 M06 I11；04防具 | N67: 只加上限，不立即回满；法器不参加甲型或防御元素投票 | O67: 候选设计记录；未注册游戏Effect
A68: t01.asset.0059.effect.02 | B68: t01.asset.0059 | C68: A06 | D68: 雷纹法袍 | E68: 恢复当前护甲 | F68: 6 | H68: 自身轮转CD合法发动 | I68: 自身 | J68: ARMOR | K68: 无攻击 | L68: 雷 | M68: 01 M06 C01 | N68: 不增加上限；与受击Buff独立计时 | O68: 候选设计记录；未注册游戏Effect
A69: t01.asset.0059.effect.03 | B69: t01.asset.0059 | C69: A06 | D69: 雷纹法袍 | E69: 施加状态 | F69: 2 | G69: 雷蕴 | H69: 轮转 | I69: 自身 | J69: ARMOR | K69: 无攻击 | L69: 雷 | M69: 02核心状态／OP_ADD；01 M02/M03/M07 | N69: 施加结果以合法应用返回值判断，不用状态池净增量；即时转盾不抹去成功施加。具体效果与施加时序依02和核心01，不由七系标签自动增加额外伤害。 | O69: 候选设计记录；未注册游戏Effect
A70: t01.asset.0060.effect.01 | B70: t01.asset.0060 | C70: A07 | D70: 皮帽 | E70: 护甲上限贡献 | F70: 4 | H70: 上阵静态贡献 | I70: 自身 | J70: ARMOR | K70: 无攻击 | L70: 风 | M70: 01 M06 I11；04防具 | N70: 只加上限，不立即回满；法器不参加甲型或防御元素投票 | O70: 候选设计记录；未注册游戏Effect
A71: t01.asset.0060.effect.02 | B71: t01.asset.0060 | C71: A07 | D71: 皮帽 | E71: 恢复当前护甲 | F71: 2 | H71: 自身轮转CD合法发动 | I71: 自身 | J71: ARMOR | K71: 无攻击 | L71: 风 | M71: 01 M06 C01 | N71: 不增加上限；与受击Buff独立计时 | O71: 候选设计记录；未注册游戏Effect
A72: t01.asset.0060.effect.03 | B72: t01.asset.0060 | C72: A07 | D72: 皮帽 | E72: 施加状态 | F72: 1 | G72: 轻灵 | H72: 受击 | I72: 自身 | J72: ARMOR | K72: 无攻击 | L72: 风 | M72: 02核心状态／OP_ADD；01 M02/M03/M07 | N72: 施加结果以合法应用返回值判断，不用状态池净增量；即时转盾不抹去成功施加。独立9秒；开战先倒数，归零后等待合格受击，成功施加后才重开；回甲CD独立。具体效果与施加时序依02和核心01，不由七系标签自动增加额外伤害。 | O72: 候选设计记录；未注册游戏Effect
A73: t01.asset.0061.effect.01 | B73: t01.asset.0061 | C73: A08 | D73: 铁盔 | E73: 护甲上限贡献 | F73: 4 | H73: 上阵静态贡献 | I73: 自身 | J73: ARMOR | K73: 无攻击 | L73: 土 | M73: 01 M06 I11；04防具 | N73: 只加上限，不立即回满；法器不参加甲型或防御元素投票 | O73: 候选设计记录；未注册游戏Effect
A74: t01.asset.0061.effect.02 | B74: t01.asset.0061 | C74: A08 | D74: 铁盔 | E74: 恢复当前护甲 | F74: 3 | H74: 自身轮转CD合法发动 | I74: 自身 | J74: ARMOR | K74: 无攻击 | L74: 土 | M74: 01 M06 C01 | N74: 不增加上限；与受击Buff独立计时 | O74: 候选设计记录；未注册游戏Effect
A75: t01.asset.0061.effect.03 | B75: t01.asset.0061 | C75: A08 | D75: 铁盔 | E75: 施加状态 | F75: 1 | G75: 坚韧 | H75: 受击 | I75: 自身 | J75: ARMOR | K75: 无攻击 | L75: 土 | M75: 02核心状态／OP_ADD；01 M02/M03/M07 | N75: 施加结果以合法应用返回值判断，不用状态池净增量；即时转盾不抹去成功施加。独立9秒；开战先倒数，归零后等待合格受击，成功施加后才重开；回甲CD独立。具体效果与施加时序依02和核心01，不由七系标签自动增加额外伤害。 | O75: 候选设计记录；未注册游戏Effect
A76: t01.asset.0062.effect.01 | B76: t01.asset.0062 | C76: A09 | D76: 木纹冠 | E76: 护甲上限贡献 | F76: 4 | H76: 上阵静态贡献 | I76: 自身 | J76: ARMOR | K76: 无攻击 | L76: 木 | M76: 01 M06 I11；04防具 | N76: 只加上限，不立即回满；法器不参加甲型或防御元素投票 | O76: 候选设计记录；未注册游戏Effect
A77: t01.asset.0062.effect.02 | B77: t01.asset.0062 | C77: A09 | D77: 木纹冠 | E77: 恢复当前护甲 | F77: 2 | H77: 自身轮转CD合法发动 | I77: 自身 | J77: ARMOR | K77: 无攻击 | L77: 木 | M77: 01 M06 C01 | N77: 不增加上限；与受击Buff独立计时 | O77: 候选设计记录；未注册游戏Effect
A78: t01.asset.0062.effect.03 | B78: t01.asset.0062 | C78: A09 | D78: 木纹冠 | E78: 施加状态 | F78: 1 | G78: 生机 | H78: 轮转 | I78: 自身 | J78: ARMOR | K78: 无攻击 | L78: 木 | M78: 02核心状态／OP_ADD；01 M02/M03/M07 | N78: 施加结果以合法应用返回值判断，不用状态池净增量；即时转盾不抹去成功施加。具体效果与施加时序依02和核心01，不由七系标签自动增加额外伤害。 | O78: 候选设计记录；未注册游戏Effect
A79: t01.asset.0063.effect.01 | B79: t01.asset.0063 | C79: A10 | D79: 风纹冠 | E79: 护甲上限贡献 | F79: 3 | H79: 上阵静态贡献 | I79: 自身 | J79: ARMOR | K79: 无攻击 | L79: 风 | M79: 01 M06 I11；04防具 | N79: 只加上限，不立即回满；法器不参加甲型或防御元素投票 | O79: 候选设计记录；未注册游戏Effect
A80: t01.asset.0063.effect.02 | B80: t01.asset.0063 | C80: A10 | D80: 风纹冠 | E80: 恢复当前护甲 | F80: 2 | H80: 自身轮转CD合法发动 | I80: 自身 | J80: ARMOR | K80: 无攻击 | L80: 风 | M80: 01 M06 C01 | N80: 不增加上限；与受击Buff独立计时 | O80: 候选设计记录；未注册游戏Effect
A81: t01.asset.0063.effect.03 | B81: t01.asset.0063 | C81: A10 | D81: 风纹冠 | E81: 施加状态 | F81: 1 | G81: 轻灵 | H81: 轮转 | I81: 自身 | J81: ARMOR | K81: 无攻击 | L81: 风 | M81: 02核心状态／OP_ADD；01 M02/M03/M07 | N81: 施加结果以合法应用返回值判断，不用状态池净增量；即时转盾不抹去成功施加。具体效果与施加时序依02和核心01，不由七系标签自动增加额外伤害。 | O81: 候选设计记录；未注册游戏Effect
A82: t01.asset.0064.effect.01 | B82: t01.asset.0064 | C82: A11 | D82: 皮护臂 | E82: 护甲上限贡献 | F82: 3 | H82: 上阵静态贡献 | I82: 自身 | J82: ARMOR | K82: 无攻击 | L82: 金 | M82: 01 M06 I11；04防具 | N82: 只加上限，不立即回满；法器不参加甲型或防御元素投票 | O82: 候选设计记录；未注册游戏Effect
A83: t01.asset.0064.effect.02 | B83: t01.asset.0064 | C83: A11 | D83: 皮护臂 | E83: 恢复当前护甲 | F83: 2 | H83: 自身轮转CD合法发动 | I83: 自身 | J83: ARMOR | K83: 无攻击 | L83: 金 | M83: 01 M06 C01 | N83: 不增加上限；与受击Buff独立计时 | O83: 候选设计记录；未注册游戏Effect
A84: t01.asset.0064.effect.03 | B84: t01.asset.0064 | C84: A11 | D84: 皮护臂 | E84: 施加状态 | F84: 1 | G84: 反锋 | H84: 受击 | I84: 自身 | J84: ARMOR | K84: 无攻击 | L84: 金 | M84: 02核心状态／OP_ADD；01 M02/M03/M07 | N84: 施加结果以合法应用返回值判断，不用状态池净增量；即时转盾不抹去成功施加。独立9秒；开战先倒数，归零后等待合格受击，成功施加后才重开；回甲CD独立。具体效果与施加时序依02和核心01，不由七系标签自动增加额外伤害。 | O84: 候选设计记录；未注册游戏Effect
A85: t01.asset.0065.effect.01 | B85: t01.asset.0065 | C85: A12 | D85: 铁护腕 | E85: 护甲上限贡献 | F85: 3 | H85: 上阵静态贡献 | I85: 自身 | J85: ARMOR | K85: 无攻击 | L85: 金 | M85: 01 M06 I11；04防具 | N85: 只加上限，不立即回满；法器不参加甲型或防御元素投票 | O85: 候选设计记录；未注册游戏Effect
A86: t01.asset.0065.effect.02 | B86: t01.asset.0065 | C86: A12 | D86: 铁护腕 | E86: 恢复当前护甲 | F86: 4 | H86: 自身轮转CD合法发动 | I86: 自身 | J86: ARMOR | K86: 无攻击 | L86: 金 | M86: 01 M06 C01 | N86: 不增加上限；与受击Buff独立计时 | O86: 候选设计记录；未注册游戏Effect
A87: t01.asset.0065.effect.03 | B87: t01.asset.0065 | C87: A12 | D87: 铁护腕 | E87: 施加状态 | F87: 1 | G87: 反锋 | H87: 轮转 | I87: 自身 | J87: ARMOR | K87: 无攻击 | L87: 金 | M87: 02核心状态／OP_ADD；01 M02/M03/M07 | N87: 施加结果以合法应用返回值判断，不用状态池净增量；即时转盾不抹去成功施加。具体效果与施加时序依02和核心01，不由七系标签自动增加额外伤害。 | O87: 候选设计记录；未注册游戏Effect
A88: t01.asset.0066.effect.01 | B88: t01.asset.0066 | C88: A13 | D88: 水纹护臂 | E88: 护甲上限贡献 | F88: 3 | H88: 上阵静态贡献 | I88: 自身 | J88: ARMOR | K88: 无攻击 | L88: 水 | M88: 01 M06 I11；04防具 | N88: 只加上限，不立即回满；法器不参加甲型或防御元素投票 | O88: 候选设计记录；未注册游戏Effect
A89: t01.asset.0066.effect.02 | B89: t01.asset.0066 | C89: A13 | D89: 水纹护臂 | E89: 恢复当前护甲 | F89: 2 | H89: 自身轮转CD合法发动 | I89: 自身 | J89: ARMOR | K89: 无攻击 | L89: 水 | M89: 01 M06 C01 | N89: 不增加上限；与受击Buff独立计时 | O89: 候选设计记录；未注册游戏Effect
A90: t01.asset.0066.effect.03 | B90: t01.asset.0066 | C90: A13 | D90: 水纹护臂 | E90: 施加状态 | F90: 1 | G90: 润脉 | H90: 受击 | I90: 自身 | J90: ARMOR | K90: 无攻击 | L90: 水 | M90: 02核心状态／OP_ADD；01 M02/M03/M07 | N90: 施加结果以合法应用返回值判断，不用状态池净增量；即时转盾不抹去成功施加。独立9秒；开战先倒数，归零后等待合格受击，成功施加后才重开；回甲CD独立。具体效果与施加时序依02和核心01，不由七系标签自动增加额外伤害。 | O90: 候选设计记录；未注册游戏Effect
A91: t01.asset.0067.effect.01 | B91: t01.asset.0067 | C91: A14 | D91: 雷纹护腕 | E91: 护甲上限贡献 | F91: 4 | H91: 上阵静态贡献 | I91: 自身 | J91: ARMOR | K91: 无攻击 | L91: 雷 | M91: 01 M06 I11；04防具 | N91: 只加上限，不立即回满；法器不参加甲型或防御元素投票 | O91: 候选设计记录；未注册游戏Effect
A92: t01.asset.0067.effect.02 | B92: t01.asset.0067 | C92: A14 | D92: 雷纹护腕 | E92: 恢复当前护甲 | F92: 3 | H92: 自身轮转CD合法发动 | I92: 自身 | J92: ARMOR | K92: 无攻击 | L92: 雷 | M92: 01 M06 C01 | N92: 不增加上限；与受击Buff独立计时 | O92: 候选设计记录；未注册游戏Effect
A93: t01.asset.0067.effect.03 | B93: t01.asset.0067 | C93: A14 | D93: 雷纹护腕 | E93: 施加状态 | F93: 2 | G93: 雷蕴 | H93: 受击 | I93: 自身 | J93: ARMOR | K93: 无攻击 | L93: 雷 | M93: 02核心状态／OP_ADD；01 M02/M03/M07 | N93: 施加结果以合法应用返回值判断，不用状态池净增量；即时转盾不抹去成功施加。独立9秒；开战先倒数，归零后等待合格受击，成功施加后才重开；回甲CD独立。具体效果与施加时序依02和核心01，不由七系标签自动增加额外伤害。 | O93: 候选设计记录；未注册游戏Effect
A94: t01.asset.0068.effect.01 | B94: t01.asset.0068 | C94: A15 | D94: 皮护腿 | E94: 护甲上限贡献 | F94: 4 | H94: 上阵静态贡献 | I94: 自身 | J94: ARMOR | K94: 无攻击 | L94: 风 | M94: 01 M06 I11；04防具 | N94: 只加上限，不立即回满；法器不参加甲型或防御元素投票 | O94: 候选设计记录；未注册游戏Effect
A95: t01.asset.0068.effect.02 | B95: t01.asset.0068 | C95: A15 | D95: 皮护腿 | E95: 恢复当前护甲 | F95: 2 | H95: 自身轮转CD合法发动 | I95: 自身 | J95: ARMOR | K95: 无攻击 | L95: 风 | M95: 01 M06 C01 | N95: 不增加上限；与受击Buff独立计时 | O95: 候选设计记录；未注册游戏Effect
A96: t01.asset.0068.effect.03 | B96: t01.asset.0068 | C96: A15 | D96: 皮护腿 | E96: 施加状态 | F96: 1 | G96: 轻灵 | H96: 轮转 | I96: 自身 | J96: ARMOR | K96: 无攻击 | L96: 风 | M96: 02核心状态／OP_ADD；01 M02/M03/M07 | N96: 施加结果以合法应用返回值判断，不用状态池净增量；即时转盾不抹去成功施加。具体效果与施加时序依02和核心01，不由七系标签自动增加额外伤害。 | O96: 候选设计记录；未注册游戏Effect
A97: t01.asset.0069.effect.01 | B97: t01.asset.0069 | C97: A16 | D97: 铁胫甲 | E97: 护甲上限贡献 | F97: 4 | H97: 上阵静态贡献 | I97: 自身 | J97: ARMOR | K97: 无攻击 | L97: 土 | M97: 01 M06 I11；04防具 | N97: 只加上限，不立即回满；法器不参加甲型或防御元素投票 | O97: 候选设计记录；未注册游戏Effect
A98: t01.asset.0069.effect.02 | B98: t01.asset.0069 | C98: A16 | D98: 铁胫甲 | E98: 恢复当前护甲 | F98: 5 | H98: 自身轮转CD合法发动 | I98: 自身 | J98: ARMOR | K98: 无攻击 | L98: 土 | M98: 01 M06 C01 | N98: 不增加上限；与受击Buff独立计时 | O98: 候选设计记录；未注册游戏Effect
A99: t01.asset.0069.effect.03 | B99: t01.asset.0069 | C99: A16 | D99: 铁胫甲 | E99: 施加状态 | F99: 2 | G99: 坚韧 | H99: 受击 | I99: 自身 | J99: ARMOR | K99: 无攻击 | L99: 土 | M99: 02核心状态／OP_ADD；01 M02/M03/M07 | N99: 施加结果以合法应用返回值判断，不用状态池净增量；即时转盾不抹去成功施加。独立9秒；开战先倒数，归零后等待合格受击，成功施加后才重开；回甲CD独立。具体效果与施加时序依02和核心01，不由七系标签自动增加额外伤害。 | O99: 候选设计记录；未注册游戏Effect
A100: t01.asset.0070.effect.01 | B100: t01.asset.0070 | C100: A17 | D100: 水纹护腿 | E100: 护甲上限贡献 | F100: 4 | H100: 上阵静态贡献 | I100: 自身 | J100: ARMOR | K100: 无攻击 | L100: 水 | M100: 01 M06 I11；04防具 | N100: 只加上限，不立即回满；法器不参加甲型或防御元素投票 | O100: 候选设计记录；未注册游戏Effect
A101: t01.asset.0070.effect.02 | B101: t01.asset.0070 | C101: A17 | D101: 水纹护腿 | E101: 恢复当前护甲 | F101: 3 | H101: 自身轮转CD合法发动 | I101: 自身 | J101: ARMOR | K101: 无攻击 | L101: 水 | M101: 01 M06 C01 | N101: 不增加上限；与受击Buff独立计时 | O101: 候选设计记录；未注册游戏Effect
A102: t01.asset.0070.effect.03 | B102: t01.asset.0070 | C102: A17 | D102: 水纹护腿 | E102: 施加状态 | F102: 1 | G102: 润脉 | H102: 轮转 | I102: 自身 | J102: ARMOR | K102: 无攻击 | L102: 水 | M102: 02核心状态／OP_ADD；01 M02/M03/M07 | N102: 施加结果以合法应用返回值判断，不用状态池净增量；即时转盾不抹去成功施加。具体效果与施加时序依02和核心01，不由七系标签自动增加额外伤害。 | O102: 候选设计记录；未注册游戏Effect
...

Sheet 18_状态来源统计
A1: t01-08｜状态来源统计
A2: 2026-09-28 · 27下品＋88凡品＝115件 · 候选数值／当前规则／游戏实现分列 · 不含平衡测试结论
A5: 系别 | B5: 状态 | C5: 独立来源数 | D5: 具体来源 | E5: 计数口径 | F5: 要求
A6: 金 | B6: 反锋 | C6: =COUNTIF('17_效果与触发'!$G$6:$G$171,B6) -> 4 | D6: A11 皮护臂；A12 铁护腕；A20 金纹护肩；A23 铁盾 | E6: 独立物品计数，不按重复发动或状态层数计；仅本批凡品 | F6: 至少2个来源
A7: 金 | B7: 锋痕 | C7: =COUNTIF('17_效果与触发'!$G$6:$G$171,B7) -> 3 | D7: W06 金纹刀；W09 金刚斧；F05 金光镜 | E7: 独立物品计数，不按重复发动或状态层数计；仅本批凡品 | F7: 至少2个来源
A8: 金 | B8: 流血 | C8: =COUNTIF('17_效果与触发'!$G$6:$G$171,B8) -> 3 | D8: W05 钢刀；W15 精铁匕；W28 刺血匕 | E8: 独立物品计数，不按重复发动或状态层数计；仅本批凡品 | F8: 至少2个来源
A9: 木 | B9: 生机 | C9: =COUNTIF('17_效果与触发'!$G$6:$G$171,B9) -> 4 | D9: A09 木纹冠；A18 藤甲护腿；A22 包铁木盾；F06 青木铃 | E9: 独立物品计数，不按重复发动或状态层数计；仅本批凡品 | F9: 至少2个来源
A10: 木 | B10: 毒蚀 | C10: =COUNTIF('17_效果与触发'!$G$6:$G$171,B10) -> 2 | D10: W24 藤鞭；H04 毒针 | E10: 独立物品计数，不按重复发动或状态层数计；仅本批凡品 | F10: 至少2个来源
A11: 木 | B11: 缠绕 | C11: =COUNTIF('17_效果与触发'!$G$6:$G$171,B11) -> 2 | D11: W17 青木枪；W32 荆鞭 | E11: 独立物品计数，不按重复发动或状态层数计；仅本批凡品 | F11: 至少2个来源
A12: 水 | B12: 润脉 | C12: =COUNTIF('17_效果与触发'!$G$6:$G$171,B12) -> 5 | D12: A02 水纹衣；A13 水纹护臂；A17 水纹护腿；A24 水纹盾；A31 润脉腰带 | E12: 独立物品计数，不按重复发动或状态层数计；仅本批凡品 | F12: 至少2个来源
A13: 水 | B13: 枯脉 | C13: =COUNTIF('17_效果与触发'!$G$6:$G$171,B13) -> 2 | D13: W12 水纹弓；F15 枯脉瓶 | E13: 独立物品计数，不按重复发动或状态层数计；仅本批凡品 | F13: 至少2个来源
A14: 水 | B14: 寒霜 | C14: =COUNTIF('17_效果与触发'!$G$6:$G$171,B14) -> 2 | D14: W03 寒水剑；F07 寒水珠 | E14: 独立物品计数，不按重复发动或状态层数计；仅本批凡品 | F14: 至少2个来源
A15: 火 | B15: 附炎 | C15: =COUNTIF('17_效果与触发'!$G$6:$G$171,B15) -> 4 | D15: A04 赤铜甲；A28 燎火护臂；A30 炎纹护肩；F08 火灵珠 | E15: 独立物品计数，不按重复发动或状态层数计；仅本批凡品 | F15: 至少2个来源
A16: 火 | B16: 灼烧 | C16: =COUNTIF('17_效果与触发'!$G$6:$G$171,B16) -> 2 | D16: W02 赤纹剑；W33 赤焰枪 | E16: 独立物品计数，不按重复发动或状态层数计；仅本批凡品 | F16: 至少2个来源
A17: 火 | B17: 破甲 | C17: =COUNTIF('17_效果与触发'!$G$6:$G$171,B17) -> 2 | D17: W07 赤焰刀；W20 炎纹锤 | E17: 独立物品计数，不按重复发动或状态层数计；仅本批凡品 | F17: 至少2个来源
... A26: 雷 | B26: 连环 | C26: =COUNTIF('17_效果与触发'!$G$6:$G$171,B26) -> 2 | D26: W14 雷纹弓；F17 锁雷环 | E26: 独立物品计数，不按重复发动或状态层数计；仅本批凡品 | F26: 至少2个来源

Sheet 19_凡品规则与模板
A1: t01-08｜凡品规则与模板
A2: 2026-09-28 · 27下品＋88凡品＝115件 · 候选数值／当前规则／游戏实现分列 · 不含平衡测试结论
A5: 规则ID | B5: 主题 | C5: 现行内容 | D5: 边界 | E5: 状态／依据
A6: FP-R01 | B6: 字段含义 | C6: 武器／暗器元素为攻击元素；防具为防御元素；法器为明确效果归类。 | D6: 标签不赠第二份伤害；仅金光镜／寒水珠有法器本体攻击。 | E6: 已按第2／3批合并
A7: FP-R02 | B7: 元素与单状态 | C7: 本批武器、防具、法器固定元素与其七系单状态匹配；无状态可有元素。 | D7: 不扩展到暗器；毒针仍无属性；丹药状态／减伤类别不作为防御投票。 | E7: 本批资产设计原则
A8: FP-R03 | B8: 品级权限 | C8: 凡品固定单元素＋一种简单状态按本批口径开放；三组具名基础联动单列。 | D8: 不扩双状态、复杂监听、来源改写、自由功能槽或凡品正式套装。 | E8: 须同步03 C010／C030
A9: FP-R04 | B9: 防御元素 | C9: 身甲每格2、其他防具每格1；NONE纳入最高候选，最高并列仍逐行扫描。 | D9: 无防具NONE；只有防具投票；不对元素决胜新增身甲优先。 | E9: FP02已确认
A10: FP-R05 | B10: 武器体力负担 | C10: 1把100%；2把所有体力成本＋25%；3把所有体力成本＋50%，按基础加算。 | D10: 本批比较按三把×1.5；具体影响留后测；不混用旧按占格＋5%口径。 | E10: 用户直接明确；更多把数不外推
A11: FP-R06 | B11: 首瓶丹药 | C11: 首瓶开局具备使用资格；只要未使用就不进CD；实际使用后进入完整CD。 | D11: 仍检查资源缺口／持续药效／容量等使用条件；不把首瓶就绪写成强制服用。 | E11: 用户直接明确；下品丹药同步
A12: FP-R07 | B12: 受击状态计时 | C12: 独立9秒；开战先走9秒，归零等待合格受击，成功施加后重开。 | D12: 普通回甲CD独立；施加成功读应用结果，不能以池净增量判断。 | E12: 复查明确，接01／02接口
A13: FP-R08 | B13: 普通灵障吸收 | C13: 符合普通防御路线的伤害按30%，实际扣值min(现灵障,进入阶段伤害×30%)。 | D13: 明确绕过该层的伤害不吸收；雷盾耗尽的同轮不接灵障；同轮原已启用灵障可继续承伤。 | E13: 核心01 §1.3／5.52～53／5.114～117
A14: FP-R09 | B14: 普通灵障再生成 | C14: 再次生成加进现有普通灵障池，实际增加不超过当前容量缺口；容量足够时10＋15＝25，溢出不存入。 | D14: 仅普通灵障；来源份额为返锋等合格效果保留，不能抹去来源。 | E14: 已确认
A15: FP-R10 | B15: 普通灵障容量 | C15: 当前普通灵障上限＝境界基础上限＋阵盘、法器及其他明确来源的上限加成。凡人10、炼气20、筑基30、结丹40、元婴50、化神60；上限加成暂不设统一封顶。池内存值仍受当前上限约束。 | D15: 不套用雷盾层数上限；不擅造境界上限。 | E15: 已确认
A16: FP-R11 | B16: 普通灵障生命周期 | C16: 战内不自然到期、不随时间衰减；剩余值保留到被消耗或战斗结束，战后清空。 | D16: 普通灵障与特殊盾分别保存；不把雷盾生层／替换当普通灵障到期。 | E16: 本次模板已补齐
... A19: FP-R14 | B19: 灵障珠发动与付费 | C19: F14灵障珠满上限仍正常发动，消耗6灵力并重开10.5秒CD，实际增加0；未满时实际增加min(15,容量缺口)，费用仍6。仍检查控制、资源等正常发动资格；费用不足不能发动。此空转支付是F14的已定策略，不自动推广其他资产。 | D19: 普通灵障生成接口与具体资产的发动门槛分开；满值不收费的建议未采用。 | E19: FP06已确认

Sheet 20_平衡核对
A1: t01-08｜平衡核对
A2: 2026-09-28 · 27下品＋88凡品＝115件 · 候选数值／当前规则／游戏实现分列 · 不含平衡测试结论
A5: 组合 | B5: 组合占格 | C5: 名义直伤每秒 | D5: 体力倍率 | E5: 修正后体力每秒 | F5: 行气珠理想供给每秒 | G5: 局限 | H5: 组合护甲上限 | I5: 名义回甲每秒 | J5: 首次药效时点
A6: 三把短刃 | B6: 3 | C6: ='02_武器'!J27/'02_武器'!K27+'02_武器'!J28/'02_武器'!K28+'02_武器'!J37/'02_武器'!K37 -> 6.3968254 | D6: 1.5 | E6: =('02_武器'!L27/'02_武器'!K27+'02_武器'!L28/'02_武器'!K28+'02_武器'!L37/'02_武器'!K37)*D6 -> 2.5238095 | F6: ='04_法器'!L11/'04_法器'!J11 -> 2.4 | G6: 命中／暴击／状态／防御／首轮／资源不足均未计；仅名义比值，不是模拟
A7: 赤焰枪 | B7: 3 | C7: ='02_武器'!J41/'02_武器'!K41 -> 4 | D7: 1 | E7: =('02_武器'!L41/'02_武器'!K41)*D7 -> 0.88888889 | F7: ='04_法器'!L11/'04_法器'!J11 -> 2.4 | G7: 命中／暴击／状态／防御／首轮／资源不足均未计；仅名义比值，不是模拟
A8: 水纹三件 | B8: 4 | G8: 状态收益／满甲溢出／首轮及控制均未计；候选参数比值，不是平衡结论 | H8: ='09_基础防具联动'!J8 -> 22 | I8: ='09_基础防具联动'!K8/'09_基础防具联动'!L8+'03_防具'!L25/'03_防具'!J25+'03_防具'!L29/'03_防具'!J29 -> 1.5882353
A9: 铁甲三件 | B9: 4 | G9: 状态收益／满甲溢出／首轮及控制均未计；候选参数比值，不是平衡结论 | H9: ='09_基础防具联动'!J9 -> 29 | I9: ='09_基础防具联动'!K9/'09_基础防具联动'!L9+'03_防具'!L24/'03_防具'!J24+'03_防具'!L28/'03_防具'!J28 -> 2.2653595
A10: 雷纹三件 | B10: 4 | G10: 状态收益／满甲溢出／首轮及控制均未计；候选参数比值，不是平衡结论 | H10: ='09_基础防具联动'!J10 -> 25 | I10: ='09_基础防具联动'!K10/'09_基础防具联动'!L10+'03_防具'!L26/'03_防具'!J26+'03_防具'!L39/'03_防具'!J39 -> 1.3333333
A11: 丹药开局 | G11: 使用资格不等于强制服药；仍检查资源缺口等条件 | J11: 回春丹最早t0用、第2/4/6秒跳；五行药t0可生效12秒，使用后CD22.5秒。

Sheet 21_修订与停列
A1: t01-08｜修订与停列
A2: 2026-09-28 · 27下品＋88凡品＝115件 · 候选数值／当前规则／游戏实现分列 · 不含平衡测试结论
A5: 编号 | B5: 修改项 | C5: 旧值 | D5: 现值 | E5: 依据 | F5: 处理
A6: W05 | B6: element | C6: 无属性 | D6: 金 | E6: 第2／3批覆盖 | F6: 已合入分类正文
A7: W08 | B7: element | C7: 无属性 | D7: 土 | E7: 第2／3批覆盖 | F7: 已合入分类正文
A8: W28 | B8: element | C8: 无属性 | D8: 金 | E8: 第2／3批覆盖 | F8: 已合入分类正文
A9: A07 | B9: element | C9: 无属性 | D9: 风 | E9: 第2／3批覆盖 | F9: 已合入分类正文
A10: A15 | B10: element | C10: 无属性 | D10: 风 | E10: 第2／3批覆盖 | F10: 已合入分类正文
A11: A21 | B11: element | C11: 无属性 | D11: 风 | E11: 第2／3批覆盖 | F11: 已合入分类正文
A12: A08 | B12: element | C12: 无属性 | D12: 土 | E12: 第2／3批覆盖 | F12: 已合入分类正文
A13: A16 | B13: element | C13: 无属性 | D13: 土 | E13: 第2／3批覆盖 | F13: 已合入分类正文
A14: A19 | B14: element | C14: 无属性 | D14: 土 | E14: 第2／3批覆盖 | F14: 已合入分类正文
A15: A11 | B15: element | C15: 无属性 | D15: 金 | E15: 第2／3批覆盖 | F15: 已合入分类正文
A16: A12 | B16: element | C16: 无属性 | D16: 金 | E16: 第2／3批覆盖 | F16: 已合入分类正文
... A37: A27 | B37: 停列 | C37: 历史候选编号 | D37: 不参与本批88计数；不复用编号 | E37: 第1／2批 | F37: 保留停列索引

Sheet 22_元素与状态核对
A1: t01-08｜元素与状态核对
A2: 2026-09-28 · 27下品＋88凡品＝115件 · 候选数值／当前规则／游戏实现分列 · 不含平衡测试结论
A5: 类别 | B5: NONE | C5: 金 | D5: 木 | E5: 水 | F5: 火 | G5: 土 | H5: 风 | I5: 雷 | J5: 合计 | K5: 无核心状态 | L5: 无核心状态但有元素 | M5: 口径
A6: 武器 | B6: =COUNTIFS('02_武器'!$C$6:$C$41,"凡品",'02_武器'!$D$6:$D$41,B$5) -> 1 | C6: =COUNTIFS('02_武器'!$C$6:$C$41,"凡品",'02_武器'!$D$6:$D$41,C$5) -> 5 | D6: =COUNTIFS('02_武器'!$C$6:$C$41,"凡品",'02_武器'!$D$6:$D$41,D$5) -> 4 | E6: =COUNTIFS('02_武器'!$C$6:$C$41,"凡品",'02_武器'!$D$6:$D$41,E$5) -> 2 | F6: =COUNTIFS('02_武器'!$C$6:$C$41,"凡品",'02_武器'!$D$6:$D$41,F$5) -> 4 | G6: =COUNTIFS('02_武器'!$C$6:$C$41,"凡品",'02_武器'!$D$6:$D$41,G$5) -> 5 | H6: =COUNTIFS('02_武器'!$C$6:$C$41,"凡品",'02_武器'!$D$6:$D$41,H$5) -> 2 | I6: =COUNTIFS('02_武器'!$C$6:$C$41,"凡品",'02_武器'!$D$6:$D$41,I$5) -> 4 | J6: =SUM(B6:I6) -> 27 | K6: =COUNTIFS('02_武器'!$C$6:$C$41,"凡品",'02_武器'!$X$6:$X$41,"") -> 3 | L6: =COUNTIFS('02_武器'!$C$6:$C$41,"凡品",'02_武器'!$X$6:$X$41,"",'02_武器'!$D$6:$D$41,"<>NONE") -> 2 | M6: 仅本批凡品及21核心状态；不施加核心状态可有元素。丹药减伤属S3，另按减伤字段登记，不作防御投票。
A7: 防具 | B7: =COUNTIFS('03_防具'!$C$6:$C$41,"凡品",'03_防具'!$D$6:$D$41,B$5) -> 3 | C7: =COUNTIFS('03_防具'!$C$6:$C$41,"凡品",'03_防具'!$D$6:$D$41,C$5) -> 4 | D7: =COUNTIFS('03_防具'!$C$6:$C$41,"凡品",'03_防具'!$D$6:$D$41,D$5) -> 3 | E7: =COUNTIFS('03_防具'!$C$6:$C$41,"凡品",'03_防具'!$D$6:$D$41,E$5) -> 5 | F7: =COUNTIFS('03_防具'!$C$6:$C$41,"凡品",'03_防具'!$D$6:$D$41,F$5) -> 3 | G7: =COUNTIFS('03_防具'!$C$6:$C$41,"凡品",'03_防具'!$D$6:$D$41,G$5) -> 3 | H7: =COUNTIFS('03_防具'!$C$6:$C$41,"凡品",'03_防具'!$D$6:$D$41,H$5) -> 4 | I7: =COUNTIFS('03_防具'!$C$6:$C$41,"凡品",'03_防具'!$D$6:$D$41,I$5) -> 3 | J7: =SUM(B7:I7) -> 28 | K7: =COUNTIFS('03_防具'!$C$6:$C$41,"凡品",'03_防具'!$X$6:$X$41,"") -> 3 | L7: =COUNTIFS('03_防具'!$C$6:$C$41,"凡品",'03_防具'!$X$6:$X$41,"",'03_防具'!$D$6:$D$41,"<>NONE") -> 0 | M7: 仅本批凡品及21核心状态；不施加核心状态可有元素。丹药减伤属S3，另按减伤字段登记，不作防御投票。
A8: 法器 | B8: =COUNTIFS('04_法器'!$C$6:$C$27,"凡品",'04_法器'!$D$6:$D$27,B$5) -> 7 | C8: =COUNTIFS('04_法器'!$C$6:$C$27,"凡品",'04_法器'!$D$6:$D$27,C$5) -> 1 | D8: =COUNTIFS('04_法器'!$C$6:$C$27,"凡品",'04_法器'!$D$6:$D$27,D$5) -> 1 | E8: =COUNTIFS('04_法器'!$C$6:$C$27,"凡品",'04_法器'!$D$6:$D$27,E$5) -> 2 | F8: =COUNTIFS('04_法器'!$C$6:$C$27,"凡品",'04_法器'!$D$6:$D$27,F$5) -> 1 | G8: =COUNTIFS('04_法器'!$C$6:$C$27,"凡品",'04_法器'!$D$6:$D$27,G$5) -> 1 | H8: =COUNTIFS('04_法器'!$C$6:$C$27,"凡品",'04_法器'!$D$6:$D$27,H$5) -> 2 | I8: =COUNTIFS('04_法器'!$C$6:$C$27,"凡品",'04_法器'!$D$6:$D$27,I$5) -> 3 | J8: =SUM(B8:I8) -> 18 | K8: =COUNTIFS('04_法器'!$C$6:$C$27,"凡品",'04_法器'!$AC$6:$AC$27,"") -> 7 | L8: =COUNTIFS('04_法器'!$C$6:$C$27,"凡品",'04_法器'!$AC$6:$AC$27,"",'04_法器'!$D$6:$D$27,"<>NONE") -> 0 | M8: 仅本批凡品及21核心状态；不施加核心状态可有元素。丹药减伤属S3，另按减伤字段登记，不作防御投票。
A9: 丹药 | B9: =COUNTIFS('05_丹药'!$C$6:$C$21,"凡品",'05_丹药'!$D$6:$D$21,B$5) -> 10 | C9: =COUNTIFS('05_丹药'!$C$6:$C$21,"凡品",'05_丹药'!$D$6:$D$21,C$5) -> 0 | D9: =COUNTIFS('05_丹药'!$C$6:$C$21,"凡品",'05_丹药'!$D$6:$D$21,D$5) -> 0 | E9: =COUNTIFS('05_丹药'!$C$6:$C$21,"凡品",'05_丹药'!$D$6:$D$21,E$5) -> 0 | F9: =COUNTIFS('05_丹药'!$C$6:$C$21,"凡品",'05_丹药'!$D$6:$D$21,F$5) -> 0 | G9: =COUNTIFS('05_丹药'!$C$6:$C$21,"凡品",'05_丹药'!$D$6:$D$21,G$5) -> 0 | H9: =COUNTIFS('05_丹药'!$C$6:$C$21,"凡品",'05_丹药'!$D$6:$D$21,H$5) -> 0 | I9: =COUNTIFS('05_丹药'!$C$6:$C$21,"凡品",'05_丹药'!$D$6:$D$21,I$5) -> 0 | J9: =SUM(B9:I9) -> 10 | K9: =COUNTIFS('05_丹药'!$C$6:$C$21,"凡品",'05_丹药'!$AB$6:$AB$21,"") -> 9 | L9: =COUNTIFS('05_丹药'!$C$6:$C$21,"凡品",'05_丹药'!$AB$6:$AB$21,"",'05_丹药'!$D$6:$D$21,"<>NONE") -> 0 | M9: 仅本批凡品及21核心状态；不施加核心状态可有元素。丹药减伤属S3，另按减伤字段登记，不作防御投票。
A10: 符箓 | B10: =COUNTIFS('06_符箓'!$C$6:$C$6,"凡品",'06_符箓'!$D$6:$D$6,B$5) -> 0 | C10: =COUNTIFS('06_符箓'!$C$6:$C$6,"凡品",'06_符箓'!$D$6:$D$6,C$5) -> 0 | D10: =COUNTIFS('06_符箓'!$C$6:$C$6,"凡品",'06_符箓'!$D$6:$D$6,D$5) -> 0 | E10: =COUNTIFS('06_符箓'!$C$6:$C$6,"凡品",'06_符箓'!$D$6:$D$6,E$5) -> 0 | F10: =COUNTIFS('06_符箓'!$C$6:$C$6,"凡品",'06_符箓'!$D$6:$D$6,F$5) -> 0 | G10: =COUNTIFS('06_符箓'!$C$6:$C$6,"凡品",'06_符箓'!$D$6:$D$6,G$5) -> 0 | H10: =COUNTIFS('06_符箓'!$C$6:$C$6,"凡品",'06_符箓'!$D$6:$D$6,H$5) -> 0 | I10: =COUNTIFS('06_符箓'!$C$6:$C$6,"凡品",'06_符箓'!$D$6:$D$6,I$5) -> 0 | J10: =SUM(B10:I10) -> 0 | K10: 0 | L10: 0 | M10: 仅本批凡品及21核心状态；不施加核心状态可有元素。丹药减伤属S3，另按减伤字段登记，不作防御投票。
A11: 暗器 | B11: =COUNTIFS('07_暗器'!$C$6:$C$10,"凡品",'07_暗器'!$D$6:$D$10,B$5) -> 4 | C11: =COUNTIFS('07_暗器'!$C$6:$C$10,"凡品",'07_暗器'!$D$6:$D$10,C$5) -> 0 | D11: =COUNTIFS('07_暗器'!$C$6:$C$10,"凡品",'07_暗器'!$D$6:$D$10,D$5) -> 0 | E11: =COUNTIFS('07_暗器'!$C$6:$C$10,"凡品",'07_暗器'!$D$6:$D$10,E$5) -> 0 | F11: =COUNTIFS('07_暗器'!$C$6:$C$10,"凡品",'07_暗器'!$D$6:$D$10,F$5) -> 1 | G11: =COUNTIFS('07_暗器'!$C$6:$C$10,"凡品",'07_暗器'!$D$6:$D$10,G$5) -> 0 | H11: =COUNTIFS('07_暗器'!$C$6:$C$10,"凡品",'07_暗器'!$D$6:$D$10,H$5) -> 0 | I11: =COUNTIFS('07_暗器'!$C$6:$C$10,"凡品",'07_暗器'!$D$6:$D$10,I$5) -> 0 | J11: =SUM(B11:I11) -> 5 | K11: =COUNTIFS('07_暗器'!$C$6:$C$10,"凡品",'07_暗器'!$S$6:$S$10,"") -> 4 | L11: =COUNTIFS('07_暗器'!$C$6:$C$10,"凡品",'07_暗器'!$S$6:$S$10,"",'07_暗器'!$D$6:$D$10,"<>NONE") -> 1 | M11: 仅本批凡品及21核心状态；不施加核心状态可有元素。丹药减伤属S3，另按减伤字段登记，不作防御投票。
A12: 合计 | B12: =SUM(B6:B11) -> 25 | C12: =SUM(C6:C11) -> 10 | D12: =SUM(D6:D11) -> 8 | E12: =SUM(E6:E11) -> 9 | F12: =SUM(F6:F11) -> 9 | G12: =SUM(G6:G11) -> 9 | H12: =SUM(H6:H11) -> 8 | I12: =SUM(I6:I11) -> 10 | ... L12: =SUM(L6:L11) -> 3 | M12: 本批88件；基础数值及有无状态均不反推运行时元素。
