Workbook

Sheet 00_使用说明
A1: t01-08｜使用说明
A2: 2026-09-28 · 27件下品 · Q01～Q04规则已确认 · 候选数值与既有配置分列 · 非游戏生产配置
A5: 记录ID | B5: 主题 | C5: 内容 | D5: 边界／状态 | E5: 依据
A6: U01 | B6: 组织方式 | C6: 六类别各自维护跨品级正文；总索引和统计由分类表派生。 | D6: 不另建下品副本作为第二份正文；以后新增品级仍进原类别表。 | E6: 用户本次问题；编制安排
A7: U02 | B7: 本批品级 | C7: 27件全部登记下品；无七系属性。 | D7: 用户最新更正“这一批道具全是下品”，覆盖此前误说的品级；与三段资料的下品表述一致。 | E7: 用户最新品级更正，2026-09-28；资料A/B/C
A8: U03 | B8: 最终数量 | C8: 9武器＋8防具＋4法器＋6丹药＝27；符箓／暗器0。 | D8: C追加铁护臂／腿，未删除旧铁盔／木圆盾；18件和25件为中间统计。 | E8: 资料A/B/C
A9: U04 | B9: 数值性质 | C9: 已有10件配置单列参考；新数值按试玩候选记录；武器设计绝对值未填。 | D9: 原资料称已测试≠本轮跑过游戏；参考配置不自动成为下品最终平衡。 | E9: 资料B；当前配置只读
A10: U05 | B10: 识别与引用 | C10: t01.asset.*为资产主表记录ID，不是新游戏注册ID；已有游戏ID保留映射。 | D10: 一件正式资产尚需合法机制、数值、制作／获取链及实现条件；不可把此表直接视作可运行JSON。 | E10: 项目工程约束；01～07
A11: U06 | B11: 公式与派生 | C11: 占格、名义回复率、组合上限和统计使用公式；公式缓存由独立输入计算后写入。 | D11: 无Excel引擎重新计算／真实渲染；名义比值不含资源、上限、控制、命中或战斗长度，不是平衡验证。 | E11: 编制验证口径
A12: U07 | B12: 当前确认 | C12: Q01～Q04均已确认并回填；当前没有待答题。两组下品邻接例外、甲型算法、多盾许可及三法器2/3上限已明确。 | D12: 03常规邻接门槛保持良品；武器绝对值、新增试玩数值及实际制作／投放／实现留后续。 | E12: t01-08 Q01～Q04用户答复，2026-09-28
A13: U08 | B13: 实现范围 | C13: 本次编制资产主表及文档衔接，游戏配置只读。 | D13: 现有10件与本批均为下品，无品级迁移；旧铁盔／木圆盾现配置未声明armor_type，其他差异见迁移表。 | E13: data/maps/inventory_items.json
A14: U09 | B14: 查阅 | C14: 01索引；02～07分类；08统计；09防具联动；10主甲型；11投放；12既有配置；13跨表关系；14确认与后续；15场景；16来源。 | D14: 所有无资产类别只有空模板行，不作为真实物品计数。 | E14: 本次编制

Sheet 01_总索引
A1: t01-08｜总索引
A2: 2026-09-28 · 27件下品 · Q01～Q04规则已确认 · 候选数值与既有配置分列 · 非游戏生产配置
A5: 资产ID | B5: 名称_分类表引用 | C5: 品级_分类表引用 | D5: 类别 | E5: 正文位置 | F5: 设计阶段 | G5: 实现核对 | H5: 资料依据
A6: t01.asset.0001 | B6: ='02_武器'!B6 -> 青石短剑 | C6: ='02_武器'!C6 -> 下品 | D6: 武器 | E6: 02_武器!A6 | F6: 骨架登记；绝对数值待平衡 | G6: 已有同名配置／品级一致；其他差异见12表 | H6: A；用户最新更正为下品
A7: t01.asset.0002 | B7: ='02_武器'!B7 -> 铁刀 | C7: ='02_武器'!C7 -> 下品 | D7: 武器 | E7: 02_武器!A7 | F7: 骨架登记；绝对数值待平衡 | G7: 尚无正式游戏配置 | H7: A；用户最新更正为下品
A8: t01.asset.0003 | B8: ='02_武器'!B8 -> 柴斧 | C8: ='02_武器'!C8 -> 下品 | D8: 武器 | E8: 02_武器!A8 | F8: 骨架登记；绝对数值待平衡 | G8: 尚无正式游戏配置 | H8: A；用户最新更正为下品
A9: t01.asset.0004 | B9: ='02_武器'!B9 -> 猎弓 | C9: ='02_武器'!C9 -> 下品 | D9: 武器 | E9: 02_武器!A9 | F9: 骨架登记；绝对数值待平衡 | G9: 已有同名配置／品级一致；其他差异见12表 | H9: A；用户最新更正为下品
A10: t01.asset.0005 | B10: ='02_武器'!B10 -> 匕首 | C10: ='02_武器'!C10 -> 下品 | D10: 武器 | E10: 02_武器!A10 | F10: 骨架登记；绝对数值待平衡 | G10: 尚无正式游戏配置 | H10: A；用户最新更正为下品
A11: t01.asset.0006 | B11: ='02_武器'!B11 -> 长枪 | C11: ='02_武器'!C11 -> 下品 | D11: 武器 | E11: 02_武器!A11 | F11: 骨架登记；绝对数值待平衡 | G11: 尚无正式游戏配置 | H11: A；用户最新更正为下品
A12: t01.asset.0007 | B12: ='02_武器'!B12 -> 短柄铁锤 | C12: ='02_武器'!C12 -> 下品 | D12: 武器 | E12: 02_武器!A12 | F12: 骨架登记；绝对数值待平衡 | G12: 已有同名配置／品级一致；其他差异见12表 | H12: A；用户最新更正为下品
A13: t01.asset.0008 | B13: ='02_武器'!B13 -> 石印 | C13: ='02_武器'!C13 -> 下品 | D13: 武器 | E13: 02_武器!A13 | F13: 骨架登记；绝对数值待平衡 | G13: 尚无正式游戏配置 | H13: A；用户最新更正为下品
A14: t01.asset.0009 | B14: ='02_武器'!B14 -> 皮鞭 | C14: ='02_武器'!C14 -> 下品 | D14: 武器 | E14: 02_武器!A14 | F14: 骨架登记；绝对数值待平衡 | G14: 尚无正式游戏配置 | H14: A；用户最新更正为下品
A15: t01.asset.0010 | B15: ='03_防具'!B6 -> 粗布甲 | C15: ='03_防具'!C6 -> 下品 | D15: 防具 | E15: 03_防具!A6 | F15: 保留资料已有值 | G15: 已有同名配置／品级一致；其他差异见12表 | H15: B2；C覆盖
A16: t01.asset.0011 | B16: ='03_防具'!B7 -> 铁甲 | C16: ='03_防具'!C7 -> 下品 | D16: 防具 | E16: 03_防具!A7 | F16: 新增试玩候选；本体6秒 | G16: 尚无正式游戏配置 | H16: B2；C覆盖
A17: t01.asset.0012 | B17: ='03_防具'!B8 -> 旧铁盔 | C17: ='03_防具'!C8 -> 下品 | D17: 防具 | E17: 03_防具!A8 | F17: 保留资料已有值；补甲型 | G17: 已有同名配置／品级一致；其他差异见12表 | H17: B2；C覆盖
A18: t01.asset.0013 | B18: ='03_防具'!B9 -> 木圆盾 | C18: ='03_防具'!C9 -> 下品 | D18: 防具 | E18: 03_防具!A9 | F18: 保留资料已有值；补甲型 | G18: 已有同名配置／品级一致；其他差异见12表 | H18: B2；C覆盖
A19: t01.asset.0014 | B19: ='03_防具'!B10 -> 布护臂 | C19: ='03_防具'!C10 -> 下品 | D19: 防具 | E19: 03_防具!A10 | F19: 新增试玩候选 | G19: 尚无正式游戏配置 | H19: B2；C覆盖
A20: t01.asset.0015 | B20: ='03_防具'!B11 -> 布护腿 | C20: ='03_防具'!C11 -> 下品 | D20: 防具 | E20: 03_防具!A11 | F20: 新增试玩候选 | G20: 尚无正式游戏配置 | H20: B2；C覆盖
A21: t01.asset.0016 | B21: ='03_防具'!B12 -> 铁护臂 | C21: ='03_防具'!C12 -> 下品 | D21: 防具 | E21: 03_防具!A12 | F21: C新增试玩候选 | G21: 尚无正式游戏配置 | H21: C
A22: t01.asset.0017 | B22: ='03_防具'!B13 -> 铁护腿 | C22: ='03_防具'!C13 -> 下品 | D22: 防具 | E22: 03_防具!A13 | F22: C新增试玩候选 | G22: 尚无正式游戏配置 | H22: C
A23: t01.asset.0018 | B23: ='04_法器'!B6 -> 温玉佩 | C23: ='04_法器'!C6 -> 下品 | D23: 法器 | E23: 04_法器!A6 | F23: 保留已有值 | G23: 已有同名配置／品级一致；其他差异见12表 | H23: B3
A24: t01.asset.0019 | B24: ='04_法器'!B7 -> 回春玉 | C24: ='04_法器'!C7 -> 下品 | D24: 法器 | E24: 04_法器!A7 | F24: 新增试玩候选 | G24: 尚无正式游戏配置 | H24: B3
A25: t01.asset.0020 | B25: ='04_法器'!B8 -> 养息珠 | C25: ='04_法器'!C8 -> 下品 | D25: 法器 | E25: 04_法器!A8 | F25: 新增试玩候选 | G25: 尚无正式游戏配置 | H25: B3
A26: t01.asset.0021 | B26: ='04_法器'!B9 -> 聚灵珠 | C26: ='04_法器'!C9 -> 下品 | D26: 法器 | E26: 04_法器!A9 | F26: 新增试玩候选 | G26: 尚无正式游戏配置 | H26: B3
A27: t01.asset.0022 | B27: ='05_丹药'!B6 -> 止血丹 | C27: ='05_丹药'!C6 -> 下品 | D27: 丹药 | E27: 05_丹药!A6 | F27: 保留资料已有值 | G27: 已有同名配置／品级一致；其他差异见12表 | H27: B4
A28: t01.asset.0023 | B28: ='05_丹药'!B7 -> 强筋丸 | C28: ='05_丹药'!C7 -> 下品 | D28: 丹药 | E28: 05_丹药!A7 | F28: 保留资料已有值 | G28: 已有同名配置／品级一致；其他差异见12表 | H28: B4
A29: t01.asset.0024 | B29: ='05_丹药'!B8 -> 消毒散 | C29: ='05_丹药'!C8 -> 下品 | D29: 丹药 | E29: 05_丹药!A8 | F29: 保留资料已有值 | G29: 已有同名配置／品级一致；其他差异见12表 | H29: B4
A30: t01.asset.0025 | B30: ='05_丹药'!B9 -> 回灵丹 | C30: ='05_丹药'!C9 -> 下品 | D30: 丹药 | E30: 05_丹药!A9 | F30: 新增试玩候选 | G30: 尚无正式游戏配置 | H30: B4
A31: t01.asset.0026 | B31: ='05_丹药'!B10 -> 金疮散 | C31: ='05_丹药'!C10 -> 下品 | D31: 丹药 | E31: 05_丹药!A10 | F31: 新增试玩候选 | G31: 尚无正式游戏配置 | H31: B4
A32: t01.asset.0027 | B32: ='05_丹药'!B11 -> 回元散 | C32: ='05_丹药'!C11 -> 下品 | D32: 丹药 | E32: 05_丹药!A11 | F32: 新增试玩候选 | G32: 尚无正式游戏配置 | H32: B4

Sheet 02_武器
A1: t01-08｜武器
A2: 2026-09-28 · 27件下品 · Q01～Q04规则已确认 · 候选数值与既有配置分列 · 非游戏生产配置
A5: 资产ID | B5: 名称 | C5: 品级 | D5: 元素 | E5: 器型 | F5: Attack Type | G5: 宽_格 | H5: 高_格 | I5: 实际占格 | J5: 设计伤害 | K5: 设计CD_秒 | L5: 设计体力费 | M5: 伤害相对档 | N5: CD相对档 | O5: 体力相对档 | P5: 基础战斗性格 | Q5: 后续元素倾向_非本件 | R5: 边界 | S5: 机制引用 | T5: 现有游戏ID | U5: 设计状态 | V5: 来源
A6: t01.asset.0001 | B6: 青石短剑 | C6: 下品 | D6: NONE | E6: 剑 | F6: 斩击 | G6: 1 | H6: 2 | I6: =G6*H6 -> 2 | M6: 中 | N6: 中 | O6: 中 | P6: 均衡斩击基准 | Q6: 火、水 | R6: 不带状态／控制／邻接；无射程，猎弓不耗箭；石印为武器。 | S6: 01 M01/M06/M08；03权限；04九器型 | T6: base.map_item.qingshi_short_sword | U6: 待绝对数值；非生产配置 | V6: A；U
A7: t01.asset.0002 | B7: 铁刀 | C7: 下品 | D7: NONE | E7: 佩刀 | F7: 斩击 | G7: 1 | H7: 1 | I7: =G7*H7 -> 1 | M7: 中低 | N7: 中短 | O7: 中低 | P7: 紧凑、以空间换单击收益 | Q7: 金、火 | R7: 不带状态／控制／邻接；无射程，猎弓不耗箭；石印为武器。 | S7: 01 M01/M06/M08；03权限；04九器型 | T7: 未配置 | U7: 待绝对数值；非生产配置 | V7: A；U
A8: t01.asset.0003 | B8: 柴斧 | C8: 下品 | D8: NONE | E8: 斧 | F8: 斩击 | G8: 2 | H8: 1 | I8: =G8*H8 -> 2 | M8: 高 | N8: 中长 | O8: 高 | P8: 重斩、强调单次爆发 | Q8: 金、土 | R8: 不带状态／控制／邻接；无射程，猎弓不耗箭；石印为武器。 | S8: 01 M01/M06/M08；03权限；04九器型 | T8: 未配置 | U8: 待绝对数值；非生产配置 | V8: A；U
A9: t01.asset.0004 | B9: 猎弓 | C9: 下品 | D9: NONE | E9: 弓 | F9: 穿刺 | G9: 1 | H9: 2 | I9: =G9*H9 -> 2 | M9: 中 | N9: 中长 | O9: 中低 | P9: 稳节奏穿刺；耗力较轻为本批方向 | Q9: 木、水；兼容面广 | R9: 不带状态／控制／邻接；无射程，猎弓不耗箭；石印为武器。 | S9: 01 M01/M06/M08；03权限；04九器型 | T9: base.map_item.hunting_bow | U9: 待绝对数值；非生产配置 | V9: A；U
A10: t01.asset.0005 | B10: 匕首 | C10: 下品 | D10: NONE | E10: 短刃 | F10: 穿刺 | G10: 1 | H10: 1 | I10: =G10*H10 -> 1 | M10: 低 | N10: 短 | O10: 低 | P10: 小占格、快循环 | Q10: 金、风 | R10: 不带状态／控制／邻接；无射程，猎弓不耗箭；石印为武器。 | S10: 01 M01/M06/M08；03权限；04九器型 | T10: 未配置 | U10: 待绝对数值；非生产配置 | V10: A；U
A11: t01.asset.0006 | B11: 长枪 | C11: 下品 | D11: NONE | E11: 枪 | F11: 穿刺 | G11: 3 | H11: 1 | I11: =G11*H11 -> 3 | M11: 高 | N11: 长 | O11: 中高 | P11: 大占格换高单击 | Q11: 雷、金、木 | R11: 不带状态／控制／邻接；无射程，猎弓不耗箭；石印为武器。 | S11: 01 M01/M06/M08；03权限；04九器型 | T11: 未配置 | U11: 待绝对数值；非生产配置 | V11: A；U
A12: t01.asset.0007 | B12: 短柄铁锤 | C12: 下品 | D12: NONE | E12: 锤 | F12: 钝击 | G12: 1 | H12: 2 | I12: =G12*H12 -> 2 | M12: 中高 | N12: 中长 | O12: 中高 | P12: 偏沉重的钝击基准 | Q12: 土、火 | R12: 不带状态／控制／邻接；无射程，猎弓不耗箭；石印为武器。 | S12: 01 M01/M06/M08；03权限；04九器型 | T12: base.map_item.short_iron_hammer | U12: 待绝对数值；非生产配置 | V12: A；U
A13: t01.asset.0008 | B13: 石印 | C13: 下品 | D13: NONE | E13: 印 | F13: 钝击 | G13: 1 | H13: 1 | I13: =G13*H13 -> 1 | M13: 中低 | N13: 中 | O13: 中 | P13: 紧凑钝击，不追求快攻 | Q13: 土、雷 | R13: 不带状态／控制／邻接；无射程，猎弓不耗箭；石印为武器。 | S13: 01 M01/M06/M08；03权限；04九器型 | T13: 未配置 | U13: 待绝对数值；非生产配置 | V13: A；U
A14: t01.asset.0009 | B14: 皮鞭 | C14: 下品 | D14: NONE | E14: 鞭 | F14: 钝击 | G14: 3 | H14: 1 | I14: =G14*H14 -> 3 | M14: 低 | N14: 短 | O14: 中低 | P14: 大占格换高轮转频率 | Q14: 雷、木 | R14: 不带状态／控制／邻接；无射程，猎弓不耗箭；石印为武器。 | S14: 01 M01/M06/M08；03权限；04九器型 | T14: 未配置 | U14: 待绝对数值；非生产配置 | V14: A；U

Sheet 03_防具
A1: t01-08｜防具
A2: 2026-09-28 · 27件下品 · Q01～Q04规则已确认 · 候选数值与既有配置分列 · 非游戏生产配置
A5: 资产ID | B5: 名称 | C5: 品级 | D5: 元素 | E5: 部位 | F5: 甲型 | G5: 宽_格 | H5: 高_格 | I5: 实际占格 | J5: CD_秒 | K5: 护甲上限贡献 | L5: 单次回甲 | M5: 名义回甲每秒 | N5: 甲型权重倍率 | O5: 甲型统计权重 | P5: 上阵部位限制 | Q5: 基础联动 | R5: 费用／数量 | S5: 机制引用 | T5: 现有游戏ID | U5: 设计状态 | V5: 来源
A6: t01.asset.0010 | B6: 粗布甲 | C6: 下品 | D6: NONE | E6: 身甲 | F6: 轻甲 | G6: 1 | H6: 2 | I6: =G6*H6 -> 2 | J6: 4 | K6: 7 | L6: 3 | M6: =L6/J6 -> 0.75 | N6: 2 | O6: =I6*N6 -> 4 | P6: 同一部位最多1件；护臂／护腿分别计限（Q03） | Q6: 布甲联动 | R6: 零体力沿用防具基线；数量不消耗 | S6: 01 C01/I11；04防具；06 Link | T6: base.map_item.coarse_cloth_armor | U6: 保留资料已有值；甲型加权Q02已确认 | V6: B2/C；U
A7: t01.asset.0011 | B7: 铁甲 | C7: 下品 | D7: NONE | E7: 身甲 | F7: 重甲 | G7: 1 | H7: 2 | I7: =G7*H7 -> 2 | J7: 6 | K7: 10 | L7: 4 | M7: =L7/J7 -> 0.66666667 | N7: 2 | O7: =I7*N7 -> 4 | P7: 同一部位最多1件；护臂／护腿分别计限（Q03） | Q7: 铁甲联动 | R7: 零体力沿用防具基线；数量不消耗 | S7: 01 C01/I11；04防具；06 Link | T7: 未配置 | U7: 新增试玩候选；本体6秒；甲型加权Q02已确认 | V7: B2/C；U
A8: t01.asset.0012 | B8: 旧铁盔 | C8: 下品 | D8: NONE | E8: 头具 | F8: 重甲 | G8: 1 | H8: 1 | I8: =G8*H8 -> 1 | J8: 5 | K8: 2 | L8: 1 | M8: =L8/J8 -> 0.2 | N8: 1 | O8: =I8*N8 -> 1 | P8: 同一部位最多1件；护臂／护腿分别计限（Q03） | Q8: 无 | R8: 零体力沿用防具基线；数量不消耗 | S8: 01 C01/I11；04防具；06 Link | T8: base.map_item.old_iron_helmet | U8: 保留资料已有值；补甲型；甲型加权Q02已确认 | V8: B2/C；U
A9: t01.asset.0013 | B9: 木圆盾 | C9: 下品 | D9: NONE | E9: 盾 | F9: 轻甲 | G9: 1 | H9: 2 | I9: =G9*H9 -> 2 | J9: 5 | K9: 2 | L9: 3 | M9: =L9/J9 -> 0.6 | N9: 1 | O9: =I9*N9 -> 2 | P9: 可多件上阵，仅受阵盘空间限制（Q03） | Q9: 无 | R9: 零体力沿用防具基线；数量不消耗 | S9: 01 C01/I11；04防具；06 Link | T9: base.map_item.round_wood_shield | U9: 保留资料已有值；补甲型；甲型加权Q02已确认 | V9: B2/C；U
A10: t01.asset.0014 | B10: 布护臂 | C10: 下品 | D10: NONE | E10: 护具·臂 | F10: 轻甲 | G10: 1 | H10: 1 | I10: =G10*H10 -> 1 | J10: 5 | K10: 1 | L10: 1 | M10: =L10/J10 -> 0.2 | N10: 1 | O10: =I10*N10 -> 1 | P10: 同一部位最多1件；护臂／护腿分别计限（Q03） | Q10: 布甲联动 | R10: 零体力沿用防具基线；数量不消耗 | S10: 01 C01/I11；04防具；06 Link | T10: 未配置 | U10: 新增试玩候选；甲型加权Q02已确认 | V10: B2/C；U
A11: t01.asset.0015 | B11: 布护腿 | C11: 下品 | D11: NONE | E11: 护具·腿 | F11: 轻甲 | G11: 1 | H11: 1 | I11: =G11*H11 -> 1 | J11: 6 | K11: 2 | L11: 1 | M11: =L11/J11 -> 0.16666667 | N11: 1 | O11: =I11*N11 -> 1 | P11: 同一部位最多1件；护臂／护腿分别计限（Q03） | Q11: 布甲联动 | R11: 零体力沿用防具基线；数量不消耗 | S11: 01 C01/I11；04防具；06 Link | T11: 未配置 | U11: 新增试玩候选；甲型加权Q02已确认 | V11: B2/C；U
A12: t01.asset.0016 | B12: 铁护臂 | C12: 下品 | D12: NONE | E12: 护具·臂 | F12: 重甲 | G12: 1 | H12: 1 | I12: =G12*H12 -> 1 | J12: 5 | K12: 2 | L12: 2 | M12: =L12/J12 -> 0.4 | N12: 1 | O12: =I12*N12 -> 1 | P12: 同一部位最多1件；护臂／护腿分别计限（Q03） | Q12: 铁甲联动 | R12: 零体力沿用防具基线；数量不消耗 | S12: 01 C01/I11；04防具；06 Link | T12: 未配置 | U12: C新增试玩候选；甲型加权Q02已确认 | V12: C
A13: t01.asset.0017 | B13: 铁护腿 | C13: 下品 | D13: NONE | E13: 护具·腿 | F13: 重甲 | G13: 1 | H13: 1 | I13: =G13*H13 -> 1 | J13: 6 | K13: 3 | L13: 3 | M13: =L13/J13 -> 0.5 | N13: 1 | O13: =I13*N13 -> 1 | P13: 同一部位最多1件；护臂／护腿分别计限（Q03） | Q13: 铁甲联动 | R13: 零体力沿用防具基线；数量不消耗 | S13: 01 C01/I11；04防具；06 Link | T13: 未配置 | U13: C新增试玩候选；甲型加权Q02已确认 | V13: C

Sheet 04_法器
A1: t01-08｜法器
A2: 2026-09-28 · 27件下品 · Q01～Q04规则已确认 · 候选数值与既有配置分列 · 非游戏生产配置
A5: 资产ID | B5: 名称 | C5: 品级 | D5: 元素 | E5: 定位 | F5: 攻击类型 | G5: 宽_格 | H5: 高_格 | I5: 实际占格 | J5: CD_秒 | K5: 气血恢复 | L5: 体力恢复 | M5: 灵力恢复 | N5: 恢复上限分子 | O5: 恢复上限分母 | P5: 恢复上限状态 | Q5: 成本与效果边界 | R5: 机制引用 | S5: 现有游戏ID | T5: 设计状态 | U5: 来源
A6: t01.asset.0018 | B6: 温玉佩 | C6: 下品 | D6: NONE | E6: 基础资源恢复 | F6: 无攻击 | G6: 1 | H6: 1 | I6: =G6*H6 -> 1 | J6: 4 | K6: 4 | L6: 6 | M6: 0 | N6: 2 | O6: 3 | P6: 已有配置上限2/3；保留 | Q6: 道具消耗0、灵力费0；资料称免费恢复，不附Buff／净化。 | R6: 01资源恢复／上限；04法器 | S6: base.map_item.warm_jade | T6: 保留已有值；具体恢复条件按主表边界 | U6: B3；U
A7: t01.asset.0019 | B7: 回春玉 | C7: 下品 | D7: NONE | E7: 基础资源恢复 | F7: 无攻击 | G7: 1 | H7: 1 | I7: =G7*H7 -> 1 | J7: 5 | K7: 6 | L7: 0 | M7: 0 | N7: 2 | O7: 3 | P7: Q04已确认：最多恢复至对应最大值2/3；已超上限不扣减、不继续恢复 | Q7: 道具消耗0、灵力费0；资料称免费恢复，不附Buff／净化。 | R7: 01资源恢复／上限；04法器 | S7: 未配置 | T7: 新增试玩候选；具体恢复条件按主表边界 | U7: B3；U；Q04用户答复2026-09-28
A8: t01.asset.0020 | B8: 养息珠 | C8: 下品 | D8: NONE | E8: 基础资源恢复 | F8: 无攻击 | G8: 1 | H8: 1 | I8: =G8*H8 -> 1 | J8: 5 | K8: 0 | L8: 9 | M8: 0 | N8: 2 | O8: 3 | P8: Q04已确认：最多恢复至对应最大值2/3；已超上限不扣减、不继续恢复 | Q8: 道具消耗0、灵力费0；资料称免费恢复，不附Buff／净化。 | R8: 01资源恢复／上限；04法器 | S8: 未配置 | T8: 新增试玩候选；具体恢复条件按主表边界 | U8: B3；U；Q04用户答复2026-09-28
A9: t01.asset.0021 | B9: 聚灵珠 | C9: 下品 | D9: NONE | E9: 基础资源恢复 | F9: 无攻击 | G9: 1 | H9: 1 | I9: =G9*H9 -> 1 | J9: 5 | K9: 0 | L9: 0 | M9: 6 | N9: 2 | O9: 3 | P9: Q04已确认：最多恢复至对应最大值2/3；已超上限不扣减、不继续恢复 | Q9: 道具消耗0、灵力费0；资料称免费恢复，不附Buff／净化。 | R9: 01资源恢复／上限；04法器 | S9: 未配置 | T9: 新增试玩候选；具体恢复条件按主表边界 | U9: B3；U；Q04用户答复2026-09-28

Sheet 05_丹药
A1: t01-08｜丹药
A2: 2026-09-28 · 27件下品 · Q01～Q04规则已确认 · 候选数值与既有配置分列 · 非游戏生产配置
A5: 资产ID | B5: 名称 | C5: 品级 | D5: 元素 | E5: 效果类型 | F5: 宽_格 | G5: 高_格 | H5: 实际占格 | I5: CD_秒 | J5: 每次气血恢复 | K5: 每次体力恢复 | L5: 每次灵力恢复 | M5: 跳间隔_秒 | N5: 次数 | O5: 总气血恢复 | P5: 总体力恢复 | Q5: 总灵力恢复 | R5: 毒蚀免疫_秒 | S5: 发动耗数量 | T5: 单位 | U5: 结算时点 | V5: 效果边界 | W5: 机制引用 | X5: 现有游戏ID | Y5: 设计状态 | Z5: 来源
A6: t01.asset.0022 | B6: 止血丹 | C6: 下品 | D6: NONE | E6: 分次 | F6: 1 | G6: 1 | H6: =F6*G6 -> 1 | I6: 6.5 | J6: 2 | K6: 0 | L6: 0 | M6: 2 | N6: 3 | O6: =IF(N6="",0,J6*N6) -> 6 | P6: =IF(N6="",0,K6*N6) -> 0 | Q6: =IF(N6="",0,L6*N6) -> 0 | R6: 0 | S6: 1 | T6: 瓶 | U6: 第2/4/6秒结算；不是发动即首跳 | V6: 仅消毒散清除毒蚀并免疫毒蚀；不扩为全负面净化。 | W6: 01时序／恢复／免疫；02 OP；03专门用途 | X6: base.map_item.hemostatic_pill | Y6: 保留资料已有值 | Z6: B4；U
A7: t01.asset.0023 | B7: 强筋丸 | C7: 下品 | D7: NONE | E7: 分次 | F7: 1 | G7: 1 | H7: =F7*G7 -> 1 | I7: 7.5 | J7: 0 | K7: 4 | L7: 0 | M7: 2 | N7: 3 | O7: =IF(N7="",0,J7*N7) -> 0 | P7: =IF(N7="",0,K7*N7) -> 12 | Q7: =IF(N7="",0,L7*N7) -> 0 | R7: 0 | S7: 1 | T7: 瓶 | U7: 第2/4/6秒结算；不是发动即首跳 | V7: 仅消毒散清除毒蚀并免疫毒蚀；不扩为全负面净化。 | W7: 01时序／恢复／免疫；02 OP；03专门用途 | X7: base.map_item.sinew_pill | Y7: 保留资料已有值 | Z7: B4；U
A8: t01.asset.0024 | B8: 消毒散 | C8: 下品 | D8: NONE | E8: 清毒＋毒蚀免疫 | F8: 1 | G8: 1 | H8: =F8*G8 -> 1 | I8: 5.5 | J8: 0 | K8: 0 | L8: 0 | O8: =IF(N8="",0,J8*N8) -> 0 | P8: =IF(N8="",0,K8*N8) -> 0 | Q8: =IF(N8="",0,L8*N8) -> 0 | R8: 15 | S8: 1 | T8: 瓶 | U8: 发动立即生效 | V8: 仅消毒散清除毒蚀并免疫毒蚀；不扩为全负面净化。 | W8: 01时序／恢复／免疫；02 OP；03专门用途 | X8: base.map_item.detox_powder | Y8: 保留资料已有值 | Z8: B4；U
A9: t01.asset.0025 | B9: 回灵丹 | C9: 下品 | D9: NONE | E9: 分次 | F9: 1 | G9: 1 | H9: =F9*G9 -> 1 | I9: 7.5 | J9: 0 | K9: 0 | L9: 3 | M9: 2 | N9: 3 | O9: =IF(N9="",0,J9*N9) -> 0 | P9: =IF(N9="",0,K9*N9) -> 0 | Q9: =IF(N9="",0,L9*N9) -> 9 | R9: 0 | S9: 1 | T9: 瓶 | U9: 第2/4/6秒结算；不是发动即首跳 | V9: 仅消毒散清除毒蚀并免疫毒蚀；不扩为全负面净化。 | W9: 01时序／恢复／免疫；02 OP；03专门用途 | X9: 未配置 | Y9: 新增试玩候选 | Z9: B4；U
A10: t01.asset.0026 | B10: 金疮散 | C10: 下品 | D10: NONE | E10: 即时 | F10: 1 | G10: 1 | H10: =F10*G10 -> 1 | I10: 5.5 | J10: 4 | K10: 0 | L10: 0 | M10: 0 | N10: 1 | O10: =IF(N10="",0,J10*N10) -> 4 | P10: =IF(N10="",0,K10*N10) -> 0 | Q10: =IF(N10="",0,L10*N10) -> 0 | R10: 0 | S10: 1 | T10: 份 | U10: 发动立即生效 | V10: 仅消毒散清除毒蚀并免疫毒蚀；不扩为全负面净化。 | W10: 01时序／恢复／免疫；02 OP；03专门用途 | X10: 未配置 | Y10: 新增试玩候选 | Z10: B4；U
A11: t01.asset.0027 | B11: 回元散 | C11: 下品 | D11: NONE | E11: 即时 | F11: 1 | G11: 1 | H11: =F11*G11 -> 1 | I11: 7 | J11: 3 | K11: 6 | L11: 0 | M11: 0 | N11: 1 | O11: =IF(N11="",0,J11*N11) -> 3 | P11: =IF(N11="",0,K11*N11) -> 6 | Q11: =IF(N11="",0,L11*N11) -> 0 | R11: 0 | S11: 1 | T11: 份 | U11: 发动立即生效 | V11: 仅消毒散清除毒蚀并免疫毒蚀；不扩为全负面净化。 | W11: 01时序／恢复／免疫；02 OP；03专门用途 | X11: 未配置 | Y11: 新增试玩候选 | Z11: B4；U

Sheet 06_符箓
A1: t01-08｜符箓
A2: 2026-09-28 · 27件下品 · Q01～Q04规则已确认 · 候选数值与既有配置分列 · 非游戏生产配置
A5: 资产ID | B5: 名称 | C5: 品级 | D5: 元素 | E5: 规格 | F5: 宽_格 | G5: 高_格 | H5: 效果 | I5: CD_秒 | J5: 数量消耗 | K5: 机制引用 | L5: 设计状态 | M5: 来源

Sheet 07_暗器
A1: t01-08｜暗器
A2: 2026-09-28 · 27件下品 · Q01～Q04规则已确认 · 候选数值与既有配置分列 · 非游戏生产配置
A5: 资产ID | B5: 名称 | C5: 品级 | D5: 元素 | E5: 规格 | F5: 宽_格 | G5: 高_格 | H5: 效果 | I5: CD_秒 | J5: 数量消耗 | K5: 机制引用 | L5: 设计状态 | M5: 来源

Sheet 08_数量统计
A1: t01-08｜数量统计
A2: 2026-09-28 · 27件下品 · Q01～Q04规则已确认 · 候选数值与既有配置分列 · 非游戏生产配置
A5: 类别 | B5: 下品 | C5: 凡品 | D5: 良品 | E5: 上品 | F5: 灵品 | G5: 玄品 | H5: 仙品 | I5: 合计
A6: 武器 | B6: =COUNTIF(T08Weapon[品级],B$5) -> 9 | C6: =COUNTIF(T08Weapon[品级],C$5) -> 0 | D6: =COUNTIF(T08Weapon[品级],D$5) -> 0 | E6: =COUNTIF(T08Weapon[品级],E$5) -> 0 | F6: =COUNTIF(T08Weapon[品级],F$5) -> 0 | G6: =COUNTIF(T08Weapon[品级],G$5) -> 0 | H6: =COUNTIF(T08Weapon[品级],H$5) -> 0 | I6: =SUM(B6:H6) -> 9
A7: 防具 | B7: =COUNTIF(T08Armor[品级],B$5) -> 8 | C7: =COUNTIF(T08Armor[品级],C$5) -> 0 | D7: =COUNTIF(T08Armor[品级],D$5) -> 0 | E7: =COUNTIF(T08Armor[品级],E$5) -> 0 | F7: =COUNTIF(T08Armor[品级],F$5) -> 0 | G7: =COUNTIF(T08Armor[品级],G$5) -> 0 | H7: =COUNTIF(T08Armor[品级],H$5) -> 0 | I7: =SUM(B7:H7) -> 8
A8: 法器 | B8: =COUNTIF(T08Artifact[品级],B$5) -> 4 | C8: =COUNTIF(T08Artifact[品级],C$5) -> 0 | D8: =COUNTIF(T08Artifact[品级],D$5) -> 0 | E8: =COUNTIF(T08Artifact[品级],E$5) -> 0 | F8: =COUNTIF(T08Artifact[品级],F$5) -> 0 | G8: =COUNTIF(T08Artifact[品级],G$5) -> 0 | H8: =COUNTIF(T08Artifact[品级],H$5) -> 0 | I8: =SUM(B8:H8) -> 4
A9: 丹药 | B9: =COUNTIF(T08Pill[品级],B$5) -> 6 | C9: =COUNTIF(T08Pill[品级],C$5) -> 0 | D9: =COUNTIF(T08Pill[品级],D$5) -> 0 | E9: =COUNTIF(T08Pill[品级],E$5) -> 0 | F9: =COUNTIF(T08Pill[品级],F$5) -> 0 | G9: =COUNTIF(T08Pill[品级],G$5) -> 0 | H9: =COUNTIF(T08Pill[品级],H$5) -> 0 | I9: =SUM(B9:H9) -> 6
A10: 符箓 | B10: =COUNTIF(T08Talisman[品级],B$5) -> 0 | C10: =COUNTIF(T08Talisman[品级],C$5) -> 0 | D10: =COUNTIF(T08Talisman[品级],D$5) -> 0 | E10: =COUNTIF(T08Talisman[品级],E$5) -> 0 | F10: =COUNTIF(T08Talisman[品级],F$5) -> 0 | G10: =COUNTIF(T08Talisman[品级],G$5) -> 0 | H10: =COUNTIF(T08Talisman[品级],H$5) -> 0 | I10: =SUM(B10:H10) -> 0
A11: 暗器 | B11: =COUNTIF(T08HiddenWeapon[品级],B$5) -> 0 | C11: =COUNTIF(T08HiddenWeapon[品级],C$5) -> 0 | D11: =COUNTIF(T08HiddenWeapon[品级],D$5) -> 0 | E11: =COUNTIF(T08HiddenWeapon[品级],E$5) -> 0 | F11: =COUNTIF(T08HiddenWeapon[品级],F$5) -> 0 | G11: =COUNTIF(T08HiddenWeapon[品级],G$5) -> 0 | H11: =COUNTIF(T08HiddenWeapon[品级],H$5) -> 0 | I11: =SUM(B11:H11) -> 0
A12: 合计 | B12: =SUM(B6:B11) -> 27 | C12: =SUM(C6:C11) -> 0 | D12: =SUM(D6:D11) -> 0 | E12: =SUM(E6:E11) -> 0 | F12: =SUM(F6:F11) -> 0 | G12: =SUM(G6:G11) -> 0 | H12: =SUM(H6:H11) -> 0 | I12: =SUM(I6:I11) -> 27

Sheet 09_基础防具联动
A1: t01-08｜基础防具联动
A2: 2026-09-28 · 27件下品 · Q01～Q04规则已确认 · 候选数值与既有配置分列 · 非游戏生产配置
A5: 联动记录ID | B5: 名称 | C5: 主体身甲 | D5: 护臂 | E5: 护腿 | F5: 构型条件 | G5: 关系身份 | H5: 上限额外贡献 | I5: 身甲发动额外回甲 | J5: 组合总上限 | K5: 身甲单次回甲 | L5: 身甲CD_秒 | M5: 总占格 | N5: 运行节奏 | O5: 生命周期边界 | P5: 设计状态 | Q5: 来源
A6: t01.link.cloth_basic | B6: 布甲联动 | C6: 粗布甲 | D6: 布护臂 | E6: 布护腿 | F6: 两护具各自正交邻接同一身甲；不要求两护具彼此相邻。 | G6: 无Set_ID；资料称基础防具联动 | H6: 2 | I6: 1 | J6: =SUM('03_防具'!K6,'03_防具'!K10,'03_防具'!K11)+H6 -> 12 | K6: ='03_防具'!L6+I6 -> 4 | L6: ='03_防具'!J6 -> 4 | M6: =SUM('03_防具'!I6,'03_防具'!I10,'03_防具'!I11) -> 4 | N6: 无额外CD；附加回甲随身甲发动 | O6: 拆联动只撤本贡献，不补满护甲；控制影响按06／02资格判断 | P6: Q01：本组下品邻接限定许可已确认；收益仍为试玩候选 | Q6: B2；C；Q01用户答复2026-09-28
A7: t01.link.iron_basic | B7: 铁甲联动 | C7: 铁甲 | D7: 铁护臂 | E7: 铁护腿 | F7: 两护具各自正交邻接同一身甲；不要求两护具彼此相邻。 | G7: 无Set_ID；资料称基础防具联动 | H7: 3 | I7: 2 | J7: =SUM('03_防具'!K7,'03_防具'!K12,'03_防具'!K13)+H7 -> 18 | K7: ='03_防具'!L7+I7 -> 6 | L7: ='03_防具'!J7 -> 6 | M7: =SUM('03_防具'!I7,'03_防具'!I12,'03_防具'!I13) -> 4 | N7: 无额外CD；附加回甲随身甲发动 | O7: 拆联动只撤本贡献，不补满护甲；控制影响按06／02资格判断 | P7: Q01：本组下品邻接限定许可已确认；收益仍为试玩候选 | Q7: B2；C；Q01用户答复2026-09-28

Sheet 10_甲型与部位规则
A1: t01-08｜甲型规则与部位范围（逐项标记效力）
A2: 2026-09-28 · 27件下品 · Q01～Q04规则已确认 · 候选数值与既有配置分列 · 非游戏生产配置
A5: 规则ID | B5: 内容 | C5: 本批处理 | D5: 与旧词典的关系 | E5: 状态
A6: ARM01 | B6: 身甲每实际格×2，其余防具每实际格×1，同甲型加总。 | C6: 分类表N/O列现按已确认规则计算甲型权重；适用双方。 | D6: Q02已覆盖04原等权统计，回填字段、正文、案例与汇总。 | E6: Q02已确认；04已回填
A7: ARM02 | B7: 最高并列含身甲甲型时优先身甲。 | C7: 铁甲重甲4与盾＋布护臂＋布护腿轻甲4并列，优先身甲，取重甲。 | D7: 双方均适用；不把甲型权重或身甲优先套给防御元素。 | E7: Q02已确认；04已回填
A8: ARM03 | B8: 无身甲或最高并列不含身甲时：玩家选最高候选；敌方按阵盘从上到下、每行从左到右扫描。 | C8: 敌方首遇最高候选胜出，跳过非候选；不随机。 | D8: 先判断身甲优先，再使用玩家／敌方的后备规则；04已回填。 | E8: Q02已确认；04已回填
A9: ARM04 | B9: 身甲、头具、护臂、护腿各最多1件；护臂与护腿分别计限。盾允许多件，仅受阵盘空间限制。所有防具仍摆在阵盘，不新增固定装备槽。 | C9: Q03已确认多盾；身甲／头具／护臂／护腿按各自部位限1，其他护具具体部位随资产明配。 | D9: 四大防具形态≠部位唯一性：护臂和护腿可各1件。 | E9: Q03已确认；04已回填
A10: ARM05 | B10: 防御元素仍沿04按实际格聚合。 | C10: 本批NONE，不投元素票；不从甲型×2推定元素×2。 | D10: Q02明确只调整主甲型；元素聚合保持原规则。 | E10: 既有规则引用

Sheet 11_获取规划
A1: t01-08｜获取规划
A2: 2026-09-28 · 27件下品 · Q01～Q04规则已确认 · 候选数值与既有配置分列 · 非游戏生产配置
A5: 规划记录ID | B5: 目标资产ID或类型 | C5: 目标名称 | D5: 渠道 | E5: 具体来源意向 | F5: 方法 | G5: 交付模式 | H5: 目标与成功对象 | I5: 缺失配置 | J5: 节奏／前提 | K5: 状态 | L5: 依据
A6: t01.acquisition.plan.001 | B6: t01.asset.0001 | C6: 青石短剑 | D6: SHOP | E6: 青石镇铁匠铺 | F6: PURCHASE | G6: DIRECT | H6: 固定实物／规格待绝对值 | I6: 数量／价格／库存／资格待配 | J6: 凡人阶段内逐步接触九器型为建议；不等于都已可买。 | K6: 投放建议，非可执行记录 | L6: A；07 D11／R05／Q05
A7: t01.acquisition.plan.002 | B7: t01.asset.0002 | C7: 铁刀 | D7: SHOP | E7: 青石镇铁匠铺 | F7: PURCHASE | G7: DIRECT | H7: 固定实物／规格待绝对值 | I7: 数量／价格／库存／资格待配 | J7: 凡人阶段内逐步接触九器型为建议；不等于都已可买。 | K7: 投放建议，非可执行记录 | L7: A；07 D11／R05／Q05
A8: t01.acquisition.plan.003 | B8: t01.asset.0003 | C8: 柴斧 | D8: SHOP | E8: 青石镇铁匠铺 | F8: PURCHASE | G8: DIRECT | H8: 固定实物／规格待绝对值 | I8: 数量／价格／库存／资格待配 | J8: 凡人阶段内逐步接触九器型为建议；不等于都已可买。 | K8: 投放建议，非可执行记录 | L8: A；07 D11／R05／Q05
A9: t01.acquisition.plan.004 | B9: t01.asset.0004 | C9: 猎弓 | D9: SHOP | E9: 青石镇商铺 | F9: PURCHASE | G9: DIRECT | H9: 固定实物／规格待绝对值 | I9: 数量／价格／库存／资格待配 | J9: 凡人阶段内逐步接触九器型为建议；不等于都已可买。 | K9: 投放建议，非可执行记录 | L9: A；07 D11／R05／Q05
A10: t01.acquisition.plan.005 | B10: t01.asset.0005 | C10: 匕首 | D10: SHOP | E10: 青石镇商铺 | F10: PURCHASE | G10: DIRECT | H10: 固定实物／规格待绝对值 | I10: 数量／价格／库存／资格待配 | J10: 凡人阶段内逐步接触九器型为建议；不等于都已可买。 | K10: 投放建议，非可执行记录 | L10: A；07 D11／R05／Q05
A11: t01.acquisition.plan.006 | B11: t01.asset.0006 | C11: 长枪 | D11: SHOP | E11: 青石镇铁匠铺 | F11: PURCHASE | G11: DIRECT | H11: 固定实物／规格待绝对值 | I11: 数量／价格／库存／资格待配 | J11: 凡人阶段内逐步接触九器型为建议；不等于都已可买。 | K11: 投放建议，非可执行记录 | L11: A；07 D11／R05／Q05
A12: t01.acquisition.plan.007 | B12: t01.asset.0007 | C12: 短柄铁锤 | D12: SHOP | E12: 青石镇铁匠铺 | F12: PURCHASE | G12: DIRECT | H12: 固定实物／规格待绝对值 | I12: 数量／价格／库存／资格待配 | J12: 凡人阶段内逐步接触九器型为建议；不等于都已可买。 | K12: 投放建议，非可执行记录 | L12: A；07 D11／R05／Q05
A13: t01.acquisition.plan.008 | B13: t01.asset.0008 | C13: 石印 | D13: SHOP | E13: 青石镇商铺 | F13: PURCHASE | G13: DIRECT | H13: 固定实物／规格待绝对值 | I13: 数量／价格／库存／资格待配 | J13: 凡人阶段内逐步接触九器型为建议；不等于都已可买。 | K13: 投放建议，非可执行记录 | L13: A；07 D11／R05／Q05
A14: t01.acquisition.plan.009 | B14: t01.asset.0009 | C14: 皮鞭 | D14: SHOP | E14: 青石镇商铺 | F14: PURCHASE | G14: DIRECT | H14: 固定实物／规格待绝对值 | I14: 数量／价格／库存／资格待配 | J14: 凡人阶段内逐步接触九器型为建议；不等于都已可买。 | K14: 投放建议，非可执行记录 | L14: A；07 D11／R05／Q05
A15: t01.acquisition.plan.010 | B15: 来源入口 | C15: 青石镇商铺 | D15: 任务／剧情待配 | E15: 救下商人条件待定义 | F15: 来源开放 | G15: SOURCE_UNLOCK | H15: 商铺入口及开放状态 | I15: 不适用实物数量；具体任务／入口ID待配 | J15: 仅建议，不从正文自行创建剧情。 | K15: 投放建议，非可执行记录 | L15: A；07 D13

Sheet 12_现有配置与迁移
A1: t01-08｜现有配置与迁移
A2: 2026-09-28 · 27件下品 · Q01～Q04规则已确认 · 候选数值与既有配置分列 · 非游戏生产配置
A5: 资产ID | B5: 名称 | C5: 现有游戏ID | D5: 现配置品级 | E5: 主表品级 | F5: 现基础伤害 | G5: 现CD_秒 | H5: 现体力费 | I5: 现甲型字段 | J5: 现上限贡献 | K5: 现回甲 | L5: 现effects原值 | M5: 差异与迁移范围 | N5: 验证性质 | O5: 证据
A6: t01.asset.0001 | B6: 青石短剑 | C6: base.map_item.qingshi_short_sword | D6: 下品 | E6: 下品 | F6: 7 | G6: 3.5 | H6: 3 | I6: 未声明 | L6: [] | M6: 主表与现配置均为下品，无品级迁移需求。已有绝对数值仅参考；本批仍以相对档位为设计输入。 | N6: 本轮只读配置；未运行游戏 | O6: data/maps/inventory_items.json
A7: t01.asset.0004 | B7: 猎弓 | C7: base.map_item.hunting_bow | D7: 下品 | E7: 下品 | F7: 9 | G7: 4.5 | H7: 5 | I7: 未声明 | L7: [] | M7: 主表与现配置均为下品，无品级迁移需求。已有绝对数值仅参考；本批仍以相对档位为设计输入。 | N7: 本轮只读配置；未运行游戏 | O7: data/maps/inventory_items.json
A8: t01.asset.0007 | B8: 短柄铁锤 | C8: base.map_item.short_iron_hammer | D8: 下品 | E8: 下品 | F8: 8 | G8: 4 | H8: 4 | I8: 未声明 | L8: [] | M8: 主表与现配置均为下品，无品级迁移需求。已有绝对数值仅参考；本批仍以相对档位为设计输入。 | N8: 本轮只读配置；未运行游戏 | O8: data/maps/inventory_items.json
A9: t01.asset.0010 | B9: 粗布甲 | C9: base.map_item.coarse_cloth_armor | D9: 下品 | E9: 下品 | G9: 4 | I9: 轻甲 | J9: 7 | K9: 3 | L9: [] | M9: 主表与现配置均为下品，无品级迁移需求。 | N9: 本轮只读配置；未运行游戏 | O9: data/maps/inventory_items.json
A10: t01.asset.0012 | B10: 旧铁盔 | C10: base.map_item.old_iron_helmet | D10: 下品 | E10: 下品 | G10: 5 | I10: 未声明 | J10: 2 | K10: 1 | L10: [] | M10: 主表与现配置均为下品，无品级迁移需求。现配置未声明armor_type；本批明确重甲。 | N10: 本轮只读配置；未运行游戏 | O10: data/maps/inventory_items.json
A11: t01.asset.0013 | B11: 木圆盾 | C11: base.map_item.round_wood_shield | D11: 下品 | E11: 下品 | G11: 5 | I11: 未声明 | J11: 2 | K11: 3 | L11: [] | M11: 主表与现配置均为下品，无品级迁移需求。现配置未声明armor_type；本批明确轻甲。 | N11: 本轮只读配置；未运行游戏 | O11: data/maps/inventory_items.json
A12: t01.asset.0018 | B12: 温玉佩 | C12: base.map_item.warm_jade | D12: 下品 | E12: 下品 | G12: 4 | I12: 未声明 | L12: [{"cap_numerator": 2, "resource": "hp", "cap_denominator": 3, "effect": "restore_capped", "value": 4, "trigger": "on_activate"}, {"cap_numerator": 2, "resource": "stamina", "cap_denominator": 3, "effect": "restore_capped", "value": 6, "trigger": "on_activate"}] | M12: 主表与现配置均为下品，无品级迁移需求。 | N12: 本轮只读配置；未运行游戏 | O12: data/maps/inventory_items.json
A13: t01.asset.0022 | B13: 止血丹 | C13: base.map_item.hemostatic_pill | D13: 下品 | E13: 下品 | G13: 6.5 | I13: 未声明 | L13: [{"resource": "hp", "interval": 2.0, "effect": "restore_ticks", "value": 2, "ticks": 3, "trigger": "on_activate"}] | M13: 主表与现配置均为下品，无品级迁移需求。 | N13: 本轮只读配置；未运行游戏 | O13: data/maps/inventory_items.json
A14: t01.asset.0023 | B14: 强筋丸 | C14: base.map_item.sinew_pill | D14: 下品 | E14: 下品 | G14: 7.5 | I14: 未声明 | L14: [{"resource": "stamina", "interval": 2.0, "effect": "restore_ticks", "value": 4, "ticks": 3, "trigger": "on_activate"}] | M14: 主表与现配置均为下品，无品级迁移需求。 | N14: 本轮只读配置；未运行游戏 | O14: data/maps/inventory_items.json
A15: t01.asset.0024 | B15: 消毒散 | C15: base.map_item.detox_powder | D15: 下品 | E15: 下品 | G15: 5.5 | I15: 未声明 | L15: [{"effect": "cleanse_toxin", "duration": 15, "trigger": "on_activate"}] | M15: 主表与现配置均为下品，无品级迁移需求。 | N15: 本轮只读配置；未运行游戏 | O15: data/maps/inventory_items.json

Sheet 13_跨词典联系
A1: t01-08｜跨词典联系
A2: 2026-09-28 · 27件下品 · Q01～Q04规则已确认 · 候选数值与既有配置分列 · 非游戏生产配置
A5: 词典 | B5: 接口 | C5: 本批关联 | D5: 边界／实际动作 | E5: 状态
A6: 01 | B6: 发动／支付／恢复／上限 | C6: 武器基础攻击、资源恢复、防具回甲与上限分开；持续药效按时钟。 | D6: 引用已有词义，不给每件物品建新运行系统。 | E6: 参考
A7: 02 | B7: 毒蚀清除与免疫／控制 | C7: 消毒散专门清毒＋15秒毒蚀免疫；药效和免疫为独立整份实例；Link按控制资格运行。 | D7: 不扩全负面净化、不自动免控；具体重复药效策略按资产/既有规则。 | E7: 参考
A8: 03 | B8: 下品权限 | C8: 仅批准粗布甲＋布护臂＋布护腿、铁甲＋铁护臂＋铁护腿两组下品基础防具联动；两个护具分别正交邻接对应身甲。其他下品仍按03原权限；无Set_ID，不新增独立CD。 | D8: 已回填03 C030的例外及引用视图，常规品级许可符号不变。 | E8: Q01已确认；03已同步
A9: 04 | B9: 器型、甲型、部位 | C9: 九器型与固定占格；Q02已定身甲每格2、其他1及最高并列身甲优先。 | D9: 04已回填；防御元素按实际格。身甲／头具／臂／腿各限1，盾可多件。 | E9: Q02／Q03已同步
A10: 05 | B10: 制作方／配方 | C10: 保留合法制作与升品接口；当前未提供这27件的方、材料、配方。 | D10: 不因下品可制作就虚构实际器方；不恢复蓝图学习或归胚。 | E10: 待具体生产资产
A11: 06 | B11: 基础联动 | C11: 两组固定主体与两护具正交邻接；无Set_ID；不额外增加独立CD。 | D11: 仍查Link资格、控制、只撤本贡献及不靠重组成套补甲。 | E11: Q01限定许可已确认；资产运行待补齐
A12: 07 | B12: 获取与交付 | C12: 9件武器购入方向＋商铺开放意向。 | D12: 全部为规划；其余18件来源未提供，不自行补投放或掉率。 | E12: 待实际获取链

Sheet 14_确认与后续事项
A1: t01-08｜确认与后续事项
A2: 2026-09-28 · 27件下品 · Q01～Q04规则已确认 · 候选数值与既有配置分列 · 非游戏生产配置
A5: 编号 | B5: 主题 | C5: 问题／工作 | D5: 当前状态 | E5: 影响范围
A6: Q01 | B6: 下品邻接权限 | C6: 03从良品常规开放正交邻接，本批两组下品联动是否限定例外？ | D6: 已确认限定两组联动；用户最新将本批品级更正为下品，例外随这两组改为下品；其他物品仍按03原权限。 | E6: 03 C030及两联动许可已同步；数值仍为候选
A7: Q02 | B7: 甲型全局覆盖 | C7: 身甲×2／其他×1、并列优先身甲是否全局替换04？ | D7: 已确认：采用整套规则，更新04（建议） | E7: 双方主甲型规则已回填04；不改防御元素
A8: Q03 | B8: 部位限制范围 | C8: 盾是否也最多1件；同部位限制与现有阵盘规格需统一。 | D8: 已确认：允许多件盾，只受阵盘空间限制 | E8: 已回填04及08部位限制
A9: Q04 | B9: 新法器恢复上限 | C9: 回春玉、养息珠、聚灵珠是否采用最多至最大值2/3？ | D9: 已确认：三件都采用2/3上限（建议） | E9: 已回填回春玉、养息珠、聚灵珠；温玉佩既有规则不变
A10: A01 | B10: 绝对武器数值 | C10: 九件之间相对伤害／CD／体力档位，待横向平衡。 | D10: 原稿明确后定；保留三已有武器参考值，未擅自代填。 | E10: 未来数值设计
A11: A02 | B11: 候选参数与平衡 | C11: 新增防具、法器、丹药及两联动收益保留试玩候选。 | D11: 未运行战斗；不把新增候选改写为已测试。 | E11: 未来确认与验证
A12: A03 | B12: 生产获取与表现 | C12: 配方、正式来源、价格库存、图标和运行配置未齐。 | D12: 未创建游戏资产；后续按实际选定范围补齐。 | E12: 未来资产落地
A13: A04 | B13: Link具体运行 | C13: 固定匹配结构已有，控制时静态上限／发动修正需与02/06实例策略衔接。 | D13: 不一律控制就断链、不用重新组合免费恢复护甲。 | E13: 未来实际运行模板

Sheet 15_核对场景
A1: t01-08｜核对场景
A2: 2026-09-28 · 27件下品 · Q01～Q04规则已确认 · 候选数值与既有配置分列 · 非游戏生产配置
A5: 案例ID | B5: 主题 | C5: 输入 | D5: 预期／边界 | E5: 状态
A6: T01 | B6: 总量 | C6: 最后一段新增两件铁护具，旧头盔和盾保留 | D6: 9＋8＋4＋6＝27；符箓暗器空模板不计数 | E6: 文本核对
A7: T02 | B7: 品级覆盖 | C7: 用户更正：“这一批道具全是下品”；覆盖此前误说。 | D7: 27件品级均下品；统计下品27、凡品0；现有10件配置同为下品。 | E7: 文本／结构核对
A8: T03 | B8: 武器数值 | C8: 猎弓已有9伤／4.5秒／5体力，但新稿体力中低 | D8: 保留旧配置证据，不把新相对档位等同旧排序已满足 | E8: 待平衡
A9: T04 | B9: 占格方向 | C9: 剑1×2、斧2×1；枪鞭3×1 | D9: 维持固定方向不可旋转；无射程加成 | E9: 文本核对
A10: T05 | B10: 布甲联动 | C10: 两护具分别贴粗布甲，互不相邻 | D10: 上限12、身甲回甲4／4秒；总4格；Q01已批准本组下品邻接例外。 | E10: 候选计算；未运行
A11: T06 | B11: 铁甲联动 | C11: 铁甲＋铁护臂＋铁护腿合法构型 | D11: 上限18、身甲回甲6／6秒；护臂5秒／腿6秒，非身甲4秒 | E11: 候选计算；未运行
A12: T07 | B12: 甲型并列 | C12: 铁甲重4，盾＋布臂＋布腿轻4 | D12: 权重重4、轻4并列，优先身甲重甲；Q02已定，04已覆盖。 | E12: 已确认规则；文本核对，未运行
A13: T08 | B13: 元素权重 | C13: 未来有属性身甲参与元素统计 | D13: 不能由甲型×2自动推出元素×2；本批NONE不投票 | E13: 既有边界
A14: T09 | B14: 解组 | C14: 布／铁三件构型失效后再成立 | D14: 只撤／恢复对应上限贡献，不凭空补满护甲；控制须查资格 | E14: 文本需求；未运行
A15: T10 | B15: 资源法器 | C15: 新三件免费回复法器接近资源上限 | D15: Q04已确认2/3上限：对应最大值60时最多恢复至40；已高于40不扣减，也不继续恢复。 | E15: 已确认规则；文本核对，未运行
A16: T11 | B16: 分次丹药 | C16: 止血／强筋／回灵在发动后2、4、6秒跳 | D16: 各总6气血／12体力／9灵力；不能发动即先跳一次 | E16: 候选／既有对照；未运行
... A18: T13 | B18: 非实物开放 | C18: 救商人后开放商铺的规划被采纳时 | D18: 按07 SOURCE_UNLOCK成功应用入口，不能为填字段虚构物品×1 | E18: 后续投放需求

Sheet 16_来源与证据
A1: t01-08｜来源与证据
A2: 2026-09-28 · 27件下品 · Q01～Q04规则已确认 · 候选数值与既有配置分列 · 非游戏生产配置
A5: 来源ID | B5: 来源位置 | C5: 性质 | D5: 有效范围 | E5: 完整性说明
A6: U/A/B/C | B6: docs\sources\t01-08_三段资料结构化摘录_2026-09-28.md | C6: 用户本轮消息的结构化摘录 | D6: 用户最新更正全为下品；C修正优先；候选与建议保留原性质 | E6: 不是附件原字节／完整逐字转录
A7: GAME10 | B7: data/maps/inventory_items.json | C7: 现行配置只读快照 | D7: 10件同名基准数据；不等于新下品设计已实现 | E7: 684c149bf81c83f6034ffbd6a1f12e52a41de4c0ba1b722e8d6899921f84a528
A8: Q01 | B8: 本轮选择题 | C8: 用户已答，2026-09-28 | D8: 历史Q01原答复：“仅允许这两组凡品防具联动，其他凡品仍按03原权限（建议）”；随后用户更正本批全部下品，现行例外限两组下品。 | E8: 原答复留作历史；现行品级按最新更正，两组限定许可不推广其他下品或凡品，候选数值未定案。
A9: DICT01-07 | B9: output/spreadsheet/t01-01～07正式词典 | C9: 既有规则参考 | D9: 引用具体接口；新全局规则须明确覆盖范围 | E9: 本轮未批准前不改旧词典
